Workbook

Sheet 市民意见信息（12345）导出
A1: 2025年12月19日至2026年4月18日接诉即办市级统计表（2026年全年台账）
A2: 系统下载内容情况 | AP2: 周报分析对应内容情况 | BV2: 市中心 | CF2: 发布周报
AR3: 1 | AS3: 2 | AT3: 3 | AU3: 4 | AV3: 5 | AW3: 6 | AX3: 7 | AY3: 8 | AZ3: 9 | BA3: 10 | BB3: 11 | BC3: 12 | BD3: 13 | BE3: 14 | BF3: 15 | BG3: 16 | BH3: 17 | BI3: 18 | BJ3: 19 | BK3: 20 | BL3: 21 | BM3: 22 | BN3: 23 | BO3: 24 | BP3: 25 | BQ3: 26 | BR3: 27 | BT3: 28 | BU3: 29 | BV3: 30 | BW3: 31 | BX3: 32 | BY3: 33 | BZ3: 34 | CA3: 35 | CB3: 36 | CC3: 37 | CD3: 38 | CE3: 39 | CF3: 40 | CG3: 41
A4: 工单编号 | B4: 派单时间 | C4: 签收日期 | D4: 下达日期 | E4: 联系人 | F4: 性别 | G4: 联系电话 | H4: 来电内容 | I4: 是否需答复 | J4: 性质 | K4: 部门 | L4: 问题分类 | M4: 标题 | N4: 单位 | O4: 线路号 | P4: 清分中心修改部门 | Q4: 车队名称 | R4: 公司到期 | S4: 答复日期 | T4: 截至时间 | U4: 当前节点 | V4: 提醒次数 | W4: 核实处理 | X4: 回访情况 | Y4: 处理结果 | Z4: 纠正措施 | AA4: 跟踪检查 | AB4: 最终意见 | AC4: 满意度 | AD4: 来电主体 | AE4: 来电时间 | AF4: TSBMID | AG4: 问题分类 | AH4: 是否表扬告知单 | AI4: 集团公司指标讲评问题 | AK4: 问题分 类简述 | AL4: 问题（部室）督办 | AM4: 问题（分中心）办结 | AP4: 序号 | AQ4: 月份 | AR4: 接诉编号 | AS4: 接诉分类 | AT4: 接诉平台 | AU4: 接诉时间 | AV4: 责任部室（系统） | AW4: 所属分中心（系统） | AX4: 接诉事由 | AY4: 内容简述 | AZ4: 是否内部职工 | BA4: 是否物业 | BB4: 作风问题 | BC4: 七有五性 | BD4: 目前状态 | BE4: 办结/截止日期 | BF4: 诉求简要分析 | BG4: 责任部室 | BH4: 所属分中心 | BI4: 系统内归属单位 | BJ4: 责任划分 | BK4: 是否可回访 | BL4: 经办人员 | BM4: 是否剔除 | BN4: 是否次要责任 | BO4: 回访情况 | BP4: 派单分类 | BQ4: 多渠道投诉情况 | BR4: 重复投诉 | BS4: 诉求渠道顺序 | BT4: 拆单情况 | BU4: 岗位 | BV4: 市服务热线编号 | BW4: 集团反馈“七有五性” | BX4: 热线是否拆单 | BY4: 诉求是否主责 | BZ4: 纳入考评件 | CA4: 响应情况（联系） | CB4: 解决情况 | CC4: 满意情况 | CD4: 考核项目 | CE4: 考核月份 | CF4: 是*；否“”
A5: 网络-251219-005951-3（1个附件） | B5: 2025-12-19 09:52:13 | C5: 2025-12-19 10:22:42 | D5: 2025-12-19 10:50:52 | E5: 雷靖静 | F5: 女 | G5: 手机,15059330130; | H5: 工单来源：微信服务号，此工单内容为网民留言时填写的标题及原文。 ============================= 留言标题：公交留言原文：公交车环境不好，味道太大了，建议及时通风。以及982和365线路有时候灯突然熄灭，也不再开启。整个车内漆黑一片，体验真的不好啊…市民填写的详细地址为：区、街道：海淀区上地街道详细地址：公交车内注：因不明具体公交信息，故回拨市民注：2025年12月19日08:48分13203回拨市民，询问具体公交信息，无法接听，2025年12月19日09:20分13203回拨市民，无人接听，2025年12月19日09:50分13203回拨市民，无人接听。 | I5: 是 | J5: 诉求 | K5: 行车安全服务部 | L5: 企业政策问题 | M5: 调整服务规范 | N5: 鸿运承物业管理中心 | O5: 西苑分中心 | P5: 物管行政部 | Q5: 西苑分中心 | R5: 2025-12-26 23:59:59 | S5: 2025-12-20 | T5: 2025-12-24 08:59:59 | U5: 结束 | V5: 0 | W5: 您好，关于您反映问题的办理情况，鸿运承物业管理中心西苑分中心现对您回复如下： | X5: 我分中心已于2025年12月19日下午13点21分对您进行电话回复。办理人：于德海；部门：鸿运承物业管理中心西苑分中心；职务；物管副主任。审核人：郑楠；部门：鸿运承物业管理中心物管行政部；职务：物管员。 | Y5: 雷女士您好，982路公交车我们在西北旺场站进行车厢服务工作，365路公交车我们在永丰场站进行车厢服务工作，您所述车辆运营中公交车环境不好，味道太大了的问题，我们非常重视您的反馈，由于我们的工作没有做好，两条线路给您带来不好的乘车体验，实在是抱歉，雷女士。两条线路车辆回到我们的清洁地点后（西北旺场站、永丰场站），日常工作时段内，我们的保洁员在清理卫生的同时，已将车门、车窗全部打开，及时对车内进行了通风作业，对车内异味进行了处理，已整改完毕。 | Z5: 我们分中心及场站班组长再次与两条线路的保洁人员进行了沟通，日常工作中我们要密切关注车内空气质量，做好通风换气作业，确保给您带来一个空气清新的出行环境。 | AA5: 我们定期会召开车厢服务工作专题会议，开展专项检查，日常工作中我们加大巡检力度，强化制度建设，不断提高管理水平。 | AB5: 您好，关于您反映问题的办理情况，鸿运承物业管理中心西苑分中心现对您回复如下：雷女士您好，982路公交车我们在西北旺场站进行车厢服务工作，365路公交车我们在永丰场站进行车厢服务工作，您所述车辆运营中公交车环境不好，味道太大了的问题，我们非常重视您的反馈，由于我们的工作没有做好，两条线路给您带来不好的乘车体验，实在是抱歉，雷女士。两条线路车辆回到我们的清洁地点后（西北旺场站、永丰场站），日常工作时段内，我们的保洁员在清理卫生的同时，已将车门、车窗全部打开，及时对车内进行了通风作业，对车内异味进行了处理，已整改完毕。我们定期会召开车厢服务工作专题会议，开展专项检查，日常工作中我们加大巡检力度，强化制度建设，不断提高管理水平。我分中心已于2025年12月19日下午13点21分对您进行电话回复。我们分中心及场站班组长再次与两条线路的保洁人员进行了沟通，日常工作中我们要密切关注车内空气质量，做好通风换气作业，确保给您带来一个空气清新的出行环境。欢迎您随时对我们的工作进行监督，感谢您提出宝贵意见，给您的出行带来的不便我们和您说声抱歉，谢谢您的支持与谅解。 | AC5: 满意 | AD5: 个人 | AE5: 2025-12-18 17:36:34 | AF5: 1725545785 | AG5: 服务 | AH5: 否 | AK5: =AG5&L5&M5 -> 服务企业政策问题调整服务规范 | AP5: 1 | AQ5: 46023 | AR5: =IFERROR(LEFT(A5,FIND("（",A5)-1),A5) -> 网络-251219-005951-3 | AS5: =J5 -> 诉求 | AT5: =IF(MID(AR5,1,2)="热线",12345)+IF(MID(AR5,1,2)="网络",12345) -> 12345 | AU5: =IFERROR(LEFT(D5,FIND(" ",D5)-1),D5) -> 2025-12-19 | AV5: =P5 -> 物管行政部 | AW5: =Q5 -> 西苑分中心 | AX5: =H5 -> 工单来源：微信服务号，此工单内容为网民留言时填写的标题及原文。 ============================= 留言标题：公交留言原文：公交车环境不好，味道太大了，建议及时通风。以及982和365线路有时候灯突然熄灭，也不再开启。整个车内漆黑一片，体验真的不好啊…市民填写的详细地址为：区、街道：海淀区上地街道详细地址：公交车内注：因不明具体公交信息，故回拨市民注：2025年12月19日08:48分13203回拨市民，询问具体公交信息，无法接听，2025年12月19日09:20分13203回拨市民，无人接听，2025年12月19日09:50分13203回拨市民，无人接听。 | AY5: =AG5 -> 服务 | AZ5: 否 | BA5: 否 | BB5: 否 | BC5: 七有五性,宜居性 | BD5: =U5 -> 结束 | BE5: =IFERROR(LEFT(T5,FIND(" ",T5)-1),T5) -> 2025-12-24 | BF5: 车辆卫生问题 （车内异味） | BG5: 物管行政部 | BH5: 西苑分中心 | BL5: =IF(BG5="物管行政部","侯旭、郑楠",IF(BG5="安保部","张耕",IF(BG5="工程设备部","华菲",IF(BG5="人力资源部","成琦",IF(BG5="党委工作部","阎鑫雨",IF(BG5="餐饮服务部","赵弘晨",IF(BG5="工会","郑欣",IF(BG5="办公室","董娜",""))))))))&IF(BG5="纪检部","黄倩",IF(BG5="信息管理部","蔡浩然","")) -> 侯旭、郑楠 | BM5: 未主动剔除 | BP5: 业务类 | BV5: =MID(AR5,1,16) -> 网络-251219-005951 | BW5: 七有五性,便利性 | BX5: =IF(COUNTIF(BV:BV,BV5)=1,"否","是") -> 否 | BY5: =MID(AR5,18,1) -> 3 | BZ5: 只评价响应率 | CE5: 1月 | CG5: =VLOOKUP(AR5,[1]市民意见信息导出!$AI$2:$AK$392,3,FALSE()) -> 结束 | CH5: =VLOOKUP(BV5,[2]Sheet1!$C$2:$AC$99,2,FALSE()) -> 1月
A6: 热线-251218-074256-2（1个附件） | B6: 2025-12-18 23:00:02 | C6: 2025-12-18 23:10:41 | D6: 2025-12-19 10:20:38 | E6: 李先生 | F6: 男 | G6: 手机,15120055651; | H6: 市民反映，自己有一个东西丢在了密云区北京公交第七客运公司，上该公司门口来领东西，女工作人员的态度特别横，自己给值班人员打电话对方态度也特别横 ，12月18日10:40自己打公交公司96166后，也未处理好此问题，来电反映北京公交第七客运公司工作人员态度恶劣等问题。 | I6: 是 | J6: 诉求 | K6: 安保部（应急管理中心） | L6: 安保专业政策问题 | M6: 安保措施 | N6: 鸿运承物业管理中心 | O6: 东直门分中心 | P6: 安保部（应急管理中心） | Q6: 东直门分中心 | R6: 2025-12-25 23:59:59 | S6: 2025-12-22 | T6: 2025-12-23 08:59:59 | U6: 结束 | V6: 1 | W6: 经核实，市民反映场站职工警卫工作态度生硬不满问题，经了解乘客将物品丢失在运营车辆上，乘客打车到场站寻找，询问警卫人员，警卫人员告知需要联系车队值班人员协助寻找，其询问怎么说，警卫人员告知，跟车队人员说就可以，造成乘客误解警卫人员态度不好。造成市民不满。 | X6: 2025年12月22日11点33分，安保主任对投诉人员进行了电话回复，说明了原因。 办理人：侯映辉，东直门分中心安保主任。 | Y6: 东直门分中心安保专业针对这件事举一反三，要求各场站负责人对职工加强培训教育，并加强监督检查力度。 | Z6: 东直门分中心安保专业针对这件事举一反三，要求各场站负责人对职工加强培训教育，并加强监督检查力度。 | AA6: 东直门分中心安保专业针对此次事件进行了分析，加强对场站职工警卫培训教育，强化责任意识管理。 | AB6: 经核实，市民反映场站职工警卫工作态度生硬不满问题，经了解乘客将物品丢失在运营车辆上，乘客打车到场站寻找，询问警卫人员，警卫人员告知需要联系车队值班人员协助寻找，其询问怎么说，警卫人员告知，跟车队人员说就可以，造成乘客误解警卫人员态度不好。造成市民不满。 | AC6: 满意 | AD6: 个人 | AE6: 2025-12-18 22:44:21 | AF6: 1725545788 | AG6: 服务 | AH6: 否 | AK6: =AG6&L6&M6 -> 服务安保专业政策问题安保措施 | AP6: 2 | AQ6: 46023 | AR6: =IFERROR(LEFT(A6,FIND("（",A6)-1),A6) -> 热线-251218-074256-2 | AS6: =J6 -> 诉求 | AT6: =IF(MID(AR6,1,2)="热线",12345)+IF(MID(AR6,1,2)="网络",12345) -> 12345 | AU6: =IFERROR(LEFT(D6,FIND(" ",D6)-1),D6) -> 2025-12-19 | AV6: =P6 -> 安保部（应急管理中心） | AW6: =Q6 -> 东直门分中心 | AX6: =H6 -> 市民反映，自己有一个东西丢在了密云区北京公交第七客运公司，上该公司门口来领东西，女工作人员的态度特别横，自己给值班人员打电话对方态度也特别横 ，12月18日10:40自己打公交公司96166后，也未处理好此问题，来电反映北京公交第七客运公司工作人员态度恶劣等问题。 | AY6: =AG6 -> 服务 | AZ6: 否 | BA6: 否 | BB6: 否 | BC6: 七有五性,便利性、安全性 | BD6: =U6 -> 结束 | BE6: =IFERROR(LEFT(T6,FIND(" ",T6)-1),T6) -> 2025-12-23 | BF6: 场站安保问题 （寻找遗失物，反映工作人员态度） 同人同诉 多渠道 | BG6: 安保部 | BH6: 东直门分中心 | BL6: =IF(BG6="物管行政部","侯旭、郑楠",IF(BG6="安保部","张耕",IF(BG6="工程设备部","华菲",IF(BG6="人力资源部","成琦",IF(BG6="党委工作部","阎鑫雨",IF(BG6="餐饮服务部","赵弘晨",IF(BG6="工会","郑欣",IF(BG6="办公室","董娜",""))))))))&IF(BG6="纪检部","黄倩",IF(BG6="信息管理部","蔡浩然","")) -> 张耕 | BM6: 未主动剔除 | BP6: 业务类 | BQ6: 同人同诉该问题（先拨打96166反映，后拨打12345） 先拨打GJ-PHONE-20251218-2482-2、后拨打热线-251218-074256-2、热线-251218-074442-2 | BR6: 是 | BS6: 先96166后12345 | BV6: =MID(AR6,1,16) -> 热线-251218-074256 | BW6: 七有五性,便利性 | BX6: =IF(COUNTIF(BV:BV,BV6)=1,"否","是") -> 否 | BY6: =MID(AR6,18,1) -> 2 | CG6: =VLOOKUP(AR6,[1]市民意见信息导出!$AI$2:$AK$392,3,FALSE()) -> 结束 | CH6: =VLOOKUP(BV6,[2]Sheet1!$C$2:$AC$99,2,FALSE()) -> #N/A
A7: 热线-251219-045803（1个附件） | B7: 2025-12-19 15:20:09 | C7: 2025-12-19 15:30:24 | D7: 2025-12-19 15:48:19 | E7: 张女士 | F7: 女 | G7: 手机,15600000314; | H7: 市民反映，自己12月18日下午4点30分-5点期间在和平门公交站乘坐142路公交车，往丽泽桥方向行驶，乘车期间发现车窗上红色的小锤子以及窗框下面，很脏，落了一层灰尘，迟迟无人清理，后面也没有擦拭，都结成黑色的了，希望相关部门核实处理，来电反映希望142路及时清理车内卫生的问题。 | I7: 是 | J7: 诉求 | K7: 行车安全服务部 | L7: 企业政策问题 | M7: 调整服务规范 | N7: 鸿运承物业管理中心 | O7: 西客站分中心 | P7: 物管行政部 | Q7: 西客站分中心 | R7: 2025-12-26 23:59:59 | S7: 2025-12-20 | T7: 2025-12-24 08:59:59 | U7: 结束 | V7: 0 | W7: 您好，关于您反映问题的办理情况，鸿运承物业管理中心西客站分中心现对您回复如下： | X7: 我分中心已于2025年12月20日上午11点08分对您进行电话回复。办理人：穆鑫；部门：鸿运承物业管理中心西客站分中心；职务；物管副主任。审核人：郑楠；部门：鸿运承物业管理中心物管行政部；职务：物管员。 | Y7: 张女士您好，142路公交车我们在丽泽桥北场站进行洗车服务工作，您所述车辆运营中车内车窗上红色的小锤子以及窗框下面，很脏，落了一层灰尘，迟迟无人清理，后面也没有擦拭，都结成黑色的了的问题我们非常重视您的反馈，由于我们的工作没有做好，142路给您带来不好的乘车体验，实在是抱歉，张女士。该线路车辆回到丽泽桥北场站后，在日常工作时段内，我们的保洁员已对车内卫生进行了全面的清理，确保我们的出场车辆卫生符合企业标准。您反馈的问题我们已整改完毕，同时我们要求保洁员对142路所有运营车辆的卫生再次进行细化清理。我们对于运营车辆车内卫生的清洁工作是一直在做的，也从未停止，已经形成了长效的清洁机制，但有时候卫生清洁工作我们做的还有不尽人意之处，您多多谅解。 | Z7: 我们分中心及场站班组长再次与142路的保洁人员进行了沟通，日常工作中我们要把清洁质量做的更加细致，同时加强保洁员清洁技能的培训，熟练掌握清洁方法，确保给您带来一个干净、整洁的出行环境。 | AA7: 我们定期会召开车辆保洁专题会议，开展车辆卫生专项检查，日常工作中我们加大巡检力度，强化制度建设，不断提高管理水平。 | AB7: 您好，关于您反映问题的办理情况，鸿运承物业管理中心西客站分中心现对您回复如下：张女士您好，142路公交车我们在丽泽桥北场站进行洗车服务工作，您所述车辆运营中车内车窗上红色的小锤子以及窗框下面，很脏，落了一层灰尘，迟迟无人清理，后面也没有擦拭，都结成黑色的了的问题我们非常重视您的反馈，由于我们的工作没有做好，142路给您带来不好的乘车体验，实在是抱歉，张女士。该线路车辆回到丽泽桥北场站后，在日常工作时段内，我们的保洁员已对车内卫生进行了全面的清理，确保我们的出场车辆卫生符合企业标准。您反馈的问题我们已整改完毕，同时我们要求保洁员对142路所有运营车辆的卫生再次进行细化清理。我们对于运营车辆车内卫生的清洁工作是一直在做的，也从未停止，已经形成了长效的清洁机制，但有时候卫生清洁工作我们做的还有不尽人意之处，您多多谅解。我们定期会召开车辆保洁专题会议，开展车辆卫生专项检查，日常工作中我们加大巡检力度，强化制度建设，不断提高管理水平。我分中心已于2025年12月20日上午11点08分对您进行电话回复。我们分中心及场站班组长再次与142路的保洁人员进行了沟通，日常工作中我们要把清洁质量做的更加细致，同时加强保洁员清洁技能的培训，熟练掌握清洁方法，确保给您带来一个干净、整洁的出行环境。欢迎您随时对我们的工作进行监督，感谢您提出宝贵意见，给您的出行带来的不便我们和您说声抱歉，谢谢您的支持与谅解。 | AC7: 满意 | AD7: 个人 | AE7: 2025-12-19 15:16:36 | AF7: 1741937701 | AG7: 服务 | AH7: 否 | AK7: =AG7&L7&M7 -> 服务企业政策问题调整服务规范 | AP7: 3 | AQ7: 46023 | AR7: =IFERROR(LEFT(A7,FIND("（",A7)-1),A7) -> 热线-251219-045803 | AS7: =J7 -> 诉求 | AT7: =IF(MID(AR7,1,2)="热线",12345)+IF(MID(AR7,1,2)="网络",12345) -> 12345 | AU7: =IFERROR(LEFT(D7,FIND(" ",D7)-1),D7) -> 2025-12-19 | AV7: =P7 -> 物管行政部 | AW7: =Q7 -> 西客站分中心 | AX7: =H7 -> 市民反映，自己12月18日下午4点30分-5点期间在和平门公交站乘坐142路公交车，往丽泽桥方向行驶，乘车期间发现车窗上红色的小锤子以及窗框下面，很脏，落了一层灰尘，迟迟无人清理，后面也没有擦拭，都结成黑色的了，希望相关部门核实处理，来电反映希望142路及时清理车内卫生的问题。 | AY7: =AG7 -> 服务 | AZ7: 否 | BA7: 否 | BB7: 否 | BC7: 七有五性,宜居性 | BD7: =U7 -> 结束 | BE7: =IFERROR(LEFT(T7,FIND(" ",T7)-1),T7) -> 2025-12-24 | BF7: 车辆卫生问题 （车窗玻璃脏） | BG7: 物管行政部 | BH7: 西客站分中心 | BL7: =IF(BG7="物管行政部","侯旭、郑楠",IF(BG7="安保部","张耕",IF(BG7="工程设备部","华菲",IF(BG7="人力资源部","成琦",IF(BG7="党委工作部","阎鑫雨",IF(BG7="餐饮服务部","赵弘晨",IF(BG7="工会","郑欣",IF(BG7="办公室","董娜",""))))))))&IF(BG7="纪检部","黄倩",IF(BG7="信息管理部","蔡浩然","")) -> 侯旭、郑楠 | BM7: 未主动剔除 | BP7: 业务类 | BV7: =MID(AR7,1,16) -> 热线-251219-045803 | BW7: 七有五性,便利性 | BX7: =IF(COUNTIF(BV:BV,BV7)=1,"否","是") -> 否 | BY7: =MID(AR7,18,1) | BZ7: 只评价响应率 | CE7: 1月 | CG7: =VLOOKUP(AR7,[1]市民意见信息导出!$AI$2:$AK$392,3,FALSE()) -> 结束 | CH7: =VLOOKUP(BV7,[2]Sheet1!$C$2:$AC$99,2,FALSE()) -> 1月
A8: 热线-251218-074442-2（1个附件） | B8: 2025-12-19 17:03:20 | C8: 2025-12-19 17:10:19 | D8: 2025-12-19 18:06:50 | E8: 李先生 | F8: 男 | G8: 手机,15120055651; | H8: 市民反映，密云区北京公交第七客运公司，2025年12月18日22:15自己丢东西了来这里找东西，门口的三个女的值班人员态度非常差，自己拨打值班电话89012827态度更加恶劣，短头发值班女士态度恶劣，8907值班男士态度不好，司机态度好，但是值班人员把责任往司机身上推，希望相关部门核实处理，从自己十点十分到这儿一直现在没有任何一个工作人员跟自己处理这个事情，职能部门使用私人电话18515596640回复自己，态度差，值班人员态度差，来电反映密云区北京公交第七客运公司值班人员态度差问题。注：市民要求2025年12月19日上午十点后回复。工单流转：密云区分中心退回：经与市民核实，北京公交第七客运公司属于公交集团监管，不属于密云区域公交监管范畴，请北京市公交集团处理市民诉求。对答复不满意 | I8: 是 | J8: 其他 | K8: 安保部（应急管理中心） | L8: 安保专业其他问题 | M8: 安保专业补充内容 | N8: 鸿运承物业管理中心 | O8: 东直门分中心 | P8: 安全保卫部（应急管理中心） | Q8: 东直门分中心 | R8: 2025-12-26 23:59:59 | S8: 2025-12-22 | T8: 2025-12-24 08:59:59 | U8: 结束 | V8: 0 | W8: 经核实，市民反映场站职工警卫工作态度生硬不满问题，经了解乘客将物品丢失在运营车辆上，乘客打车到场站寻找，询问警卫人员，警卫人员告知需要联系车队值班人员协助寻找，其询问怎么说，警卫人员告知，跟车队人员说就可以，造成乘客误解警卫人员态度不好。造成市民不满。 | X8: 2025年12月22日11点33分，安保主任对投诉人员进行了电话回复，说明了原因。 办理人：侯映辉，东直门分中心安保主任。 | Y8: 东直门分中心安保专业针对这件事举一反三，要求各场站负责人对职工加强培训教育，并加强监督检查力度。 | Z8: 东直门分中心安保专业针对这件事举一反三，要求各场站负责人对职工加强培训教育，并加强监督检查力度。 | AA8: 东直门分中心安保专业针对此次事件进行了分析，加强对场站职工警卫培训教育，强化责任意识管理。 | AB8: 经核实，市民反映场站职工警卫工作态度生硬不满问题，经了解乘客将物品丢失在运营车辆上，乘客打车到场站寻找，询问警卫人员，警卫人员告知需要联系车队值班人员协助寻找，其询问怎么说，警卫人员告知，跟车队人员说就可以，造成乘客误解警卫人员态度不好。造成市民不满。 | AC8: 满意 | AD8: 个人 | AE8: 2025-12-18 22:54:16 | AF8: 1725545788 | AG8: 服务 | AH8: 否 | AK8: =AG8&L8&M8 -> 服务安保专业其他问题安保专业补充内容 | AP8: 4 | AQ8: 46023 | AR8: =IFERROR(LEFT(A8,FIND("（",A8)-1),A8) -> 热线-251218-074442-2 | AS8: =J8 -> 其他 | AT8: =IF(MID(AR8,1,2)="热线",12345)+IF(MID(AR8,1,2)="网络",12345) -> 12345 | AU8: =IFERROR(LEFT(D8,FIND(" ",D8)-1),D8) -> 2025-12-19 | AV8: =P8 -> 安全保卫部（应急管理中心） | AW8: =Q8 -> 东直门分中心 | AX8: =H8 -> 市民反映，密云区北京公交第七客运公司，2025年12月18日22:15自己丢东西了来这里找东西，门口的三个女的值班人员态度非常差，自己拨打值班电话89012827态度更加恶劣，短头发值班女士态度恶劣，8907值班男士态度不好，司机态度好，但是值班人员把责任往司机身上推，希望相关部门核实处理，从自己十点十分到这儿一直现在没有任何一个工作人员跟自己处理这个事情，职能部门使用私人电话18515596640回复自己，态度差，值班人员态度差，来电反映密云区北京公交第七客运公司值班人员态度差问题。注：市民要求2025年12月19日上午十点后回复。工单流转：密云区分中心退回：经与市民核实，北京公交第七客运公司属于公交集团监管，不属于密云区域公交监管范畴，请北京市公交集团处理市民诉求。对答复不满意 | AY8: =AG8 -> 服务 | AZ8: 否 | BA8: 否 | BB8: 否 | BC8: 七有五性,便利性、安全性 | BD8: =U8 -> 结束 | BE8: =IFERROR(LEFT(T8,FIND(" ",T8)-1),T8) -> 2025-12-24 | BF8: 场站安保问题 （寻找遗失物，反映工作人员态度） 同人同诉 多渠道 | BG8: 安保部 | BH8: 东直门分中心 | BL8: =IF(BG8="物管行政部","侯旭、郑楠",IF(BG8="安保部","张耕",IF(BG8="工程设备部","华菲",IF(BG8="人力资源部","成琦",IF(BG8="党委工作部","阎鑫雨",IF(BG8="餐饮服务部","赵弘晨",IF(BG8="工会","郑欣",IF(BG8="办公室","董娜",""))))))))&IF(BG8="纪检部","黄倩",IF(BG8="信息管理部","蔡浩然","")) -> 张耕 | BM8: 未主动剔除 | BP8: 业务类 | BQ8: 同人同诉该问题（先拨打96166反映，后拨打12345） 先拨打GJ-PHONE-20251218-2482-2、后拨打热线-251218-074256-2、热线-251218-074442-2 | BR8: 是 | BS8: 先96166后12345 | BV8: =MID(AR8,1,16) -> 热线-251218-074442 | BW8: 七有五性,便利性 | BX8: =IF(COUNTIF(BV:BV,BV8)=1,"否","是") -> 否 | BY8: =MID(AR8,18,1) -> 2 | BZ8: 只评价响应率 | CE8: 1月 | CG8: =VLOOKUP(AR8,[1]市民意见信息导出!$AI$2:$AK$392,3,FALSE()) -> 结束 | CH8: =VLOOKUP(BV8,[2]Sheet1!$C$2:$AC$99,2,FALSE()) -> 1月
A9: 网络-251220-031514 | B9: 2025-12-20 14:53:10 | C9: 2025-12-20 15:04:49 | D9: 2025-12-20 15:09:56 | E9: 保密 | F9: 女 | G9: 保密 | H9: 工单来源：微信服务号，此工单内容为网民留言时填写的标题及原文。 ============================= 留言标题：120公交车辆卫生差留言原文：今早在天坛乘坐120公交车，发现车内卫生脏，座椅有灰尘，座椅缝隙全是垃圾。希望有关部门加强管理。市民填写的详细地址为：区、街道：东城区天坛街道详细地址：天桥120公交车辆卫生差问题 | I9: 是 | J9: 诉求 | K9: 行车安全服务部 | L9: 乘车环境问题 | M9: 车辆卫生 | N9: 鸿运承物业管理中心 | O9: 动物园分中心 | P9: 物管行政部 | Q9: 动物园分中心 | R9: 2025-12-27 23:59:59 | S9: 2025-12-22 | T9: 2025-12-25 08:59:59 | U9: 结束 | V9: 0 | W9: 您好，关于您反映问题的办理情况，鸿运承物业管理中心动物园分中心现对您回复如下： | X9: 因您的联系方式保密，我们未能对您进行电话回复。办理人：杜伟；部门：鸿运承物业管理中心动物园分中心；职务；物管副主任。审核人：郑楠；部门：鸿运承物业管理中心物管行政部；职务：物管员。 | Y9: 女士您好，120路公交车我们在左家庄场站进行洗车服务工作，您所述车辆运营中车内卫生脏，座椅有灰尘，座椅缝隙全是垃圾的问题我们非常重视您的反馈，由于我们的工作没有做好，120路给您带来不好的乘车体验，实在是抱歉，女士。该线路车辆回到左家庄场站后，在日常工作时段内，我们的保洁员已对车内座椅卫生进行了全面的清理，确保我们的出场车辆卫生符合企业标准。您反馈的问题我们已整改完毕，同时我们要求保洁员对120路所有运营车辆的卫生再次进行细化清理。我们对于运营车辆车内卫生的清洁工作是一直在做的，也从未停止，已经形成了长效的清洁机制，但有时候卫生清洁工作我们做的还有不尽人意之处，您多多谅解。 | Z9: 我们分中心及场站班组长再次与120路的保洁人员进行了沟通，日常工作中我们要把清洁质量做的更加细致，同时加强保洁员清洁技能的培训，熟练掌握清洁方法，确保给您带来一个干净、整洁的出行环境。 | AA9: 我们定期会召开车辆保洁专题会议，开展车辆卫生专项检查，日常工作中我们加大巡检力度，强化制度建设，不断提高管理水平。 | AB9: 欢迎您随时对我们的工作进行监督，感谢您提出宝贵意见，给您的出行带来的不便我们和您说声抱歉，谢谢您的支持与谅解。 | AC9: 满意 | AD9: 个人 | AE9: 2025-12-20 09:53:24 | AF9: 1741937703 | AG9: 服务 | AH9: 否 | AK9: =AG9&L9&M9 -> 服务乘车环境问题车辆卫生 | AP9: 5 | AQ9: 46023 | AR9: =IFERROR(LEFT(A9,FIND("（",A9)-1),A9) -> 网络-251220-031514 | AS9: =J9 -> 诉求 | AT9: =IF(MID(AR9,1,2)="热线",12345)+IF(MID(AR9,1,2)="网络",12345) -> 12345 | AU9: =IFERROR(LEFT(D9,FIND(" ",D9)-1),D9) -> 2025-12-20 | AV9: =P9 -> 物管行政部 | AW9: =Q9 -> 动物园分中心 | AX9: =H9 -> 工单来源：微信服务号，此工单内容为网民留言时填写的标题及原文。 ============================= 留言标题：120公交车辆卫生差留言原文：今早在天坛乘坐120公交车，发现车内卫生脏，座椅有灰尘，座椅缝隙全是垃圾。希望有关部门加强管理。市民填写的详细地址为：区、街道：东城区天坛街道详细地址：天桥120公交车辆卫生差问题 | AY9: =AG9 -> 服务 | AZ9: 否 | BA9: 否 | BB9: 否 | BC9: 七有五性,宜居性 | BD9: =U9 -> 结束 | BE9: =IFERROR(LEFT(T9,FIND(" ",T9)-1),T9) -> 2025-12-25 | BF9: 车辆卫生问题 （车内卫生脏、座椅脏） | BG9: 物管行政部 | BH9: 动物园分中心 | BL9: =IF(BG9="物管行政部","侯旭、郑楠",IF(BG9="安保部","张耕",IF(BG9="工程设备部","华菲",IF(BG9="人力资源部","成琦",IF(BG9="党委工作部","阎鑫雨",IF(BG9="餐饮服务部","赵弘晨",IF(BG9="工会","郑欣",IF(BG9="办公室","董娜",""))))))))&IF(BG9="纪检部","黄倩",IF(BG9="信息管理部","蔡浩然","")) -> 侯旭、郑楠 | BM9: 未主动剔除 | BP9: 业务类 | BV9: =MID(AR9,1,16) -> 网络-251220-031514 | BW9: 七有五性,便利性 | BX9: =IF(COUNTIF(BV:BV,BV9)=1,"否","是") -> 否 | BY9: =MID(AR9,18,1) | CG9: =VLOOKUP(AR9,[1]市民意见信息导出!$AI$2:$AK$392,3,FALSE()) -> 结束 | CH9: =VLOOKUP(BV9,[2]Sheet1!$C$2:$AC$99,2,FALSE()) -> #N/A
A10: 网络-251221-010505 | B10: 2025-12-21 10:30:51 | C10: 2025-12-21 10:45:49 | D10: 2025-12-21 11:07:04 | E10: 保密 | F10: 女 | G10: 保密 | H10: 工单来源：微信服务号，此工单内容为网民留言时填写的标题及原文。============================= 留言标题：362车卫生问题留言原文：今天下午从人民医院看完病在西直门南座362公交车,上车发现扶手又黑又脏,现在冬季传染病多车内卫生差.容易交叉感染。希望改正加强管理。市民填写的详细地址为：区、街道：海淀区花园路街道详细地址：西直门 | I10: 是 | J10: 诉求 | K10: 行车安全服务部 | L10: 乘车环境问题 | M10: 车辆卫生 | N10: 鸿运承物业管理中心 | O10: 动物园分中心 | P10: 物管行政部 | Q10: 动物园分中心 | R10: 2025-12-28 23:59:59 | S10: 2025-12-22 | T10: 2025-12-26 08:59:59 | U10: 结束 | V10: 0 | W10: 您好，关于您反映问题的办理情况，鸿运承物业管理中心动物园分中心现对您回复如下： | X10: 因您的联系方式保密，我们未能对您进行电话回复。办理人：杜伟；部门：鸿运承物业管理中心动物园分中心；职务；物管副主任。审核人：郑楠；部门：鸿运承物业管理中心物管行政部；职务：物管员。 | Y10: 女士您好，362路公交车我们在西直门南场站进行洗车服务工作，您所述车辆运营中扶手又黑又脏的问题我们非常重视您的反馈，由于我们的工作没有做好，362路给您带来不好的乘车体验，实在是抱歉，女士。该线路车辆回到西直门南场站后，在日常工作时段内，我们的保洁员已对车内扶手卫生进行了全面的清理，确保我们的出场车辆卫生符合企业标准。您反馈的问题我们已整改完毕，同时我们要求保洁员对362路所有运营车辆的卫生再次进行细化清理。我们对于运营车辆车内卫生的清洁工作是一直在做的，也从未停止，已经形成了长效的清洁机制，但有时候卫生清洁工作我们做的还有不尽人意之处，您多多谅解。 | Z10: 我们分中心及场站班组长再次与362路的保洁人员进行了沟通，日常工作中我们要把清洁质量做的更加细致，同时加强保洁员清洁技能的培训，熟练掌握清洁方法，确保给您带来一个干净、整洁的出行环境。 | AA10: 我们定期会召开车辆保洁专题会议，开展车辆卫生专项检查，日常工作中我们加大巡检力度，强化制度建设，不断提高管理水平。 | AB10: 欢迎您随时对我们的工作进行监督，感谢您提出宝贵意见，给您的出行带来的不便我们和您说声抱歉，谢谢您的支持与谅解。 | AC10: 满意 | AD10: 个人 | AE10: 2025-12-20 18:13:34 | AF10: 1741937703 | AG10: 服务 | AH10: 否 | AK10: =AG10&L10&M10 -> 服务乘车环境问题车辆卫生 | AP10: 6 | AQ10: 46023 | AR10: =IFERROR(LEFT(A10,FIND("（",A10)-1),A10) -> 网络-251221-010505 | AS10: =J10 -> 诉求 | AT10: =IF(MID(AR10,1,2)="热线",12345)+IF(MID(AR10,1,2)="网络",12345) -> 12345 | AU10: =IFERROR(LEFT(D10,FIND(" ",D10)-1),D10) -> 2025-12-21 | AV10: =P10 -> 物管行政部 | AW10: =Q10 -> 动物园分中心 | AX10: =H10 -> 工单来源：微信服务号，此工单内容为网民留言时填写的标题及原文。============================= 留言标题：362车卫生问题留言原文：今天下午从人民医院看完病在西直门南座362公交车,上车发现扶手又黑又脏,现在冬季传染病多车内卫生差.容易交叉感染。希望改正加强管理。市民填写的详细地址为：区、街道：海淀区花园路街道详细地址：西直门 | AY10: =AG10 -> 服务 | AZ10: 否 | BA10: 否 | BB10: 否 | BC10: 七有五性,宜居性 | BD10: =U10 -> 结束 | BE10: =IFERROR(LEFT(T10,FIND(" ",T10)-1),T10) -> 2025-12-26 | BF10: 车辆卫生问题 （车内扶手脏） | BG10: 物管行政部 | BH10: 动物园分中心 | BL10: =IF(BG10="物管行政部","侯旭、郑楠",IF(BG10="安保部","张耕",IF(BG10="工程设备部","华菲",IF(BG10="人力资源部","成琦",IF(BG10="党委工作部","阎鑫雨",IF(BG10="餐饮服务部","赵弘晨",IF(BG10="工会","郑欣",IF(BG10="办公室","董娜",""))))))))&IF(BG10="纪检部","黄倩",IF(BG10="信息管理部","蔡浩然","")) -> 侯旭、郑楠 | BM10: 未主动剔除 | BP10: 业务类 | BV10: =MID(AR10,1,16) -> 网络-251221-010505 | BW10: 七有五性,便利性 | BX10: =IF(COUNTIF(BV:BV,BV10)=1,"否","是") -> 否 | BY10: =MID(AR10,18,1) | CG10: =VLOOKUP(AR10,[1]市民意见信息导出!$AI$2:$AK$392,3,FALSE()) -> 结束 | CH10: =VLOOKUP(BV10,[2]Sheet1!$C$2:$AC$99,2,FALSE()) -> #N/A
A11: 热线-251221-020766-1（1个附件） | B11: 2025-12-21 15:27:36 | C11: 2025-12-21 15:30:26 | D11: 2025-12-21 15:47:06 | E11: 张女士 | F11: 女 | G11: 手机,15600091981; | H11: 市民反映，自己是北京公交集团鸿运承物业管理中心方庄分中心的职工，领导给自己发了一条通知要求12月上网课（匠心筑梦技能领航主题线上活动），没有说是自主学还是必须学，市民问领导该网课是否是必须上的，领导不予正面回复，问工会和党委书记不仅不答复市民还对市民大呼小叫，如果必须上的企业该给自己承担和网费，休息时间学要付加班费，注册地址：北京市西城区南礼士路44号，来电反映企业领导的指示不明确及工会和党委书记态度不好不作为问题。企业领导的指示不明确及工会和党委书记态度不好不作为问题企业领导的指示不明确及工会和党委书记态度不好不作为问题组织人力 | I11: 是 | J11: 诉求 | K11: 党委组织部（统战部） | L11: 领导干部问题 | M11: 领导行为不当 | N11: 鸿运承物业管理中心 | O11: 党委工作部 | P11: 党委工作部 | Q11: 机关 | R11: 2025-12-28 23:59:59 | S11: 2025-12-22 | T11: 2025-12-26 08:59:59 | U11: 结束 | V11: 0 | W11: 接到市民反映的问题后，我们立即进行了核实，经核实，与实际情况不符。 | X11: 接到市民反映的问题后，党委工作部立即进行核实，经核实，投诉内容与事实不符，不存在投诉人反映的情况，方庄分中心不存在管理人员大喊大叫的行为，感谢职工对我们工作中的不足提出宝贵意见，党委工作部会继续做好干部监督管理。办理人：高伟；部门：鸿运承物业管理中心党委工作部；职务：党委工作部副部长。审核人：吕东霞；职务：党委工作部部长。 | Y11: 无。 | Z11: 无。 | AA11: 无。 | AB11: 接到市民反映的问题后，党委工作部立即进行核实，经核实，投诉内容与事实不符，不存在投诉人反映的情况，方庄分中心不存在管理人员大喊大叫的行为，感谢职工对我们工作中的不足提出宝贵意见，党委工作部会继续做好干部监督管理。 | AC11: 满意 | AD11: 个人 | AE11: 2025-12-21 13:15:02 | AF11: 1047563 | AG11: 劳动合同及用工管理 | AH11: 否 | AK11: =AG11&L11&M11 -> 劳动合同及用工管理领导干部问题领导行为不当 | AP11: 7 | AQ11: 46023 | AR11: =IFERROR(LEFT(A11,FIND("（",A11)-1),A11) -> 热线-251221-020766-1 | AS11: =J11 -> 诉求 | AT11: =IF(MID(AR11,1,2)="热线",12345)+IF(MID(AR11,1,2)="网络",12345) -> 12345 | AU11: =IFERROR(LEFT(D11,FIND(" ",D11)-1),D11) -> 2025-12-21 | AV11: =P11 -> 党委工作部 | AW11: =Q11 -> 机关 | AX11: =H11 -> 市民反映，自己是北京公交集团鸿运承物业管理中心方庄分中心的职工，领导给自己发了一条通知要求12月上网课（匠心筑梦技能领航主题线上活动），没有说是自主学还是必须学，市民问领导该网课是否是必须上的，领导不予正面回复，问工会和党委书记不仅不答复市民还对市民大呼小叫，如果必须上的企业该给自己承担和网费，休息时间学要付加班费，注册地址：北京市西城区南礼士路44号，来电反映企业领导的指示不明确及工会和党委书记态度不好不作为问题。企业领导的指示不明确及工会和党委书记态度不好不作为问题企业领导的指示不明确及工会和党委书记态度不好不作为问题组织人力 | AY11: =AG11 -> 劳动合同及用工管理 | AZ11: 是 | BA11: 是 | BB11: 否 | BC11: 七有五性,公正性 | BD11: =U11 -> 结束 | BE11: =IFERROR(LEFT(T11,FIND(" ",T11)-1),T11) -> 2025-12-26 | BF11: 管理人员工作态度 （网上培训学习）拆单 | BG11: 党委工作部 | BH11: 机关 | BL11: =IF(BG11="物管行政部","侯旭、郑楠",IF(BG11="安保部","张耕",IF(BG11="工程设备部","华菲",IF(BG11="人力资源部","成琦",IF(BG11="党委工作部","阎鑫雨",IF(BG11="餐饮服务部","赵弘晨",IF(BG11="工会","郑欣",IF(BG11="办公室","董娜",""))))))))&IF(BG11="纪检部","黄倩",IF(BG11="信息管理部","蔡浩然","")) -> 阎鑫雨 | BM11: 未主动剔除 | BP11: 政策类 | BQ11: 拆单问题（内部职工拨打） | BT11: 由党工部、人力资源办理 | BV11: =MID(AR11,1,16) -> 热线-251221-020766 | BW11: 七有五性,劳有所得 | BX11: =IF(COUNTIF(BV:BV,BV11)=1,"否","是") -> 是 | BY11: =MID(AR11,18,1) -> 1 | BZ11: 只评价响应率 | CE11: 1月 | CG11: =VLOOKUP(AR11,[1]市民意见信息导出!$AI$2:$AK$392,3,FALSE()) -> 结束 | CH11: =VLOOKUP(BV11,[2]Sheet1!$C$2:$AC$99,2,FALSE()) -> 1月
A12: 热线-251221-020766-2（1个附件） | B12: 2025-12-21 15:27:36 | C12: 2025-12-21 15:30:26 | D12: 2025-12-21 15:47:05 | E12: 张女士 | F12: 女 | G12: 手机,15600091981; | H12: 市民反映，自己是北京公交集团鸿运承物业管理中心方庄分中心的职工，领导给自己发了一条通知要求12月上网课（匠心筑梦技能领航主题线上活动），没有说是自主学还是必须学，市民问领导该网课是否是必须上的，领导不予正面回复，问工会和党委书记不仅不答复市民还对市民大呼小叫，如果必须上的企业该给自己承担和网费，休息时间学要付加班费，注册地址：北京市西城区南礼士路44号，来电反映企业领导的指示不明确及工会和党委书记态度不好不作为问题。企业领导的指示不明确及工会和党委书记态度不好不作为问题企业领导的指示不明确及工会和党委书记态度不好不作为问题组织人力 | I12: 是 | J12: 诉求 | K12: 人力资源部（人力资源发展中心） | L12: 培训及福利 | M12: 职工培训 | N12: 鸿运承物业管理中心 | O12: 方庄分中心 | P12: 人力资源部 | Q12: 方庄分中心 | R12: 2025-12-28 23:59:59 | S12: 2025-12-22 | T12: 2025-12-26 08:59:59 | U12: 结束 | V12: 0 | W12: 经核实，来电人反映情况与实际不符，接到诉求后第一时间给职工讲解“匠心筑梦 技能领航”主题线上活动通知内容。 | X12: 2025年12月22日 上午11点02分电话回复来电人，我分中心劳动专业接到诉求后，第一时间给职工讲解“匠心筑梦 技能领航”主题线上活动通知内容，并进一步给职工解释本次活动以专栏学习、知识竞赛形式开展，职工可自愿参加。经过与来电人沟通，来电人表示知晓。办理人：吕琦，鸿运承物业管理中心方庄分中心，职务一般管理；审核人：高强；部门：鸿运承物业管理中心人力资源部；职务：中级管理。 | Y12: 2025年12月22日 上午11点02分电话回复来电人，我分中心劳动专业接到诉求后，第一时间给职工讲解“匠心筑梦 技能领航”主题线上活动通知内容，并进一步给职工解释本次活动以专栏学习、知识竞赛形式开展，职工可自愿参加。经过与来电人沟通，来电人表示知晓。 | Z12: 无 | AA12: 无 | AB12: 2025年12月22日 上午11点02分电话回复来电人，我分中心劳动专业接到诉求后，第一时间给职工讲解“匠心筑梦 技能领航”主题线上活动通知内容，并进一步给职工解释本次活动以专栏学习、知识竞赛形式开展，职工可自愿参加。经过与来电人沟通，来电人表示知晓。 | AC12: 满意 | AD12: 个人 | AE12: 2025-12-21 13:15:02 | AF12: 1741937709 | AG12: 劳动合同及用工管理 | AH12: 否 | AK12: =AG12&L12&M12 -> 劳动合同及用工管理培训及福利职工培训 | AP12: 8 | AQ12: 46023 | AR12: =IFERROR(LEFT(A12,FIND("（",A12)-1),A12) -> 热线-251221-020766-2 | AS12: =J12 -> 诉求 | AT12: =IF(MID(AR12,1,2)="热线",12345)+IF(MID(AR12,1,2)="网络",12345) -> 12345 | AU12: =IFERROR(LEFT(D12,FIND(" ",D12)-1),D12) -> 2025-12-21 | AV12: =P12 -> 人力资源部 | AW12: =Q12 -> 方庄分中心 | AX12: =H12 -> 市民反映，自己是北京公交集团鸿运承物业管理中心方庄分中心的职工，领导给自己发了一条通知要求12月上网课（匠心筑梦技能领航主题线上活动），没有说是自主学还是必须学，市民问领导该网课是否是必须上的，领导不予正面回复，问工会和党委书记不仅不答复市民还对市民大呼小叫，如果必须上的企业该给自己承担和网费，休息时间学要付加班费，注册地址：北京市西城区南礼士路44号，来电反映企业领导的指示不明确及工会和党委书记态度不好不作为问题。企业领导的指示不明确及工会和党委书记态度不好不作为问题企业领导的指示不明确及工会和党委书记态度不好不作为问题组织人力 | AY12: =AG12 -> 劳动合同及用工管理 | AZ12: 是 | BA12: 是 | BB12: 否 | BC12: 七有五性,公正性 | BD12: =U12 -> 结束 | BE12: =IFERROR(LEFT(T12,FIND(" ",T12)-1),T12) -> 2025-12-26 | BF12: 劳动人员管理及劳动纪律 （网上培训学习）拆单 | BG12: 人力资源部 | BH12: 方庄分中心 | BL12: =IF(BG12="物管行政部","侯旭、郑楠",IF(BG12="安保部","张耕",IF(BG12="工程设备部","华菲",IF(BG12="人力资源部","成琦",IF(BG12="党委工作部","阎鑫雨",IF(BG12="餐饮服务部","赵弘晨",IF(BG12="工会","郑欣",IF(BG12="办公室","董娜",""))))))))&IF(BG12="纪检部","黄倩",IF(BG12="信息管理部","蔡浩然","")) -> 成琦 | BM12: 未主动剔除 | BP12: 政策类 | BQ12: 拆单问题（内部职工拨打） | BT12: 由党工部、人力资源办理 | BV12: =MID(AR12,1,16) -> 热线-251221-020766 | BW12: 七有五性,劳有所得 | BX12: =IF(COUNTIF(BV:BV,BV12)=1,"否","是") -> 是 | BY12: =MID(AR12,18,1) -> 2 | BZ12: 只评价响应率 | CE12: 1月 | CG12: =VLOOKUP(AR12,[1]市民意见信息导出!$AI$2:$AK$392,3,FALSE()) -> 结束 | CH12: =VLOOKUP(BV12,[2]Sheet1!$C$2:$AC$99,2,FALSE()) -> 1月
A13: 热线-251222-018664（3个附件） | B13: 2025-12-22 10:56:00 | C13: 2025-12-22 11:28:39 | D13: 2025-12-22 11:29:48 | E13: 胡亚静女士 | F13: 女 | G13: 手机,13716588237; | H13: 市民反映，市民是公交集团鸿运承物业管理中心的职工，鸿运承物业管理中心作为公交集团的下属二级单位，从2022年7月1日至2023年8月，鸿运承物业管理中心违背北京公交集团下发的红头文件内容，违法给部分综合站务员B岗C岗职工转为综合站务员A岗，这些转岗人员并没有履行集团公司下发红头文件的综合站务员A岗岗位职责等内容，直接目的是为了追求A岗工资，这番操作直接浪费了公交集团大量资金，从而使综合站务员A岗人员杂乱不堪，以至于综合站务员A岗人员称呼多样，如老综A，旧综A，原综A，后转综A，现在又弄出新综A，从今年3月份开始，鸿运承在没有任何集团下发文件的前提下，把违规转岗的A岗职工保护起来，反而针对性给受红头文件保护的职工恶意调岗，共进行三次恶意调岗，性质特别恶劣，致使被针对职工，身心收到严重创伤，11月27日鸿运承人力资源部经理和工会主席，都承认此次改革是在没有集团公司相关书面文件前提下进行的，在我们坚持一切以劳动法为根基的基础上，他们承诺去和集团领导协商获取有效文件，并且还承诺一定会给职工明确答复，有录音为证，但现在在没有任何答复的前提下，12月26日已经停止排班，已下发排班表，我们职工真心不明白，身为下属二级单位领导，身为共产党干部，怎么会做出霸权主义的事情，敬请北京公交集团相关领导给予职工明确回复，职工姓名：胡亚静，来电反映敬请北京公交集团相关领导给予职工明确回复的问题。 | I13: 是 | J13: 诉求 | K13: 人力资源部（人力资源发展中心） | L13: 工资及五险二金 | M13: 工资方面 | N13: 鸿运承物业管理中心 | O13: 凌家庙分中心 | P13: 人力资源部 | Q13: 凌家庙分中心 | R13: 2025-12-29 23:59:59 | S13: 2025-12-25 | T13: 2025-12-27 08:59:59 | U13: 结束 | V13: 1 | W13: 经核实，与来电人所述情况存在出入。来电人胡亚静为我单位凌家庙分中心职工，此前我单位并未对来电人进行转岗，不涉及来电人所述的恶意调岗问题。本次企业改革是根据《鸿运承物业管理中心综合站务员优化配置改革工作实施方案》、《鸿运承物业管理中心综合站务员A岗管理规定（试行）》等制度文件开展，我单位为落选的原综A人员提供4类转岗安置方案。此前我单位凌家庙分中心于2025年11月27日、12月11日以及22日多次与来电人进行面对面的沟通，来电人均表示坚决拒绝调整A岗安置工作。 | X13: 经核实，与来电人所述情况存在出入。来电人胡亚静为我单位凌家庙分中心职工，此前我单位并未对来电人进行转岗，不涉及来电人所述的恶意调岗问题。本次企业改革是根据《鸿运承物业管理中心综合站务员优化配置改革工作实施方案》、《鸿运承物业管理中心综合站务员A岗管理规定（试行）》等制度文件开展，我单位为落选的原综A人员提供4类转岗安置方案。此前我单位凌家庙分中心于2025年11月27日、12月11日以及22日多次与来电人进行面对面的沟通，来电人均表示坚决拒绝调整A岗安置工作。 接到诉求后，我单位凌家庙分中心于2025年12月25日9点53分电话回复来电人，来电人将电话挂断，故我单位再次通过短信形式告知来电人办理结果。 办理人：王跃，鸿运承物业管理中心凌家庙分中心，职务：一般管理； 审核人：高强；部门：鸿运承物业管理中心人力资源部；职务：中级管理。 | Y13: 接到诉求后，我单位凌家庙分中心于2025年12月25日9点53分电话回复来电人，来电人将电话挂断，故我单位再次通过短信形式告知来电人办理结果。 | Z13: 无 | AA13: 无 | AB13: 经核实，与来电人所述情况存在出入。来电人胡亚静为我单位凌家庙分中心职工，此前我单位并未对来电人进行转岗，不涉及来电人所述的恶意调岗问题。本次企业改革是根据《鸿运承物业管理中心综合站务员优化配置改革工作实施方案》、《鸿运承物业管理中心综合站务员A岗管理规定（试行）》等制度文件开展，我单位为落选的原综A人员提供4类转岗安置方案。此前我单位凌家庙分中心于2025年11月27日、12月11日以及22日多次与来电人进行面对面的沟通，来电人均表示坚决拒绝调整A岗安置工作。 接到诉求后，我单位凌家庙分中心于2025年12月25日9点53分电话回复来电人，来电人将电话挂断，故我单位再次通过短信形式告知来电人办理结果。 | AC13: 满意 | AD13: 个人 | AE13: 2025-12-22 10:37:01 | AF13: 1862108387 | AG13: 运营调度 | AH13: 否 | AK13: =AG13&L13&M13 -> 运营调度工资及五险二金工资方面 | AP13: 9 | AQ13: 46023 | AR13: =IFERROR(LEFT(A13,FIND("（",A13)-1),A13) -> 热线-251222-018664 | AS13: =J13 -> 诉求 | AT13: =IF(MID(AR13,1,2)="热线",12345)+IF(MID(AR13,1,2)="网络",12345) -> 12345 | AU13: =IFERROR(LEFT(D13,FIND(" ",D13)-1),D13) -> 2025-12-22 | AV13: =P13 -> 人力资源部 | AW13: =Q13 -> 凌家庙分中心 | AX13: =H13 -> 市民反映，市民是公交集团鸿运承物业管理中心的职工，鸿运承物业管理中心作为公交集团的下属二级单位，从2022年7月1日至2023年8月，鸿运承物业管理中心违背北京公交集团下发的红头文件内容，违法给部分综合站务员B岗C岗职工转为综合站务员A岗，这些转岗人员并没有履行集团公司下发红头文件的综合站务员A岗岗位职责等内容，直接目的是为了追求A岗工资，这番操作直接浪费了公交集团大量资金，从而使综合站务员A岗人员杂乱不堪，以至于综合站务员A岗人员称呼多样，如老综A，旧综A，原综A，后转综A，现在又弄出新综A，从今年3月份开始，鸿运承在没有任何集团下发文件的前提下，把违规转岗的A岗职工保护起来，反而针对性给受红头文件保护的职工恶意调岗，共进行三次恶意调岗，性质特别恶劣，致使被针对职工，身心收到严重创伤，11月27日鸿运承人力资源部经理和工会主席，都承认此次改革是在没有集团公司相关书面文件前提下进行的，在我们坚持一切以劳动法为根基的基础上，他们承诺去和集团领导协商获取有效文件，并且还承诺一定会给职工明确答复，有录音为证，但现在在没有任何答复的前提下，12月26日已经停止排班，已下发排班表，我们职工真心不明白，身为下属二级单位领导，身为共产党干部，怎么会做出霸权主义的事情，敬请北京公交集团相关领导给予职工明确回复，职工姓名：胡亚静，来电反映敬请北京公交集团相关领导给予职工明确回复的问题。 | AY13: =AG13 -> 运营调度 | AZ13: 是 | BA13: 是 | BB13: 否 | BC13: 七有五性,公正性 | BD13: =U13 -> 结束 | BE13: =IFERROR(LEFT(T13,FIND(" ",T13)-1),T13) -> 2025-12-27 | BF13: 劳动人员调配及薪酬 （公开选聘综A岗-学历问题） 多渠道同人同诉 | BG13: 人力资源部 | BH13: 凌家庙分中心 | BL13: =IF(BG13="物管行政部","侯旭、郑楠",IF(BG13="安保部","张耕",IF(BG13="工程设备部","华菲",IF(BG13="人力资源部","成琦",IF(BG13="党委工作部","阎鑫雨",IF(BG13="餐饮服务部","赵弘晨",IF(BG13="工会","郑欣",IF(BG13="办公室","董娜",""))))))))&IF(BG13="纪检部","黄倩",IF(BG13="信息管理部","蔡浩然","")) -> 成琦 | BM13: 未主动剔除 | BP13: 政策类 | BQ13: 综A公开招聘，针对政策条件不认可。（同人同诉）：热线-250611-039775、热线-250611-059472-1、热线-250618-048072-1、热线-250708-035022、热线-251222-018664 | BR13: 是 | BS13: 先96166后12345 | BV13: =MID(AR13,1,16) -> 热线-251222-018664 | BW13: 七有五性,便利性 | BX13: =IF(COUNTIF(BV:BV,BV13)=1,"否","是") -> 否 | BY13: =MID(AR13,18,1) | CG13: =VLOOKUP(AR13,[1]市民意见信息导出!$AI$2:$AK$392,3,FALSE()) -> 结束 | CH13: =VLOOKUP(BV13,[2]Sheet1!$C$2:$AC$99,2,FALSE()) -> #N/A
A14: 网络-251222-008037（1个附件） | B14: 2025-12-22 09:15:32 | C14: 2025-12-22 09:41:01 | D14: 2025-12-22 11:29:48 | E14: 倪大伟 | F14: 男 | G14: 手机,13681321121; | H14: 工单来源：微信服务号，此工单内容为网民留言时填写的标题及原文。 ============================= 留言标题：投诉公交集团压榨员工留言原文：尊敬的北京公交鸿运承物业管理有限公司领导 / 上级主管部门： 您好！ 我是贵公司的一名老员工的家属。我怀着非常沉重和无奈的心情，向您反映公司近期对我爱人进行的不合理调岗降薪问题。 一、 本人基本情况与工作履历我爱你自进入公交系统工作，至今已有31年工龄。其中，她在运营一线担任调度员长达20多年，积累了丰富的管理经验和业务能力。2022年，转岗至北京公交鸿运承物业管理有限公司，担任综合站务员A岗，至今已在该岗位稳定工作3年。 二、 投诉事由：不合理的“岗变薪变”与学历歧视近期，公司以持有“红头文件”为由，突然要求综合站务员A岗必须具备大专学历，并以此为由要求我爱人转岗降薪。我认为这一决定极不合理，理由如下： 1. 岗位实质未变，能力完全胜任：目前的综合站务员A岗，其岗位职责与我爱人过去三年所从事的工作基本一致。我爱人在公交系统工作31年，拥有20多年调度经验和3年A岗实操经验，我爱人的业务能力和工作表现完全能够胜任当前岗位。公司在我爱人已熟练掌握岗位技能的情况下，突然以“学历”卡人，属于典型的形式主义，忽视了员工的实际工作能力。​2. 临近退休，此举缺乏人文关怀：我爱人距离法定退休年龄仅剩两年多。在企业工作了大半辈子，临近退休却面临如此大幅度的降薪，这对我爱人的生活和精神造成了巨大打击。公司的这种做法，严重违背了《劳动合同法》中关于“在本单位连续工作满十五年且距法定退休年龄不足五年的，用人单位不得依照本法第四十条、第四十一条的规定解除劳动合同”的精神，虽然公司未直接解除合同，但通过降薪逼迫员工离职，性质同样恶劣。 三、 协商过程中的不公待遇在与公司协商过程中，公司给出了四项安置方案，实则是“霸王条款”： 1. 转岗至综合站务员C岗： 工资从原A岗的（岗资3700+绩效4720）降至（岗资3100+绩效2720），降幅超过30%，这是我无法接受的。​2. 转岗至巡检员： 同样面临降薪。​3. 买断工龄。​4. 如不选择以上方案，则视为“下岗代工”。 由于我爱人拒绝签字同意这种不合理的降薪，公司相关人员频繁找我爱人“约谈”。这种高频次的约谈已经严重干扰了我爱人的正常工作和生活，导致我爱人精神压力巨大，身心状态极差。 四、 诉求综上所述，我恳请公司： 1. 立即停止这种针对老员工的不合理调岗降薪行为，尊重我31年的工作贡献和实际业务能力。​2. 维持我爱人目前的综合站务员A岗待遇，直至退休。​3. 停止高频次的施压约谈，给老员工一个安稳的工作环境。 我希望公司能从实际出发，妥善解决我爱人的问题，不要让一名即将退休的老员工寒心。 此致敬礼 市民填写的详细地址为：区：朝阳区街道：不详详细地址：北京市公共交通有限公司鸿运城物业中心 | I14: 是 | J14: 诉求 | K14: 人力资源部（人力资源发展中心） | L14: 工资及五险二金 | M14: 工资方面 | N14: 鸿运承物业管理中心 | O14: 人力资源部 | P14: 人力资源部 | Q14: 机关 | R14: 2025-12-29 23:59:59 | S14: 2025-12-23 | T14: 2025-12-27 08:59:59 | U14: 结束 | V14: 0 | W14: 经核实，与来电人所述情况存在出入：1.本次企业改革是根据《鸿运承物业管理中心综合站务员优化配置改革工作实施方案》、《鸿运承物业管理中心综合站务员A岗管理规定（试行）》等制度文件开展，综合站务员A岗岗位职责，管理方式均发生改变，现综合站务员A岗负责物业场站和人员的现场管理，以及辅助客运单位开展驾驶员安全叮嘱工作，与诉求中“岗位实质未变”存在出入。 2.企业根据实际业务需要进行岗位职责调整，适用于每一位职工，并非是针对来电人个人，鸿运承物业管理中心综合站务员A岗管理规定（试行）明确说明，新聘综合站务员A岗需具有大专学历，属工作需要并非学历歧视。 3.分中心与职工谈话属于正常工作谈话，旨在为职工详细讲解政策，情绪疏导，帮助落选人员进行安置，不存在“高频次施压”行为。 | X14: 经核实，与来电人所述情况存在出入：1.本次企业改革是根据《鸿运承物业管理中心综合站务员优化配置改革工作实施方案》、《鸿运承物业管理中心综合站务员A岗管理规定（试行）》等制度文件开展，综合站务员A岗岗位职责，管理方式均发生改变，现综合站务员A岗负责物业场站和人员的现场管理，以及辅助客运单位开展驾驶员安全叮嘱工作，与诉求中“岗位实质未变”存在出入。 2.企业根据实际业务需要进行岗位职责调整，适用于每一位职工，并非是针对来电人个人，鸿运承物业管理中心综合站务员A岗管理规定（试行）明确说明，新聘综合站务员A岗需具有大专学历，属工作需要并非学历歧视。 3.分中心与职工谈话属于正常工作谈话，旨在为职工详细讲解政策，情绪疏导，帮助落选人员进行安置，不存在“高频次施压”行为。 2025年12月23日上午9点47分左右电话与来电人回复，经过与来电人沟通，来电人对此表示不认可。 办理人：周健辉，鸿运承物业管理中心人力资源部，职务：一般管理； 审核人：高强；部门：鸿运承物业管理中心人力资源部；职务：中级管理。 | Y14: 2025年12月23日上午9点47分左右电话与来电人回复，经过与来电人沟通，来电人对此表示不认可。 | Z14: 无 | AA14: 无 | AB14: 经核实，与来电人所述情况存在出入：1.本次企业改革是根据《鸿运承物业管理中心综合站务员优化配置改革工作实施方案》、《鸿运承物业管理中心综合站务员A岗管理规定（试行）》等制度文件开展，综合站务员A岗岗位职责，管理方式均发生改变，现综合站务员A岗负责物业场站和人员的现场管理，以及辅助客运单位开展驾驶员安全叮嘱工作，与诉求中“岗位实质未变”存在出入。 2.企业根据实际业务需要进行岗位职责调整，适用于每一位职工，并非是针对来电人个人，鸿运承物业管理中心综合站务员A岗管理规定（试行）明确说明，新聘综合站务员A岗需具有大专学历，属工作需要并非学历歧视。 3.分中心与职工谈话属于正常工作谈话，旨在为职工详细讲解政策，情绪疏导，帮助落选人员进行安置，不存在“高频次施压”行为。 2025年12月23日上午9点47分左右电话与来电人回复，经过与来电人沟通，来电人对此表示不认可。 | AC14: 满意 | AD14: 个人 | AE14: 2025-12-21 15:18:26 | AF14: 1049051 | AG14: 劳动合同及用工管理 | AH14: 否 | AK14: =AG14&L14&M14 -> 劳动合同及用工管理工资及五险二金工资方面 | AP14: 10 | AQ14: 46023 | AR14: =IFERROR(LEFT(A14,FIND("（",A14)-1),A14) -> 网络-251222-008037 | AS14: =J14 -> 诉求 | AT14: =IF(MID(AR14,1,2)="热线",12345)+IF(MID(AR14,1,2)="网络",12345) -> 12345 | AU14: =IFERROR(LEFT(D14,FIND(" ",D14)-1),D14) -> 2025-12-22 | AV14: =P14 -> 人力资源部 | AW14: =Q14 -> 机关 | AX14: =H14 -> 工单来源：微信服务号，此工单内容为网民留言时填写的标题及原文。 ============================= 留言标题：投诉公交集团压榨员工留言原文：尊敬的北京公交鸿运承物业管理有限公司领导 / 上级主管部门： 您好！ 我是贵公司的一名老员工的家属。我怀着非常沉重和无奈的心情，向您反映公司近期对我爱人进行的不合理调岗降薪问题。 一、 本人基本情况与工作履历我爱你自进入公交系统工作，至今已有31年工龄。其中，她在运营一线担任调度员长达20多年，积累了丰富的管理经验和业务能力。2022年，转岗至北京公交鸿运承物业管理有限公司，担任综合站务员A岗，至今已在该岗位稳定工作3年。 二、 投诉事由：不合理的“岗变薪变”与学历歧视近期，公司以持有“红头文件”为由，突然要求综合站务员A岗必须具备大专学历，并以此为由要求我爱人转岗降薪。我认为这一决定极不合理，理由如下： 1. 岗位实质未变，能力完全胜任：目前的综合站务员A岗，其岗位职责与我爱人过去三年所从事的工作基本一致。我爱人在公交系统工作31年，拥有20多年调度经验和3年A岗实操经验，我爱人的业务能力和工作表现完全能够胜任当前岗位。公司在我爱人已熟练掌握岗位技能的情况下，突然以“学历”卡人，属于典型的形式主义，忽视了员工的实际工作能力。​2. 临近退休，此举缺乏人文关怀：我爱人距离法定退休年龄仅剩两年多。在企业工作了大半辈子，临近退休却面临如此大幅度的降薪，这对我爱人的生活和精神造成了巨大打击。公司的这种做法，严重违背了《劳动合同法》中关于“在本单位连续工作满十五年且距法定退休年龄不足五年的，用人单位不得依照本法第四十条、第四十一条的规定解除劳动合同”的精神，虽然公司未直接解除合同，但通过降薪逼迫员工离职，性质同样恶劣。 三、 协商过程中的不公待遇在与公司协商过程中，公司给出了四项安置方案，实则是“霸王条款”： 1. 转岗至综合站务员C岗： 工资从原A岗的（岗资3700+绩效4720）降至（岗资3100+绩效2720），降幅超过30%，这是我无法接受的。​2. 转岗至巡检员： 同样面临降薪。​3. 买断工龄。​4. 如不选择以上方案，则视为“下岗代工”。 由于我爱人拒绝签字同意这种不合理的降薪，公司相关人员频繁找我爱人“约谈”。这种高频次的约谈已经严重干扰了我爱人的正常工作和生活，导致我爱人精神压力巨大，身心状态极差。 四、 诉求综上所述，我恳请公司： 1. 立即停止这种针对老员工的不合理调岗降薪行为，尊重我31年的工作贡献和实际业务能力。​2. 维持我爱人目前的综合站务员A岗待遇，直至退休。​3. 停止高频次的施压约谈，给老员工一个安稳的工作环境。 我希望公司能从实际出发，妥善解决我爱人的问题，不要让一名即将退休的老员工寒心。 此致敬礼 市民填写的详细地址为：区：朝阳区街道：不详详细地址：北京市公共交通有限公司鸿运城物业中心 | AY14: =AG14 -> 劳动合同及用工管理 | AZ14: 是 | BA14: 是 | BB14: 否 | BC14: 七有五性,公正性 | BD14: =U14 -> 结束 | BE14: =IFERROR(LEFT(T14,FIND(" ",T14)-1),T14) -> 2025-12-27 | BF14: 劳动人员调配及薪酬 （公开选聘综A岗-学历问题）同人同诉 | BG14: 人力资源部 | BH14: 机关 | BL14: =IF(BG14="物管行政部","侯旭、郑楠",IF(BG14="安保部","张耕",IF(BG14="工程设备部","华菲",IF(BG14="人力资源部","成琦",IF(BG14="党委工作部","阎鑫雨",IF(BG14="餐饮服务部","赵弘晨",IF(BG14="工会","郑欣",IF(BG14="办公室","董娜",""))))))))&IF(BG14="纪检部","黄倩",IF(BG14="信息管理部","蔡浩然","")) -> 成琦 | BM14: 未主动剔除 | BP14: 政策类 | BQ14: 同人同诉：网络-251222-008037、网络-251223-037876 | BR14: 是 | BV14: =MID(AR14,1,16) -> 网络-251222-008037 | BW14: 七有五性,劳有所得 | BX14: =IF(COUNTIF(BV:BV,BV14)=1,"否","是") -> 否 | BY14: =MID(AR14,18,1) | CG14: =VLOOKUP(AR14,[1]市民意见信息导出!$AI$2:$AK$392,3,FALSE()) -> 结束 | CH14: =VLOOKUP(BV14,[2]Sheet1!$C$2:$AC$99,2,FALSE()) -> #N/A
A15: 热线-251222-022648（2个附件） | B15: 2025-12-22 11:12:47 | C15: 2025-12-22 11:32:06 | D15: 2025-12-22 11:33:40 | E15: 姜长明女士 | F15: 女 | G15: 手机,15210100103; | H15: 市民反映，自己是在北京公交集团的下属二级单位鸿运承物业管理中心职工，属于公交集团的下属二级单位，被所述下级公司恶意调岗，也向鸿运承物业管理中心公司的人力资源经理高强反馈过，公司承认是没有经过公交集团文件下发处理的，说沟通文件下发后给出回复，现在既没有回复，还直接没有任何排岗排班，市民现在岗位都是北京公交集团直接下发确认的岗位，都有红头文件，也从2025年3月开始变相调岗三次了，希望公交集团负责的领导给予处理回复，因为本次调岗是公交集团下属二级单位调岗操作，并不是公交集团进行处理的，故希望公交集团负责领导给出回复，姓名：姜长明，来电反映北京公交集团下属单位恶意调岗问题。 | I15: 是 | J15: 诉求 | K15: 人力资源部（人力资源发展中心） | L15: 工资及五险二金 | M15: 工资方面 | N15: 鸿运承物业管理中心 | O15: 凌家庙分中心 | P15: 人力资源部 | Q15: 凌家庙分中心 | R15: 2025-12-29 23:59:59 | S15: 2025-12-25 | T15: 2025-12-27 08:59:59 | U15: 结束 | V15: 1 | W15: 经核实，与来电人所述情况存在出入。来电人姜长明为我单位凌家庙分中心职工，其此前并未转岗，不涉及来电人所述的恶意调岗问题。本次企业改革是根据《鸿运承物业管理中心综合站务员优化配置改革工作实施方案》、《鸿运承物业管理中心综合站务员A岗管理规定（试行）》等制度文件开展，我单位为落选的原综A人员提供4类转岗安置方案。此前我单位凌家庙分中心于2025年11月27日、12月11日以及22日多次与来电人进行面对面的沟通，来电人均表示坚决拒绝调整A岗安置工作。 | X15: 经核实，与来电人所述情况存在出入。来电人姜长明为我单位凌家庙分中心职工，其此前并未转岗，不涉及来电人所述的恶意调岗问题。本次企业改革是根据《鸿运承物业管理中心综合站务员优化配置改革工作实施方案》、《鸿运承物业管理中心综合站务员A岗管理规定（试行）》等制度文件开展，我单位为落选的原综A人员提供4类转岗安置方案。此前我单位凌家庙分中心于2025年11月27日、12月11日以及22日多次与来电人进行面对面的沟通，来电人均表示坚决拒绝调整A岗安置工作。 接到诉求后，于2025年12月25日10点01分电话回复来电人，来电人表示已知晓后挂断电话，为确保来电人知晓政策，故我单位再次通过短信形式告知来电人办理结果。 办理人：王跃，鸿运承物业管理中心凌家庙分中心，职务：一般管理； 审核人：高强；部门：鸿运承物业管理中心人力资源部；职务：中级管理。 | Y15: 接到诉求后，于2025年12月25日10点01分电话回复来电人，来电人表示已知晓后挂断电话，为确保来电人知晓政策，故我单位再次通过短信形式告知来电人办理结果。 | Z15: 无 | AA15: 无 | AB15: 经核实，与来电人所述情况存在出入。来电人姜长明为我单位凌家庙分中心职工，其此前并未转岗，不涉及来电人所述的恶意调岗问题。本次企业改革是根据《鸿运承物业管理中心综合站务员优化配置改革工作实施方案》、《鸿运承物业管理中心综合站务员A岗管理规定（试行）》等制度文件开展，我单位为落选的原综A人员提供4类转岗安置方案。此前我单位凌家庙分中心于2025年11月27日、12月11日以及22日多次与来电人进行面对面的沟通，来电人均表示坚决拒绝调整A岗安置工作。 接到诉求后，于2025年12月25日10点01分电话回复来电人，来电人表示已知晓后挂断电话，为确保来电人知晓政策，故我单位再次通过短信形式告知来电人办理结果。 | AC15: 满意 | AD15: 个人 | AE15: 2025-12-22 11:03:19 | AF15: 1862108387 | AG15: 运营调度 | AH15: 否 | AK15: =AG15&L15&M15 -> 运营调度工资及五险二金工资方面 | AP15: 11 | AQ15: 46023 | AR15: =IFERROR(LEFT(A15,FIND("（",A15)-1),A15) -> 热线-251222-022648 | AS15: =J15 -> 诉求 | AT15: =IF(MID(AR15,1,2)="热线",12345)+IF(MID(AR15,1,2)="网络",12345) -> 12345 | AU15: =IFERROR(LEFT(D15,FIND(" ",D15)-1),D15) -> 2025-12-22 | AV15: =P15 -> 人力资源部 | AW15: =Q15 -> 凌家庙分中心 | AX15: =H15 -> 市民反映，自己是在北京公交集团的下属二级单位鸿运承物业管理中心职工，属于公交集团的下属二级单位，被所述下级公司恶意调岗，也向鸿运承物业管理中心公司的人力资源经理高强反馈过，公司承认是没有经过公交集团文件下发处理的，说沟通文件下发后给出回复，现在既没有回复，还直接没有任何排岗排班，市民现在岗位都是北京公交集团直接下发确认的岗位，都有红头文件，也从2025年3月开始变相调岗三次了，希望公交集团负责的领导给予处理回复，因为本次调岗是公交集团下属二级单位调岗操作，并不是公交集团进行处理的，故希望公交集团负责领导给出回复，姓名：姜长明，来电反映北京公交集团下属单位恶意调岗问题。 | AY15: =AG15 -> 运营调度 | AZ15: 是 | BA15: 是 | BB15: 否 | BC15: 七有五性,公正性 | BD15: =U15 -> 结束 | BE15: =IFERROR(LEFT(T15,FIND(" ",T15)-1),T15) -> 2025-12-27 | BF15: 劳动人员调配及薪酬 （综A岗调整） 多渠道同人同诉 | BG15: 人力资源部 | BH15: 凌家庙分中心 | BL15: =IF(BG15="物管行政部","侯旭、郑楠",IF(BG15="安保部","张耕",IF(BG15="工程设备部","华菲",IF(BG15="人力资源部","成琦",IF(BG15="党委工作部","阎鑫雨",IF(BG15="餐饮服务部","赵弘晨",IF(BG15="工会","郑欣",IF(BG15="办公室","董娜",""))))))))&IF(BG15="纪检部","黄倩",IF(BG15="信息管理部","蔡浩然","")) -> 成琦 | BM15: 未主动剔除 | BP15: 政策类 | BQ15: 综A公开招聘，针对政策条件不认可。（同人同诉多渠道）：GJ-PHONE-20251222-0767、热线-251222-022648 | BR15: 是 | BS15: 先96166后12345 | BV15: =MID(AR15,1,16) -> 热线-251222-022648 | BW15: 七有五性,便利性 | BX15: =IF(COUNTIF(BV:BV,BV15)=1,"否","是") -> 否 | BY15: =MID(AR15,18,1) | CG15: =VLOOKUP(AR15,[1]市民意见信息导出!$AI$2:$AK$392,3,FALSE()) -> 结束 | CH15: =VLOOKUP(BV15,[2]Sheet1!$C$2:$AC$99,2,FALSE()) -> #N/A
A16: 热线-251222-060978（1个附件） | B16: 2025-12-22 17:13:13 | C16: 2025-12-22 17:21:15 | D16: 2025-12-22 17:25:24 | E16: 何威涛女士 | F16: 女 | G16: 手机,13520598546; | H16: 市民反映，自己是肢体四级残疾人，一直在北京公交集团鸿运承物业九龙分中心工作，属于北京公交集团有限公司，今年49岁，是综合站务A岗，还有不到1年退休，之前因自己学历不够单位不让自己报名乘务巡查员，现在告知从1月15日起将对自己执行C岗工资，直降2600元，自己同意但是没有签字，期间劳人部门及工会主席，共给自己打9次电话及三次面谈，导致自己精神压力大现在患有焦虑症，姓名：何威涛， 希望单位不要再因此事联系自己，给自己造成精神压力导致病情加重，来电反映希望单位领导不要再给自己施加压力导致病情加重。注：另一问题见热线-251222-062831 | I16: 是 | J16: 其他 | K16: 人力资源部（人力资源发展中心） | L16: 人力资源方面其他问题 | M16: 人力资源方面补充内容 | N16: 鸿运承物业管理中心 | O16: 九龙分中心 | P16: 人力资源部 | Q16: 九龙分中心 | R16: 2025-12-29 23:59:59 | S16: 2025-12-23 | T16: 2025-12-27 08:59:59 | U16: 结束 | V16: 0 | W16: 接到职工投诉九龙分中心高度重视，立即核实情况。何威涛明春苑场站职工，按鸿运承物业管理中心综合站务员优化配置改革工作实施方案，对职工进行面对面告知。 | X16: 对以上内容于2025年12月23日下午15点进行电话回复，对以上问题进行回复，职工表示基本满意。 | Y16: 无 | Z16: 无 | AA16: 无 | AB16: 接到职工投诉九龙分中心高度重视，立即核实情况。何威涛明春苑场站职工，按鸿运承物业管理中心综合站务员优化配置改革工作实施方案，对职工进行面对面告知。对以上内容于2025年12月23日下午15点进行电话回复，对以上问题进行回复，职工表示基本满意。 | AC16: 满意 | AD16: 个人 | AE16: 2025-12-22 16:51:03 | AF16: 1741937714 | AG16: 劳动合同及用工管理 | AH16: 否 | AK16: =AG16&L16&M16 -> 劳动合同及用工管理人力资源方面其他问题人力资源方面补充内容 | AP16: 12 | AQ16: 46023 | AR16: =IFERROR(LEFT(A16,FIND("（",A16)-1),A16) -> 热线-251222-060978 | AS16: =J16 -> 其他 | AT16: =IF(MID(AR16,1,2)="热线",12345)+IF(MID(AR16,1,2)="网络",12345) -> 12345 | AU16: =IFERROR(LEFT(D16,FIND(" ",D16)-1),D16) -> 2025-12-22 | AV16: =P16 -> 人力资源部 | AW16: =Q16 -> 九龙分中心 | AX16: =H16 -> 市民反映，自己是肢体四级残疾人，一直在北京公交集团鸿运承物业九龙分中心工作，属于北京公交集团有限公司，今年49岁，是综合站务A岗，还有不到1年退休，之前因自己学历不够单位不让自己报名乘务巡查员，现在告知从1月15日起将对自己执行C岗工资，直降2600元，自己同意但是没有签字，期间劳人部门及工会主席，共给自己打9次电话及三次面谈，导致自己精神压力大现在患有焦虑症，姓名：何威涛， 希望单位不要再因此事联系自己，给自己造成精神压力导致病情加重，来电反映希望单位领导不要再给自己施加压力导致病情加重。注：另一问题见热线-251222-062831 | AY16: =AG16 -> 劳动合同及用工管理 | AZ16: 是 | BA16: 是 | BB16: 否 | BC16: 七有五性,公正性 | BD16: =U16 -> 结束 | BE16: =IFERROR(LEFT(T16,FIND(" ",T16)-1),T16) -> 2025-12-27 | BF16: 劳动人员调配及薪酬 （综A岗调整） 多渠道同人同诉 | BG16: 人力资源部 | BH16: 九龙分中心 | BL16: =IF(BG16="物管行政部","侯旭、郑楠",IF(BG16="安保部","张耕",IF(BG16="工程设备部","华菲",IF(BG16="人力资源部","成琦",IF(BG16="党委工作部","阎鑫雨",IF(BG16="餐饮服务部","赵弘晨",IF(BG16="工会","郑欣",IF(BG16="办公室","董娜",""))))))))&IF(BG16="纪检部","黄倩",IF(BG16="信息管理部","蔡浩然","")) -> 成琦 | BM16: 未主动剔除 | BP16: 政策类 | BV16: =MID(AR16,1,16) -> 热线-251222-060978 | BW16: 七有五性,劳有所得 | BX16: =IF(COUNTIF(BV:BV,BV16)=1,"否","是") -> 否 | BY16: =MID(AR16,18,1) | BZ16: 只评价响应率 | CE16: 1月 | CG16: =VLOOKUP(AR16,[1]市民意见信息导出!$AI$2:$AK$392,3,FALSE()) -> 结束 | CH16: =VLOOKUP(BV16,[2]Sheet1!$C$2:$AC$99,2,FALSE()) -> 1月
A17: 热线-251223-016057（2个附件） | B17: 2025-12-23 10:13:34 | C17: 2025-12-23 11:14:51 | D17: 2025-12-23 11:30:26 | E17: 胡亚静女士 | F17: 女 | G17: 手机,13716588237; | H17: 市民反映，市民是公交集团鸿运承物业管理中心的职工，鸿运承物业管理中心作为公交集团的下属二级单位，从2022年7月1日至2023年8月，鸿运承物业管理中心违背北京公交集团下发的红头文件内容，违法给部分综合站务员B岗C岗职工转为综合站务员A岗，这些转岗人员并没有履行集团公司下发红头文件的综合站务员A岗岗位职责等内容，直接目的是为了追求A岗工资，这番操作直接浪费了公交集团大量资金，从而使综合站务员A岗人员杂乱不堪，以至于综合站务员A岗人员称呼多样，如老综A，旧综A，原综A，后转综A，现在又弄出新综A，从今年3月份开始，鸿运承在没有任何集团下发文件的前提下，把违规转岗的A岗职工保护起来，反而针对性给受红头文件保护的职工恶意调岗，共进行三次恶意调岗，性质特别恶劣，致使被针对职工，身心收到严重创伤，11月27日鸿运承人力资源部经理和工会主席，都承认此次改革是在没有集团公司相关书面文件前提下进行的，在我们坚持一切以劳动法为根基的基础上，他们承诺去和集团领导协商获取有效文件，并且还承诺一定会给职工明确答复，有录音为证，但现在在没有任何答复的前提下，12月26日已经停止排班，已下发排班表，我们职工真心不明白，身为下属二级单位领导，身为共产党干部，怎么会做出霸权主义的事情，敬请北京公交集团相关领导给予职工明确回复，职工姓名：胡亚静，自己来到了公交集团，但没有公交集团的人员来处理问题，来电反映敬请北京公交集团相关领导给予职工明确回复的问题。 | I17: 是 | J17: 诉求 | K17: 人力资源部（人力资源发展中心） | L17: 工资及五险二金 | M17: 工资方面 | N17: 鸿运承物业管理中心 | O17: 凌家庙分中心 | P17: 人力资源部 | Q17: 凌家庙分中心 | R17: 2025-12-30 23:59:59 | S17: 2025-12-25 | T17: 2025-12-28 08:59:59 | U17: 结束 | V17: 1 | W17: 经核实，与来电人所述情况存在出入。来电人胡亚静为我单位凌家庙分中心职工，此前我单位并未对来电人进行转岗，不涉及来电人所述的恶意调岗问题。本次企业改革是根据《鸿运承物业管理中心综合站务员优化配置改革工作实施方案》、《鸿运承物业管理中心综合站务员A岗管理规定（试行）》等制度文件开展，我单位为落选的原综A人员提供4类转岗安置方案。此前我单位凌家庙分中心于2025年11月27日、12月11日以及22日多次与来电人进行面对面的沟通，来电人均表示坚决拒绝调整A岗安置工作。 | X17: 经核实，与来电人所述情况存在出入。来电人胡亚静为我单位凌家庙分中心职工，此前我单位并未对来电人进行转岗，不涉及来电人所述的恶意调岗问题。本次企业改革是根据《鸿运承物业管理中心综合站务员优化配置改革工作实施方案》、《鸿运承物业管理中心综合站务员A岗管理规定（试行）》等制度文件开展，我单位为落选的原综A人员提供4类转岗安置方案。此前我单位凌家庙分中心于2025年11月27日、12月11日以及22日多次与来电人进行面对面的沟通，来电人均表示坚决拒绝调整A岗安置工作。 接到诉求后，我单位凌家庙分中心于2025年12月25日9点53分电话回复来电人，来电人将电话挂断，故我单位再次通过短信形式告知来电人办理结果。 办理人：王跃，鸿运承物业管理中心凌家庙分中心，职务：一般管理； 审核人：高强；部门：鸿运承物业管理中心人力资源部；职务：中级管理。 | Y17: 接到诉求后，我单位凌家庙分中心于2025年12月25日9点53分电话回复来电人，来电人将电话挂断，故我单位再次通过短信形式告知来电人办理结果。 | Z17: 无 | AA17: 无 | AB17: 经核实，与来电人所述情况存在出入。来电人胡亚静为我单位凌家庙分中心职工，此前我单位并未对来电人进行转岗，不涉及来电人所述的恶意调岗问题。本次企业改革是根据《鸿运承物业管理中心综合站务员优化配置改革工作实施方案》、《鸿运承物业管理中心综合站务员A岗管理规定（试行）》等制度文件开展，我单位为落选的原综A人员提供4类转岗安置方案。此前我单位凌家庙分中心于2025年11月27日、12月11日以及22日多次与来电人进行面对面的沟通，来电人均表示坚决拒绝调整A岗安置工作。 接到诉求后，我单位凌家庙分中心于2025年12月25日9点53分电话回复来电人，来电人将电话挂断，故我单位再次通过短信形式告知来电人办理结果。 | AC17: 满意 | AD17: 个人 | AE17: 2025-12-23 10:11:21 | AF17: 1862108387 | AG17: 运营调度 | AH17: 否 | AK17: =AG17&L17&M17 -> 运营调度工资及五险二金工资方面 | AP17: 13 | AQ17: 46023 | AR17: =IFERROR(LEFT(A17,FIND("（",A17)-1),A17) -> 热线-251223-016057 | AS17: =J17 -> 诉求 | AT17: =IF(MID(AR17,1,2)="热线",12345)+IF(MID(AR17,1,2)="网络",12345) -> 12345 | AU17: =IFERROR(LEFT(D17,FIND(" ",D17)-1),D17) -> 2025-12-23 | AV17: =P17 -> 人力资源部 | AW17: =Q17 -> 凌家庙分中心 | AX17: =H17 -> 市民反映，市民是公交集团鸿运承物业管理中心的职工，鸿运承物业管理中心作为公交集团的下属二级单位，从2022年7月1日至2023年8月，鸿运承物业管理中心违背北京公交集团下发的红头文件内容，违法给部分综合站务员B岗C岗职工转为综合站务员A岗，这些转岗人员并没有履行集团公司下发红头文件的综合站务员A岗岗位职责等内容，直接目的是为了追求A岗工资，这番操作直接浪费了公交集团大量资金，从而使综合站务员A岗人员杂乱不堪，以至于综合站务员A岗人员称呼多样，如老综A，旧综A，原综A，后转综A，现在又弄出新综A，从今年3月份开始，鸿运承在没有任何集团下发文件的前提下，把违规转岗的A岗职工保护起来，反而针对性给受红头文件保护的职工恶意调岗，共进行三次恶意调岗，性质特别恶劣，致使被针对职工，身心收到严重创伤，11月27日鸿运承人力资源部经理和工会主席，都承认此次改革是在没有集团公司相关书面文件前提下进行的，在我们坚持一切以劳动法为根基的基础上，他们承诺去和集团领导协商获取有效文件，并且还承诺一定会给职工明确答复，有录音为证，但现在在没有任何答复的前提下，12月26日已经停止排班，已下发排班表，我们职工真心不明白，身为下属二级单位领导，身为共产党干部，怎么会做出霸权主义的事情，敬请北京公交集团相关领导给予职工明确回复，职工姓名：胡亚静，自己来到了公交集团，但没有公交集团的人员来处理问题，来电反映敬请北京公交集团相关领导给予职工明确回复的问题。 | AY17: =AG17 -> 运营调度 | AZ17: 是 | BA17: 是 | BB17: 否 | BC17: 七有五性,公正性 | BD17: =U17 -> 结束 | BE17: =IFERROR(LEFT(T17,FIND(" ",T17)-1),T17) -> 2025-12-28 | BF17: 劳动人员调配及薪酬 （公开选聘综A岗-学历问题） 多渠道同人同诉 多次 | BG17: 人力资源部 | BH17: 凌家庙分中心 | BL17: =IF(BG17="物管行政部","侯旭、郑楠",IF(BG17="安保部","张耕",IF(BG17="工程设备部","华菲",IF(BG17="人力资源部","成琦",IF(BG17="党委工作部","阎鑫雨",IF(BG17="餐饮服务部","赵弘晨",IF(BG17="工会","郑欣",IF(BG17="办公室","董娜",""))))))))&IF(BG17="纪检部","黄倩",IF(BG17="信息管理部","蔡浩然","")) -> 成琦 | BM17: 未主动剔除 | BP17: 政策类 | BQ17: 综A公开招聘，针对政策条件不认可。（同人同诉）：热线-250611-039775、热线-250611-059472-1、热线-250618-048072-1、热线-250708-035022、热线-251222-018664、热线-251223-016057 | BR17: 是 | BS17: 先96166后12345 | BV17: =MID(AR17,1,16) -> 热线-251223-016057 | BW17: 七有五性,便利性 | BX17: =IF(COUNTIF(BV:BV,BV17)=1,"否","是") -> 否 | BY17: =MID(AR17,18,1) | CG17: =VLOOKUP(AR17,[1]市民意见信息导出!$AI$2:$AK$392,3,FALSE()) -> 结束 | CH17: =VLOOKUP(BV17,[2]Sheet1!$C$2:$AC$99,2,FALSE()) -> #N/A
A18: 网络-251223-037876（2个附件） | B18: 2025-12-23 14:06:32 | C18: 2025-12-23 14:10:21 | D18: 2025-12-23 14:27:48 | E18: 倪大伟 | F18: 男 | G18: 手机,13681321121; | H18: 工单来源：微信服务号，此工单内容为网民留言时填写的标题及原文。 ============================= 留言标题：北京公交鸿运承物业管理有限公司不合理调岗降薪的投诉信留言原文： 尊敬的北京公共交通控股集团有限公司领导： 您好！ 我是贵公司下属北京公交鸿运承物业管理有限公司一名老员工的家属，怀着无奈与失望的心情，向您反映公司针对我爱人的不合理调岗降薪问题。 一、员工基本情况与工作履历 我爱人在公交系统工作长达31年，其中在运营一线担任调度员20多年，积累了丰富管理经验与业务能力。2022年转岗至北京公交鸿运承物业管理有限公司，任综合站务员A岗，至今已稳定工作3年。 二、投诉事由 （一）不合理的“岗变薪变”与学历歧视 1. 岗位实质与能力匹配：当前综合站务员A岗的岗位职责与我爱人过去3年从事的工作基本一致。她拥有31年公交系统工作经验，其中包括20多年调度经验和3年A岗实操经验，完全能够胜任岗位。公司此时以“学历”为由卡人，属于形式主义，忽视员工实际工作能力。​2. 临近退休缺乏人文关怀：我爱人距法定退休年龄仅剩两年多，在企业奉献大半辈子，临近退休却面临大幅降薪，这对其生活和精神造成巨大打击。公司此举违背了《劳动合同法》第四十二条规定，即“在本单位连续工作满十五年且距法定退休年龄不足五年的，用人单位不得依照本法第四十条、第四十一条的规定解除劳动合同”。虽公司未直接解除合同，但通过降薪逼迫员工离职，性质恶劣。 （二）协商过程中的不公待遇 在与公司协商过程中，公司给出的四项安置方案实为“霸王条款”： 1. 转岗至综合站务员C岗：工资从原A岗的（岗资3700 + 绩效4720）降至（岗资3100 + 绩效2720），降幅超30%，难以接受。​2. 转岗至巡检员：同样面临降薪。​3. 买断工龄。​4. **如不选择以上方案，则视为“下岗代工”。 因我爱人拒绝签字同意不合理降薪，公司相关人员频繁“约谈”，严重干扰其正常工作和生活，导致她精神压力巨大，身心状态极差。在录音中也可明确听到，我爱人明确表示不同意，但公司人员却歪曲事实，称其同意签字认可，这种行为极其不妥。 （三）内部反映无果 此前，我们已向北京公交鸿运承物业管理有限公司反映该问题，希望公司能重视员工权益，合理解决调岗降薪事宜。然而，公司反馈称其做法合理，并未对不合理之处进行纠正，这让我们深感失望。我们认为公司未能充分考虑员工实际情况和合法权益，处理方式有失公正。 三、诉求 综上所述，恳请贵集团： 1. 立即停止下属公司针对老员工的不合理调岗降薪行为，尊重我爱人31年的工作贡献和实际业务能力。​2. 督促北京公交鸿运承物业管理有限公司维持我爱人目前的综合站务员A岗待遇，直至退休。​3. 要求下属公司停止高频次的施压约谈，给予老员工安稳的工作环境。 希望贵集团能从实际出发，妥善解决问题，不要让为公交系统奉献多年的老员工寒心。 此致 敬礼！ 市民填写的详细地址为：区、街道：丰台区卢沟桥街道详细地址：北京公交集团 | I18: 是 | J18: 诉求 | K18: 人力资源部（人力资源发展中心） | L18: 工资及五险二金 | M18: 工资方面 | N18: 鸿运承物业管理中心 | O18: 单店分中心 | P18: 人力资源部 | Q18: 单店分中心 | R18: 2025-12-30 23:59:59 | S18: 2025-12-25 | T18: 2025-12-28 08:59:59 | U18: 结束 | V18: 1 | W18: 经核实，来电人为我单位职工家属，与来电人所述情况存在出入。首先，本次企业改革是根据《鸿运承物业管理中心综合站务员优化配置改革工作实施方案》、《鸿运承物业管理中心综合站务员A岗管理规定（试行）》等制度文件开展，综合站务员A岗岗位职责，管理方式均发生改变，现综合站务员A岗负责物业场站和人员的现场管理，以及辅助客运单位开展驾驶员安全叮嘱工作，与诉求中“岗位实质未变”存在出入。 企业根据实际业务需要进行岗位职责调整，适用于每一位职工，并非是针对来电人家属个人，鸿运承物业管理中心综合站务员A岗管理规定（试行）明确说明，新聘综合站务员A岗需具有大专学历，属工作需要并非学历歧视。 分中心与职工谈话属于正常工作谈话，旨在为职工详细讲解政策，情绪疏导，帮助落选人员进行安置，不存在“高频次施压”行为。 | X18: 经核实，来电人为我单位职工家属，与来电人所述情况存在出入。首先，本次企业改革是根据《鸿运承物业管理中心综合站务员优化配置改革工作实施方案》、《鸿运承物业管理中心综合站务员A岗管理规定（试行）》等制度文件开展，综合站务员A岗岗位职责，管理方式均发生改变，现综合站务员A岗负责物业场站和人员的现场管理，以及辅助客运单位开展驾驶员安全叮嘱工作，与诉求中“岗位实质未变”存在出入。 企业根据实际业务需要进行岗位职责调整，适用于每一位职工，并非是针对来电人家属个人，鸿运承物业管理中心综合站务员A岗管理规定（试行）明确说明，新聘综合站务员A岗需具有大专学历，属工作需要并非学历歧视。 分中心与职工谈话属于正常工作谈话，旨在为职工详细讲解政策，情绪疏导，帮助落选人员进行安置，不存在“高频次施压”行为。 接到本条投诉后，分中心于2025年12月25日下午13点56分左右电话回复，来电人未听完回复就挂断电话，后我单位又以短信形式再次与来电人进行回复。 办理人：杨飞，部门：鸿运承物业管理中心单店分中心，职务：一般管理； 审核人：高强；部门：鸿运承物业管理中心人力资源部；职务：中级管理。 | Y18: 接到本条投诉后，分中心于2025年12月25日下午13点56分左右电话回复，来电人未听完回复就挂断电话，后我单位又以短信形式再次与来电人进行回复。 | Z18: 无 | AA18: 无 | AB18: 经核实，来电人为我单位职工家属，与来电人所述情况存在出入。首先，本次企业改革是根据《鸿运承物业管理中心综合站务员优化配置改革工作实施方案》、《鸿运承物业管理中心综合站务员A岗管理规定（试行）》等制度文件开展，综合站务员A岗岗位职责，管理方式均发生改变，现综合站务员A岗负责物业场站和人员的现场管理，以及辅助客运单位开展驾驶员安全叮嘱工作，与诉求中“岗位实质未变”存在出入。 企业根据实际业务需要进行岗位职责调整，适用于每一位职工，并非是针对来电人家属个人，鸿运承物业管理中心综合站务员A岗管理规定（试行）明确说明，新聘综合站务员A岗需具有大专学历，属工作需要并非学历歧视。 分中心与职工谈话属于正常工作谈话，旨在为职工详细讲解政策，情绪疏导，帮助落选人员进行安置，不存在“高频次施压”行为。 接到本条投诉后，分中心于2025年12月25日下午13点56分左右电话回复，来电人未听完回复就挂断电话，后我单位又以短信形式再次与来电人进行回复。 | AC18: 满意 | AD18: 个人 | AE18: 2025-12-23 11:41:15 | AF18: 1741937706 | AG18: 劳动合同及用工管理 | AH18: 否 | AK18: =AG18&L18&M18 -> 劳动合同及用工管理工资及五险二金工资方面 | AP18: 14 | AQ18: 46023 | AR18: =IFERROR(LEFT(A18,FIND("（",A18)-1),A18) -> 网络-251223-037876 | AS18: =J18 -> 诉求 | AT18: =IF(MID(AR18,1,2)="热线",12345)+IF(MID(AR18,1,2)="网络",12345) -> 12345 | AU18: =IFERROR(LEFT(D18,FIND(" ",D18)-1),D18) -> 2025-12-23 | AV18: =P18 -> 人力资源部 | AW18: =Q18 -> 单店分中心 | AX18: =H18 -> 工单来源：微信服务号，此工单内容为网民留言时填写的标题及原文。 ============================= 留言标题：北京公交鸿运承物业管理有限公司不合理调岗降薪的投诉信留言原文： 尊敬的北京公共交通控股集团有限公司领导： 您好！ 我是贵公司下属北京公交鸿运承物业管理有限公司一名老员工的家属，怀着无奈与失望的心情，向您反映公司针对我爱人的不合理调岗降薪问题。 一、员工基本情况与工作履历 我爱人在公交系统工作长达31年，其中在运营一线担任调度员20多年，积累了丰富管理经验与业务能力。2022年转岗至北京公交鸿运承物业管理有限公司，任综合站务员A岗，至今已稳定工作3年。 二、投诉事由 （一）不合理的“岗变薪变”与学历歧视 1. 岗位实质与能力匹配：当前综合站务员A岗的岗位职责与我爱人过去3年从事的工作基本一致。她拥有31年公交系统工作经验，其中包括20多年调度经验和3年A岗实操经验，完全能够胜任岗位。公司此时以“学历”为由卡人，属于形式主义，忽视员工实际工作能力。​2. 临近退休缺乏人文关怀：我爱人距法定退休年龄仅剩两年多，在企业奉献大半辈子，临近退休却面临大幅降薪，这对其生活和精神造成巨大打击。公司此举违背了《劳动合同法》第四十二条规定，即“在本单位连续工作满十五年且距法定退休年龄不足五年的，用人单位不得依照本法第四十条、第四十一条的规定解除劳动合同”。虽公司未直接解除合同，但通过降薪逼迫员工离职，性质恶劣。 （二）协商过程中的不公待遇 在与公司协商过程中，公司给出的四项安置方案实为“霸王条款”： 1. 转岗至综合站务员C岗：工资从原A岗的（岗资3700 + 绩效4720）降至（岗资3100 + 绩效2720），降幅超30%，难以接受。​2. 转岗至巡检员：同样面临降薪。​3. 买断工龄。​4. **如不选择以上方案，则视为“下岗代工”。 因我爱人拒绝签字同意不合理降薪，公司相关人员频繁“约谈”，严重干扰其正常工作和生活，导致她精神压力巨大，身心状态极差。在录音中也可明确听到，我爱人明确表示不同意，但公司人员却歪曲事实，称其同意签字认可，这种行为极其不妥。 （三）内部反映无果 此前，我们已向北京公交鸿运承物业管理有限公司反映该问题，希望公司能重视员工权益，合理解决调岗降薪事宜。然而，公司反馈称其做法合理，并未对不合理之处进行纠正，这让我们深感失望。我们认为公司未能充分考虑员工实际情况和合法权益，处理方式有失公正。 三、诉求 综上所述，恳请贵集团： 1. 立即停止下属公司针对老员工的不合理调岗降薪行为，尊重我爱人31年的工作贡献和实际业务能力。​2. 督促北京公交鸿运承物业管理有限公司维持我爱人目前的综合站务员A岗待遇，直至退休。​3. 要求下属公司停止高频次的施压约谈，给予老员工安稳的工作环境。 希望贵集团能从实际出发，妥善解决问题，不要让为公交系统奉献多年的老员工寒心。 此致 敬礼！ 市民填写的详细地址为：区、街道：丰台区卢沟桥街道详细地址：北京公交集团 | AY18: =AG18 -> 劳动合同及用工管理 | AZ18: 是 | BA18: 是 | BB18: 否 | BC18: 七有五性,公正性 | BD18: =U18 -> 结束 | BE18: =IFERROR(LEFT(T18,FIND(" ",T18)-1),T18) -> 2025-12-28 | BF18: 劳动人员调配及薪酬 （公开选聘综A岗-学历问题）同人同诉 | BG18: 人力资源部 | BH18: 单店分中心 | BL18: =IF(BG18="物管行政部","侯旭、郑楠",IF(BG18="安保部","张耕",IF(BG18="工程设备部","华菲",IF(BG18="人力资源部","成琦",IF(BG18="党委工作部","阎鑫雨",IF(BG18="餐饮服务部","赵弘晨",IF(BG18="工会","郑欣",IF(BG18="办公室","董娜",""))))))))&IF(BG18="纪检部","黄倩",IF(BG18="信息管理部","蔡浩然","")) -> 成琦 | BM18: 未主动剔除 | BP18: 政策类 | BQ18: 同人同诉：网络-251222-008037、网络-251223-037876 | BR18: 是 | BV18: =MID(AR18,1,16) -> 网络-251223-037876 | BW18: 七有五性,劳有所得 | BX18: =IF(COUNTIF(BV:BV,BV18)=1,"否","是") -> 否 | BY18: =MID(AR18,18,1) | BZ18: 只评价响应率 | CE18: 1月 | CG18: =VLOOKUP(AR18,[1]市民意见信息导出!$AI$2:$AK$392,3,FALSE()) -> 结束 | CH18: =VLOOKUP(BV18,[2]Sheet1!$C$2:$AC$99,2,FALSE()) -> 1月
A19: 网络-251223-042262-4 | B19: 2025-12-23 14:43:46 | C19: 2025-12-23 14:53:58 | D19: 2025-12-23 15:04:49 | E19: 高新生 | F19: 男 | G19: 手机,13717801036; | H19: 工单来源：微信服务号，此工单内容为网民留言时填写的标题及原文。 ============================= 留言标题：不雅.肮脏.懒政.失职的北京市599路公交车（当值随车保安和司机）留言原文：2025-12-16下午16：26本人在此车内，发现有许多区域肮脏.不雅.上座前还需本人自行清理（车号3628334），这又一次证明此车队人员不尽责；车队领导们不作为（书记王广宇13910701906；队长王璐女15910568188等数名责任人员）问题仍存在！急需整顿.治理.纠正和换人！望市民热线和上级职能部门做深入督查和惩处！还市民对北京市公共交道以信心！！！市民填写的详细地址为：区、街道：大兴区黄村镇详细地址：博兴六路公交场站，67834230/67656962。安服安保组织 鸿运承 | I19: 是 | J19: 诉求 | K19: 行车安全服务部 | L19: 企业政策问题 | M19: 调整服务规范 | N19: 鸿运承物业管理中心 | O19: 明月湾分中心 | P19: 物管行政部 | Q19: 明月湾分中心 | R19: 2025-12-30 23:59:59 | S19: 2025-12-24 | T19: 2025-12-28 08:59:59 | U19: 结束 | V19: 0 | W19: 您好，关于您反映问题的办理情况，鸿运承物业管理中心明月湾分中心现对您回复如下： | X19: 我分中心已于2025年12月24日上午10点52分对您进行电话回复。办理人：吴岩；部门：鸿运承物业管理中心明月湾分中心；职务；物管副主任。审核人：郑楠；部门：鸿运承物业管理中心物管行政部；职务：物管员。 | Y19: 高先生您好，599路公交车我们在泰和园三里场站进行洗车服务工作，您所述3628334号车，车辆运营中发现有许多区域肮脏、不雅、上座前还需您自行清理的问题，我们非常重视您的反馈，您提供的问题照片我们已收到，由于我们的工作没有做好，599路给您带来不好的乘车体验，实在是抱歉，高先生。该车辆回到泰和园三里场站后，在日常工作时段内，我们保洁员已对车内玻璃、座椅、内壁等部位的卫生进行了全面的清理，确保我们的出场车辆卫生符合企业标准。您反馈的问题我们已整改完毕，同时我们要求保洁员对599路所有运营车辆的卫生再次进行细化清理。我们对于运营车辆车内卫生的清洁工作是一直在做的，也从未停止，已经形成了长效的清洁机制，但有时候卫生清洁工作我们做的还有不尽人意之处，您多多谅解。 | Z19: 我们分中心及场站班组长再次与599路的保洁人员进行了沟通，日常工作中我们要把清洁质量做的更加细致，同时加强保洁员清洁技能的培训，熟练掌握清洁方法，确保给您带来一个干净、整洁的出行环境。 | AA19: 我们定期会召开车辆保洁专题会议，开展车辆卫生专项检查，日常工作中我们加大巡检力度，强化制度建设，不断提高管理水平。 | AB19: 欢迎您随时对我们的工作进行监督，感谢您提出宝贵意见，给您的出行带来的不便我们和您说声抱歉，谢谢您的支持与谅解。 | AC19: 满意 | AD19: 个人 | AE19: 2025-12-23 11:56:07 | AF19: 1741937713 | AG19: 服务 | AH19: 否 | AK19: =AG19&L19&M19 -> 服务企业政策问题调整服务规范 | AP19: 15 | AQ19: 46023 | AR19: =IFERROR(LEFT(A19,FIND("（",A19)-1),A19) -> 网络-251223-042262-4 | AS19: =J19 -> 诉求 | AT19: =IF(MID(AR19,1,2)="热线",12345)+IF(MID(AR19,1,2)="网络",12345) -> 12345 | AU19: =IFERROR(LEFT(D19,FIND(" ",D19)-1),D19) -> 2025-12-23 | AV19: =P19 -> 物管行政部 | AW19: =Q19 -> 明月湾分中心 | AX19: =H19 -> 工单来源：微信服务号，此工单内容为网民留言时填写的标题及原文。 ============================= 留言标题：不雅.肮脏.懒政.失职的北京市599路公交车（当值随车保安和司机）留言原文：2025-12-16下午16：26本人在此车内，发现有许多区域肮脏.不雅.上座前还需本人自行清理（车号3628334），这又一次证明此车队人员不尽责；车队领导们不作为（书记王广宇13910701906；队长王璐女15910568188等数名责任人员）问题仍存在！急需整顿.治理.纠正和换人！望市民热线和上级职能部门做深入督查和惩处！还市民对北京市公共交道以信心！！！市民填写的详细地址为：区、街道：大兴区黄村镇详细地址：博兴六路公交场站，67834230/67656962。安服安保组织 鸿运承 | AY19: =AG19 -> 服务 | AZ19: 否 | BA19: 否 | BB19: 否 | BC19: 七有五性,宜居性 | BD19: =U19 -> 结束 | BE19: =IFERROR(LEFT(T19,FIND(" ",T19)-1),T19) -> 2025-12-28 | BF19: 车辆卫生问题 （车内卫生、玻璃） | BG19: 物管行政部 | BH19: 明月湾分中心 | BL19: =IF(BG19="物管行政部","侯旭、郑楠",IF(BG19="安保部","张耕",IF(BG19="工程设备部","华菲",IF(BG19="人力资源部","成琦",IF(BG19="党委工作部","阎鑫雨",IF(BG19="餐饮服务部","赵弘晨",IF(BG19="工会","郑欣",IF(BG19="办公室","董娜",""))))))))&IF(BG19="纪检部","黄倩",IF(BG19="信息管理部","蔡浩然","")) -> 侯旭、郑楠 | BM19: 未主动剔除 | BP19: 业务类 | BQ19: 多渠道同人同诉：网络-251223-042262-4、热线-260105-038505-2、网络-260109-053098-1、GJ-PHONE-20260111-0012 | BR19: 是 | BS19: 先12345再96166 | BV19: =MID(AR19,1,16) -> 网络-251223-042262 | BW19: 七有五性,便利性 | BX19: =IF(COUNTIF(BV:BV,BV19)=1,"否","是") -> 否 | BY19: =MID(AR19,18,1) -> 4 | CG19: =VLOOKUP(AR19,[1]市民意见信息导出!$AI$2:$AK$392,3,FALSE()) -> 结束 | CH19: =VLOOKUP(BV19,[2]Sheet1!$C$2:$AC$99,2,FALSE()) -> #N/A
A20: 热线-251222-074443（1个附件） | B20: 2025-12-23 17:32:42 | C20: 2025-12-23 17:42:33 | D20: 2025-12-23 17:47:18 | E20: 樊女士 | F20: 女 | G20: 手机,13513266399; | H20: 市民反映，自己是公交集团（公司名称：北京公共交通控股（集团）有限公司，地址：西城区南礼士路44号）的员工，自己生育后回到公司，公司给自己安排的都是体力活，对此不认可，沟通后说让自己待岗三个月，每月1800元，来电反映公司安排工作不合理问题。工单流转：西城区分中心退回：经核实，诉求人反映北京公共交通控股（集团）有限公司鸿运承物业管理中心工作安排不合理的问题。市民表示其产假后返岗后在河北香河县工作，公司拟安排市民返回单位内部分配的B、C岗位或继续待岗，市民认为其市民身体情况不适宜B、C岗位，希望单位或上级单位能够重新考虑安排。经查，鸿运承物业管理中心上级单位为北京公共交通控股（集团）有限公司。工作人员告知市民希望与单位协商工作安排事宜属于单位内部管理问题，烦请市中心转上级单位北京公共交通控股（集团）有限公司进行协调。 | I20: 是 | J20: 诉求 | K20: 人力资源部（人力资源发展中心） | L20: 工资及五险二金 | M20: 工资方面 | N20: 鸿运承物业管理中心 | O20: 凌家庙分中心 | P20: 人力资源部 | Q20: 凌家庙分中心 | R20: 2025-12-30 23:59:59 | S20: 2025-12-25 | T20: 2025-12-28 08:59:59 | U20: 结束 | V20: 1 | W20: 经核实，来电人为我单位凌家庙分中心职工，与来电人所述情况存在出入。本次企业改革是根据《鸿运承物业管理中心综合站务员优化配置改革工作实施方案》、《鸿运承物业管理中心综合站务员A岗管理规定（试行）》等制度文件开展，我单位为落选的原综A人员提供4类转岗安置方案，并非直接安排B岗、C岗工作。且分中心于12月15日通过微信形式通知来电人可参与乘务巡检员竞聘，来电人未报名。12月22日凌家庙分中心相关领导及劳人员也与来电人进行面对面沟通。 | X20: 经核实，来电人为我单位凌家庙分中心职工，与来电人所述情况存在出入。本次企业改革是根据《鸿运承物业管理中心综合站务员优化配置改革工作实施方案》、《鸿运承物业管理中心综合站务员A岗管理规定（试行）》等制度文件开展，我单位为落选的原综A人员提供4类转岗安置方案，并非直接安排B岗、C岗工作。且分中心于12月15日通过微信形式通知来电人可参与乘务巡检员竞聘，来电人未报名。12月22日凌家庙分中心相关领导及劳人员也与来电人进行面对面沟通。 接到诉求后，我单位分中心于12月25日10点31分与来电人进行电话回复，经过与来电人沟通，来电人表示已知晓。 办理人：王跃，鸿运承物业管理中心凌家庙分中心，职务：一般管理； 审核人：高强；部门：鸿运承物业管理中心人力资源部；职务：中级管理。 | Y20: 接到诉求后，我单位分中心于12月25日10点31分与来电人进行电话回复，经过与来电人沟通，来电人表示已知晓。 | Z20: 无 | AA20: 无 | AB20: 经核实，来电人为我单位凌家庙分中心职工，与来电人所述情况存在出入。本次企业改革是根据《鸿运承物业管理中心综合站务员优化配置改革工作实施方案》、《鸿运承物业管理中心综合站务员A岗管理规定（试行）》等制度文件开展，我单位为落选的原综A人员提供4类转岗安置方案，并非直接安排B岗、C岗工作。且分中心于12月15日通过微信形式通知来电人可参与乘务巡检员竞聘，来电人未报名。12月22日凌家庙分中心相关领导及劳人员也与来电人进行面对面沟通。 接到诉求后，我单位分中心于12月25日10点31分与来电人进行电话回复，经过与来电人沟通，来电人表示已知晓。 | AC20: 满意 | AD20: 个人 | AE20: 2025-12-22 20:31:08 | AF20: 1862108387 | AG20: 劳动合同及用工管理 | AH20: 否 | AK20: =AG20&L20&M20 -> 劳动合同及用工管理工资及五险二金工资方面 | AP20: 16 | AQ20: 46023 | AR20: =IFERROR(LEFT(A20,FIND("（",A20)-1),A20) -> 热线-251222-074443 | AS20: =J20 -> 诉求 | AT20: =IF(MID(AR20,1,2)="热线",12345)+IF(MID(AR20,1,2)="网络",12345) -> 12345 | AU20: =IFERROR(LEFT(D20,FIND(" ",D20)-1),D20) -> 2025-12-23 | AV20: =P20 -> 人力资源部 | AW20: =Q20 -> 凌家庙分中心 | AX20: =H20 -> 市民反映，自己是公交集团（公司名称：北京公共交通控股（集团）有限公司，地址：西城区南礼士路44号）的员工，自己生育后回到公司，公司给自己安排的都是体力活，对此不认可，沟通后说让自己待岗三个月，每月1800元，来电反映公司安排工作不合理问题。工单流转：西城区分中心退回：经核实，诉求人反映北京公共交通控股（集团）有限公司鸿运承物业管理中心工作安排不合理的问题。市民表示其产假后返岗后在河北香河县工作，公司拟安排市民返回单位内部分配的B、C岗位或继续待岗，市民认为其市民身体情况不适宜B、C岗位，希望单位或上级单位能够重新考虑安排。经查，鸿运承物业管理中心上级单位为北京公共交通控股（集团）有限公司。工作人员告知市民希望与单位协商工作安排事宜属于单位内部管理问题，烦请市中心转上级单位北京公共交通控股（集团）有限公司进行协调。 | AY20: =AG20 -> 劳动合同及用工管理 | AZ20: 是 | BA20: 是 | BB20: 否 | BC20: 七有五性,公正性 | BD20: =U20 -> 结束 | BE20: =IFERROR(LEFT(T20,FIND(" ",T20)-1),T20) -> 2025-12-28 | BF20: 劳动人员调配及薪酬 （综A岗-产后复岗） | BG20: 人力资源部 | BH20: 凌家庙分中心 | BL20: =IF(BG20="物管行政部","侯旭、郑楠",IF(BG20="安保部","张耕",IF(BG20="工程设备部","华菲",IF(BG20="人力资源部","成琦",IF(BG20="党委工作部","阎鑫雨",IF(BG20="餐饮服务部","赵弘晨",IF(BG20="工会","郑欣",IF(BG20="办公室","董娜",""))))))))&IF(BG20="纪检部","黄倩",IF(BG20="信息管理部","蔡浩然","")) -> 成琦 | BM20: 未主动剔除 | BP20: 政策类 | BV20: =MID(AR20,1,16) -> 热线-251222-074443 | BW20: 七有五性,劳有所得 | BX20: =IF(COUNTIF(BV:BV,BV20)=1,"否","是") -> 否 | BY20: =MID(AR20,18,1) | CG20: =VLOOKUP(AR20,[1]市民意见信息导出!$AI$2:$AK$392,3,FALSE()) -> 结束 | CH20: =VLOOKUP(BV20,[2]Sheet1!$C$2:$AC$99,2,FALSE()) -> #N/A
A21: 热线-251223-071646-3（1个附件） | B21: 2025-12-23 20:41:51 | C21: 2025-12-23 20:52:29 | D21: 2025-12-23 20:56:51 | E21: 高先生 | F21: 男 | G21: 手机,18701035101; | H21: 市民反映，12月23号双峪车站（去往新桥方向）的992路公交车没有窗帘，而且车内还很脏乱，市民认为作为交通运输服务行业，窗帘是最基本的，原来反映过其他车队，给出回复说没钱，市民不认可，市民表示问题没有解决，来电反映公交车没有窗帘问题。科信 安服 鸿运承 | I21: 是 | J21: 诉求 | K21: 行车安全服务部 | L21: 企业政策问题 | M21: 调整服务规范 | N21: 鸿运承物业管理中心 | O21: 河滩分中心 | P21: 物管行政部 | Q21: 河滩分中心 | R21: 2025-12-30 23:59:59 | S21: 2025-12-24 | T21: 2025-12-28 08:59:59 | U21: 结束 | V21: 0 | W21: 您好，关于您反映问题的办理情况，鸿运承物业管理中心河滩分中心现对您回复如下： | X21: 我分中心已于2025年12月24日下午13点59分对您进行电话回复，我对您没有答复完整，通话中您在与其他人对话，故我冒昧给您发送短信告诉您一下我们对您反映问题的办理结果。办理人：杨壑松；部门：鸿运承物业管理中心河滩分中心；职务；物管副主任。审核人：郑楠；部门：鸿运承物业管理中心物管行政部；职务：物管员。 | Y21: 高先生您好，992路公交车我们在龙泉西场站进行洗车服务工作，您所述车辆运营中车内很脏乱的问题我们非常重视您的反馈，由于我们的工作没有做好，992路给您带来不好的乘车体验，实在是抱歉，高先生。该线路车辆回到龙泉西场站后，在日常工作时段内，我们的保洁员已对车内卫生进行了全面的清理，确保我们的出场车辆卫生符合企业标准。您反馈的问题我们已整改完毕，同时我们要求保洁员对992路所有运营车辆的卫生再次进行细化清理。我们对于运营车辆车内卫生的清洁工作是一直在做的，也从未停止，已经形成了长效的清洁机制，但有时候卫生清洁工作我们做的还有不尽人意之处，您多多谅解。部分车辆车内未安装窗帘的问题，待车队配齐窗帘后，我们会立即进行安装。 | Z21: 我们分中心及场站班组长再次与992路的保洁人员进行了沟通，日常工作中我们要把清洁质量做的更加细致，同时加强保洁员清洁技能的培训，熟练掌握清洁方法，确保给您带来一个干净、整洁的出行环境。 | AA21: 我们定期会召开车辆保洁专题会议，开展车辆卫生专项检查，日常工作中我们加大巡检力度，强化制度建设，不断提高管理水平。 | AB21: 您好，关于您反映问题的办理情况，鸿运承物业管理中心河滩分中心现对您回复如下：高先生您好，992路公交车我们在龙泉西场站进行洗车服务工作，您所述车辆运营中车内很脏乱的问题我们非常重视您的反馈，由于我们的工作没有做好，992路给您带来不好的乘车体验，实在是抱歉，高先生。该线路车辆回到龙泉西场站后，在日常工作时段内，我们的保洁员已对车内卫生进行了全面的清理，确保我们的出场车辆卫生符合企业标准。您反馈的问题我们已整改完毕，同时我们要求保洁员对992路所有运营车辆的卫生再次进行细化清理。我们对于运营车辆车内卫生的清洁工作是一直在做的，也从未停止，已经形成了长效的清洁机制，但有时候卫生清洁工作我们做的还有不尽人意之处，您多多谅解。部分车辆车内未安装窗帘的问题，待车队配齐窗帘后，我们会立即进行安装。我们定期会召开车辆保洁专题会议，开展车辆卫生专项检查，日常工作中我们加大巡检力度，强化制度建设，不断提高管理水平。我分中心已于2025年12月24日下午13点59分对您进行电话回复，我对您没有答复完整，通话中您在与其他人对话，故我冒昧给您发送短信告诉您一下我们对您反映问题的办理结果。我们分中心及场站班组长再次与992路的保洁人员进行了沟通，日常工作中我们要把清洁质量做的更加细致，同时加强保洁员清洁技能的培训，熟练掌握清洁方法，确保给您带来一个干净、整洁的出行环境。欢迎您随时对我们的工作进行监督，感谢您提出宝贵意见，给您的出行带来的不便我们和您说声抱歉，谢谢您的支持与谅解。 | AC21: 满意 | AD21: 个人 | AE21: 2025-12-23 20:31:05 | AF21: 1725545789 | AG21: 设施设备 | AH21: 否 | AK21: =AG21&L21&M21 -> 设施设备企业政策问题调整服务规范 | AP21: 17 | AQ21: 46023 | AR21: =IFERROR(LEFT(A21,FIND("（",A21)-1),A21) -> 热线-251223-071646-3 | AS21: =J21 -> 诉求 | AT21: =IF(MID(AR21,1,2)="热线",12345)+IF(MID(AR21,1,2)="网络",12345) -> 12345 | AU21: =IFERROR(LEFT(D21,FIND(" ",D21)-1),D21) -> 2025-12-23 | AV21: =P21 -> 物管行政部 | AW21: =Q21 -> 河滩分中心 | AX21: =H21 -> 市民反映，12月23号双峪车站（去往新桥方向）的992路公交车没有窗帘，而且车内还很脏乱，市民认为作为交通运输服务行业，窗帘是最基本的，原来反映过其他车队，给出回复说没钱，市民不认可，市民表示问题没有解决，来电反映公交车没有窗帘问题。科信 安服 鸿运承 | AY21: =AG21 -> 设施设备 | AZ21: 否 | BA21: 否 | BB21: 否 | BC21: 七有五性,宜居性 | BD21: =U21 -> 结束 | BE21: =IFERROR(LEFT(T21,FIND(" ",T21)-1),T21) -> 2025-12-28 | BF21: 车辆卫生问题 （车内脏、窗帘） | BG21: 物管行政部 | BH21: 河滩分中心 | BL21: =IF(BG21="物管行政部","侯旭、郑楠",IF(BG21="安保部","张耕",IF(BG21="工程设备部","华菲",IF(BG21="人力资源部","成琦",IF(BG21="党委工作部","阎鑫雨",IF(BG21="餐饮服务部","赵弘晨",IF(BG21="工会","郑欣",IF(BG21="办公室","董娜",""))))))))&IF(BG21="纪检部","黄倩",IF(BG21="信息管理部","蔡浩然","")) -> 侯旭、郑楠 | BM21: 未主动剔除 | BP21: 业务类 | BV21: =MID(AR21,1,16) -> 热线-251223-071646 | BW21: 七有五性,便利性 | BX21: =IF(COUNTIF(BV:BV,BV21)=1,"否","是") -> 否 | BY21: =MID(AR21,18,1) -> 3 | CG21: =VLOOKUP(AR21,[1]市民意见信息导出!$AI$2:$AK$392,3,FALSE()) -> 结束 | CH21: =VLOOKUP(BV21,[2]Sheet1!$C$2:$AC$99,2,FALSE()) -> #N/A
A22: 热线-251223-074632（3个附件） | B22: 2025-12-23 22:03:04 | C22: 2025-12-24 00:13:27 | D22: 2025-12-24 08:38:42 | E22: 刘先生 | F22: 男 | G22: 手机,15210598471; | H22: 市民反映，朝阳区朝阳五路居公交场站（117路与107路等车辆），门口保安人员向路侧建安东路停车人员主动索要停车费，不交费不让停车，市民表示公交场站门口建安东路路段是违停路段，属于非法索要停车费，要求核查，来电反映非法索要停车费问题。 | I22: 是 | J22: 诉求 | K22: 安保部（应急管理中心） | L22: 场站保安问题 | M22: 场站保安 | N22: 鸿运承物业管理中心 | O22: 小营分中心 | P22: 安保部（应急管理中心） | Q22: 小营分中心 | R22: 2025-12-30 23:59:59 | S22: 2025-12-24 | T22: 2025-12-28 08:59:59 | U22: 结束 | V22: 0 | W22: 市民反映，朝阳区朝阳五路居公交场站（117路与107路等车辆），门口保安人员向路侧建安东路停车人员主动索要停车费，不交费不让停车，市民表示公交场站门口建安东路路段是违停路段，属于非法索要停车费，要求核查，来电反映非法索要停车费问题。经核实： 经核实：分中心接到投诉人所反映的问题后，给予了高度重视，第一时间与场站班长及保安负责人进行了核实，核实后是投诉人停车的位置属于公交车进出入场站的必要位置，门岗警卫人员也告知了投诉人此处不能停车，容易产生安全隐患，并告知投诉人场站门放置了锥桶，并也没有向投诉人所反映的门岗警卫人员存在，向车主收取费用一事，故与投诉人所说内容不属实申请剔除。与投诉人电话回访后，以得到投诉人的理解。 | X22: 回访情况：2025年12月24日下午10:34分，电话回访市民，以得到市民的谅解（回访电话：13439848360）办理人：何少楠。审核员：贾志尧。单位：小营分中心。职务：副主任 | Y22: 分中心再次对门岗警卫值守加强检查，及时发现问题后立即作出相关处理。 | Z22: 对场站所有的警卫职工，在岗期间继续履行好自己的岗位职责，严格按照物业公司对门岗警卫人员工作要求的相关文件，做好本职工作， 分中心对在其在职保安公司人员，进行严格检查及培训。发现问题第一时间整改，做出处理。 | AA22: 对场站所有的警卫职工，分中心要求在岗期间继续履行好自己的岗位职责，做到生人必问，生车必拦做到登记工作。 | AB22: 市民反映，朝阳区朝阳五路居公交场站（117路与107路等车辆），门口保安人员向路侧建安东路停车人员主动索要停车费，不交费不让停车，市民表示公交场站门口建安东路路段是违停路段，属于非法索要停车费，要求核查，来电反映非法索要停车费问题。经核实： 经核实：分中心接到投诉人所反映的问题后，给予了高度重视，第一时间与场站班长及保安负责人进行了核实，核实后是投诉人停车的位置属于公交车进出入场站的必要位置，门岗警卫人员也告知了投诉人此处不能停车，容易产生安全隐患，并告知投诉人场站门放置了锥桶，并也没有向投诉人所反映的门岗警卫人员存在，向车主收取费用一事，故与投诉人所说内容不属实申请剔除。与投诉人电话回访后，以得到投诉人的理解。 | AC22: 满意 | AD22: 个人 | AE22: 2025-12-23 21:49:47 | AF22: 1741937704 | AG22: 服务 | AH22: 否 | AK22: =AG22&L22&M22 -> 服务场站保安问题场站保安 | AP22: 18 | AQ22: 46023 | AR22: =IFERROR(LEFT(A22,FIND("（",A22)-1),A22) -> 热线-251223-074632 | AS22: =J22 -> 诉求 | AT22: =IF(MID(AR22,1,2)="热线",12345)+IF(MID(AR22,1,2)="网络",12345) -> 12345 | AU22: =IFERROR(LEFT(D22,FIND(" ",D22)-1),D22) -> 2025-12-24 | AV22: =P22 -> 安保部（应急管理中心） | AW22: =Q22 -> 小营分中心 | AX22: =H22 -> 市民反映，朝阳区朝阳五路居公交场站（117路与107路等车辆），门口保安人员向路侧建安东路停车人员主动索要停车费，不交费不让停车，市民表示公交场站门口建安东路路段是违停路段，属于非法索要停车费，要求核查，来电反映非法索要停车费问题。 | AY22: =AG22 -> 服务 | AZ22: 否 | BA22: 否 | BB22: 否 | BC22: 七有五性,安全性,便利性 | BD22: =U22 -> 结束 | BE22: =IFERROR(LEFT(T22,FIND(" ",T22)-1),T22) -> 2025-12-28 | BF22: 场站安保问题 （私家车停车收费） | BG22: 安保部 | BH22: 小营分中心 | BL22: =IF(BG22="物管行政部","侯旭、郑楠",IF(BG22="安保部","张耕",IF(BG22="工程设备部","华菲",IF(BG22="人力资源部","成琦",IF(BG22="党委工作部","阎鑫雨",IF(BG22="餐饮服务部","赵弘晨",IF(BG22="工会","郑欣",IF(BG22="办公室","董娜",""))))))))&IF(BG22="纪检部","黄倩",IF(BG22="信息管理部","蔡浩然","")) -> 张耕 | BM22: 未主动剔除 | BP22: 业务类 | BV22: =MID(AR22,1,16) -> 热线-251223-074632 | BW22: 七有五性,便利性 | BX22: =IF(COUNTIF(BV:BV,BV22)=1,"否","是") -> 否 | BY22: =MID(AR22,18,1) | CG22: =VLOOKUP(AR22,[1]市民意见信息导出!$AI$2:$AK$392,3,FALSE()) -> 结束 | CH22: =VLOOKUP(BV22,[2]Sheet1!$C$2:$AC$99,2,FALSE()) -> #N/A
A23: 网络-251224-000503 | B23: 2025-12-24 00:49:36 | C23: 2025-12-24 00:58:28 | D23: 2025-12-24 08:50:42 | E23: 保密 | F23: 女 | G23: 保密 | H23: 工单来源：微信服务号，此工单内容为网民留言时填写的标题及原文。 ============================= 留言标题：动物园地下一层回复不满意。留言原文：就动物园枢纽换乘大厅一事回复不满意。原文回复内容如下。【北京公共交通控股（集团）有限公司回复反馈】:您好，关于您反映问题的办理情况，公交集团回复如下:经动物园分中心核实此情况，动物园公交枢纽的所有滚动扶梯已停用，并且枢纽地下公交IC卡充值点已撤点多年，枢纽地上能满足公交与地铁的换乘，并且动物园公交枢纽场站地下空间现在是公交区域调度、公交电车客运分公司车队和公交物业动物园分中心的办公场所和公交职工食堂，为了确保办公区域安全，关闭卷帘门。就动物园枢纽换乘大厅一事回复不满意。认为不调查，敷衍了事，原来动物园枢纽出了地铁就是地下一层换乘大厅，非常利于乘客方便换乘。现在成了职工食堂，运营车队办公室和物业办公室，这不是属于占用公共资源，不服务于人民。说滚动扶梯停用，这是方便乘客换乘，凭什么不使用。本身是服务于人民，方便于换乘，现成为单位的办公区域。希望领导重视，早日打开换乘大厅。市民填写的详细地址为：区、街道：海淀区甘家口街道详细地址：动物园公交枢纽地下一层 答复不满意 | I23: 是 | J23: 其他 | K23: 安保部（应急管理中心） | L23: 安保专业其他问题 | M23: 安保专业补充内容 | N23: 鸿运承物业管理中心 | O23: 动物园分中心 | P23: 安全保卫部（应急管理中心） | Q23: 动物园分中心 | R23: 2025-12-31 23:59:59 | S23: 2025-12-25 | T23: 2025-12-29 08:59:59 | U23: 结束 | V23: 2 | W23: 经动物园分中心再次调查核实此情况，动物园公交枢纽地上能满足市民公交与地铁的换乘，动物园公交枢纽场站地下空间现在是公交内部办公场所，为了确保公交办公区域安全，关闭卷帘门。 | X23: 由于诉求人未留联系姓名和联系电话，无法取得联系。处理人动物园分中心安保主任翟祺。 | Y23: 通过此事件提醒动物园公交枢纽场站工作人员遇有乘客询问时耐心做好解释。 | Z23: 通过此事件提醒动物园公交枢纽场站工作人员遇有乘客询问时耐心做好解释。 | AA23: 通过此事件提醒动物园公交枢纽场站工作人员遇有乘客询问时耐心做好解释。 | AB23: 经动物园分中心再次调查核实此情况，动物园公交枢纽地上能满足市民公交与地铁的换乘，动物园公交枢纽场站地下空间现在是公交内部办公场所，为了确保公交办公区域安全，关闭卷帘门。通过此事件提醒动物园公交枢纽场站工作人员遇有乘客询问时耐心做好解释。由于诉求人未留联系姓名和联系电话，无法取得联系。处理人动物园分中心安保主任翟祺。 | AC23: 满意 | AD23: 个人 | AE23: 2025-12-21 12:09:39 | AF23: 1741937703 | AG23: 服务 | AH23: 否 | AK23: =AG23&L23&M23 -> 服务安保专业其他问题安保专业补充内容 | AP23: 19 | AQ23: 46023 | AR23: =IFERROR(LEFT(A23,FIND("（",A23)-1),A23) -> 网络-251224-000503 | AS23: =J23 -> 其他 | AT23: =IF(MID(AR23,1,2)="热线",12345)+IF(MID(AR23,1,2)="网络",12345) -> 12345 | AU23: =IFERROR(LEFT(D23,FIND(" ",D23)-1),D23) -> 2025-12-24 | AV23: =P23 -> 安全保卫部（应急管理中心） | AW23: =Q23 -> 动物园分中心 | AX23: =H23 -> 工单来源：微信服务号，此工单内容为网民留言时填写的标题及原文。 ============================= 留言标题：动物园地下一层回复不满意。留言原文：就动物园枢纽换乘大厅一事回复不满意。原文回复内容如下。【北京公共交通控股（集团）有限公司回复反馈】:您好，关于您反映问题的办理情况，公交集团回复如下:经动物园分中心核实此情况，动物园公交枢纽的所有滚动扶梯已停用，并且枢纽地下公交IC卡充值点已撤点多年，枢纽地上能满足公交与地铁的换乘，并且动物园公交枢纽场站地下空间现在是公交区域调度、公交电车客运分公司车队和公交物业动物园分中心的办公场所和公交职工食堂，为了确保办公区域安全，关闭卷帘门。就动物园枢纽换乘大厅一事回复不满意。认为不调查，敷衍了事，原来动物园枢纽出了地铁就是地下一层换乘大厅，非常利于乘客方便换乘。现在成了职工食堂，运营车队办公室和物业办公室，这不是属于占用公共资源，不服务于人民。说滚动扶梯停用，这是方便乘客换乘，凭什么不使用。本身是服务于人民，方便于换乘，现成为单位的办公区域。希望领导重视，早日打开换乘大厅。市民填写的详细地址为：区、街道：海淀区甘家口街道详细地址：动物园公交枢纽地下一层 答复不满意 | AY23: =AG23 -> 服务 | AZ23: 否 | BA23: 否 | BB23: 否 | BC23: 七有五性,安全性,便利性 | BD23: =U23 -> 结束 | BE23: =IFERROR(LEFT(T23,FIND(" ",T23)-1),T23) -> 2025-12-29 | BF23: 场站安保问题 （咨询换乘大厅启用） | BG23: 安保部 | BH23: 动物园分中心 | BL23: =IF(BG23="物管行政部","侯旭、郑楠",IF(BG23="安保部","张耕",IF(BG23="工程设备部","华菲",IF(BG23="人力资源部","成琦",IF(BG23="党委工作部","阎鑫雨",IF(BG23="餐饮服务部","赵弘晨",IF(BG23="工会","郑欣",IF(BG23="办公室","董娜",""))))))))&IF(BG23="纪检部","黄倩",IF(BG23="信息管理部","蔡浩然","")) -> 张耕 | BM23: 未主动剔除 | BP23: 政策类 | BR23: 是 | BV23: =MID(AR23,1,16) -> 网络-251224-000503 | BW23: 七有五性,便利性 | BX23: =IF(COUNTIF(BV:BV,BV23)=1,"否","是") -> 否 | BY23: =MID(AR23,18,1) | CG23: =VLOOKUP(AR23,[1]市民意见信息导出!$AI$2:$AK$392,3,FALSE()) -> 结束 | CH23: =VLOOKUP(BV23,[2]Sheet1!$C$2:$AC$99,2,FALSE()) -> #N/A
A24: 热线-251224-024222（2个附件） | B24: 2025-12-24 11:21:46 | C24: 2025-12-24 11:31:43 | D24: 2025-12-24 11:48:14 | E24: 李先生 | F24: 男 | G24: 手机,13387580220; | H24: 市民举报，北京公共交通控股（集团）有限公司的售票员刘婷婷，这位工作人员涉嫌挪用单位公章，为自己开具虚假过高的收入证明材料，违反事业单位管理条例规定，在外参与金融借贷活动从中获利，违反了中华人民共和国政务处分法规定，售票员身份证号：110111198205082844，盖章单位：公共交通控股有限公司鸿运承物业管理中心，来电举报北京公共交通控股（集团）有限公司的售票员刘婷婷问题 | I24: 是 | J24: 其他 | K24: 人力资源部（人力资源发展中心） | L24: 人力资源方面其他问题 | M24: 人力资源方面补充内容 | N24: 鸿运承物业管理中心 | O24: 九龙分中心 | P24: 人力资源部 | Q24: 九龙分中心 | R24: 2025-12-31 23:59:59 | S24: 2025-12-25 | T24: 2025-12-29 08:59:59 | U24: 结束 | V24: 1 | W24: 经核实，与来电人所述情况存在出入。来电人所述职工刘婷婷已于2025年11月与我单位鸿运承物业管理中心协商一致解除劳动合同。该职工2020年11月划转至我单位，离职前原为我单位鸿运承物业管理中心九龙分中心职工，职工原分中心自刘婷婷划转到2025年11月未给其开具过相关收入证明。且经电话和李先生沟通，其表明反映的是2017年的相关情况，刘婷婷2017年非我单位职工。 | X24: 经核实，与来电人所述情况存在出入。来电人所述职工刘婷婷已于2025年11月与我单位鸿运承物业管理中心协商一致解除劳动合同。该职工2020年11月划转至我单位，离职前原为我单位鸿运承物业管理中心九龙分中心职工，职工原分中心自刘婷婷划转到2025年11月未给其开具过相关收入证明。且经电话和李先生沟通，其表明反映的是2017年的相关情况，刘婷婷2017年非我单位职工。 接到市民举报，我单位立即核实信息，并于2025年12月25日上午9点24分左右与来电人核实情况，于下午13点38分再次告知来电人情况。 办理人：唐国云，部门：鸿运承物业管理中心九龙分中心，职务：一般管理； 审核人：高强；部门：鸿运承物业管理中心人力资源部；职务：中级管理。 | Y24: 接到市民举报，我单位立即核实信息，并于2025年12月25日上午9点24分左右与来电人核实情况，于下午13点38分再次告知来电人情况。 | Z24: 无 | AA24: 无 | AB24: 经核实，与来电人所述情况存在出入。来电人所述职工刘婷婷已于2025年11月与我单位鸿运承物业管理中心协商一致解除劳动合同。该职工2020年11月划转至我单位，离职前原为我单位鸿运承物业管理中心九龙分中心职工，职工原分中心自刘婷婷划转到2025年11月未给其开具过相关收入证明。且经电话和李先生沟通，其表明反映的是2017年的相关情况，刘婷婷2017年非我单位职工。 接到市民举报，我单位立即核实信息，并于2025年12月25日上午9点24分左右与来电人核实情况，于下午13点38分再次告知来电人情况。 | AC24: 满意 | AD24: 个人 | AE24: 2025-12-24 11:13:45 | AF24: 1741937714 | AG24: 服务 | AH24: 否 | AK24: =AG24&L24&M24 -> 服务人力资源方面其他问题人力资源方面补充内容 | AP24: 20 | AQ24: 46023 | AR24: =IFERROR(LEFT(A24,FIND("（",A24)-1),A24) -> 热线-251224-024222 | AS24: =J24 -> 其他 | AT24: =IF(MID(AR24,1,2)="热线",12345)+IF(MID(AR24,1,2)="网络",12345) -> 12345 | AU24: =IFERROR(LEFT(D24,FIND(" ",D24)-1),D24) -> 2025-12-24 | AV24: =P24 -> 人力资源部 | AW24: =Q24 -> 九龙分中心 | AX24: =H24 -> 市民举报，北京公共交通控股（集团）有限公司的售票员刘婷婷，这位工作人员涉嫌挪用单位公章，为自己开具虚假过高的收入证明材料，违反事业单位管理条例规定，在外参与金融借贷活动从中获利，违反了中华人民共和国政务处分法规定，售票员身份证号：110111198205082844，盖章单位：公共交通控股有限公司鸿运承物业管理中心，来电举报北京公共交通控股（集团）有限公司的售票员刘婷婷问题 | AY24: =AG24 -> 服务 | AZ24: 否 | BA24: 否 | BB24: 否 | BC24: 七有五性,多样性 | BD24: =U24 -> 结束 | BE24: =IFERROR(LEFT(T24,FIND(" ",T24)-1),T24) -> 2025-12-29 | BF24: 劳动人员管理 | BG24: 人力资源部 | BH24: 九龙分中心 | BL24: =IF(BG24="物管行政部","侯旭、郑楠",IF(BG24="安保部","张耕",IF(BG24="工程设备部","华菲",IF(BG24="人力资源部","成琦",IF(BG24="党委工作部","阎鑫雨",IF(BG24="餐饮服务部","赵弘晨",IF(BG24="工会","郑欣",IF(BG24="办公室","董娜",""))))))))&IF(BG24="纪检部","黄倩",IF(BG24="信息管理部","蔡浩然","")) -> 成琦 | BM24: 未主动剔除 | BP24: 业务类 | BV24: =MID(AR24,1,16) -> 热线-251224-024222 | BW24: 七有五性,便利性 | BX24: =IF(COUNTIF(BV:BV,BV24)=1,"否","是") -> 否 | BY24: =MID(AR24,18,1) | BZ24: 只评价响应率 | CE24: 1月 | CG24: =VLOOKUP(AR24,[1]市民意见信息导出!$AI$2:$AK$392,3,FALSE()) -> 结束 | CH24: =VLOOKUP(BV24,[2]Sheet1!$C$2:$AC$99,2,FALSE()) -> 1月
A25: 热线-251224-022346-1（3个附件） | B25: 2025-12-24 13:34:58 | C25: 2025-12-24 13:43:03 | D25: 2025-12-24 13:56:20 | E25: 陈先生 | F25: 男 | G25: 手机,15510303087; | H25: 市民反映，朝阳区望京大西洋新城公交场站，场站内出口车道设置为靠左行，但是出口后立即和社会车辆交叉，存在较大的安全隐患，靠左行设置不合理，自己联系过公交集团，公交集团答复的是方便场内车辆调头运行，市民对此不认可，按照中国道路交通法规，应该靠右行驶，不知道在场站内设置为靠左行驶是否合理，来电反映核实大西洋新城公交场站内设置靠左行驶是否合理的问题。答复不满 | I25: 是 | J25: 其他 | K25: 基建行政部 | L25: 基建行政专业其他问题 | M25: 基建行政专业补充内容 | N25: 鸿运承物业管理中心 | O25: 南湖分中心 | P25: 机关 | Q25: 南湖分中心 | R25: 2025-12-31 23:59:59 | S25: 2025-12-25 | T25: 2025-12-29 08:59:59 | U25: 结束 | V25: 1 | W25: 此单为拆单投诉，公交物业负责回复“场站内引导标线施画方向违法，从而导致存在安全隐患”的问题。市民反映的是南湖公交场站站务设施设置问题。南湖公交场站是公交首末站。接到市民诉求后，公交物业公司南湖分中心非常重视，我们立即对相关情况进行多方咨询和求证。1.市民所说的大西洋新城公交场站（公交内部该场站叫南湖公交场站），场站自建成启用已经十余年，该场站内部设施设计、功能区域划分、行车导向线等都是由专业设计单位结合场站实际情况以及公交车运营需求设计（公交车车身长，进、出场站要考虑到拐弯半径以及在场站内安全运行线路），符合相关安全标准。2.该公交场站的车辆进、出口仅此一个，公交车进出也是此口。3.公交场站内部行车导向线也是由正规施工单位负责施画。4.针对市民的诉求点，我们于2025年12月24日再次向属地交通安全管理部门进行求证，经与朝阳交通支队询问沟通，朝阳交通支队答复“不违规、不违法”。公交场站内正规内部行车导向线属于场站内部标线，符合交通部门法律法规，不涉及标线违规施划，同时场站大门位置的出车或进车也不影响社会交通通行。 | X25: 南湖分中心于2025年12月25日9点47分与市民进行电话沟通与答复，和市民说明我们核实的情况，标线合规。市民不认可我们的解释说明，认为就是因为标线不合规，影响场站门口骑电动车出行。因为没有满足市民（要求更改场站引导标线）诉求，所以市民不认可、不满意。办理人：左强 鸿运承物业管理中心南湖分中心 物管设备主任。审核人：华菲 物管中心工程设备部 一般管理 | Y25: 针对市民的诉求点，我们于2025年12月24日再次向属地交通安全管理部门进行求证，经与朝阳交通支队询问沟通，朝阳交通支队答复“不违规、不违法”。公交场站内正规内部行车导向线属于场站内部标线，符合交通部门法律法规，不涉及标线违规施划，同时场站大门位置的出车或进车也不影响社会交通通行。 | Z25: 针对投诉人所反映情况，分中心要求各场站进一步细化服务工作，避免类似情况造成投诉。 | AA25: 无 | AB25: 此单为拆单投诉，公交物业负责回复“场站内引导标线施画方向违法，从而导致存在安全隐患”的问题。市民反映的是南湖公交场站站务设施设置问题。南湖公交场站是公交首末站。接到市民诉求后，公交物业公司南湖分中心非常重视，我们立即对相关情况进行多方咨询和求证。1.市民所说的大西洋新城公交场站（公交内部该场站叫南湖公交场站），场站自建成启用已经十余年，该场站内部设施设计、功能区域划分、行车导向线等都是由专业设计单位结合场站实际情况以及公交车运营需求设计（公交车车身长，进、出场站要考虑到拐弯半径以及在场站内安全运行线路），符合相关安全标准。2.该公交场站的车辆进、出口仅此一个，公交车进出也是此口。3.公交场站内部行车导向线也是由正规施工单位负责施画。4.针对市民的诉求点，我们于2025年12月24日再次向属地交通安全管理部门进行求证，经与朝阳交通支队询问沟通，朝阳交通支队答复“不违规、不违法”。公交场站内正规内部行车导向线属于场站内部标线，符合交通部门法律法规，不涉及标线违规施划，同时场站大门位置的出车或进车也不影响社会交通通行。南湖分中心于2025年12月25日9点47分与市民进行电话沟通与答复，和市民说明我们核实的情况，标线合规。市民不认可我们的解释说明，认为就是因为标线不合规，影响场站门口骑电动车出行。因为没有满足市民（要求更改场站引导标线）诉求，所以市民不认可、不满意。 | AC25: 满意 | AD25: 个人 | AE25: 2025-12-24 10:57:49 | AF25: 1741937705 | AG25: 线路站点 | AH25: 否 | AK25: =AG25&L25&M25 -> 线路站点基建行政专业其他问题基建行政专业补充内容 | AP25: 21 | AQ25: 46023 | AR25: =IFERROR(LEFT(A25,FIND("（",A25)-1),A25) -> 热线-251224-022346-1 | AS25: =J25 -> 其他 | AT25: =IF(MID(AR25,1,2)="热线",12345)+IF(MID(AR25,1,2)="网络",12345) -> 12345 | AU25: =IFERROR(LEFT(D25,FIND(" ",D25)-1),D25) -> 2025-12-24 | AV25: =P25 -> 机关 | AW25: =Q25 -> 南湖分中心 | AX25: =H25 -> 市民反映，朝阳区望京大西洋新城公交场站，场站内出口车道设置为靠左行，但是出口后立即和社会车辆交叉，存在较大的安全隐患，靠左行设置不合理，自己联系过公交集团，公交集团答复的是方便场内车辆调头运行，市民对此不认可，按照中国道路交通法规，应该靠右行驶，不知道在场站内设置为靠左行驶是否合理，来电反映核实大西洋新城公交场站内设置靠左行驶是否合理的问题。答复不满 | AY25: =AG25 -> 线路站点 | AZ25: 否 | BA25: 否 | BB25: 否 | BC25: 七有五性,安全性,便利性 | BD25: =U25 -> 结束 | BE25: =IFERROR(LEFT(T25,FIND(" ",T25)-1),T25) -> 2025-12-29 | BF25: 站务设施设置 （站内行车方向设置）多渠道同人同诉 | BG25: 工程设备部 | BH25: 南湖分中心 | BL25: =IF(BG25="物管行政部","侯旭、郑楠",IF(BG25="安保部","张耕",IF(BG25="工程设备部","华菲",IF(BG25="人力资源部","成琦",IF(BG25="党委工作部","阎鑫雨",IF(BG25="餐饮服务部","赵弘晨",IF(BG25="工会","郑欣",IF(BG25="办公室","董娜",""))))))))&IF(BG25="纪检部","黄倩",IF(BG25="信息管理部","蔡浩然","")) -> 华菲 | BM25: 未主动剔除 | BP25: 政策类 | BQ25: 多渠道同人同诉问题：GJ-PHONE-20251223-0664、热线-251224-022346-1 | BR25: 是 | BS25: 先96166后12345 | BV25: =MID(AR25,1,16) -> 热线-251224-022346 | BW25: 七有五性,便利性 | BX25: =IF(COUNTIF(BV:BV,BV25)=1,"否","是") -> 否 | BY25: =MID(AR25,18,1) -> 1 | BZ25: 只评价响应率 | CE25: 1月 | CG25: =VLOOKUP(AR25,[1]市民意见信息导出!$AI$2:$AK$392,3,FALSE()) -> 结束 | CH25: =VLOOKUP(BV25,[2]Sheet1!$C$2:$AC$99,2,FALSE()) -> 1月
A26: 热线-251225-059571（1个附件） | B26: 2025-12-25 17:22:28 | C26: 2025-12-25 17:43:49 | D26: 2025-12-25 20:04:36 | E26: 刘先生 | F26: 男 | G26: 手机,13552107771; | H26: 市民反映，前几天自己乘坐2次896路公交车，公交车特别脏，车厢内有痰，还有唾沫，玻璃上有头油，没有人打扫，希望相关职能部门核实处理，来电反映协调公交集团打扫公交车内卫生问题 | I26: 是 | J26: 诉求 | K26: 行车安全服务部 | L26: 企业政策问题 | M26: 调整服务规范 | N26: 鸿运承物业管理中心 | O26: 九龙分中心 | P26: 物管行政部 | Q26: 九龙分中心 | R26: 2026-01-01 23:59:59 | S26: 2025-12-26 | T26: 2025-12-30 08:59:59 | U26: 结束 | V26: 0 | W26: 您好，关于您反映问题的办理情况，鸿运承物业管理中心九龙分中心现对您回复如下： | X26: 我分中心已于2025年12月26日中午12点33分对您进行电话回复。办理人：潘志清；部门：鸿运承物业管理中心九龙分中心；职务；物管副主任。审核人：郑楠；部门：鸿运承物业管理中心物管行政部；职务：物管员。 | Y26: 刘先生您好，896路公交车我们在梨村场站进行洗车服务工作，您所述车辆运营中公交车特别脏，车厢内有痰，还有唾沫，玻璃上有头油，没有人打扫的问题我们非常重视您的反馈，由于我们的工作没有做好，896路给您带来不好的乘车体验，实在是抱歉，刘先生。该线路车辆回到梨村场站后，在日常工作时段内，我们的保洁员已对车内卫生进行了全面的清理，确保我们的出场车辆卫生符合企业标准。您反馈的问题我们已整改完毕，同时我们要求保洁员对896路所有运营车辆的卫生再次进行细化清理。我们对于运营车辆车内卫生的清洁工作是一直在做的，也从未停止，已经形成了长效的清洁机制，但有时候卫生清洁工作我们做的还有不尽人意之处，您多多谅解。 | Z26: 我们分中心及场站班组长再次与896路的保洁人员进行了沟通，日常工作中我们要把清洁质量做的更加细致，同时加强保洁员清洁技能的培训，熟练掌握清洁方法，确保给您带来一个干净、整洁的出行环境。 | AA26: 我们定期会召开车辆保洁专题会议，开展车辆卫生专项检查，日常工作中我们加大巡检力度，强化制度建设，不断提高管理水平。 | AB26: 您好，关于您反映问题的办理情况，鸿运承物业管理中心九龙分中心现对您回复如下：刘先生您好，896路公交车我们在梨村场站进行洗车服务工作，您所述车辆运营中公交车特别脏，车厢内有痰，还有唾沫，玻璃上有头油，没有人打扫的问题我们非常重视您的反馈，由于我们的工作没有做好，896路给您带来不好的乘车体验，实在是抱歉，刘先生。该线路车辆回到梨村场站后，在日常工作时段内，我们的保洁员已对车内卫生进行了全面的清理，确保我们的出场车辆卫生符合企业标准。您反馈的问题我们已整改完毕，同时我们要求保洁员对896路所有运营车辆的卫生再次进行细化清理。我们对于运营车辆车内卫生的清洁工作是一直在做的，也从未停止，已经形成了长效的清洁机制，但有时候卫生清洁工作我们做的还有不尽人意之处，您多多谅解。我们定期会召开车辆保洁专题会议，开展车辆卫生专项检查，日常工作中我们加大巡检力度，强化制度建设，不断提高管理水平。我分中心已于2025年12月26日中午12点33分对您进行电话回复。我们分中心及场站班组长再次与896路的保洁人员进行了沟通，日常工作中我们要把清洁质量做的更加细致，同时加强保洁员清洁技能的培训，熟练掌握清洁方法，确保给您带来一个干净、整洁的出行环境。欢迎您随时对我们的工作进行监督，感谢您提出宝贵意见，给您的出行带来的不便我们和您说声抱歉，谢谢您的支持与谅解。 | AC26: 满意 | AD26: 个人 | AE26: 2025-12-25 17:16:08 | AF26: 1741937714 | AG26: 服务 | AH26: 否 | AK26: =AG26&L26&M26 -> 服务企业政策问题调整服务规范 | AP26: 22 | AQ26: 46023 | AR26: =IFERROR(LEFT(A26,FIND("（",A26)-1),A26) -> 热线-251225-059571 | AS26: =J26 -> 诉求 | AT26: =IF(MID(AR26,1,2)="热线",12345)+IF(MID(AR26,1,2)="网络",12345) -> 12345 | AU26: =IFERROR(LEFT(D26,FIND(" ",D26)-1),D26) -> 2025-12-25 | AV26: =P26 -> 物管行政部 | AW26: =Q26 -> 九龙分中心 | AX26: =H26 -> 市民反映，前几天自己乘坐2次896路公交车，公交车特别脏，车厢内有痰，还有唾沫，玻璃上有头油，没有人打扫，希望相关职能部门核实处理，来电反映协调公交集团打扫公交车内卫生问题 | AY26: =AG26 -> 服务 | AZ26: 否 | BA26: 否 | BB26: 否 | BC26: 七有五性,宜居性 | BD26: =U26 -> 结束 | BE26: =IFERROR(LEFT(T26,FIND(" ",T26)-1),T26) -> 2025-12-30 | BF26: 车辆卫生问题 （车内卫生、玻璃） | BG26: 物管行政部 | BH26: 九龙分中心 | BL26: =IF(BG26="物管行政部","侯旭、郑楠",IF(BG26="安保部","张耕",IF(BG26="工程设备部","华菲",IF(BG26="人力资源部","成琦",IF(BG26="党委工作部","阎鑫雨",IF(BG26="餐饮服务部","赵弘晨",IF(BG26="工会","郑欣",IF(BG26="办公室","董娜",""))))))))&IF(BG26="纪检部","黄倩",IF(BG26="信息管理部","蔡浩然","")) -> 侯旭、郑楠 | BM26: 未主动剔除 | BP26: 业务类 | BV26: =MID(AR26,1,16) -> 热线-251225-059571 | BW26: 七有五性,便利性 | BX26: =IF(COUNTIF(BV:BV,BV26)=1,"否","是") -> 否 | BY26: =MID(AR26,18,1) | BZ26: 只评价响应率 | CE26: 1月 | CG26: =VLOOKUP(AR26,[1]市民意见信息导出!$AI$2:$AK$392,3,FALSE()) -> 结束 | CH26: =VLOOKUP(BV26,[2]Sheet1!$C$2:$AC$99,2,FALSE()) -> 1月
A27: 热线-251226-040071（1个附件） | B27: 2025-12-26 14:31:56 | C27: 2025-12-26 14:40:47 | D27: 2025-12-26 14:49:10 | E27: 陈莉女士 | F27: 女 | G27: 手机,13141299994; | H27: 市民反映，自己1980年进入京华客车厂上班，地址：西城区右安门内大街，自己在37岁的时候被公司办理了退休，当时申请的是自己完全丧失劳动能力，公司申请了之后劳动局直接通过了这个申请，他们给自己办理完成离职之后自己也一直在这个公司，但是他们并没有给自己按照规定缴纳社保，这家公司在2010年被北京市公共交通控股（集团）有限公司合并了，现在自己的问题在由公交公司处理，姓名：陈莉，身份证：110104196403043026，单位给自己交但是工作地的劳动局不收，希望西城区劳动局进行处理，从1992年到现在没有上保险，没有退休费，7月28日自己也去了通州区城市副中心，保安拦着不让进，耽误了一个小时，1.37岁退休不对，法律没有规定37岁退休的；2.自己没有完全丧失劳动能力，3.从1992年-2014年都没有保险，市民称问题未解决，要求再次反映，希望尽快处理，来电反映协调公交集团尽快上保险问题。 注：市民要求回电至新增手机号码。 | I27: 是 | J27: 其他 | K27: 人力资源部（人力资源发展中心） | L27: 人力资源方面其他问题 | M27: 人力资源方面补充内容 | N27: 鸿运承物业管理中心 | O27: 人力资源部 | P27: 人力资源部 | Q27: 机关 | R27: 2026-01-02 23:59:59 | S27: 2025-12-29 | T27: 2025-12-31 08:59:59 | U27: 结束 | V27: 0 | W27: 经核实，与来电人所述情况不相符。来电人陈莉女士系原京华客车退休职工，因京华客车解散，其退休关系于2009年划转至我单位鸿运承物业管理中心。经查阅资料，来电人曾申请过劳动鉴定，北京市公共交通总公司于2001年6月同意其申请。《北京市企业城镇劳动者退休审批表》显示，来电人的退休审批于2001年8月14日盖章审批通过。落款时间为2010年6月18日《北京市企业城镇劳动者退休审批表》显示，来电人退休时间为2001年8月。此外，来电人的情况2011年已经过北京市西城人民法院、北京市第一中级人民法院裁决，2012年3月12日北京市人力资源和社会保障局也已针对来电人情况做出《陈莉信访事项答复意见书》，2012年6月11日北京市人民政府也已作出《北京市人民政府信访事项复审意见书》。 | X27: 经核实，与来电人所述情况不相符。来电人陈莉女士系原京华客车退休职工，因京华客车解散，其退休关系于2009年划转至我单位鸿运承物业管理中心。经查阅资料，来电人曾申请过劳动鉴定，北京市公共交通总公司于2001年6月同意其申请。《北京市企业城镇劳动者退休审批表》显示，来电人的退休审批于2001年8月14日盖章审批通过。落款时间为2010年6月18日《北京市企业城镇劳动者退休审批表》显示，来电人退休时间为2001年8月。此外，来电人的情况2011年已经过北京市西城人民法院、北京市第一中级人民法院裁决，2012年3月12日北京市人力资源和社会保障局也已针对来电人情况做出《陈莉信访事项答复意见书》，2012年6月11日北京市人民政府也已作出《北京市人民政府信访事项复审意见书》。 接到诉求后，我单位于2025年12月29日下午13点23分左右电话与来电人沟通，此前我单位已多次陪同来电人陈莉女士前往西城区社保、北京市人社局、信访办、西城法院等部门协调其保险问题，其不认同此前的退休审批。 办理人：范泽，部门：鸿运承物业管理中心人力资源部； 审核人：高强，部门：鸿运承物业管理中心人力资源部，职务：中级管理。 | Y27: 接到诉求后，我单位于2025年12月29日下午13点23分左右电话与来电人沟通，此前我单位已多次陪同来电人陈莉女士前往西城区社保、北京市人社局、信访办、西城法院等部门协调其保险问题，其不认同此前的退休审批。 | Z27: 无 | AA27: 无 | AB27: 经核实，与来电人所述情况不相符。来电人陈莉女士系原京华客车退休职工，因京华客车解散，其退休关系于2009年划转至我单位鸿运承物业管理中心。经查阅资料，来电人曾申请过劳动鉴定，北京市公共交通总公司于2001年6月同意其申请。《北京市企业城镇劳动者退休审批表》显示，来电人的退休审批于2001年8月14日盖章审批通过。落款时间为2010年6月18日《北京市企业城镇劳动者退休审批表》显示，来电人退休时间为2001年8月。此外，来电人的情况2011年已经过北京市西城人民法院、北京市第一中级人民法院裁决，2012年3月12日北京市人力资源和社会保障局也已针对来电人情况做出《陈莉信访事项答复意见书》，2012年6月11日北京市人民政府也已作出《北京市人民政府信访事项复审意见书》。 接到诉求后，我单位于2025年12月29日下午13点23分左右电话与来电人沟通，此前我单位已多次陪同来电人陈莉女士前往西城区社保、北京市人社局、信访办、西城法院等部门协调其保险问题，其不认同此前的退休审批。 | AC27: 满意 | AD27: 个人 | AE27: 2025-12-26 14:28:49 | AF27: 1049051 | AG27: 退休 | AH27: 否 | AK27: =AG27&L27&M27 -> 退休人力资源方面其他问题人力资源方面补充内容 | AP27: 23 | AQ27: 46023 | AR27: =IFERROR(LEFT(A27,FIND("（",A27)-1),A27) -> 热线-251226-040071 | AS27: =J27 -> 其他 | AT27: =IF(MID(AR27,1,2)="热线",12345)+IF(MID(AR27,1,2)="网络",12345) -> 12345 | AU27: =IFERROR(LEFT(D27,FIND(" ",D27)-1),D27) -> 2025-12-26 | AV27: =P27 -> 人力资源部 | AW27: =Q27 -> 机关 | AX27: =H27 -> 市民反映，自己1980年进入京华客车厂上班，地址：西城区右安门内大街，自己在37岁的时候被公司办理了退休，当时申请的是自己完全丧失劳动能力，公司申请了之后劳动局直接通过了这个申请，他们给自己办理完成离职之后自己也一直在这个公司，但是他们并没有给自己按照规定缴纳社保，这家公司在2010年被北京市公共交通控股（集团）有限公司合并了，现在自己的问题在由公交公司处理，姓名：陈莉，身份证：110104196403043026，单位给自己交但是工作地的劳动局不收，希望西城区劳动局进行处理，从1992年到现在没有上保险，没有退休费，7月28日自己也去了通州区城市副中心，保安拦着不让进，耽误了一个小时，1.37岁退休不对，法律没有规定37岁退休的；2.自己没有完全丧失劳动能力，3.从1992年-2014年都没有保险，市民称问题未解决，要求再次反映，希望尽快处理，来电反映协调公交集团尽快上保险问题。 注：市民要求回电至新增手机号码。 | AY27: =AG27 -> 退休 | AZ27: 是 | BA27: 是 | BB27: 否 | BC27: 七有五性，公正性 | BD27: =U27 -> 结束 | BE27: =IFERROR(LEFT(T27,FIND(" ",T27)-1),T27) -> 2025-12-31 | BF27: 其他问题（退休）多次 | BG27: 人力资源部 | BH27: 机关 | BL27: =IF(BG27="物管行政部","侯旭、郑楠",IF(BG27="安保部","张耕",IF(BG27="工程设备部","华菲",IF(BG27="人力资源部","成琦",IF(BG27="党委工作部","阎鑫雨",IF(BG27="餐饮服务部","赵弘晨",IF(BG27="工会","郑欣",IF(BG27="办公室","董娜",""))))))))&IF(BG27="纪检部","黄倩",IF(BG27="信息管理部","蔡浩然","")) -> 成琦 | BM27: 未主动剔除 | BP27: 政策类 | BQ27: 同人同诉多次（陈莉） | BR27: 是 | BV27: =MID(AR27,1,16) -> 热线-251226-040071 | BX27: =IF(COUNTIF(BV:BV,BV27)=1,"否","是") -> 否 | BY27: =MID(AR27,18,1) | CG27: =VLOOKUP(AR27,[1]市民意见信息导出!$AI$2:$AK$392,3,FALSE()) -> 结束 | CH27: =VLOOKUP(BV27,[2]Sheet1!$C$2:$AC$99,2,FALSE()) -> #N/A
A28: 网络-251226-026269-1（1个附件） | B28: 2025-12-26 11:50:29 | C28: 2025-12-26 12:00:26 | D28: 2025-12-27 12:59:08 | E28: 李玉江 | F28: 男 | G28: 手机,18101130290; | H28: 工单来源：微信服务号，此工单内容为网民留言时填写的标题及原文。 ============================= 留言标题：公交留言原文：骊龙园北侧、回龙园公园东侧的回龙观公交保养场及场站（立体公交场站，非综合枢纽），完工已经很长时间，截至2025年12月26日，仍未投运！为何？堵点在哪里？市民填写的详细地址为：区、街道：昌平区龙泽园街道详细地址：昌平区龙泽园街道，龙禧二街与育知路交叉口东南角，骊龙园北侧、回龙园公园东侧。 | I28: 是 | J28: 诉求 | K28: 基建行政部 | L28: 场站问题 | M28: 场站建设 | N28: 鸿运承物业管理中心 | O28: 工程设备部 | P28: 工程设备部 | Q28: 机关 | R28: 2026-01-02 23:59:59 | S28: 2025-12-29 | T28: 2025-12-31 08:59:59 | U28: 结束 | V28: 0 | W28: 此单为拆单投诉，公交物业负责回复“仍未投入运营”的问题。市民反映的是回龙观公交场站站务设施设置问题。回龙观公交场站是公交首末站。经核实，市民诉求点位是回龙观场站，回龙观场站是新建成的公交场站，目前场站部分功能已经投入使用，例如公交物业已经进驻负责场站相关后勤保障、部分线路公交车在此处停靠，并从这里发车（但并不是始发公交站）。由于相关运营线路队部并没有正式进驻回龙观公交场站，所以场站作为线路始发站功能并未启用。 | X28: 公交物业回龙观分中心于2025年12月29日10点08分与市民进行电话沟通与答复，和市民说明我们核实的情况，针对市民诉求点进行解释说明。办理人：李满 鸿运承物业管理中心回龙观分中心 物管设备主任。审核人：华菲 物管中心工程设备部 一般管理。 | Y28: 经了解，公交集团正在紧锣密鼓规划进驻场站线路方案，因为涉及线路多、运营单位多，相关计划正在稳步推进中。各线路队部正式进驻场站后，相关线路的始发站也会进行更改。公交场站其他相关功能，我们也正在积极按照要求，向政府管理部门进行申报办理中。 | Z28: 经了解，公交集团正在紧锣密鼓规划进驻场站线路方案，因为涉及线路多、运营单位多，相关计划正在稳步推进中。各线路队部正式进驻场站后，相关线路的始发站也会进行更改。公交场站其他相关功能，我们也正在积极按照要求，向政府管理部门进行申报办理中。 | AA28: 无 | AB28: 此单为拆单投诉，公交物业负责回复“仍未投入运营”的问题。市民反映的是回龙观公交场站站务设施设置问题。回龙观公交场站是公交首末站。经核实，市民诉求点位是回龙观场站，回龙观场站是新建成的公交场站，目前场站部分功能已经投入使用，例如公交物业已经进驻负责场站相关后勤保障、部分线路公交车在此处停靠，并从这里发车（但并不是始发公交站）。由于相关运营线路队部并没有正式进驻回龙观公交场站，所以场站作为线路始发站功能并未启用。经了解，公交集团正在紧锣密鼓规划进驻场站线路方案，因为涉及线路多、运营单位多，相关计划正在稳步推进中。各线路队部正式进驻场站后，相关线路的始发站也会进行更改。公交场站其他相关功能，我们也正在积极按照要求，向政府管理部门进行申报办理中。公交物业回龙观分中心于2025年12月29日10点08分与市民进行电话沟通与答复，和市民说明我们核实的情况，针对市民诉求点进行解释说明。 | AC28: 满意 | AD28: 个人 | AE28: 2025-12-26 08:07:18 | AF28: 1728084326 | AG28: 设施设备 | AH28: 否 | AK28: =AG28&L28&M28 -> 设施设备场站问题场站建设 | AP28: 24 | AQ28: 46023 | AR28: =IFERROR(LEFT(A28,FIND("（",A28)-1),A28) -> 网络-251226-026269-1 | AS28: =J28 -> 诉求 | AT28: =IF(MID(AR28,1,2)="热线",12345)+IF(MID(AR28,1,2)="网络",12345) -> 12345 | AU28: =IFERROR(LEFT(D28,FIND(" ",D28)-1),D28) -> 2025-12-27 | AV28: =P28 -> 工程设备部 | AW28: =Q28 -> 机关 | AX28: =H28 -> 工单来源：微信服务号，此工单内容为网民留言时填写的标题及原文。 ============================= 留言标题：公交留言原文：骊龙园北侧、回龙园公园东侧的回龙观公交保养场及场站（立体公交场站，非综合枢纽），完工已经很长时间，截至2025年12月26日，仍未投运！为何？堵点在哪里？市民填写的详细地址为：区、街道：昌平区龙泽园街道详细地址：昌平区龙泽园街道，龙禧二街与育知路交叉口东南角，骊龙园北侧、回龙园公园东侧。 | AY28: =AG28 -> 设施设备 | AZ28: 否 | BA28: 否 | BB28: 否 | BC28: 七有五性,便利性 | BD28: =U28 -> 结束 | BE28: =IFERROR(LEFT(T28,FIND(" ",T28)-1),T28) -> 2025-12-31 | BF28: 站务设施设置 （枢纽站启用） | BG28: 工程设备部 | BH28: 回龙观分中心 | BL28: =IF(BG28="物管行政部","侯旭、郑楠",IF(BG28="安保部","张耕",IF(BG28="工程设备部","华菲",IF(BG28="人力资源部","成琦",IF(BG28="党委工作部","阎鑫雨",IF(BG28="餐饮服务部","赵弘晨",IF(BG28="工会","郑欣",IF(BG28="办公室","董娜",""))))))))&IF(BG28="纪检部","黄倩",IF(BG28="信息管理部","蔡浩然","")) -> 华菲 | BM28: 未主动剔除 | BP28: 政策类 | BV28: =MID(AR28,1,16) -> 网络-251226-026269 | BX28: =IF(COUNTIF(BV:BV,BV28)=1,"否","是") -> 否 | BY28: =MID(AR28,18,1) -> 1 | CG28: =VLOOKUP(AR28,[1]市民意见信息导出!$AI$2:$AK$392,3,FALSE()) -> 结束 | CH28: =VLOOKUP(BV28,[2]Sheet1!$C$2:$AC$99,2,FALSE()) -> #N/A
A29: 热线-251227-018516-1（7个附件） | B29: 2025-12-27 11:51:40 | C29: 2025-12-27 12:01:53 | D29: 2025-12-27 12:59:06 | E29: 匿名女士 | F29: 女 | G29: 手机,18612938216; | H29: 市民反映，在朝阳区慧忠里公共汽车站，市民称要乘坐车，自己进站没有看到自己要乘坐的车，自己找了半天都没有找到，市民表示自己询问司机也不清楚，市民称觉得不合理称司机都不清楚也没有工作人员非常不不便民，没有指示牌，希望有关部门监管处理，来电反映公共汽车站没有指示牌问题。 | I29: 是 | J29: 诉求 | K29: 基建行政部 | L29: 场站问题 | M29: 场站建设 | N29: 鸿运承物业管理中心 | O29: 鸿运承物业管理中心 | P29: 基建行政部 | Q29: 北京公共交通控股（集团）有限公司 | R29: 2026-01-03 23:59:59 | S29: 2025-12-29 | T29: 2026-01-01 08:59:59 | U29: 结束 | V29: 0 | W29: 此单为拆单投诉，公交物业负责回复“共汽车站没有指示牌”的问题。市民反映的是慧忠里公交场站站务设施（线路标识）设置问题。慧忠里公交场站是公交首末站。经核实，市民在慧忠里公交场站内没有找到142路上车站台，所以希望增加指示牌。142路公交车始发站，并不在慧忠里公交场站内上车，142路仅在慧忠里公交场站内停车，142路公交车始发站台上车位置位于慧忠里公交场站外的马路边上。所以公交物业无法在公交场站内设置142路相应的引导标识（反而容易引起歧义）。 | X29: 公交物业小营分中心于2025年12月29日16点01分与市民进行电话沟通与答复，向市民说明我们核实的情况、解决方案及办理情况。办理人：李留成 鸿运承物业管理中心小营分中心 工程设备主任。审核人：华菲 物管中心工程设备部 一般管理。 | Y29: 为了解决市民诉求，公交物业计划在慧忠里公交场站的2个行人进出口设置线路牌，明确场站内上车线路号，预计10个工作日完成标牌安装；同时，公交物业还要叮嘱物业职工，熟悉场站内相关线路号，做好乘客引导，方便乘客便捷乘车。 | Z29: 为了解决市民诉求，公交物业计划在慧忠里公交场站的2个行人进出口设置线路牌，明确场站内上车线路号，预计10个工作日完成标牌安装；同时，公交物业还要叮嘱物业职工，熟悉场站内相关线路号，做好乘客引导，方便乘客便捷乘车。 | AA29: 慧忠里场站属于物业主责场站。 | AB29: 此单为拆单投诉，公交物业负责回复“共汽车站没有指示牌”的问题。市民反映的是慧忠里公交场站站务设施（线路标识）设置问题。慧忠里公交场站是公交首末站。经核实，市民在慧忠里公交场站内没有找到142路上车站台，所以希望增加指示牌。142路公交车始发站，并不在慧忠里公交场站内上车，142路仅在慧忠里公交场站内停车，142路公交车始发站台上车位置位于慧忠里公交场站外的马路边上。所以公交物业无法在公交场站内设置142路相应的引导标识（反而容易引起歧义）。为了解决市民诉求，公交物业计划在慧忠里公交场站的2个行人进出口设置线路牌，明确场站内上车线路号，预计10个工作日完成标牌安装；同时，公交物业还要叮嘱物业职工，熟悉场站内相关线路号，做好乘客引导，方便乘客便捷乘车。公交物业小营分中心于2025年12月29日16点01分与市民进行电话沟通与答复，向市民说明我们核实的情况、解决方案及办理情况。 | AC29: 满意 | AD29: 个人 | AE29: 2025-12-27 11:45:15 | AF29: 1046001 | AG29: 服务 | AH29: 否 | AK29: =AG29&L29&M29 -> 服务场站问题场站建设 | AP29: 25 | AQ29: 46023 | AR29: =IFERROR(LEFT(A29,FIND("（",A29)-1),A29) -> 热线-251227-018516-1 | AS29: =J29 -> 诉求 | AT29: =IF(MID(AR29,1,2)="热线",12345)+IF(MID(AR29,1,2)="网络",12345) -> 12345 | AU29: =IFERROR(LEFT(D29,FIND(" ",D29)-1),D29) -> 2025-12-27 | AV29: =P29 -> 基建行政部 | AW29: =Q29 -> 北京公共交通控股（集团）有限公司 | AX29: =H29 -> 市民反映，在朝阳区慧忠里公共汽车站，市民称要乘坐车，自己进站没有看到自己要乘坐的车，自己找了半天都没有找到，市民表示自己询问司机也不清楚，市民称觉得不合理称司机都不清楚也没有工作人员非常不不便民，没有指示牌，希望有关部门监管处理，来电反映公共汽车站没有指示牌问题。 | AY29: =AG29 -> 服务 | AZ29: 否 | BA29: 否 | BB29: 否 | BC29: 七有五性,便利性 | BD29: =U29 -> 结束 | BE29: =IFERROR(LEFT(T29,FIND(" ",T29)-1),T29) -> 2026-01-01 | BF29: 站务设施设置 （指示牌） | BG29: 工程设备部 | BH29: 小营分中心 | BL29: =IF(BG29="物管行政部","侯旭、郑楠",IF(BG29="安保部","张耕",IF(BG29="工程设备部","华菲",IF(BG29="人力资源部","成琦",IF(BG29="党委工作部","阎鑫雨",IF(BG29="餐饮服务部","赵弘晨",IF(BG29="工会","郑欣",IF(BG29="办公室","董娜",""))))))))&IF(BG29="纪检部","黄倩",IF(BG29="信息管理部","蔡浩然","")) -> 华菲 | BM29: 未主动剔除 | BP29: 业务类 | BR29: 是 | BV29: =MID(AR29,1,16) -> 热线-251227-018516 | BW29: 七有五性,便利性 | BX29: =IF(COUNTIF(BV:BV,BV29)=1,"否","是") -> 否 | BY29: =MID(AR29,18,1) -> 1 | CG29: =VLOOKUP(AR29,[1]市民意见信息导出!$AI$2:$AK$392,3,FALSE()) -> 结束 | CH29: =VLOOKUP(BV29,[2]Sheet1!$C$2:$AC$99,2,FALSE()) -> #N/A
A30: 热线-251227-037858（1个附件） | B30: 2025-12-27 16:19:31 | C30: 2025-12-27 16:23:35 | D30: 2025-12-27 16:44:08 | E30: 高先生 | F30: 男 | G30: 手机,13520393394; | H30: 市民反映，西城区阜成门内公交站，这里相当于一个小型交通枢纽，是公交车423路，121路，409路，601路总站，这里之前有一个调度室，现在把调度室取消了改成休息室了，市民认为不合理，因为这里乘车的人非常多，改成休息室非常不方便，来电反映调度室改成休息室不合理问题。调度室改成休息室不合理问题 | I30: 是 | J30: 其他 | K30: 基建行政部 | L30: 基建行政专业其他问题 | M30: 基建行政专业补充内容 | N30: 鸿运承物业管理中心 | O30: 物管行政部 | P30: 基建行政部 | Q30: 机关 | R30: 2026-01-03 23:59:59 | S30: 2025-12-29 | T30: 2026-01-01 08:59:59 | U30: 结束 | V30: 0 | W30: 接到此投诉，我们非常重视。并立即派专人核实情况。 | X30: 分中心已经于2025年12月30日，将处理结果告知了市民，办理人：李营，部门:阜成门分中心，职务：物管副主任。审核人：侯旭，物业管理中心机关，物管行政部，科员。 | Y30: 经核实，市民描述的地方，目前仍然是调度室，司机上班前酒测，都是在该房屋内，并不是休息室。在答复时已经跟市民解释清楚了，希望市民不要误会。 | Z30: 无 | AA30: 无 | AB30: 接到此投诉，我们非常重视。并立即派专人核实情况。经核实，市民描述的地方，目前仍然是调度室，司机上班前酒测，都是在该房屋内，并不是休息室。在答复时已经跟市民解释清楚了，希望市民不要误会。分中心已经于2025年12月30日，将处理结果告知了市民，办理人：李营，部门:阜成门分中心，职务：物管副主任。审核人：侯旭，物业管理中心机关，物管行政部，科员。 | AC30: 满意 | AD30: 个人 | AE30: 2025-12-27 16:12:41 | AF30: 1049648 | AG30: 服务 | AH30: 否 | AK30: =AG30&L30&M30 -> 服务基建行政专业其他问题基建行政专业补充内容 | AP30: 26 | AQ30: 46023 | AR30: =IFERROR(LEFT(A30,FIND("（",A30)-1),A30) -> 热线-251227-037858 | AS30: =J30 -> 其他 | AT30: =IF(MID(AR30,1,2)="热线",12345)+IF(MID(AR30,1,2)="网络",12345) -> 12345 | AU30: =IFERROR(LEFT(D30,FIND(" ",D30)-1),D30) -> 2025-12-27 | AV30: =P30 -> 基建行政部 | AW30: =Q30 -> 机关 | AX30: =H30 -> 市民反映，西城区阜成门内公交站，这里相当于一个小型交通枢纽，是公交车423路，121路，409路，601路总站，这里之前有一个调度室，现在把调度室取消了改成休息室了，市民认为不合理，因为这里乘车的人非常多，改成休息室非常不方便，来电反映调度室改成休息室不合理问题。调度室改成休息室不合理问题 | AY30: =AG30 -> 服务 | AZ30: 否 | BA30: 否 | BB30: 否 | BC30: 七有五性,便利性 | BD30: =U30 -> 结束 | BE30: =IFERROR(LEFT(T30,FIND(" ",T30)-1),T30) -> 2026-01-01 | BF30: 站务设施设置 （调度室功能） | BG30: 物管行政部 | BH30: 阜成门分中心 | BL30: =IF(BG30="物管行政部","侯旭、郑楠",IF(BG30="安保部","张耕",IF(BG30="工程设备部","华菲",IF(BG30="人力资源部","成琦",IF(BG30="党委工作部","阎鑫雨",IF(BG30="餐饮服务部","赵弘晨",IF(BG30="工会","郑欣",IF(BG30="办公室","董娜",""))))))))&IF(BG30="纪检部","黄倩",IF(BG30="信息管理部","蔡浩然","")) -> 侯旭、郑楠 | BM30: 未主动剔除 | BP30: 政策类 | BV30: =MID(AR30,1,16) -> 热线-251227-037858 | BW30: 七有五性,便利性 | BX30: =IF(COUNTIF(BV:BV,BV30)=1,"否","是") -> 否 | BY30: =MID(AR30,18,1) | BZ30: 只评价响应率 | CE30: 1月 | CG30: =VLOOKUP(AR30,[1]市民意见信息导出!$AI$2:$AK$392,3,FALSE()) -> 结束 | CH30: =VLOOKUP(BV30,[2]Sheet1!$C$2:$AC$99,2,FALSE()) -> 1月
A31: 热线-251227-050756-3（2个附件） | B31: 2025-12-27 20:30:08 | C31: 2025-12-27 20:40:20 | D31: 2025-12-27 21:01:44 | E31: 黄女士 | F31: 女 | G31: 手机,18010212286; | H31: 市民反映，自己12月26号下午坐312路公交车，在果园站下车，车号：32161，自己下车时间是15点10分38秒，但是自己的包忘在了车上，自己看监控是身穿黑色衣服带着格子围巾手里拿着黄色手提袋，自己的包里有现金银行卡和公司的U盾和硬盘，公司的硬盘设计公司的机密文件，自己联系派出所，但是公交公司没上班没办法去找，对方在新华联家园东上车再垂杨柳下车，都是在车的前门上下车的，然后对方坐57路公交车在六里桥东站下车进了莲花池长途汽车站，嫌疑人进了站内后再也没有出现，自己要求调取监控，物业工作人员表示需要民警配合，现在自己带着民警过来，对方表示下班了，找其他部门也不配合，自己现在需要查看监控，需要有具体负责人出面配合自己，确定嫌疑人是否已经坐车离开，来电反映协调公交集团找回个人物品问题。客二客四安服安保科技 | I31: 是 | J31: 诉求 | K31: 安保部（应急管理中心） | L31: 视频监控问题 | M31: 视频监控 | N31: 鸿运承物业管理中心 | O31: 西客站分中心 | P31: 安保部（应急管理中心） | Q31: 西客站分中心 | R31: 2026-01-03 23:59:59 | S31: 2025-12-30 | T31: 2026-01-01 08:59:59 | U31: 结束 | V31: 0 | W31: 西客站分中心于2025年12月30日10时由安保副主任石海东与所属场站核实此情况。经现场监控视频核查，当日在岗值机员在接到黄女士现场请求时，无民警陪同。现场告知黄女士可以配合，但因规定只有公检法部门有权调查监控，所以需要属地民警到现场一同查看。 | X31: 12月30日10时50分，给黄女士电话回访，得知：黄女士已通过公安部门查到当时监控情况。处理人：西客站分中心安保副主任石海东。 | Y31: 西客站分中心于2025年12月30日10时由安保副主任石海东与所属场站核实此情况。经现场监控视频核查，当日在岗值机员在接到黄女士现场请求时，无民警陪同。现场告知黄女士可以配合，但因规定只有公检法部门有权调查监控，所以需要属地民警到现场一同查看。 | Z31: 无 | AA31: 无 | AB31: 西客站分中心于2025年12月30日10时由安保副主任石海东与所属场站核实此情况。经现场监控视频核查，当日在岗值机员在接到黄女士现场请求时，无民警陪同。现场告知黄女士可以配合，但因规定只有公检法部门有权调查监控，所以需要属地民警到现场一同查看。 | AC31: 满意 | AD31: 个人 | AE31: 2025-12-27 20:10:03 | AF31: 1741937701 | AG31: 服务 | AH31: 否 | AK31: =AG31&L31&M31 -> 服务视频监控问题视频监控 | AP31: 27 | AQ31: 46023 | AR31: =IFERROR(LEFT(A31,FIND("（",A31)-1),A31) -> 热线-251227-050756-3 | AS31: =J31 -> 诉求 | AT31: =IF(MID(AR31,1,2)="热线",12345)+IF(MID(AR31,1,2)="网络",12345) -> 12345 | AU31: =IFERROR(LEFT(D31,FIND(" ",D31)-1),D31) -> 2025-12-27 | AV31: =P31 -> 安保部（应急管理中心） | AW31: =Q31 -> 西客站分中心 | AX31: =H31 -> 市民反映，自己12月26号下午坐312路公交车，在果园站下车，车号：32161，自己下车时间是15点10分38秒，但是自己的包忘在了车上，自己看监控是身穿黑色衣服带着格子围巾手里拿着黄色手提袋，自己的包里有现金银行卡和公司的U盾和硬盘，公司的硬盘设计公司的机密文件，自己联系派出所，但是公交公司没上班没办法去找，对方在新华联家园东上车再垂杨柳下车，都是在车的前门上下车的，然后对方坐57路公交车在六里桥东站下车进了莲花池长途汽车站，嫌疑人进了站内后再也没有出现，自己要求调取监控，物业工作人员表示需要民警配合，现在自己带着民警过来，对方表示下班了，找其他部门也不配合，自己现在需要查看监控，需要有具体负责人出面配合自己，确定嫌疑人是否已经坐车离开，来电反映协调公交集团找回个人物品问题。客二客四安服安保科技 | AY31: =AG31 -> 服务 | AZ31: 否 | BA31: 否 | BB31: 否 | BC31: 七有五性,安全性、便利性 | BD31: =U31 -> 结束 | BE31: =IFERROR(LEFT(T31,FIND(" ",T31)-1),T31) -> 2026-01-01 | BF31: 场站安保问题 （调取安保监控录像） | BG31: 安保部 | BH31: 西客站分中心 | BL31: =IF(BG31="物管行政部","侯旭、郑楠",IF(BG31="安保部","张耕",IF(BG31="工程设备部","华菲",IF(BG31="人力资源部","成琦",IF(BG31="党委工作部","阎鑫雨",IF(BG31="餐饮服务部","赵弘晨",IF(BG31="工会","郑欣",IF(BG31="办公室","董娜",""))))))))&IF(BG31="纪检部","黄倩",IF(BG31="信息管理部","蔡浩然","")) -> 张耕 | BM31: 未主动剔除 | BP31: 政策类 | BV31: =MID(AR31,1,16) -> 热线-251227-050756 | BW31: 七有五性,便利性 | BX31: =IF(COUNTIF(BV:BV,BV31)=1,"否","是") -> 否 | BY31: =MID(AR31,18,1) -> 3 | CG31: =VLOOKUP(AR31,[1]市民意见信息导出!$AI$2:$AK$392,3,FALSE()) -> 结束 | CH31: =VLOOKUP(BV31,[2]Sheet1!$C$2:$AC$99,2,FALSE()) -> #N/A
A32: 网络-251229-006506 | B32: 2025-12-29 09:00:07 | C32: 2025-12-29 09:22:26 | D32: 2025-12-29 12:02:20 | E32: 保密 | F32: 男 | G32: 保密 | H32: 工单来源：微信服务号，此工单内容为网民留言时填写的标题及原文。 ============================= 留言标题：希望增设公交站台护栏问题留言原文：12月27日下午，我在朝阳区侯庄路口北等409路公交车，这时候发现自称是公交物业的张姓工作人员，在测量站台的护栏，我于是询问他说他是公交集团物业公司的，上级让他看一下这个地方的护栏破损了，他重新布局一下。我和他反应除了这个侯庄站，附近还有南湖西园公交站护栏是遮挡公交车下车门的，广顺桥南的护栏破损了，大西洋新城和阜通地铁站没有护栏，特别是望京医院站，老年人上车都没有站台护栏能够扶一下子。这位张师傅听完我的建议后，立即开车拉着我前往了以上地点，按照我的意思画了个图。但是说按照要求他的上报公司领导后才能定，这个公交站决定装不装。我这次第一要表扬咱们公交集团物业公司负责站台护栏维修的张师傅，最后还给我送到了家门口，第二希望我以上说的几个公交站护栏问题尽快整改，提升望京地区的形象。上面的领导支持张师傅的工作，不要为难人家，真正让张师傅这样的好人为老百姓做点事。市民填写的详细地址为：区：朝阳区街道：不详详细地址：公交站台护栏 | I32: 是 | J32: 诉求 | K32: 基建行政部 | L32: 站务设施问题 | M32: 站台护栏问题 | N32: 鸿运承物业管理中心 | O32: 工程设备部 | P32: 工程设备部 | Q32: 机关 | R32: 2026-01-05 23:59:59 | S32: 2025-12-29 | T32: 2026-01-03 08:59:59 | U32: 结束 | V32: 0 | W32: 公交站台（护栏）站务设施设置问题。公交站台护栏属于公交站台站务设施。经核实，市民诉求中提到的几处望京地区的站台护栏，公交集团物业确实有整改计划。 | X32: 由于市民联系方式保密，无法进行电话答复。办理人：华菲 工程设备部 一般管理。 审核人：贾新宇 工程设备部 经理。 | Y32: 依据北京市相关规定，站台护栏属于"城市家具"，无论维修拆除安装，都须到属地管理部门进行规划方案审批。1.侯庄、南湖西园、广顺桥南站台护栏调整，公交物业已经列入护栏维修调整计划，因为是站台原有护栏的维修调整，所以相关审批程序比较快，预计2026年1月底完成破损护栏维修、护栏布局调整施工。2.市民提到大西洋新城、阜通地铁、望京医院几处站台新增护栏施工，因为目前站台上没有护栏，属于新增站台护栏，所以属地相关政府管理部门审批流程进度就会比较缓慢。公交集团物业公司非常重视本次市民诉求，大西洋新城、阜通地铁、望京医院公交站台新增护栏施工，我们将按流程向属地城管委进行项目申报。新增护栏施工进度，取决于各类手续的办理情况。政府管理部门内部审批流程，公交集团无权也无法控制，我们只能等待政府管理部门答复。公交集团将根据审批进度，实时跟进，新增护栏完成时间暂时无法向市民承诺。 | Z32: 1.侯庄、南湖西园、广顺桥南站台护栏调整，公交物业已经列入护栏维修调整计划，因为是站台原有护栏的维修调整，所以相关审批程序比较快，预计2026年1月底完成破损护栏维修、护栏布局调整施工。2.大西洋新城、阜通地铁、望京医院几处站台新增护栏施工，属于新增站台护栏，我们将按流程向属地城管委进行项目申报。新增护栏施工进度，取决于各类手续的办理情况。 | AA32: 公交集团物业公司会持续关注此事进展，也请市民理解谅解。 | AB32: 公交站台（护栏）站务设施设置问题。公交站台护栏属于公交站台站务设施。经核实，市民诉求中提到的几处望京地区的站台护栏，公交集团物业确实有整改计划。依据北京市相关规定，站台护栏属于"城市家具"，无论维修拆除安装，都须到属地管理部门进行规划方案审批。1.侯庄、南湖西园、广顺桥南站台护栏调整，公交物业已经列入护栏维修调整计划，因为是站台原有护栏的维修调整，所以相关审批程序比较快，预计2026年1月底完成破损护栏维修、护栏布局调整施工。2.市民提到大西洋新城、阜通地铁、望京医院几处站台新增护栏施工，因为目前站台上没有护栏，属于新增站台护栏，所以属地相关政府管理部门审批流程进度就会比较缓慢。公交集团物业公司非常重视本次市民诉求，大西洋新城、阜通地铁、望京医院公交站台新增护栏施工，我们将按流程向属地城管委进行项目申报。新增护栏施工进度，取决于各类手续的办理情况。政府管理部门内部审批流程，公交集团无权也无法控制，我们只能等待政府管理部门答复。公交集团将根据审批进度，实时跟进，新增护栏完成时间暂时无法向市民承诺。公交集团物业公司会持续关注此事进展，也请市民理解谅解。由于市民联系方式保密，无法进行电话答复。 | AC32: 满意 | AD32: 个人 | AE32: 2025-12-27 19:40:46 | AF32: 1728084326 | AG32: 设施设备 | AH32: 否 | AK32: =AG32&L32&M32 -> 设施设备站务设施问题站台护栏问题 | AP32: 28 | AQ32: 46023 | AR32: =IFERROR(LEFT(A32,FIND("（",A32)-1),A32) -> 网络-251229-006506 | AS32: =J32 -> 诉求 | AT32: =IF(MID(AR32,1,2)="热线",12345)+IF(MID(AR32,1,2)="网络",12345) -> 12345 | AU32: =IFERROR(LEFT(D32,FIND(" ",D32)-1),D32) -> 2025-12-29 | AV32: =P32 -> 工程设备部 | AW32: =Q32 -> 机关 | AX32: =H32 -> 工单来源：微信服务号，此工单内容为网民留言时填写的标题及原文。 ============================= 留言标题：希望增设公交站台护栏问题留言原文：12月27日下午，我在朝阳区侯庄路口北等409路公交车，这时候发现自称是公交物业的张姓工作人员，在测量站台的护栏，我于是询问他说他是公交集团物业公司的，上级让他看一下这个地方的护栏破损了，他重新布局一下。我和他反应除了这个侯庄站，附近还有南湖西园公交站护栏是遮挡公交车下车门的，广顺桥南的护栏破损了，大西洋新城和阜通地铁站没有护栏，特别是望京医院站，老年人上车都没有站台护栏能够扶一下子。这位张师傅听完我的建议后，立即开车拉着我前往了以上地点，按照我的意思画了个图。但是说按照要求他的上报公司领导后才能定，这个公交站决定装不装。我这次第一要表扬咱们公交集团物业公司负责站台护栏维修的张师傅，最后还给我送到了家门口，第二希望我以上说的几个公交站护栏问题尽快整改，提升望京地区的形象。上面的领导支持张师傅的工作，不要为难人家，真正让张师傅这样的好人为老百姓做点事。市民填写的详细地址为：区：朝阳区街道：不详详细地址：公交站台护栏 | AY32: =AG32 -> 设施设备 | AZ32: 否 | BA32: 否 | BB32: 否 | BC32: 七有五性,便利性 | BD32: =U32 -> 结束 | BE32: =IFERROR(LEFT(T32,FIND(" ",T32)-1),T32) -> 2026-01-03 | BF32: 站台护栏 | BG32: 工程设备部 | BH32: 机关 | BL32: =IF(BG32="物管行政部","侯旭、郑楠",IF(BG32="安保部","张耕",IF(BG32="工程设备部","华菲",IF(BG32="人力资源部","成琦",IF(BG32="党委工作部","阎鑫雨",IF(BG32="餐饮服务部","赵弘晨",IF(BG32="工会","郑欣",IF(BG32="办公室","董娜",""))))))))&IF(BG32="纪检部","黄倩",IF(BG32="信息管理部","蔡浩然","")) -> 华菲 | BM32: 未主动剔除 | BP32: 政策类 | BV32: =MID(AR32,1,16) -> 网络-251229-006506 | BW32: 疏整促,城市家具,便利性,七有五性 | BX32: =IF(COUNTIF(BV:BV,BV32)=1,"否","是") -> 否 | BY32: =MID(AR32,18,1) | CG32: =VLOOKUP(AR32,[1]市民意见信息导出!$AI$2:$AK$392,3,FALSE()) -> 结束 | CH32: =VLOOKUP(BV32,[2]Sheet1!$C$2:$AC$99,2,FALSE()) -> #N/A
A33: 网络-251229-041813 | B33: 2025-12-29 14:17:14 | C33: 2025-12-29 14:21:16 | D33: 2025-12-29 14:31:42 | E33: 张瑞虹 | F33: 女 | G33: 手机,18511571775; | H33: 工单来源：微信服务号，此工单内容为网民留言时填写的标题及原文。 ============================= 留言标题：公交留言原文：12月28日20点02分至26分乘坐631快公交车，从六里桥南站上车，20点26分从洪村站下车，车上靠近前车门一侧第二个座位右侧扶手上有黑色类似油漆的粘稠物质，粘到我的羽绒服和手上，羽绒服上粘的擦不掉，手上的也基本上擦不掉，衣服被弄脏污物无法清除，要求赔偿。市民填写的详细地址为：区、街道：丰台区六里桥街道详细地址：丰台区六里桥南公交站至洪村站区间 | I33: 是 | J33: 诉求 | K33: 行车安全服务部 | L33: 乘车环境问题 | M33: 车辆卫生 | N33: 鸿运承物业管理中心 | O33: 天宫院分中心 | P33: 物管行政部 | Q33: 天宫院分中心 | R33: 2026-01-05 23:59:59 | S33: 2025-12-30 | T33: 2026-01-03 08:59:59 | U33: 结束 | V33: 0 | W33: 您好，关于您反映问题的办理情况，鸿运承物业管理中心天宫院分中心现对您回复如下： | X33: 我分中心已于2025年12月29日下午16点44分；12月30日上午8点29分、下午13点07分对您进行了电话回复，您都未能接听我的来电，故我们以短信的形式告诉您办理结果。办理人：李虎；部门：鸿运承物业管理中心天宫院分中心；职务；物管副主任。审核人：郑楠；部门：鸿运承物业管理中心物管行政部；职务：物管员。 | Y33: 张女士您好，631快路公交车我们在黄村火车站场站进行洗车服务工作，您所述车辆运营中车上靠近前车门一侧第二个座位右侧扶手上有黑色类似油漆的粘稠物质的问题我们非常重视您的反馈，经过我们认真核查，您所反馈的问题车辆为3833988号车。您提供的照片我们已收到，由于我们的工作没有做好，631快路给您带来不好的乘车体验，实在是抱歉，张女士。该车辆回到黄村火车站场站后，在日常工作时段内，我们的保洁员已对车内卫生进行了全面的清理，确保我们的出场车辆卫生符合企业标准。您反馈的问题我们已整改完毕，同时我们要求保洁员对631快路所有运营车辆的卫生再次进行细化清理。我们对于运营车辆车内卫生的清洁工作是一直在做的，也从未停止，已经形成了长效的清洁机制，但有时候卫生清洁工作我们做的还有不尽人意之处，您多多谅解。您收到短信后请及时的与我进行联系，我们给您报销清洗衣服的相关费用。 | Z33: 我们分中心及场站班组长再次与631快路的保洁人员进行了沟通，日常工作中我们要把清洁质量做的更加细致，同时加强保洁员清洁技能的培训，熟练掌握清洁方法，确保给您带来一个干净、整洁的出行环境。 | AA33: 我们定期会召开车辆保洁专题会议，开展车辆卫生专项检查，日常工作中我们加大巡检力度，强化制度建设，不断提高管理水平。 | AB33: 欢迎您随时对我们的工作进行监督，感谢您提出宝贵意见，给您的出行带来的不便我们和您说声抱歉，谢谢您的支持与谅解。 | AC33: 满意 | AD33: 个人 | AE33: 2025-12-28 20:41:13 | AF33: 1741937712 | AG33: 设施设备 | AH33: 否 | AK33: =AG33&L33&M33 -> 设施设备乘车环境问题车辆卫生 | AP33: 29 | AQ33: 46023 | AR33: =IFERROR(LEFT(A33,FIND("（",A33)-1),A33) -> 网络-251229-041813 | AS33: =J33 -> 诉求 | AT33: =IF(MID(AR33,1,2)="热线",12345)+IF(MID(AR33,1,2)="网络",12345) -> 12345 | AU33: =IFERROR(LEFT(D33,FIND(" ",D33)-1),D33) -> 2025-12-29 | AV33: =P33 -> 物管行政部 | AW33: =Q33 -> 天宫院分中心 | AX33: =H33 -> 工单来源：微信服务号，此工单内容为网民留言时填写的标题及原文。 ============================= 留言标题：公交留言原文：12月28日20点02分至26分乘坐631快公交车，从六里桥南站上车，20点26分从洪村站下车，车上靠近前车门一侧第二个座位右侧扶手上有黑色类似油漆的粘稠物质，粘到我的羽绒服和手上，羽绒服上粘的擦不掉，手上的也基本上擦不掉，衣服被弄脏污物无法清除，要求赔偿。市民填写的详细地址为：区、街道：丰台区六里桥街道详细地址：丰台区六里桥南公交站至洪村站区间 | AY33: =AG33 -> 设施设备 | AZ33: 否 | BA33: 否 | BB33: 否 | BC33: 七有五性,宜居性 | BD33: =U33 -> 结束 | BE33: =IFERROR(LEFT(T33,FIND(" ",T33)-1),T33) -> 2026-01-03 | BF33: 车辆卫生问题 （车内遗洒致衣物变脏） | BG33: 物管行政部 | BH33: 天宫院分中心 | BL33: =IF(BG33="物管行政部","侯旭、郑楠",IF(BG33="安保部","张耕",IF(BG33="工程设备部","华菲",IF(BG33="人力资源部","成琦",IF(BG33="党委工作部","阎鑫雨",IF(BG33="餐饮服务部","赵弘晨",IF(BG33="工会","郑欣",IF(BG33="办公室","董娜",""))))))))&IF(BG33="纪检部","黄倩",IF(BG33="信息管理部","蔡浩然","")) -> 侯旭、郑楠 | BM33: 未主动剔除 | BP33: 业务类 | BV33: =MID(AR33,1,16) -> 网络-251229-041813 | BX33: =IF(COUNTIF(BV:BV,BV33)=1,"否","是") -> 否 | BY33: =MID(AR33,18,1) | CG33: =VLOOKUP(AR33,[1]市民意见信息导出!$AI$2:$AK$392,3,FALSE()) -> 结束 | CH33: =VLOOKUP(BV33,[2]Sheet1!$C$2:$AC$99,2,FALSE()) -> #N/A
A34: 热线-251229-054242-2（1个附件） | B34: 2025-12-29 16:17:12 | C34: 2025-12-29 18:26:21 | D34: 2025-12-29 18:29:45 | E34: 王女士 | F34: 女 | G34: 手机,13674813439; | H34: 市民表扬，自己父母2025年12月29日乘坐462路公交车，不慎将包裹遗留在公交车上，市民拨打96166公交集团热线，接线人员认真负责，426车队及时响应，不到半个小时就迅速找到了背包，还有昌平区二拨子村462总站的值班保安，尽职尽责，非常感动，来电表扬462路车队及公交热线接线人员。 | I34: 是 | J34: 表扬 | K34: 安保部（应急管理中心） | L34: 安保专业服务意识方面表扬 | M34: 表扬保安人员 | N34: 鸿运承物业管理中心 | O34: 史各庄分中心 | P34: 安全保卫部（应急管理中心） | Q34: 史各庄分中心 | S34: 2025-12-30 | T34: 2026-01-03 08:59:59 | U34: 结束 | V34: 0 | W34: 经核实，情况属实，二拨子当班警卫尽职尽责，把遗失物完好交换给了失主。 | X34: 史各庄分中心12月30日11.40，对致电人王女士的表扬电话给与感谢，核实当时情况，确定遗失物完好交还给失主。 | Y34: 史各庄分中心对二拨子场站当班警卫进行表扬，同事借此事件，对所有场站人员进行宣讲和教育，提高员工整体素质和觉悟，更好的为乘客服务。 | Z34: 无 | AA34: 无 | AB34: 史各庄分中心对二拨子场站当班警卫进行表扬，同事借此事件，对所有场站人员进行宣讲和教育，提高员工整体素质和觉悟，更好的为乘客服务。 | AC34: 满意 | AD34: 个人 | AE34: 2025-12-29 16:05:06 | AF34: 1725545790 | AG34: 办事效率 | AH34: 是 | AK34: =AG34&L34&M34 -> 办事效率安保专业服务意识方面表扬表扬保安人员 | AP34: 30 | AQ34: 46023 | AR34: =IFERROR(LEFT(A34,FIND("（",A34)-1),A34) -> 热线-251229-054242-2 | AS34: =J34 -> 表扬 | AT34: =IF(MID(AR34,1,2)="热线",12345)+IF(MID(AR34,1,2)="网络",12345) -> 12345 | AU34: =IFERROR(LEFT(D34,FIND(" ",D34)-1),D34) -> 2025-12-29 | AV34: =P34 -> 安全保卫部（应急管理中心） | AW34: =Q34 -> 史各庄分中心 | AX34: =H34 -> 市民表扬，自己父母2025年12月29日乘坐462路公交车，不慎将包裹遗留在公交车上，市民拨打96166公交集团热线，接线人员认真负责，426车队及时响应，不到半个小时就迅速找到了背包，还有昌平区二拨子村462总站的值班保安，尽职尽责，非常感动，来电表扬462路车队及公交热线接线人员。 | AY34: =AG34 -> 办事效率 | AZ34: 否 | BA34: 否 | BB34: 否 | BC34: 七有五性,安全性、便利性 | BD34: =U34 -> 结束 | BE34: =IFERROR(LEFT(T34,FIND(" ",T34)-1),T34) -> 2026-01-03 | BF34: 表扬工作人员 （遗失物保管） | BG34: 安保部 | BH34: 史各庄分中心 | BL34: =IF(BG34="物管行政部","侯旭、郑楠",IF(BG34="安保部","张耕",IF(BG34="工程设备部","华菲",IF(BG34="人力资源部","成琦",IF(BG34="党委工作部","阎鑫雨",IF(BG34="餐饮服务部","赵弘晨",IF(BG34="工会","郑欣",IF(BG34="办公室","董娜",""))))))))&IF(BG34="纪检部","黄倩",IF(BG34="信息管理部","蔡浩然","")) -> 张耕 | BN34: 表扬 | BP34: 业务类 | BV34: =MID(AR34,1,16) -> 热线-251229-054242 | BX34: =IF(COUNTIF(BV:BV,BV34)=1,"否","是") -> 否 | BY34: =MID(AR34,18,1) -> 2 | CG34: =VLOOKUP(AR34,[1]市民意见信息导出!$AI$2:$AK$392,3,FALSE()) -> 结束 | CH34: =VLOOKUP(BV34,[2]Sheet1!$C$2:$AC$99,2,FALSE()) -> #N/A
A35: 网络-251230-035268（2个附件） | B35: 2025-12-30 13:39:47 | C35: 2025-12-30 13:44:40 | D35: 2025-12-30 13:48:39 | E35: 倪大伟 | F35: 男 | G35: 手机,13681321121; | H35: 工单来源：微信服务号，此工单内容为网民留言时填写的标题及原文。 ============================= 留言标题： 北京公共交通有限公司不合理给员工变岗降薪留言原文：关于北京公交集团鸿运承物业管理有限公司不合理调岗降薪等问题的投诉信 尊敬的国资委领导： 您好！ 我是北京公交集团鸿运承物业管理有限公司一名老员工的家属，此前就我爱人的调岗降薪问题向北京公共交通控股集团有限公司投诉，但下属公司的回复强词夺理，问题未得到妥善解决，故向贵单位再次反映，恳请关注。 一、员工基本情况与工作履历 我爱人在公交系统工作长达31年，其中20多年在运营一线担任调度员，积累了丰富管理经验与业务能力。2022年转岗至北京公交鸿运承物业管理有限公司任综合站务员A岗，至今已稳定工作3年。 二、不合理调岗降薪及相关问题详述 （一）岗位实质未变却强行“岗变薪变”与学历歧视 1. 目前综合站务员A岗的岗位职责与我爱人过去3年从事的工作基本一致。她凭借31年公交系统工作经验，包括20多年调度经验和3年A岗实操经验，完全胜任岗位。公司以“学历”为由卡人，是形式主义，严重忽视员工实际工作能力。​2. 我爱人距法定退休年龄仅剩两年多，为企业奉献大半辈子，临近退休却面临大幅降薪，这对其生活和精神造成巨大打击。公司虽未直接解除合同，但通过降薪逼迫员工离职，违背了《劳动合同法》第四十二条规定。 （二）协商过程存在诸多不公 1. 公司给出的四项安置方案实为“霸王条款”：​- 转岗至综合站务员C岗，工资从原A岗的（岗资3700 + 绩效4720）降至（岗资3100 + 绩效2720），降幅超30%，令人难以接受。​- 转岗至巡检员同样面临降薪。​- 提出买断工龄。​- 如不选择以上方案，则视为“下岗代工”，这种做法严重损害员工权益，且在当下是不被允许的。​2. 因我爱人拒绝签字同意不合理降薪，公司相关人员频繁“约谈”，严重干扰其正常工作和生活，导致她精神压力巨大，身心状态极差。公司人员还歪曲事实，称其同意签字认可，行为极其不妥。 （三）薪资调整的不公平性 公司在对基层员工进行调岗降薪时，中高层薪资待遇却未见变化。这种只削减基层工人工资，以维持中高层薪资的做法，有剥削工人之嫌，凸显公司决策的不合理与不公正。同时，众多员工迫于压力签字同意，并非真实意愿，这反映出公司处理方式给员工带来极大困扰。 三、诉求 1. 责令北京公交鸿运承物业管理有限公司立即停止针对老员工的不合理调岗降薪行为，尊重我爱人31年的工作贡献和实际业务能力。​2. 督促该公司维持我爱人目前的综合站务员A岗待遇，直至退休。​3. 要求公司停止高频次的施压约谈，给予老员工安稳的工作环境。​4. 对公司中高层薪资情况进行审查，要求薪资公开透明，确保决策公平公正，杜绝类似不合理剥削员工利益的情况再次发生。 希望贵单位能重视此事，从实际出发，妥善解决问题，不要让为公交系统奉献多年的老员工寒心。 市民填写的详细地址为：区、街道：通州区潞源街道详细地址：北京市人民政府国有资产监督管理委员会，负责 | I35: 是 | J35: 诉求 | K35: 人力资源部（人力资源发展中心） | L35: 工资及五险二金 | M35: 工资方面 | N35: 鸿运承物业管理中心 | O35: 单店分中心 | P35: 人力资源部 | Q35: 单店分中心 | R35: 2026-01-06 23:59:59 | S35: 2025-12-30 | T35: 2026-01-04 08:59:59 | U35: 结束 | V35: 0 | W35: 经核实，来电人为我单位职工家属，与来电人所述的情况存在出入。首先，本次企业改革是根据《鸿运承物业管理中心综合站务员优化配置改革工作实施方案》、《鸿运承物业管理中心综合站务员A岗管理规定（试行）》等制度文件开展，综合站务员A岗岗位职责，管理方式均发生改变，现综合站务员A岗负责物业场站和人员的现场管理，以及辅助客运单位开展驾驶员安全叮嘱工作，与来电人所述的“目前综合站务员A岗的岗位职责与我爱人过去3年从事的工作基本一致”存在出入。 企业根据实际业务需要进行岗位职责调整，适用于每一位职工，并非是霸王条款或针对来电人家属个人。我单位《鸿运承物业管理中心综合站务员A岗管理规定（试行）》明确说明，新聘综合站务员A岗需具有大专学历，属工作需要并非学历歧视。分中心与职工谈话属于正常工作谈话，旨在为职工详细讲解政策，情绪疏导，帮助落选人员进行安置，不存在“高频次施压”行为。 来电人反馈的薪酬问题，我单位工人、管理人员薪酬严格按照《鸿运承物业管理中心工人绩效考核薪酬管理实施细则》、《鸿运承物业管理中心管理人员绩效考核薪酬管理实施细则》相关文件执行。 | X35: 经核实，来电人为我单位职工家属，与来电人所述的情况存在出入。首先，本次企业改革是根据《鸿运承物业管理中心综合站务员优化配置改革工作实施方案》、《鸿运承物业管理中心综合站务员A岗管理规定（试行）》等制度文件开展，综合站务员A岗岗位职责，管理方式均发生改变，现综合站务员A岗负责物业场站和人员的现场管理，以及辅助客运单位开展驾驶员安全叮嘱工作，与来电人所述的“目前综合站务员A岗的岗位职责与我爱人过去3年从事的工作基本一致”存在出入。 企业根据实际业务需要进行岗位职责调整，适用于每一位职工，并非是霸王条款或针对来电人家属个人。我单位《鸿运承物业管理中心综合站务员A岗管理规定（试行）》明确说明，新聘综合站务员A岗需具有大专学历，属工作需要并非学历歧视。分中心与职工谈话属于正常工作谈话，旨在为职工详细讲解政策，情绪疏导，帮助落选人员进行安置，不存在“高频次施压”行为。 来电人反馈的薪酬问题，我单位工人、管理人员薪酬严格按照《鸿运承物业管理中心工人绩效考核薪酬管理实施细则》、《鸿运承物业管理中心管理人员绩效考核薪酬管理实施细则》相关文件执行。 接到诉求后，我单位立即与来电人取得联系，2025年12月30日下午14点44分左右电话与来电人沟通，来电人表示未向我单位发投诉并挂断电话，故我单位又以短信形式再次与来电人进行回复。 办理人：杨飞，部门：鸿运承物业管理中心单店分中心，职务：一般管理； 审核人：高强；部门：鸿运承物业管理中心人力资源部；职务：中级管理。 | Y35: 接到诉求后，我单位立即与来电人取得联系，2025年12月30日下午14点44分左右电话与来电人沟通，来电人表示未向我单位发投诉并挂断电话，故我单位又以短信形式再次与来电人进行回复。 | Z35: 无 | AA35: 无 | AB35: 经核实，来电人为我单位职工家属，与来电人所述的情况存在出入。首先，本次企业改革是根据《鸿运承物业管理中心综合站务员优化配置改革工作实施方案》、《鸿运承物业管理中心综合站务员A岗管理规定（试行）》等制度文件开展，综合站务员A岗岗位职责，管理方式均发生改变，现综合站务员A岗负责物业场站和人员的现场管理，以及辅助客运单位开展驾驶员安全叮嘱工作，与来电人所述的“目前综合站务员A岗的岗位职责与我爱人过去3年从事的工作基本一致”存在出入。 企业根据实际业务需要进行岗位职责调整，适用于每一位职工，并非是霸王条款或针对来电人家属个人。我单位《鸿运承物业管理中心综合站务员A岗管理规定（试行）》明确说明，新聘综合站务员A岗需具有大专学历，属工作需要并非学历歧视。分中心与职工谈话属于正常工作谈话，旨在为职工详细讲解政策，情绪疏导，帮助落选人员进行安置，不存在“高频次施压”行为。 来电人反馈的薪酬问题，我单位工人、管理人员薪酬严格按照《鸿运承物业管理中心工人绩效考核薪酬管理实施细则》、《鸿运承物业管理中心管理人员绩效考核薪酬管理实施细则》相关文件执行。 接到诉求后，我单位立即与来电人取得联系，2025年12月30日下午14点44分左右电话与来电人沟通，来电人表示未向我单位发投诉并挂断电话，故我单位又以短信形式再次与来电人进行回复。 | AC35: 满意 | AD35: 个人 | AE35: 2025-12-29 20:10:27 | AF35: 1741937706 | AG35: 劳动合同及用工管理 | AH35: 否 | AK35: =AG35&L35&M35 -> 劳动合同及用工管理工资及五险二金工资方面 | AP35: 31 | AQ35: 46023 | AR35: =IFERROR(LEFT(A35,FIND("（",A35)-1),A35) -> 网络-251230-035268 | AS35: =J35 -> 诉求 | AT35: =IF(MID(AR35,1,2)="热线",12345)+IF(MID(AR35,1,2)="网络",12345) -> 12345 | AU35: =IFERROR(LEFT(D35,FIND(" ",D35)-1),D35) -> 2025-12-30 | AV35: =P35 -> 人力资源部 | AW35: =Q35 -> 单店分中心 | AX35: =H35 -> 工单来源：微信服务号，此工单内容为网民留言时填写的标题及原文。 ============================= 留言标题： 北京公共交通有限公司不合理给员工变岗降薪留言原文：关于北京公交集团鸿运承物业管理有限公司不合理调岗降薪等问题的投诉信 尊敬的国资委领导： 您好！ 我是北京公交集团鸿运承物业管理有限公司一名老员工的家属，此前就我爱人的调岗降薪问题向北京公共交通控股集团有限公司投诉，但下属公司的回复强词夺理，问题未得到妥善解决，故向贵单位再次反映，恳请关注。 一、员工基本情况与工作履历 我爱人在公交系统工作长达31年，其中20多年在运营一线担任调度员，积累了丰富管理经验与业务能力。2022年转岗至北京公交鸿运承物业管理有限公司任综合站务员A岗，至今已稳定工作3年。 二、不合理调岗降薪及相关问题详述 （一）岗位实质未变却强行“岗变薪变”与学历歧视 1. 目前综合站务员A岗的岗位职责与我爱人过去3年从事的工作基本一致。她凭借31年公交系统工作经验，包括20多年调度经验和3年A岗实操经验，完全胜任岗位。公司以“学历”为由卡人，是形式主义，严重忽视员工实际工作能力。​2. 我爱人距法定退休年龄仅剩两年多，为企业奉献大半辈子，临近退休却面临大幅降薪，这对其生活和精神造成巨大打击。公司虽未直接解除合同，但通过降薪逼迫员工离职，违背了《劳动合同法》第四十二条规定。 （二）协商过程存在诸多不公 1. 公司给出的四项安置方案实为“霸王条款”：​- 转岗至综合站务员C岗，工资从原A岗的（岗资3700 + 绩效4720）降至（岗资3100 + 绩效2720），降幅超30%，令人难以接受。​- 转岗至巡检员同样面临降薪。​- 提出买断工龄。​- 如不选择以上方案，则视为“下岗代工”，这种做法严重损害员工权益，且在当下是不被允许的。​2. 因我爱人拒绝签字同意不合理降薪，公司相关人员频繁“约谈”，严重干扰其正常工作和生活，导致她精神压力巨大，身心状态极差。公司人员还歪曲事实，称其同意签字认可，行为极其不妥。 （三）薪资调整的不公平性 公司在对基层员工进行调岗降薪时，中高层薪资待遇却未见变化。这种只削减基层工人工资，以维持中高层薪资的做法，有剥削工人之嫌，凸显公司决策的不合理与不公正。同时，众多员工迫于压力签字同意，并非真实意愿，这反映出公司处理方式给员工带来极大困扰。 三、诉求 1. 责令北京公交鸿运承物业管理有限公司立即停止针对老员工的不合理调岗降薪行为，尊重我爱人31年的工作贡献和实际业务能力。​2. 督促该公司维持我爱人目前的综合站务员A岗待遇，直至退休。​3. 要求公司停止高频次的施压约谈，给予老员工安稳的工作环境。​4. 对公司中高层薪资情况进行审查，要求薪资公开透明，确保决策公平公正，杜绝类似不合理剥削员工利益的情况再次发生。 希望贵单位能重视此事，从实际出发，妥善解决问题，不要让为公交系统奉献多年的老员工寒心。 市民填写的详细地址为：区、街道：通州区潞源街道详细地址：北京市人民政府国有资产监督管理委员会，负责 | AY35: =AG35 -> 劳动合同及用工管理 | AZ35: 否 | BA35: 否 | BB35: 否 | BC35: 七有五性,公正性 | BD35: =U35 -> 结束 | BE35: =IFERROR(LEFT(T35,FIND(" ",T35)-1),T35) -> 2026-01-04 | BF35: 劳动人员调配及薪酬 （综A岗调整） 多渠道同人同诉 | BG35: 人力资源部 | BH35: 单店分中心 | BL35: =IF(BG35="物管行政部","侯旭、郑楠",IF(BG35="安保部","张耕",IF(BG35="工程设备部","华菲",IF(BG35="人力资源部","成琦",IF(BG35="党委工作部","阎鑫雨",IF(BG35="餐饮服务部","赵弘晨",IF(BG35="工会","郑欣",IF(BG35="办公室","董娜",""))))))))&IF(BG35="纪检部","黄倩",IF(BG35="信息管理部","蔡浩然","")) -> 成琦 | BM35: 未主动剔除 | BP35: 政策类 | BQ35: 同人同诉：网络-251222-008037、网络-251223-037876、网络-251230-035268 | BR35: 是 | BV35: =MID(AR35,1,16) -> 网络-251230-035268 | BW35: 七有五性,劳有所得 | BX35: =IF(COUNTIF(BV:BV,BV35)=1,"否","是") -> 否 | BY35: =MID(AR35,18,1) | BZ35: 只评价响应率 | CE35: 1月 | CG35: =VLOOKUP(AR35,[1]市民意见信息导出!$AI$2:$AK$392,3,FALSE()) -> 结束 | CH35: =VLOOKUP(BV35,[2]Sheet1!$C$2:$AC$99,2,FALSE()) -> 1月
A36: 热线-251230-036223（1个附件） | B36: 2025-12-30 13:52:18 | C36: 2025-12-30 14:00:58 | D36: 2025-12-30 14:13:03 | E36: 毛先生 | F36: 男 | G36: 手机,18519660528; | H36: 市民反映，朝阳区东大桥东北角处有一个公交车的内部停车场，市民不清楚是多少路的总站，里面有很多公交车，该停车场看门的工作人员态度非常差，自己不小心走错了，走到停车场里面了，对方辱骂自己，还要打自己，市民不认可，市民表示该停车场属公交公司管辖，来电反映公交内部停车场看门人员态度问题。 | I36: 是 | J36: 诉求 | K36: 安保部（应急管理中心） | L36: 场站保安问题 | M36: 场站保安 | N36: 鸿运承物业管理中心 | O36: 方庄分中心 | P36: 安全保卫部（应急管理中心） | Q36: 方庄分中心 | R36: 2026-01-06 23:59:59 | S36: 2025-12-31 | T36: 2026-01-04 08:59:59 | U36: 结束 | V36: 0 | W36: 经方庄分中心核实此情况，投诉人所反映的场站看门工作人员为在场站长期坐着的社会人员，不属于公交职工。 | X36: 方庄分中心于2025年12月31日8点46分，由鸿运承物业管理中心方庄分中心副主任张涛与投诉人进行电话沟通，感谢投诉人的监督。 | Y36: 经方庄分中心核实此情况，投诉人所反映的场站看门工作人员为在场站长期坐着的社会人员，不属于公交职工。 | Z36: 经方庄分中心核实此情况，投诉人所反映的场站看门工作人员为在场站长期坐着的社会人员，不属于公交职工。 | AA36: 经方庄分中心核实此情况，投诉人所反映的场站看门工作人员为在场站长期坐着的社会人员，不属于公交职工。 | AB36: 经方庄分中心核实此情况，投诉人所反映的场站看门工作人员为在场站长期坐着的社会人员，不属于公交职工。方庄分中心于2025年12月31日8点46分，由鸿运承物业管理中心方庄分中心副主任张涛与投诉人进行电话沟通，感谢投诉人的监督。处理人：方庄分中心副主任张涛 | AC36: 满意 | AD36: 个人 | AE36: 2025-12-30 13:46:59 | AF36: 1741937709 | AG36: 服务 | AH36: 否 | AK36: =AG36&L36&M36 -> 服务场站保安问题场站保安 | AP36: 32 | AQ36: 46023 | AR36: =IFERROR(LEFT(A36,FIND("（",A36)-1),A36) -> 热线-251230-036223 | AS36: =J36 -> 诉求 | AT36: =IF(MID(AR36,1,2)="热线",12345)+IF(MID(AR36,1,2)="网络",12345) -> 12345 | AU36: =IFERROR(LEFT(D36,FIND(" ",D36)-1),D36) -> 2025-12-30 | AV36: =P36 -> 安全保卫部（应急管理中心） | AW36: =Q36 -> 方庄分中心 | AX36: =H36 -> 市民反映，朝阳区东大桥东北角处有一个公交车的内部停车场，市民不清楚是多少路的总站，里面有很多公交车，该停车场看门的工作人员态度非常差，自己不小心走错了，走到停车场里面了，对方辱骂自己，还要打自己，市民不认可，市民表示该停车场属公交公司管辖，来电反映公交内部停车场看门人员态度问题。 | AY36: =AG36 -> 服务 | AZ36: 否 | BA36: 否 | BB36: 否 | BC36: 七有五性,安全性、便利性 | BD36: =U36 -> 结束 | BE36: =IFERROR(LEFT(T36,FIND(" ",T36)-1),T36) -> 2026-01-04 | BF36: 保安工作态度 | BG36: 安保部 | BH36: 方庄分中心 | BL36: =IF(BG36="物管行政部","侯旭、郑楠",IF(BG36="安保部","张耕",IF(BG36="工程设备部","华菲",IF(BG36="人力资源部","成琦",IF(BG36="党委工作部","阎鑫雨",IF(BG36="餐饮服务部","赵弘晨",IF(BG36="工会","郑欣",IF(BG36="办公室","董娜",""))))))))&IF(BG36="纪检部","黄倩",IF(BG36="信息管理部","蔡浩然","")) -> 张耕 | BM36: 未主动剔除 | BP36: 业务类 | BV36: =MID(AR36,1,16) -> 热线-251230-036223 | BW36: 七有五性,便利性 | BX36: =IF(COUNTIF(BV:BV,BV36)=1,"否","是") -> 否 | BY36: =MID(AR36,18,1) | CG36: =VLOOKUP(AR36,[1]市民意见信息导出!$AI$2:$AK$392,3,FALSE()) -> 结束 | CH36: =VLOOKUP(BV36,[2]Sheet1!$C$2:$AC$99,2,FALSE()) -> #N/A
A37: 网络-251231-007653（1个附件） | B37: 2025-12-31 09:10:58 | C37: 2025-12-31 09:22:10 | D37: 2025-12-31 09:31:42 | E37: 刘佳祺 | F37: 男 | G37: 手机,15901130764; | H37: 工单来源：微信服务号，此工单内容为网民留言时填写的标题及原文。 ============================= 留言标题：公交留言原文：今天我在乘坐387路1835717于4.33在六里桥北里站在倒数第二排座椅下面发现零食残渣并未打扫 市民填写的详细地址为：区、街道：丰台区六里桥街道详细地址：六里桥北里 | I37: 是 | J37: 诉求 | K37: 行车安全服务部 | L37: 企业政策问题 | M37: 调整服务规范 | N37: 鸿运承物业管理中心 | O37: 小营分中心 | P37: 物管行政部 | Q37: 小营分中心 | R37: 2026-01-07 23:59:59 | S37: 2025-12-31 | T37: 2026-01-05 08:59:59 | U37: 结束 | V37: 0 | W37: 您好，关于您反映问题的办理情况，鸿运承物业管理中心小营分中心现对您回复如下： | X37: 我分中心已于2025年12月31日中午12点30分对您进行电话回复。办理人：李留成；部门：鸿运承物业管理中心小营分中心；职务；物管副主任。审核人：郑楠；部门：鸿运承物业管理中心物管行政部；职务：物管员。 | Y37: 刘先生您好，387路公交车我们在东小区场站进行洗车服务工作，您所述1835717号车，车辆运营中车内倒数第二排座椅下面发现零食残渣并未打扫的问题我们非常重视您的反馈，您提供的问题照片我们已收到，由于我们的工作没有做好，387路给您带来不好的乘车体验，实在是抱歉，刘先生。该车辆回到东小区场站后，在日常工作时段内，我们的保洁员已对车内地板卫生进行了全面的清理，确保我们的出场车辆卫生符合企业标准。您反馈的问题我们已整改完毕，同时我们要求保洁员对387路所有运营车辆的卫生再次进行细化清理。我们对于运营车辆车内卫生的清洁工作是一直在做的，也从未停止，已经形成了长效的清洁机制，但有时候卫生清洁工作我们做的还有不尽人意之处，您多多谅解。 | Z37: 我们分中心及场站班组长再次与387路的保洁人员进行了沟通，日常工作中我们要把清洁质量做的更加细致，同时加强保洁员清洁技能的培训，熟练掌握清洁方法，确保给您带来一个干净、整洁的出行环境。 | AA37: 我们定期会召开车辆保洁专题会议，开展车辆卫生专项检查，日常工作中我们加大巡检力度，强化制度建设，不断提高管理水平。 | AB37: 您好，关于您反映问题的办理情况，鸿运承物业管理中心小营分中心现对您回复如下：刘先生您好，387路公交车我们在东小区场站进行洗车服务工作，您所述1835717号车，车辆运营中车内倒数第二排座椅下面发现零食残渣并未打扫的问题我们非常重视您的反馈，您提供的问题照片我们已收到，由于我们的工作没有做好，387路给您带来不好的乘车体验，实在是抱歉，刘先生。该车辆回到东小区场站后，在日常工作时段内，我们的保洁员已对车内地板卫生进行了全面的清理，确保我们的出场车辆卫生符合企业标准。您反馈的问题我们已整改完毕，同时我们要求保洁员对387路所有运营车辆的卫生再次进行细化清理。我们对于运营车辆车内卫生的清洁工作是一直在做的，也从未停止，已经形成了长效的清洁机制，但有时候卫生清洁工作我们做的还有不尽人意之处，您多多谅解。我们定期会召开车辆保洁专题会议，开展车辆卫生专项检查，日常工作中我们加大巡检力度，强化制度建设，不断提高管理水平。我分中心已于2025年12月31日中午12点30分对您进行电话回复。我们分中心及场站班组长再次与387路的保洁人员进行了沟通，日常工作中我们要把清洁质量做的更加细致，同时加强保洁员清洁技能的培训，熟练掌握清洁方法，确保给您带来一个干净、整洁的出行环境。欢迎您随时对我们的工作进行监督，感谢您提出宝贵意见，给您的出行带来的不便我们和您说声抱歉，谢谢您的支持与谅解。 | AC37: 满意 | AD37: 个人 | AE37: 2025-12-30 16:34:21 | AF37: 1741937704 | AG37: 服务 | AH37: 否 | AK37: =AG37&L37&M37 -> 服务企业政策问题调整服务规范 | AP37: 33 | AQ37: 46023 | AR37: =IFERROR(LEFT(A37,FIND("（",A37)-1),A37) -> 网络-251231-007653 | AS37: =J37 -> 诉求 | AT37: =IF(MID(AR37,1,2)="热线",12345)+IF(MID(AR37,1,2)="网络",12345) -> 12345 | AU37: =IFERROR(LEFT(D37,FIND(" ",D37)-1),D37) -> 2025-12-31 | AV37: =P37 -> 物管行政部 | AW37: =Q37 -> 小营分中心 | AX37: =H37 -> 工单来源：微信服务号，此工单内容为网民留言时填写的标题及原文。 ============================= 留言标题：公交留言原文：今天我在乘坐387路1835717于4.33在六里桥北里站在倒数第二排座椅下面发现零食残渣并未打扫 市民填写的详细地址为：区、街道：丰台区六里桥街道详细地址：六里桥北里 | AY37: =AG37 -> 服务 | AZ37: 否 | BA37: 否 | BB37: 否 | BC37: 七有五性,宜居性 | BD37: =U37 -> 结束 | BE37: =IFERROR(LEFT(T37,FIND(" ",T37)-1),T37) -> 2026-01-05 | BF37: 车辆卫生问题 （车内卫生） | BG37: 物管行政部 | BH37: 小营分中心 | BL37: =IF(BG37="物管行政部","侯旭、郑楠",IF(BG37="安保部","张耕",IF(BG37="工程设备部","华菲",IF(BG37="人力资源部","成琦",IF(BG37="党委工作部","阎鑫雨",IF(BG37="餐饮服务部","赵弘晨",IF(BG37="工会","郑欣",IF(BG37="办公室","董娜",""))))))))&IF(BG37="纪检部","黄倩",IF(BG37="信息管理部","蔡浩然","")) -> 侯旭、郑楠 | BM37: 未主动剔除 | BP37: 业务类 | BV37: =MID(AR37,1,16) -> 网络-251231-007653 | BW37: 七有五性,便利性 | BX37: =IF(COUNTIF(BV:BV,BV37)=1,"否","是") -> 否 | BY37: =MID(AR37,18,1) | BZ37: 只评价响应率 | CE37: 1月 | CG37: =VLOOKUP(AR37,[1]市民意见信息导出!$AI$2:$AK$392,3,FALSE()) -> 结束 | CH37: =VLOOKUP(BV37,[2]Sheet1!$C$2:$AC$99,2,FALSE()) -> 1月
A38: 热线-251231-006369-2（1个附件） | B38: 2025-12-31 08:58:14 | C38: 2025-12-31 09:08:18 | D38: 2025-12-31 13:43:09 | E38: 王女士 | F38: 女 | G38: 手机,64968180; | H38: 市民反映，北京市朝阳区大屯街道慧忠里汽车总站（63路公交车），市民表示在慧忠里汽车总站路南有三个铁栅栏门，但是2号门一直没有开放，导致去到站内还要绕远，对此不认可，希望可以开放，来电反映协调车站开放栅栏门问题。注：此工单为拆分工单，录音详见热线-251231-005745。 | I38: 是 | J38: 诉求 | K38: 安保部（应急管理中心） | L38: 安保专业政策问题 | M38: 安保措施 | N38: 鸿运承物业管理中心 | O38: 小营分中心 | P38: 安全保卫部（应急管理中心） | Q38: 小营分中心 | R38: 2026-01-07 23:59:59 | S38: 2025-12-31 | T38: 2026-01-05 08:59:59 | U38: 结束 | V38: 0 | W38: 接到投诉后，小营分中心高度重视，对投诉人反映问题立即进行核实。经分中心实地核实后，我们于2025年12月31日下午14时14分对诉求人关于此项问题致电回复。 | X38: 接到投诉后，小营分中心高度重视，对投诉人反映问题立即进行核实。经分中心实地考察后，我们于2025年12月31日下午14时14分对诉求人关于此项问题致电回复。诉求人所反映的慧忠里公交场站属于大型综合类场站，场站内外来乘客等人员较多，虽设有安保人员，但仍存在视线死角。诉求人反映的北边小门因处于灌木丛中，为视线死角。为了杜绝场站内的安全事故，决定将此门锁上。对于诉求人反映的情况，分中心将结合该场站的后续工作情况及乘客需求，合理安排开放此门。办理人：何少楠。审核员：陶春辉。单位：小营分中心。职务：党支部书记兼主任 | Y38: 接到投诉后，小营分中心高度重视，对投诉人反映问题立即进行核实。经分中心实地考察后，我们于2025年12月31日下午14时14分对诉求人关于此项问题致电回复。诉求人所反映的慧忠里公交场站属于大型综合类场站，场站内外来乘客等人员较多，虽设有安保人员，但仍存在视线死角。诉求人反映的北边小门因处于灌木丛中，为视线死角。为了杜绝场站内的安全事故，决定将此门锁上。对于诉求人反映的情况，分中心将结合该场站的后续工作情况及乘客需求，合理安排开放此门。 | Z38: 针对此次投诉人所反映的情况，分中心将结合下辖场站的实际情况，合理安排警卫人员的场站检查工作，避免因类似情况造成投诉。 | AA38: 无 | AB38: 接到投诉后，小营分中心高度重视，对投诉人反映问题立即进行核实。经分中心实地考察后，我们于2025年12月31日下午14时14分对诉求人关于此项问题致电回复。诉求人所反映的慧忠里公交场站属于大型综合类场站，场站内外来乘客等人员较多，虽设有安保人员，但仍存在视线死角。诉求人反映的北边小门因处于灌木丛中，为视线死角。为了杜绝场站内的安全事故，决定将此门锁上。对于诉求人反映的情况，分中心将结合该场站的后续工作情况及乘客需求，合理安排开放此门。 针对此次投诉人所反映的情况，分中心将结合下辖场站的实际情况，合理安排警卫人员的场站检查工作，避免因类似情况造成投诉。 | AC38: 满意 | AD38: 个人 | AE38: 2025-12-31 08:56:22 | AF38: 1741937704 | AG38: 设施设备 | AH38: 否 | AK38: =AG38&L38&M38 -> 设施设备安保专业政策问题安保措施 | AP38: 34 | AQ38: 46023 | AR38: =IFERROR(LEFT(A38,FIND("（",A38)-1),A38) -> 热线-251231-006369-2 | AS38: =J38 -> 诉求 | AT38: =IF(MID(AR38,1,2)="热线",12345)+IF(MID(AR38,1,2)="网络",12345) -> 12345 | AU38: =IFERROR(LEFT(D38,FIND(" ",D38)-1),D38) -> 2025-12-31 | AV38: =P38 -> 安全保卫部（应急管理中心） | AW38: =Q38 -> 小营分中心 | AX38: =H38 -> 市民反映，北京市朝阳区大屯街道慧忠里汽车总站（63路公交车），市民表示在慧忠里汽车总站路南有三个铁栅栏门，但是2号门一直没有开放，导致去到站内还要绕远，对此不认可，希望可以开放，来电反映协调车站开放栅栏门问题。注：此工单为拆分工单，录音详见热线-251231-005745。 | AY38: =AG38 -> 设施设备 | AZ38: 否 | BA38: 否 | BB38: 否 | BC38: 七有五性,安全性、便利性 | BD38: =U38 -> 结束 | BE38: =IFERROR(LEFT(T38,FIND(" ",T38)-1),T38) -> 2026-01-05 | BF38: 场站安保问题 （站内导乘不便） | BG38: 安保部 | BH38: 小营分中心 | BL38: =IF(BG38="物管行政部","侯旭、郑楠",IF(BG38="安保部","张耕",IF(BG38="工程设备部","华菲",IF(BG38="人力资源部","成琦",IF(BG38="党委工作部","阎鑫雨",IF(BG38="餐饮服务部","赵弘晨",IF(BG38="工会","郑欣",IF(BG38="办公室","董娜",""))))))))&IF(BG38="纪检部","黄倩",IF(BG38="信息管理部","蔡浩然","")) -> 张耕 | BM38: 未主动剔除 | BP38: 业务类 | BV38: =MID(AR38,1,16) -> 热线-251231-006369 | BW38: 七有五性,便利性 | BX38: =IF(COUNTIF(BV:BV,BV38)=1,"否","是") -> 否 | BY38: =MID(AR38,18,1) -> 2 | BZ38: 只评价响应率 | CE38: 1月 | CG38: =VLOOKUP(AR38,[1]市民意见信息导出!$AI$2:$AK$392,3,FALSE()) -> 结束 | CH38: =VLOOKUP(BV38,[2]Sheet1!$C$2:$AC$99,2,FALSE()) -> 1月
A39: 热线-251231-023645 | B39: 2025-12-31 13:12:32 | C39: 2025-12-31 13:35:22 | D39: 2025-12-31 13:43:10 | E39: 保密 | F39: 女 | G39: 保密 | H39: 市民反映，大兴区公交集团鸿运城天宫院分中心，中A综合站务岗位无人看守酒测，车队和综合站务员说明了，但还是没有人看守，属于迟到，希望对综合站务员按照公司考核制度扣罚，来电反映协调对综合站务员进行处理问题。注：要求保密来电人信息（已解释）。 | I39: 是 | J39: 诉求 | K39: 人力资源部（人力资源发展中心） | L39: 劳动用工 | M39: 劳动工时 | N39: 鸿运承物业管理中心 | O39: 天宫院分中心 | P39: 人力资源部 | Q39: 天宫院分中心 | R39: 2026-01-07 23:59:59 | S39: 2026-01-04 | T39: 2026-01-05 08:59:59 | U39: 结束 | V39: 0 | W39: 经核实，与来电人所述情况存在出入。我单位天宫院分中心共有两个场站设有综合站务员A岗，分别为丽园场站和南湖路公交场站。经核实，两个场站综合站务员A岗上班时间为8:00-16:00。通过核实系统打卡情况，职工不存在迟到早退问题。 | X39: 经核实，与来电人所述情况存在出入。我单位天宫院分中心共有两个场站设有综合站务员A岗，分别为丽园场站和南湖路公交场站。经核实，两个场站综合站务员A岗上班时间为8:00-16:00。通过核实系统打卡情况，职工不存在迟到早退问题。因来电人未留姓名及联系方式，故我单位无法与来电人进行电话回复。我单位天宫院分中心领导班子、人力专业高度重视此类问题，会进一步加大检查力度，发现问题，严肃处理。 办理人：张鹤颖 ；部门：鸿运承物业管理中心天宫院分中心，职务：一般管理； 审核人：高强；部门：鸿运承物业管理中心人力资源部；职务：中级管理。 | Y39: 因来电人未留姓名及联系方式，故我单位无法与来电人进行电话回复。我单位天宫院分中心领导班子、人力专业高度重视此类问题，会进一步加大检查力度，发现问题，严肃处理。 | Z39: 无 | AA39: 我单位天宫院分中心领导班子、人力专业高度重视此类问题，会进一步加大检查力度，发现问题，严肃处理。 | AB39: 经核实，与来电人所述情况存在出入。我单位天宫院分中心共有两个场站设有综合站务员A岗，分别为丽园场站和南湖路公交场站。经核实，两个场站综合站务员A岗上班时间为8:00-16:00。通过核实系统打卡情况，职工不存在迟到早退问题。因来电人未留姓名及联系方式，故我单位无法与来电人进行电话回复。我单位天宫院分中心领导班子、人力专业高度重视此类问题，会进一步加大检查力度，发现问题，严肃处理。 | AC39: 满意 | AD39: 个人 | AE39: 2025-12-31 11:23:43 | AF39: 1741937712 | AG39: 服务 | AH39: 否 | AK39: =AG39&L39&M39 -> 服务劳动用工劳动工时 | AP39: 35 | AQ39: 46023 | AR39: =IFERROR(LEFT(A39,FIND("（",A39)-1),A39) -> 热线-251231-023645 | AS39: =J39 -> 诉求 | AT39: =IF(MID(AR39,1,2)="热线",12345)+IF(MID(AR39,1,2)="网络",12345) -> 12345 | AU39: =IFERROR(LEFT(D39,FIND(" ",D39)-1),D39) -> 2025-12-31 | AV39: =P39 -> 人力资源部 | AW39: =Q39 -> 天宫院分中心 | AX39: =H39 -> 市民反映，大兴区公交集团鸿运城天宫院分中心，中A综合站务岗位无人看守酒测，车队和综合站务员说明了，但还是没有人看守，属于迟到，希望对综合站务员按照公司考核制度扣罚，来电反映协调对综合站务员进行处理问题。注：要求保密来电人信息（已解释）。 | AY39: =AG39 -> 服务 | AZ39: 是 | BA39: 是 | BB39: 否 | BC39: 七有五性,公正性 | BD39: =U39 -> 结束 | BE39: =IFERROR(LEFT(T39,FIND(" ",T39)-1),T39) -> 2026-01-05 | BF39: 劳动人员管理及劳动纪律问题 （劳动出勤） | BG39: 人力资源部 | BH39: 天宫院分中心 | BL39: =IF(BG39="物管行政部","侯旭、郑楠",IF(BG39="安保部","张耕",IF(BG39="工程设备部","华菲",IF(BG39="人力资源部","成琦",IF(BG39="党委工作部","阎鑫雨",IF(BG39="餐饮服务部","赵弘晨",IF(BG39="工会","郑欣",IF(BG39="办公室","董娜",""))))))))&IF(BG39="纪检部","黄倩",IF(BG39="信息管理部","蔡浩然","")) -> 成琦 | BM39: 未主动剔除 | BP39: 政策类 | BV39: =MID(AR39,1,16) -> 热线-251231-023645 | BW39: 七有五性,便利性 | BX39: =IF(COUNTIF(BV:BV,BV39)=1,"否","是") -> 否 | BY39: =MID(AR39,18,1) | CG39: =VLOOKUP(AR39,[1]市民意见信息导出!$AI$2:$AK$392,3,FALSE()) -> 结束 | CH39: =VLOOKUP(BV39,[2]Sheet1!$C$2:$AC$99,2,FALSE()) -> #N/A
A40: 网络-251231-040038（1个附件） | B40: 2025-12-31 14:39:22 | C40: 2025-12-31 14:46:57 | D40: 2025-12-31 14:59:02 | E40: 李 | F40: 女 | G40: 手机,13810696219; | H40: 工单来源：微信服务号，此工单内容为网民留言时填写的标题及原文。 ============================= 留言标题：公交集团鸿运承物业管理中心天宫院分中心给我公园年票办错了留言原文：我要求办理市属公园年票，分中心给办错了，我要求尽快纠正。耽误我元旦假期。市民填写的详细地址为：区、街道：大兴区天宫院街道详细地址：天宫院注：因留言中缺少问题详细情况，故回拨市民。2025年12月31日14:38分14305号回拨市民，经与市民沟通，市民称单位给员工办理公园年票时候办错了，向公交集团鸿运承物业管理中心天宫院分中心反映没有收到回复，故希望将问题反映至公交集团帮助协调解决公园年票问题。 | I40: 是 | J40: 诉求 | K40: 工会 | L40: 职工福利帮扶问题 | M40: 职工福利 | N40: 鸿运承物业管理中心 | O40: 工会 | P40: 工会 | Q40: 机关 | R40: 2026-01-07 23:59:59 | S40: 2026-01-04 | T40: 2026-01-05 08:59:59 | U40: 结束 | V40: 0 | W40: 接到投诉后，物业管理中心工会高度重视，天宫院分中心工会主席于1月4日10:51于职工进行电话核实。经核实，市民所反映问题与事实有出入，现已解决。经与市民进行沟通，表示理解并满意。 | X40: 公交集团物业管理中心天宫院分中心工会主席于2026年1月4日10:51拨打当事人电话，与职工进行沟通，了解情况。办理人:赵艳维;部门:鸿运承物业管理中心天宫院分中心;职务:工会主席。审核人:白莉;部门鸿运承物业管理中心工会;职务:工会副主席。 | Y40: 物业管理中心天宫院分中心与职工进行沟通，了解情况。经核实，市民所反映问题与事实有出入，2025年12月31日为职工办理实属公园年票。经与市民进行沟通，表示理解并满意，物业管理中心工会提出工作要求，各分会须加强与职工的沟通把工作做好、做细、做实，减少职工对工作产生的误会更好的服务职工。 | Z40: 针对此问题，物业管理中心工会提出工作要求，各分会须加强与职工的沟通，把工作做好、做细、做实，减少职工对工作产生的误会，更好的服务职工。 | AA40: 物业管理中心工会提出工作要求，各分会须加强与职工的沟通，把工作做好、做细、做实，减少职工对工作产生的误会，更好的服务职工。 | AB40: 建议不予回访。接到投诉后，物业管理中心工会高度重视，工会干事进行核实。2025年12月31日为职工办理实属公园年票。经与市民进行沟通，表示理解并满意。物业管理中心工会提出工作要求，各分会须加强与职工的沟通把工作做好、做细、做实，减少职工对工作产生的误会更好的服务职工。 | AC40: 满意 | AD40: 个人 | AE40: 2025-12-31 09:41:03 | AF40: 771020823 | AG40: 劳动合同及用工管理 | AH40: 否 | AK40: =AG40&L40&M40 -> 劳动合同及用工管理职工福利帮扶问题职工福利 | AP40: 36 | AQ40: 46023 | AR40: =IFERROR(LEFT(A40,FIND("（",A40)-1),A40) -> 网络-251231-040038 | AS40: =J40 -> 诉求 | AT40: =IF(MID(AR40,1,2)="热线",12345)+IF(MID(AR40,1,2)="网络",12345) -> 12345 | AU40: =IFERROR(LEFT(D40,FIND(" ",D40)-1),D40) -> 2025-12-31 | AV40: =P40 -> 工会 | AW40: =Q40 -> 机关 | AX40: =H40 -> 工单来源：微信服务号，此工单内容为网民留言时填写的标题及原文。 ============================= 留言标题：公交集团鸿运承物业管理中心天宫院分中心给我公园年票办错了留言原文：我要求办理市属公园年票，分中心给办错了，我要求尽快纠正。耽误我元旦假期。市民填写的详细地址为：区、街道：大兴区天宫院街道详细地址：天宫院注：因留言中缺少问题详细情况，故回拨市民。2025年12月31日14:38分14305号回拨市民，经与市民沟通，市民称单位给员工办理公园年票时候办错了，向公交集团鸿运承物业管理中心天宫院分中心反映没有收到回复，故希望将问题反映至公交集团帮助协调解决公园年票问题。 | AY40: =AG40 -> 劳动合同及用工管理 | AZ40: 是 | BA40: 是 | BB40: 否 | BC40: 七有五性,公正性 | BD40: =U40 -> 结束 | BE40: =IFERROR(LEFT(T40,FIND(" ",T40)-1),T40) -> 2026-01-05 | BF40: 职工福利惠及 （公园年票） | BG40: 工会 | BH40: 天宫院分中心 | BL40: =IF(BG40="物管行政部","侯旭、郑楠",IF(BG40="安保部","张耕",IF(BG40="工程设备部","华菲",IF(BG40="人力资源部","成琦",IF(BG40="党委工作部","阎鑫雨",IF(BG40="餐饮服务部","赵弘晨",IF(BG40="工会","郑欣",IF(BG40="办公室","董娜",""))))))))&IF(BG40="纪检部","黄倩",IF(BG40="信息管理部","蔡浩然","")) -> 郑欣 | BM40: 未主动剔除 | BP40: 政策类 | BQ40: 同人同诉：网络-251231-040038、热线-251231-006944 | BR40: 是 | BV40: =MID(AR40,1,16) -> 网络-251231-040038 | BW40: 七有五性,劳有所得 | BX40: =IF(COUNTIF(BV:BV,BV40)=1,"否","是") -> 否 | BY40: =MID(AR40,18,1) | CG40: =VLOOKUP(AR40,[1]市民意见信息导出!$AI$2:$AK$392,3,FALSE()) -> 结束 | CH40: =VLOOKUP(BV40,[2]Sheet1!$C$2:$AC$99,2,FALSE()) -> #N/A
A41: 热线-251231-006944（1个附件） | B41: 2025-12-31 17:09:46 | C41: 2025-12-31 17:29:24 | D41: 2025-12-31 17:49:41 | E41: 李女士 | F41: 女 | G41: 手机,13810696219; | H41: 市民反映，自己公司是北京公交集团鸿运城物业管理中心（地址：北京市西城区核桃园东街3号），当时公司承诺每年会为市民办理市属公园年票，但是今年公司突然通知办理的是城市文化年票。市民认为不合理，影响到了自己的生活计划，希望相关部门协调企业按照约定提供市属公园年票。来电反映要求公司按照约定办理年票问题。工单流转，西城区退回：经核实，诉求人为北京公交集团鸿运城物业管理中心下属分中心员工，反映公司办理公园年票福利待遇问题。我院工作人员告知诉求人其反映的问题属于单位内部福利待遇问题，不属于用人单位与员工的劳动争议，不属于劳动仲裁受案范围，也不涉及劳动违法问题，应当积极与单位协商处理。经查与核实，北京公交集团鸿运城物业管理中心的上级单位为北京公共交通控股（集团）有限公司，该单位为北京市属国企，工作人员就该问题进行解释，并告知诉求人该问题将转至北京公共交通控股（集团）有限公司答复处理，诉求人表示清楚。因此，建议退至北京公共交通控股（集团）有限公司。 | I41: 是 | J41: 诉求 | K41: 工会 | L41: 职工福利帮扶问题 | M41: 职工福利 | N41: 鸿运承物业管理中心 | O41: 工会 | P41: 工会 | Q41: 机关 | R41: 2026-01-07 23:59:59 | S41: 2026-01-04 | T41: 2026-01-05 08:59:59 | U41: 结束 | V41: 0 | W41: 接到投诉后，物业管理中心工会高度重视，天宫院分中心工会主席于1月4日10:51于职工进行电话核实。经核实，市民所反映问题与事实有出入，现已解决。经与市民进行沟通，表示理解并满意。 | X41: 公交集团物业管理中心天宫院分中心工会主席于2026年1月4日10:51拨打当事人电话，与职工进行沟通，了解情况。办理人:赵艳维;部门:鸿运承物业管理中心天宫院分中心;职务:工会主席。审核人:白莉;部门:鸿运承物业管理中心工会;职务:工会副主席。 | Y41: 物业管理中心天宫院分中心与职工进行沟通，了解情况。经核实，市民所反映问题与事实有出入，2025年12月31日为职工办理实属公园年票。经与市民进行沟通，表示理解并满意。物业管理中心工会提出工作要求，各分会须加强与职工的沟通把工作做好、做细、做实，减少职工对工作产生的误会更好的服务职工。 | Z41: 针对此问题，物业管理中心工会提出工作要求，各分会须加强与职工的沟通，把工作做好、做细、做实，减少职工对工作产生的误会，更好的服务职工。 | AA41: 物业管理中心工会提出工作要求，各分会须加强与职工的沟通，把工作做好、做细、做实，减少职工对工作产生的误会，更好的服务职工。 | AB41: 建议不予回访。接到投诉后，物业管理中心工会高度重视，工会干事进行核实。2025年12月31日为职工办理实属公园年票。经与市民进行沟通，表示理解并满意。物业管理中心工会提出工作要求，各分会须加强与职工的沟通把工作做好、做细、做实，减少职工对工作产生的误会更好的服务职工。 | AC41: 满意 | AD41: 个人 | AE41: 2025-12-31 09:03:01 | AF41: 771020823 | AG41: 劳动合同及用工管理 | AH41: 否 | AK41: =AG41&L41&M41 -> 劳动合同及用工管理职工福利帮扶问题职工福利 | AP41: 37 | AQ41: 46023 | AR41: =IFERROR(LEFT(A41,FIND("（",A41)-1),A41) -> 热线-251231-006944 | AS41: =J41 -> 诉求 | AT41: =IF(MID(AR41,1,2)="热线",12345)+IF(MID(AR41,1,2)="网络",12345) -> 12345 | AU41: =IFERROR(LEFT(D41,FIND(" ",D41)-1),D41) -> 2025-12-31 | AV41: =P41 -> 工会 | AW41: =Q41 -> 机关 | AX41: =H41 -> 市民反映，自己公司是北京公交集团鸿运城物业管理中心（地址：北京市西城区核桃园东街3号），当时公司承诺每年会为市民办理市属公园年票，但是今年公司突然通知办理的是城市文化年票。市民认为不合理，影响到了自己的生活计划，希望相关部门协调企业按照约定提供市属公园年票。来电反映要求公司按照约定办理年票问题。工单流转，西城区退回：经核实，诉求人为北京公交集团鸿运城物业管理中心下属分中心员工，反映公司办理公园年票福利待遇问题。我院工作人员告知诉求人其反映的问题属于单位内部福利待遇问题，不属于用人单位与员工的劳动争议，不属于劳动仲裁受案范围，也不涉及劳动违法问题，应当积极与单位协商处理。经查与核实，北京公交集团鸿运城物业管理中心的上级单位为北京公共交通控股（集团）有限公司，该单位为北京市属国企，工作人员就该问题进行解释，并告知诉求人该问题将转至北京公共交通控股（集团）有限公司答复处理，诉求人表示清楚。因此，建议退至北京公共交通控股（集团）有限公司。 | AY41: =AG41 -> 劳动合同及用工管理 | AZ41: 是 | BA41: 是 | BB41: 否 | BC41: 七有五性,公正性 | BD41: =U41 -> 结束 | BE41: =IFERROR(LEFT(T41,FIND(" ",T41)-1),T41) -> 2026-01-05 | BF41: 职工福利惠及 （公园年票） | BG41: 工会 | BH41: 天宫院分中心 | BL41: =IF(BG41="物管行政部","侯旭、郑楠",IF(BG41="安保部","张耕",IF(BG41="工程设备部","华菲",IF(BG41="人力资源部","成琦",IF(BG41="党委工作部","阎鑫雨",IF(BG41="餐饮服务部","赵弘晨",IF(BG41="工会","郑欣",IF(BG41="办公室","董娜",""))))))))&IF(BG41="纪检部","黄倩",IF(BG41="信息管理部","蔡浩然","")) -> 郑欣 | BM41: 未主动剔除 | BP41: 政策类 | BQ41: 同人同诉：网络-251231-040038、热线-251231-006944 | BR41: 是 | BV41: =MID(AR41,1,16) -> 热线-251231-006944 | BW41: 七有五性,劳有所得 | BX41: =IF(COUNTIF(BV:BV,BV41)=1,"否","是") -> 否 | BY41: =MID(AR41,18,1) | CG41: =VLOOKUP(AR41,[1]市民意见信息导出!$AI$2:$AK$392,3,FALSE()) -> 结束 | CH41: =VLOOKUP(BV41,[2]Sheet1!$C$2:$AC$99,2,FALSE()) -> #N/A
A42: 网络-260102-004649 | B42: 2026-01-02 09:08:14 | C42: 2026-01-02 09:27:38 | D42: 2026-01-02 10:13:38 | E42: 保密 | F42: 女 | G42: 保密 | H42: 工单来源：微信服务号，此工单内容为网民留言时填写的标题及原文。 ============================= 留言标题：107车辆卫生差留言原文：今下午三点多从天文馆出来坐107公交车，发现车里卫生很差，扶手杆黑，坐位上有土。过节期间这样真是不好，影响北京公交形象。公交领导多检查看看。市民填写的详细地址为：区、街道：海淀区学院路街道详细地址：白石桥 | I42: 是 | J42: 诉求 | K42: 行车安全服务部 | L42: 企业政策问题 | M42: 调整服务规范 | N42: 鸿运承物业管理中心 | O42: 动物园分中心 | P42: 物管行政部 | Q42: 动物园分中心 | R42: 2026-01-09 23:59:59 | S42: 2026-01-03 | T42: 2026-01-07 08:59:59 | U42: 结束 | V42: 0 | W42: 您好，关于您反映问题的办理情况，鸿运承物业管理中心动物园分中心现对您回复如下： | X42: 因您的联系方式保密，我们未能对您进行电话回复。办理人：杜伟；部门：鸿运承物业管理中心动物园分中心；职务；物管副主任。审核人：郑楠；部门：鸿运承物业管理中心物管行政部；职务：物管员。 | Y42: 女士您好，107路公交车我们在东直门外场站进行洗车服务工作，您所述车辆运营中车里卫生很差，扶手杆黑，坐位上有土的问题我们非常重视您的反馈，由于我们的工作没有做好，107路给您带来不好的乘车体验，实在是抱歉，女士。该线路车辆回到东直门外场站后，在日常工作时段内，我们的保洁员已对车内卫生进行了全面的清理，确保我们的出场车辆卫生符合企业标准。您反馈的问题我们已整改完毕，同时我们要求保洁员对107路所有运营车辆的卫生再次进行细化清理。我们对于运营车辆车内卫生的清洁工作是一直在做的，也从未停止，已经形成了长效的清洁机制，但有时候卫生清洁工作我们做的还有不尽人意之处，您多多谅解。 | Z42: 我们分中心及场站班组长再次与107路的保洁人员进行了沟通，日常工作中我们要把清洁质量做的更加细致，同时加强保洁员清洁技能的培训，熟练掌握清洁方法，确保给您带来一个干净、整洁的出行环境。 | AA42: 我们定期会召开车辆保洁专题会议，开展车辆卫生专项检查，日常工作中我们加大巡检力度，强化制度建设，不断提高管理水平。 | AB42: 您好，关于您反映问题的办理情况，鸿运承物业管理中心动物园分中心现对您回复如下：女士您好，107路公交车我们在东直门外场站进行洗车服务工作，您所述车辆运营中车里卫生很差，扶手杆黑，坐位上有土的问题我们非常重视您的反馈，由于我们的工作没有做好，107路给您带来不好的乘车体验，实在是抱歉，女士。该线路车辆回到东直门外场站后，在日常工作时段内，我们的保洁员已对车内卫生进行了全面的清理，确保我们的出场车辆卫生符合企业标准。您反馈的问题我们已整改完毕，同时我们要求保洁员对107路所有运营车辆的卫生再次进行细化清理。我们对于运营车辆车内卫生的清洁工作是一直在做的，也从未停止，已经形成了长效的清洁机制，但有时候卫生清洁工作我们做的还有不尽人意之处，您多多谅解。我们定期会召开车辆保洁专题会议，开展车辆卫生专项检查，日常工作中我们加大巡检力度，强化制度建设，不断提高管理水平。因您的联系方式保密，我们未能对您进行电话回复。我们分中心及场站班组长再次与107路的保洁人员进行了沟通，日常工作中我们要把清洁质量做的更加细致，同时加强保洁员清洁技能的培训，熟练掌握清洁方法，确保给您带来一个干净、整洁的出行环境。欢迎您随时对我们的工作进行监督，感谢您提出宝贵意见，给您的出行带来的不便我们和您说声抱歉，谢谢您的支持与谅解。 | AC42: 满意 | AD42: 个人 | AE42: 2026-01-01 17:19:11 | AF42: 1741937703 | AG42: 服务 | AH42: 否 | AK42: =AG42&L42&M42 -> 服务企业政策问题调整服务规范 | AP42: 38 | AQ42: 46023 | AR42: =IFERROR(LEFT(A42,FIND("（",A42)-1),A42) -> 网络-260102-004649 | AS42: =J42 -> 诉求 | AT42: =IF(MID(AR42,1,2)="热线",12345)+IF(MID(AR42,1,2)="网络",12345) -> 12345 | AU42: =IFERROR(LEFT(D42,FIND(" ",D42)-1),D42) -> 2026-01-02 | AV42: =P42 -> 物管行政部 | AW42: =Q42 -> 动物园分中心 | AX42: =H42 -> 工单来源：微信服务号，此工单内容为网民留言时填写的标题及原文。 ============================= 留言标题：107车辆卫生差留言原文：今下午三点多从天文馆出来坐107公交车，发现车里卫生很差，扶手杆黑，坐位上有土。过节期间这样真是不好，影响北京公交形象。公交领导多检查看看。市民填写的详细地址为：区、街道：海淀区学院路街道详细地址：白石桥 | AY42: =AG42 -> 服务 | AZ42: 否 | BA42: 否 | BB42: 否 | BC42: 七有五性,宜居性 | BD42: =U42 -> 结束 | BE42: =IFERROR(LEFT(T42,FIND(" ",T42)-1),T42) -> 2026-01-07 | BF42: 车辆卫生问题 （车内卫生、扶手脏） | BG42: 物管行政部 | BH42: 动物园分中心 | BL42: =IF(BG42="物管行政部","侯旭、郑楠",IF(BG42="安保部","张耕",IF(BG42="工程设备部","华菲",IF(BG42="人力资源部","成琦",IF(BG42="党委工作部","阎鑫雨",IF(BG42="餐饮服务部","赵弘晨",IF(BG42="工会","郑欣",IF(BG42="办公室","董娜",""))))))))&IF(BG42="纪检部","黄倩",IF(BG42="信息管理部","蔡浩然","")) -> 侯旭、郑楠 | BM42: 未主动剔除 | BP42: 业务类 | BV42: =MID(AR42,1,16) -> 网络-260102-004649 | BW42: 七有五性,便利性 | BX42: =IF(COUNTIF(BV:BV,BV42)=1,"否","是") -> 否 | BY42: =MID(AR42,18,1) | CG42: =VLOOKUP(AR42,[1]市民意见信息导出!$AI$2:$AK$392,3,FALSE()) -> 结束 | CH42: =VLOOKUP(BV42,[2]Sheet1!$C$2:$AC$99,2,FALSE()) -> #N/A
A43: 热线-260102-015903（1个附件） | B43: 2026-01-02 11:42:51 | C43: 2026-01-02 11:50:34 | D43: 2026-01-02 11:51:40 | E43: 李先生 | F43: 男 | G43: 手机,13522049284; | H43: 市民举报，883路（德胜门西-南口西站），870路（南口西-兴寿北），887路（南口北-回龙观）公交车卫生脏乱差，来电反映883路和870路以及887路公交车卫生脏乱差问题。 | I43: 是 | J43: 诉求 | K43: 行车安全服务部 | L43: 乘车环境问题 | M43: 车辆卫生 | N43: 鸿运承物业管理中心 | O43: 史各庄分中心 | P43: 物管行政部 | Q43: 史各庄分中心 | R43: 2026-01-09 23:59:59 | S43: 2026-01-03 | T43: 2026-01-07 08:59:59 | U43: 结束 | V43: 0 | W43: 您好，关于您反映问题的办理情况，鸿运承物业管理中心史各庄分中心现对您回复如下： | X43: 我分中心已于2026年1月2日下午15点08分对您进行电话回复。办理人：刘扬；部门：鸿运承物业管理中心史各庄分中心；职务；物管副主任。审核人：郑楠；部门：鸿运承物业管理中心物管行政部；职务：物管员。 | Y43: 先生您好，883路、870路、887路公交车我们在南口场站进行车厢服务工作，您所述3条运营线路公交车卫生脏乱差的问题，我们非常重视您的反馈，由于我们的工作没有做好，3条线路给您带来不好的乘车体验，实在是抱歉，先生。3条线路车辆回到南口场站后，在日常工作时段内，我们的保洁员已对车内卫生进行了全面的清理，确保我们的出场车辆卫生符合企业标准。您反馈的问题我们已整改完毕，同时我们要求保洁员对3条线路所有运营车辆的卫生再次进行细化清理。我们对于运营车辆车内卫生的清洁工作是一直在做的，也从未停止，已经形成了长效的清洁机制，但有时候卫生清洁工作我们做的还有不尽人意之处，您多多谅解。 | Z43: 我们分中心及场站班组长再次与3条线路的保洁人员进行了沟通，日常工作中我们要把清洁质量做的更加细致，同时加强保洁员清洁技能的培训，熟练掌握清洁方法，确保给您带来一个干净、整洁的出行环境。 | AA43: 我们定期会召开车辆保洁专题会议，开展车辆卫生专项检查，日常工作中我们加大巡检力度，强化制度建设，不断提高管理水平。 | AB43: 您好，关于您反映问题的办理情况，鸿运承物业管理中心史各庄分中心现对您回复如下：先生您好，883路、870路、887路公交车我们在南口场站进行车厢服务工作，您所述3条运营线路公交车卫生脏乱差的问题，我们非常重视您的反馈，由于我们的工作没有做好，3条线路给您带来不好的乘车体验，实在是抱歉，先生。3条线路车辆回到南口场站后，在日常工作时段内，我们的保洁员已对车内卫生进行了全面的清理，确保我们的出场车辆卫生符合企业标准。您反馈的问题我们已整改完毕，同时我们要求保洁员对3条线路所有运营车辆的卫生再次进行细化清理。我们对于运营车辆车内卫生的清洁工作是一直在做的，也从未停止，已经形成了长效的清洁机制，但有时候卫生清洁工作我们做的还有不尽人意之处，您多多谅解。我们定期会召开车辆保洁专题会议，开展车辆卫生专项检查，日常工作中我们加大巡检力度，强化制度建设，不断提高管理水平。我分中心已于2026年1月2日下午15点08分对您进行电话回复。我们分中心及场站班组长再次与3条线路的保洁人员进行了沟通，日常工作中我们要把清洁质量做的更加细致，同时加强保洁员清洁技能的培训，熟练掌握清洁方法，确保给您带来一个干净、整洁的出行环境。欢迎您随时对我们的工作进行监督，感谢您提出宝贵意见，给您的出行带来的不便我们和您说声抱歉，谢谢您的支持与谅解。 | AC43: 满意 | AD43: 个人 | AE43: 2026-01-02 11:39:16 | AF43: 1725545790 | AG43: 服务 | AH43: 否 | AK43: =AG43&L43&M43 -> 服务乘车环境问题车辆卫生 | AP43: 39 | AQ43: 46023 | AR43: =IFERROR(LEFT(A43,FIND("（",A43)-1),A43) -> 热线-260102-015903 | AS43: =J43 -> 诉求 | AT43: =IF(MID(AR43,1,2)="热线",12345)+IF(MID(AR43,1,2)="网络",12345) -> 12345 | AU43: =IFERROR(LEFT(D43,FIND(" ",D43)-1),D43) -> 2026-01-02 | AV43: =P43 -> 物管行政部 | AW43: =Q43 -> 史各庄分中心 | AX43: =H43 -> 市民举报，883路（德胜门西-南口西站），870路（南口西-兴寿北），887路（南口北-回龙观）公交车卫生脏乱差，来电反映883路和870路以及887路公交车卫生脏乱差问题。 | AY43: =AG43 -> 服务 | AZ43: 否 | BA43: 否 | BB43: 否 | BC43: 七有五性,宜居性 | BD43: =U43 -> 结束 | BE43: =IFERROR(LEFT(T43,FIND(" ",T43)-1),T43) -> 2026-01-07 | BF43: 车辆卫生问题 （车内卫生） | BG43: 物管行政部 | BH43: 史各庄分中心 | BL43: =IF(BG43="物管行政部","侯旭、郑楠",IF(BG43="安保部","张耕",IF(BG43="工程设备部","华菲",IF(BG43="人力资源部","成琦",IF(BG43="党委工作部","阎鑫雨",IF(BG43="餐饮服务部","赵弘晨",IF(BG43="工会","郑欣",IF(BG43="办公室","董娜",""))))))))&IF(BG43="纪检部","黄倩",IF(BG43="信息管理部","蔡浩然","")) -> 侯旭、郑楠 | BM43: 未主动剔除 | BP43: 业务类 | BQ43: 同人反映问题：热线-260102-015903、 | BR43: 是 | BU43: 有恶意嫌疑 | BV43: =MID(AR43,1,16) -> 热线-260102-015903 | BW43: 七有五性,便利性 | BX43: =IF(COUNTIF(BV:BV,BV43)=1,"否","是") -> 否 | BY43: =MID(AR43,18,1) | BZ43: 只评价响应率 | CE43: 1月 | CG43: =VLOOKUP(AR43,[1]市民意见信息导出!$AI$2:$AK$392,3,FALSE()) -> 结束 | CH43: =VLOOKUP(BV43,[2]Sheet1!$C$2:$AC$99,2,FALSE()) -> 1月
A44: 热线-260103-039044-1（1个附件） | B44: 2026-01-03 17:42:16 | C44: 2026-01-03 17:52:01 | D44: 2026-01-03 19:46:01 | E44: 焦女士 | F44: 女 | G44: 手机,13466785896; | H44: 市民反映，投诉北京市朝阳区公交车总站，地址：温榆河公园21号门，自己想要借用洗手间，问了两次，对方不能对外借，自己走过去的，自己想要乘坐857路公交车，并且自己询问857几点发车，不能清晰的告诉自己，天气很冷，来电反映投诉北京市朝阳区公交车总站问题。安保基建 | I44: 是 | J44: 诉求 | K44: 安保部（应急管理中心） | L44: 场站保安问题 | M44: 场站保安 | N44: 鸿运承物业管理中心 | O44: 单店分中心 | P44: 安全保卫部（应急管理中心） | Q44: 单店分中心 | R44: 2026-01-10 23:59:59 | S44: 2026-01-04 | T44: 2026-01-08 08:59:59 | U44: 结束 | V44: 0 | W44: 单店分中心安保专业于2026年1月4日上午10点55分与投诉人第一时间进行回复，跟投诉人说明事情原因，并告知并非工作人员故意不让其进入使用厕所，下次如果乘客在想上厕所可以登记进入，经过解释后，投诉人对此情况表示理解。 | X44: 单店分中心安保专业于2026年1月4日上午10点55分与投诉人第一时间进行回复，跟投诉人说明事情原因，并告知并非工作人员故意不让其进入使用厕所，下次如果乘客在想上厕所可以登记进入，经过解释后，投诉人对此情况表示理解。通过此事件单店分中心安保专业第一时间对该场站警卫人员进行值守培训教育并说明如有乘客实在有厕所需求可以先登记再进入使用厕所，再次教育警卫人员如遇特殊情况第一时间通知班长，不能与外来人员发生冲突，说话时要礼貌用语注意措辞拒绝生冷硬。 | Y44: 单店分中心安保专业于2026年1月4日上午10点55分与投诉人第一时间进行回复，跟投诉人说明事情原因，并告知并非工作人员故意不让其进入使用厕所，下次如果乘客在想上厕所可以登记进入，经过解释后，投诉人对此情况表示理解。 | Z44: 通过此事件单店分中心安保专业第一时间对该场站警卫人员进行值守培训教育并说明如有乘客实在有厕所需求可以先登记再进入使用厕所，再次教育警卫人员如遇特殊情况第一时间通知班长，不能与外来人员发生冲突，说话时要礼貌用语注意措辞拒绝生冷硬。 | AA44: 通过此事件单店分中心安保专业第一时间对该场站警卫人员进行值守培训教育并说明如有乘客实在有厕所需求可以先登记再进入使用厕所，再次教育警卫人员如遇特殊情况第一时间通知班长，不能与外来人员发生冲突，说话时要礼貌用语注意措辞拒绝生冷硬。 | AB44: 通过此事件单店分中心安保专业第一时间对该场站警卫人员进行值守培训教育并说明如有乘客实在有厕所需求可以先登记再进入使用厕所，再次教育警卫人员如遇特殊情况第一时间通知班长，不能与外来人员发生冲突，说话时要礼貌用语注意措辞拒绝生冷硬。 | AC44: 满意 | AD44: 个人 | AE44: 2026-01-03 17:39:30 | AF44: 1741937706 | AG44: 服务 | AH44: 否 | AK44: =AG44&L44&M44 -> 服务场站保安问题场站保安 | AP44: 40 | AQ44: 46023 | AR44: =IFERROR(LEFT(A44,FIND("（",A44)-1),A44) -> 热线-260103-039044-1 | AS44: =J44 -> 诉求 | AT44: =IF(MID(AR44,1,2)="热线",12345)+IF(MID(AR44,1,2)="网络",12345) -> 12345 | AU44: =IFERROR(LEFT(D44,FIND(" ",D44)-1),D44) -> 2026-01-03 | AV44: =P44 -> 安全保卫部（应急管理中心） | AW44: =Q44 -> 单店分中心 | AX44: =H44 -> 市民反映，投诉北京市朝阳区公交车总站，地址：温榆河公园21号门，自己想要借用洗手间，问了两次，对方不能对外借，自己走过去的，自己想要乘坐857路公交车，并且自己询问857几点发车，不能清晰的告诉自己，天气很冷，来电反映投诉北京市朝阳区公交车总站问题。安保基建 | AY44: =AG44 -> 服务 | AZ44: 否 | BA44: 否 | BB44: 否 | BC44: 七有五性,安全性、便利性 | BD44: =U44 -> 结束 | BE44: =IFERROR(LEFT(T44,FIND(" ",T44)-1),T44) -> 2026-01-08 | BF44: 场站安保问题 （场站如厕） | BG44: 安保部 | BH44: 南湖分中心 | BL44: =IF(BG44="物管行政部","侯旭、郑楠",IF(BG44="安保部","张耕",IF(BG44="工程设备部","华菲",IF(BG44="人力资源部","成琦",IF(BG44="党委工作部","阎鑫雨",IF(BG44="餐饮服务部","赵弘晨",IF(BG44="工会","郑欣",IF(BG44="办公室","董娜",""))))))))&IF(BG44="纪检部","黄倩",IF(BG44="信息管理部","蔡浩然","")) -> 张耕 | BM44: 未主动剔除 | BP44: 业务类 | BV44: =MID(AR44,1,16) -> 热线-260103-039044 | BW44: 七有五性,便利性 | BX44: =IF(COUNTIF(BV:BV,BV44)=1,"否","是") -> 是 | BY44: =MID(AR44,18,1) -> 1 | CG44: =VLOOKUP(AR44,[1]市民意见信息导出!$AI$2:$AK$392,3,FALSE()) -> 结束 | CH44: =VLOOKUP(BV44,[2]Sheet1!$C$2:$AC$99,2,FALSE()) -> #N/A
A45: 热线-260103-039044-2（1个附件） | B45: 2026-01-03 17:42:16 | C45: 2026-01-03 17:52:01 | D45: 2026-01-03 19:46:02 | E45: 焦女士 | F45: 女 | G45: 手机,13466785896; | H45: 市民反映，投诉北京市朝阳区公交车总站，地址：温榆河公园21号门，自己想要借用洗手间，问了两次，对方不能对外借，自己走过去的，自己想要乘坐857路公交车，并且自己询问857几点发车，不能清晰的告诉自己，天气很冷，来电反映投诉北京市朝阳区公交车总站问题。安保基建 | I45: 是 | J45: 诉求 | K45: 基建行政部 | L45: 场站问题 | M45: 场站生活设施问题 | N45: 鸿运承物业管理中心 | O45: 物管行政部 | P45: 物管行政部 | Q45: 机关 | R45: 2026-01-10 23:59:59 | S45: 2026-01-04 | T45: 2026-01-08 08:59:59 | U45: 结束 | V45: 0 | W45: 接到此投诉，我们非常重视，并立即核实情况。 | X45: 分中心已经于2026年1月4日，将处理结果告知了市民，办理人：左强，部门:南湖分中心，职务：物管副主任。审核人：侯旭，物业管理中心机关，物管行政部，科员。 | Y45: 该场站是封闭式管理，非该场站职工是不能进入的，焦女士要求使用，在门口安保岗亭登记后是可以使用的。在态度上，我们今后一定要注意态度和文明用语。在答复中对市民道歉并安抚。 | Z45: 在态度上，我们今后一定要注意态度和文明用语。 | AA45: 无 | AB45: 接到此投诉，我们非常重视，并立即核实情况。该场站是封闭式管理，非该场站职工是不能进入的，焦女士要求使用，在门口安保岗亭登记后是可以使用的。在态度上，我们今后一定要注意态度和文明用语。在答复中对市民道歉并安抚。分中心已经于2026年1月4日，将处理结果告知了市民，办理人：左强，部门:南湖分中心，职务：物管副主任。审核人：侯旭，物业管理中心机关，物管行政部，科员。 | AC45: 满意 | AD45: 个人 | AE45: 2026-01-03 17:39:30 | AF45: 1049648 | AG45: 服务 | AH45: 否 | AK45: =AG45&L45&M45 -> 服务场站问题场站生活设施问题 | AP45: 41 | AQ45: 46023 | AR45: =IFERROR(LEFT(A45,FIND("（",A45)-1),A45) -> 热线-260103-039044-2 | AS45: =J45 -> 诉求 | AT45: =IF(MID(AR45,1,2)="热线",12345)+IF(MID(AR45,1,2)="网络",12345) -> 12345 | AU45: =IFERROR(LEFT(D45,FIND(" ",D45)-1),D45) -> 2026-01-03 | AV45: =P45 -> 物管行政部 | AW45: =Q45 -> 机关 | AX45: =H45 -> 市民反映，投诉北京市朝阳区公交车总站，地址：温榆河公园21号门，自己想要借用洗手间，问了两次，对方不能对外借，自己走过去的，自己想要乘坐857路公交车，并且自己询问857几点发车，不能清晰的告诉自己，天气很冷，来电反映投诉北京市朝阳区公交车总站问题。安保基建 | AY45: =AG45 -> 服务 | AZ45: 否 | BA45: 否 | BB45: 否 | BC45: 七有五性,安全性、便利性 | BD45: =U45 -> 结束 | BE45: =IFERROR(LEFT(T45,FIND(" ",T45)-1),T45) -> 2026-01-08 | BF45: 场站安保问题 （场站如厕）拆单 | BG45: 物管行政部 | BH45: 南湖分中心 | BL45: =IF(BG45="物管行政部","侯旭、郑楠",IF(BG45="安保部","张耕",IF(BG45="工程设备部","华菲",IF(BG45="人力资源部","成琦",IF(BG45="党委工作部","阎鑫雨",IF(BG45="餐饮服务部","赵弘晨",IF(BG45="工会","郑欣",IF(BG45="办公室","董娜",""))))))))&IF(BG45="纪检部","黄倩",IF(BG45="信息管理部","蔡浩然","")) -> 侯旭、郑楠 | BM45: 未主动剔除 | BP45: 业务类 | BV45: =MID(AR45,1,16) -> 热线-260103-039044 | BW45: 七有五性,便利性 | BX45: =IF(COUNTIF(BV:BV,BV45)=1,"否","是") -> 是 | BY45: =MID(AR45,18,1) -> 2 | CG45: =VLOOKUP(AR45,[1]市民意见信息导出!$AI$2:$AK$392,3,FALSE()) -> 结束 | CH45: =VLOOKUP(BV45,[2]Sheet1!$C$2:$AC$99,2,FALSE()) -> #N/A
A46: 网络-260103-048481-2 | B46: 2026-01-03 22:03:30 | C46: 2026-01-03 22:13:29 | D46: 2026-01-04 09:36:32 | E46: 保密 | F46: 女 | G46: 保密 | H46: 工单来源：微信服务号，此工单内容为网民留言时填写的标题及原文。 ============================= 留言标题： 公交动物园枢纽回复不满意。留言原文：公交动物园枢纽地下一层回复不满意。动物园分中心核实情况不正确，敷衍了事。强烈要求打开地铁与公交的换乘大厅的卷帘门。重新使用换乘大厅。原来从换乘大厅过马路，上楼坐公交都非常的方便。现在成了公交办公地点了。公交枢纽就是为了方便乘客使用的。设计的四通八达现在公交单位使用属于占用公共资源。公共设施是为人民方便服务的不是为了个别单位办公所用。要求上级领导核实情况，回复。市民填写的详细地址为：区、街道：海淀区甘家口街道详细地址：动物园公交枢纽安保基建 | I46: 是 | J46: 其他 | K46: 基建行政部 | L46: 基建行政专业其他问题 | M46: 基建行政专业补充内容 | N46: 鸿运承物业管理中心 | O46: 物管行政部 | P46: 物管行政部 | Q46: 机关 | R46: 2026-01-10 23:59:59 | S46: 2026-01-06 | T46: 2026-01-08 08:59:59 | U46: 结束 | V46: 1 | W46: 接到此投诉，我们非常重视，并立即核实。 | X46: 因市民没有留下电话，所以无法对其进行反馈。办理人：杜伟，部门:动物园分中心，职务：物管副主任。审核人：侯旭，物业管理中心机关，物管行政部，科员。 | Y46: 经动物园分中心核实此情况，动物园公交枢纽的所有滚动扶梯已停用，并且枢纽地下公交IC卡充值点已撤点多年，枢纽地上能满足公交与地铁的换乘，并且动物园公交枢纽场站地下空间现在是公交区域调度、公交电车客运分公司车队和公交物业动物园分中心的办公场所和公交职工食堂，为了确保办公区域安全，关闭卷帘门。通过此事件提醒动物园公交枢纽场站工作人员遇有乘客询问时耐心做好解释。由于诉求人未留联系姓名和联系电话，无法与市民反馈。 | Z46: 无 | AA46: 无 | AB46: 接到此投诉，我们非常重视，并立即核实。经动物园分中心核实此情况，动物园公交枢纽的所有滚动扶梯已停用，并且枢纽地下公交IC卡充值点已撤点多年，枢纽地上能满足公交与地铁的换乘，并且动物园公交枢纽场站地下空间现在是公交区域调度、公交电车客运分公司车队和公交物业动物园分中心的办公场所和公交职工食堂，为了确保办公区域安全，关闭卷帘门。通过此事件提醒动物园公交枢纽场站工作人员遇有乘客询问时耐心做好解释。由于诉求人未留联系姓名和联系电话，无法与市民反馈。因市民没有留下电话，所以无法对其进行反馈。办理人：杜伟，部门:动物园分中心，职务：物管副主任。审核人：侯旭，物业管理中心机关，物管行政部，科员。 | AC46: 满意 | AD46: 个人 | AE46: 2025-12-31 16:12:24 | AF46: 1049648 | AG46: 服务 | AH46: 否 | AK46: =AG46&L46&M46 -> 服务基建行政专业其他问题基建行政专业补充内容 | AP46: 42 | AQ46: 46023 | AR46: =IFERROR(LEFT(A46,FIND("（",A46)-1),A46) -> 网络-260103-048481-2 | AS46: =J46 -> 其他 | AT46: =IF(MID(AR46,1,2)="热线",12345)+IF(MID(AR46,1,2)="网络",12345) -> 12345 | AU46: =IFERROR(LEFT(D46,FIND(" ",D46)-1),D46) -> 2026-01-04 | AV46: =P46 -> 物管行政部 | AW46: =Q46 -> 机关 | AX46: =H46 -> 工单来源：微信服务号，此工单内容为网民留言时填写的标题及原文。 ============================= 留言标题： 公交动物园枢纽回复不满意。留言原文：公交动物园枢纽地下一层回复不满意。动物园分中心核实情况不正确，敷衍了事。强烈要求打开地铁与公交的换乘大厅的卷帘门。重新使用换乘大厅。原来从换乘大厅过马路，上楼坐公交都非常的方便。现在成了公交办公地点了。公交枢纽就是为了方便乘客使用的。设计的四通八达现在公交单位使用属于占用公共资源。公共设施是为人民方便服务的不是为了个别单位办公所用。要求上级领导核实情况，回复。市民填写的详细地址为：区、街道：海淀区甘家口街道详细地址：动物园公交枢纽安保基建 | AY46: =AG46 -> 服务 | AZ46: 否 | BA46: 否 | BB46: 否 | BC46: 七有五性,安全性、便利性 | BD46: =U46 -> 结束 | BE46: =IFERROR(LEFT(T46,FIND(" ",T46)-1),T46) -> 2026-01-08 | BF46: 场站安保问题 （咨询换乘大厅启用）多次 | BG46: 物管行政部 | BH46: 动物园分中心 | BL46: =IF(BG46="物管行政部","侯旭、郑楠",IF(BG46="安保部","张耕",IF(BG46="工程设备部","华菲",IF(BG46="人力资源部","成琦",IF(BG46="党委工作部","阎鑫雨",IF(BG46="餐饮服务部","赵弘晨",IF(BG46="工会","郑欣",IF(BG46="办公室","董娜",""))))))))&IF(BG46="纪检部","黄倩",IF(BG46="信息管理部","蔡浩然","")) -> 侯旭、郑楠 | BM46: 未主动剔除 | BP46: 政策类 | BQ46: 多次反映该问题 | BR46: 是 | BV46: =MID(AR46,1,16) -> 网络-260103-048481 | BW46: 七有五性,便利性 | BX46: =IF(COUNTIF(BV:BV,BV46)=1,"否","是") -> 是 | BY46: =MID(AR46,18,1) -> 2 | CG46: =VLOOKUP(AR46,[1]市民意见信息导出!$AI$2:$AK$392,3,FALSE()) -> 结束 | CH46: =VLOOKUP(BV46,[2]Sheet1!$C$2:$AC$99,2,FALSE()) -> #N/A
A47: 网络-260103-048481-1 | B47: 2026-01-03 22:03:30 | C47: 2026-01-03 22:13:29 | D47: 2026-01-04 09:36:32 | E47: 保密 | F47: 女 | G47: 保密 | H47: 工单来源：微信服务号，此工单内容为网民留言时填写的标题及原文。 ============================= 留言标题： 公交动物园枢纽回复不满意。留言原文：公交动物园枢纽地下一层回复不满意。动物园分中心核实情况不正确，敷衍了事。强烈要求打开地铁与公交的换乘大厅的卷帘门。重新使用换乘大厅。原来从换乘大厅过马路，上楼坐公交都非常的方便。现在成了公交办公地点了。公交枢纽就是为了方便乘客使用的。设计的四通八达现在公交单位使用属于占用公共资源。公共设施是为人民方便服务的不是为了个别单位办公所用。要求上级领导核实情况，回复。市民填写的详细地址为：区、街道：海淀区甘家口街道详细地址：动物园公交枢纽安保基建 | I47: 是 | J47: 其他 | K47: 安保部（应急管理中心） | L47: 安保专业其他问题 | M47: 安保专业补充内容 | N47: 鸿运承物业管理中心 | O47: 动物园分中心 | P47: 安全保卫部（应急管理中心） | Q47: 动物园分中心 | R47: 2026-01-10 23:59:59 | S47: 2026-01-05 | T47: 2026-01-08 08:59:59 | U47: 结束 | V47: 0 | W47: 经动物园分中心再次调查核实此情况，动物园公交枢纽场站地下空间通往地铁方向的卷帘门外是通往北京市动物园的地下通道，该通道确实有个地铁口，但是地铁公司也已经将该地铁口的卷帘门关闭多年。该情况我们上级单位已知晓。 | X47: 由于诉求人未留联系姓名和联系电话，无法取得联系。处理人动物园分中心安保主任翟祺。 | Y47: 通过此事件提醒动物园公交枢纽场站工作人员遇有乘客询问时耐心做好解释。 | Z47: 通过此事件提醒动物园公交枢纽场站工作人员遇有乘客询问时耐心做好解释。 | AA47: 通过此事件提醒动物园公交枢纽场站工作人员遇有乘客询问时耐心做好解释。 | AB47: 经动物园分中心再次调查核实此情况，动物园公交枢纽场站地下空间通往地铁方向的卷帘门外是通往北京市动物园的地下通道，该通道确实有个地铁口，但是地铁公司也已经将该地铁口的卷帘门关闭多年。该情况我们上级单位已知晓。通过此事件提醒动物园公交枢纽场站工作人员遇有乘客询问时耐心做好解释。由于诉求人未留联系姓名和联系电话，无法取得联系。处理人动物园分中心安保主任翟祺。 | AC47: 满意 | AD47: 个人 | AE47: 2025-12-31 16:12:24 | AF47: 1741937703 | AG47: 服务 | AH47: 否 | AK47: =AG47&L47&M47 -> 服务安保专业其他问题安保专业补充内容 | AP47: 43 | AQ47: 46023 | AR47: =IFERROR(LEFT(A47,FIND("（",A47)-1),A47) -> 网络-260103-048481-1 | AS47: =J47 -> 其他 | AT47: =IF(MID(AR47,1,2)="热线",12345)+IF(MID(AR47,1,2)="网络",12345) -> 12345 | AU47: =IFERROR(LEFT(D47,FIND(" ",D47)-1),D47) -> 2026-01-04 | AV47: =P47 -> 安全保卫部（应急管理中心） | AW47: =Q47 -> 动物园分中心 | AX47: =H47 -> 工单来源：微信服务号，此工单内容为网民留言时填写的标题及原文。 ============================= 留言标题： 公交动物园枢纽回复不满意。留言原文：公交动物园枢纽地下一层回复不满意。动物园分中心核实情况不正确，敷衍了事。强烈要求打开地铁与公交的换乘大厅的卷帘门。重新使用换乘大厅。原来从换乘大厅过马路，上楼坐公交都非常的方便。现在成了公交办公地点了。公交枢纽就是为了方便乘客使用的。设计的四通八达现在公交单位使用属于占用公共资源。公共设施是为人民方便服务的不是为了个别单位办公所用。要求上级领导核实情况，回复。市民填写的详细地址为：区、街道：海淀区甘家口街道详细地址：动物园公交枢纽安保基建 | AY47: =AG47 -> 服务 | AZ47: 否 | BA47: 否 | BB47: 否 | BC47: 七有五性,安全性、便利性 | BD47: =U47 -> 结束 | BE47: =IFERROR(LEFT(T47,FIND(" ",T47)-1),T47) -> 2026-01-08 | BF47: 场站安保问题 （咨询换乘大厅启用）多次 | BG47: 安保部 | BH47: 动物园分中心 | BL47: =IF(BG47="物管行政部","侯旭、郑楠",IF(BG47="安保部","张耕",IF(BG47="工程设备部","华菲",IF(BG47="人力资源部","成琦",IF(BG47="党委工作部","阎鑫雨",IF(BG47="餐饮服务部","赵弘晨",IF(BG47="工会","郑欣",IF(BG47="办公室","董娜",""))))))))&IF(BG47="纪检部","黄倩",IF(BG47="信息管理部","蔡浩然","")) -> 张耕 | BM47: 未主动剔除 | BP47: 政策类 | BQ47: 多次反映该问题 | BR47: 是 | BV47: =MID(AR47,1,16) -> 网络-260103-048481 | BW47: 七有五性,便利性 | BX47: =IF(COUNTIF(BV:BV,BV47)=1,"否","是") -> 是 | BY47: =MID(AR47,18,1) -> 1 | CG47: =VLOOKUP(AR47,[1]市民意见信息导出!$AI$2:$AK$392,3,FALSE()) -> 结束 | CH47: =VLOOKUP(BV47,[2]Sheet1!$C$2:$AC$99,2,FALSE()) -> #N/A
A48: 热线-260104-031911（1个附件） | B48: 2026-01-04 13:38:36 | C48: 2026-01-04 13:44:57 | D48: 2026-01-04 13:46:02 | E48: 杨先生 | F48: 男 | G48: 手机,13141327081; | H48: 市民反映，自己走到北京公交集团南湖公交场站，自己因为手机没电了自己没法做公交车回家，自己找门口的保安借用一下充电器，但是保安说公交公司有规定充电器不外借，而且自己觉得这个保安还神智不清，自己觉得这个保安酗酒，自己要求公交集团的领导进行调查，来电反映公交集团保安不借充电器问题。 | I48: 是 | J48: 诉求 | K48: 安保部（应急管理中心） | L48: 场站保安问题 | M48: 场站保安 | N48: 鸿运承物业管理中心 | O48: 南湖分中心 | P48: 安保部（应急管理中心） | Q48: 南湖分中心 | R48: 2026-01-11 23:59:59 | S48: 2026-01-05 | T48: 2026-01-09 08:59:59 | U48: 结束 | V48: 0 | W48: 市民反映，自己走到北京公交集团南湖公交场站，自己因为手机没电了自己没法做公交车回家，自己找门口的保安借用一下充电器，但是保安说公交公司有规定充电器不外借，而且自己觉得这个保安还神智不清 | X48: 2026年1月5日，9点04分，分中心安保主任与投诉人员进行沟通，了解情况后，并解释清楚。对保安员进行叮嘱，教育。私人物品在方便、可行、安全的前提下，适当的提供帮助。 | Y48: 市民反映，自己走到北京公交集团南湖公交场站，自己因为手机没电了自己没法做公交车回家，自己找门口的保安借用一下充电器，但是保安说公交公司有规定充电器不外借。经分中心核实后，与市民沟通，并解释清楚情况。 | Z48: 市民反映，自己走到北京公交集团南湖公交场站，自己因为手机没电了自己没法做公交车回家，自己找门口的保安借用一下充电器，但是保安说公交公司有规定充电器不外借，而且自己觉得这个保安还神智不清。2026年1月5日，9点04分，分中心安保主任与投诉人员进行沟通，了解情况后，并解释清楚。对保安员进行叮嘱，教育。私人物品在方便、可行、安全的前提下，适当的提供帮助。 | AA48: 市民反映，自己走到北京公交集团南湖公交场站，自己因为手机没电了自己没法做公交车回家，自己找门口的保安借用一下充电器，但是保安说公交公司有规定充电器不外借。经分中心核实后，与市民沟通，并解释清楚情况。 | AB48: 市民反映，自己走到北京公交集团南湖公交场站，自己因为手机没电了自己没法做公交车回家，自己找门口的保安借用一下充电器，但是保安说公交公司有规定充电器不外借，而且自己觉得这个保安还神智不清。2026年1月5日，9点04分，分中心安保主任与投诉人员进行沟通，了解情况后，并解释清楚。对保安员进行叮嘱，教育。私人物品在方便、可行、安全的前提下，适当的提供帮助。 | AC48: 满意 | AD48: 个人 | AE48: 2026-01-04 13:25:32 | AF48: 1741937705 | AG48: 服务 | AH48: 否 | AK48: =AG48&L48&M48 -> 服务场站保安问题场站保安 | AP48: 44 | AQ48: 46023 | AR48: =IFERROR(LEFT(A48,FIND("（",A48)-1),A48) -> 热线-260104-031911 | AS48: =J48 -> 诉求 | AT48: =IF(MID(AR48,1,2)="热线",12345)+IF(MID(AR48,1,2)="网络",12345) -> 12345 | AU48: =IFERROR(LEFT(D48,FIND(" ",D48)-1),D48) -> 2026-01-04 | AV48: =P48 -> 安保部（应急管理中心） | AW48: =Q48 -> 南湖分中心 | AX48: =H48 -> 市民反映，自己走到北京公交集团南湖公交场站，自己因为手机没电了自己没法做公交车回家，自己找门口的保安借用一下充电器，但是保安说公交公司有规定充电器不外借，而且自己觉得这个保安还神智不清，自己觉得这个保安酗酒，自己要求公交集团的领导进行调查，来电反映公交集团保安不借充电器问题。 | AY48: =AG48 -> 服务 | AZ48: 否 | BA48: 否 | BB48: 否 | BC48: 七有五性,安全性、便利性 | BD48: =U48 -> 结束 | BE48: =IFERROR(LEFT(T48,FIND(" ",T48)-1),T48) -> 2026-01-09 | BF48: 场站安保问题 | BG48: 安保部 | BH48: 南湖分中心 | BL48: =IF(BG48="物管行政部","侯旭、郑楠",IF(BG48="安保部","张耕",IF(BG48="工程设备部","华菲",IF(BG48="人力资源部","成琦",IF(BG48="党委工作部","阎鑫雨",IF(BG48="餐饮服务部","赵弘晨",IF(BG48="工会","郑欣",IF(BG48="办公室","董娜",""))))))))&IF(BG48="纪检部","黄倩",IF(BG48="信息管理部","蔡浩然","")) -> 张耕 | BM48: 未主动剔除 | BP48: 业务类 | BV48: =MID(AR48,1,16) -> 热线-260104-031911 | BW48: 七有五性,便利性 | BX48: =IF(COUNTIF(BV:BV,BV48)=1,"否","是") -> 否 | BY48: =MID(AR48,18,1) | CG48: =VLOOKUP(AR48,[1]市民意见信息导出!$AI$2:$AK$392,3,FALSE()) -> 结束 | CH48: =VLOOKUP(BV48,[2]Sheet1!$C$2:$AC$99,2,FALSE()) -> #N/A
A49: 热线-260104-041011-2（1个附件） | B49: 2026-01-04 14:57:18 | C49: 2026-01-04 15:04:43 | D49: 2026-01-04 15:11:30 | E49: 周女士 | F49: 女 | G49: 手机,15810392696; | H49: 市民反映，在丰台区玉泉营街道300内快总站草桥公交站，附近没有公共卫生间，市民无法正常上厕所，市民听说在北京公共交通控股（集团）有限公司客一分公司场站内有卫生间，不知道外部人员是否可以使用，市民表示附近没有公共卫生间，来电反映核实北京公共交通控股（集团）有限公司客一分公司场站内卫生间外部人员是否可以使用。客一基建 鸿运承安保 | I49: 是 | J49: 诉求 | K49: 安保部（应急管理中心） | L49: 安保专业政策问题 | M49: 安保措施 | N49: 鸿运承物业管理中心 | O49: 方庄分中心 | P49: 安全保卫部（应急管理中心） | Q49: 方庄分中心 | R49: 2026-01-11 23:59:59 | S49: 2026-01-05 | T49: 2026-01-09 08:59:59 | U49: 结束 | V49: 0 | W49: 经我单位方庄分中心核实此情况，与来电人所述的情况存在出入。为更好的服务群众，公交场站内的卫生间是允许群众使用的，但是为场站安全角度出发，群众如果需要进入公交场站，需要在门岗处登记事由和联系方式。 | X49: 2026年1月5日9点39分，由我单位方庄分中心安保主任张涛与来电人进行电话沟通，向来电人讲明情况，来电人表示知晓。 | Y49: 为更好的服务群众，公交场站内的卫生间是允许群众使用的，但是为场站安全角度出发，群众如果需要进入公交场站，需要在门岗处登记事由和联系方式。 | Z49: 为更好的服务群众，公交场站内的卫生间是允许群众使用的，但是为场站安全角度出发，群众如果需要进入公交场站，需要在门岗处登记事由和联系方式。 | AA49: 为更好的服务群众，公交场站内的卫生间是允许群众使用的，但是为场站安全角度出发，群众如果需要进入公交场站，需要在门岗处登记事由和联系方式。 | AB49: 经我单位方庄分中心核实此情况，与来电人所述的情况存在出入。为更好的服务群众，公交场站内的卫生间是允许群众使用的，但是为场站安全角度出发，群众如果需要进入公交场站，需要在门岗处登记事由和联系方式。2026年1月5日9点39分，由我单位方庄分中心安保主任张涛与来电人进行电话沟通，向来电人讲明情况，来电人表示知晓。 | AC49: 满意 | AD49: 个人 | AE49: 2026-01-04 14:53:23 | AF49: 1741937709 | AG49: 公共厕所 | AH49: 否 | AK49: =AG49&L49&M49 -> 公共厕所安保专业政策问题安保措施 | AP49: 45 | AQ49: 46023 | AR49: =IFERROR(LEFT(A49,FIND("（",A49)-1),A49) -> 热线-260104-041011-2 | AS49: =J49 -> 诉求 | AT49: =IF(MID(AR49,1,2)="热线",12345)+IF(MID(AR49,1,2)="网络",12345) -> 12345 | AU49: =IFERROR(LEFT(D49,FIND(" ",D49)-1),D49) -> 2026-01-04 | AV49: =P49 -> 安全保卫部（应急管理中心） | AW49: =Q49 -> 方庄分中心 | AX49: =H49 -> 市民反映，在丰台区玉泉营街道300内快总站草桥公交站，附近没有公共卫生间，市民无法正常上厕所，市民听说在北京公共交通控股（集团）有限公司客一分公司场站内有卫生间，不知道外部人员是否可以使用，市民表示附近没有公共卫生间，来电反映核实北京公共交通控股（集团）有限公司客一分公司场站内卫生间外部人员是否可以使用。客一基建 鸿运承安保 | AY49: =AG49 -> 公共厕所 | AZ49: 否 | BA49: 否 | BB49: 否 | BC49: 七有五性,便利性 | BD49: =U49 -> 结束 | BE49: =IFERROR(LEFT(T49,FIND(" ",T49)-1),T49) -> 2026-01-09 | BF49: 场站安保问题 （场站如厕） | BG49: 安保部 | BH49: 方庄分中心 | BL49: =IF(BG49="物管行政部","侯旭、郑楠",IF(BG49="安保部","张耕",IF(BG49="工程设备部","华菲",IF(BG49="人力资源部","成琦",IF(BG49="党委工作部","阎鑫雨",IF(BG49="餐饮服务部","赵弘晨",IF(BG49="工会","郑欣",IF(BG49="办公室","董娜",""))))))))&IF(BG49="纪检部","黄倩",IF(BG49="信息管理部","蔡浩然","")) -> 张耕 | BM49: 未主动剔除 | BP49: 业务类 | BV49: =MID(AR49,1,16) -> 热线-260104-041011 | BW49: 七有五性,宜居性 | BX49: =IF(COUNTIF(BV:BV,BV49)=1,"否","是") -> 否 | BY49: =MID(AR49,18,1) -> 2 | CG49: =VLOOKUP(AR49,[1]市民意见信息导出!$AI$2:$AK$392,3,FALSE()) -> 结束 | CH49: =VLOOKUP(BV49,[2]Sheet1!$C$2:$AC$99,2,FALSE()) -> #N/A
A50: 热线-260104-013011-1（1个附件） | B50: 2026-01-04 15:17:10 | C50: 2026-01-04 15:21:13 | D50: 2026-01-04 15:33:54 | E50: 马先生 | F50: 男 | G50: 手机,18612578380; | H50: 市民举报，延庆区延庆停保中心场站，市民称该场站消防操作员人手不够，按理来讲应该有10多人，但是只配备了3个人，把这方面活交给厨师做，然后还不给这方面的工钱，并且消防隐患特别大，要求整改以及支付这方面工资，希望相关工作人员尽快帮助核实或帮助解决，来电反映延庆区延庆停保中心场站消防操作员人手不够问题。注：市民同时反映拖欠工资问题，已建新工单，详见热线-260104-013562工单流转：延庆区分中心退回：区交通局:1月4日，我单位接收停保中心场站消防操作人手不够问题工单，经核实，反映人为公交集团第八客运分公司公交场站第三方外聘人员，公交公司指派物业公司负责站区内消防工作，物业公司因人手不够为由，又要求第三方外聘人员协助处理相关消防工作，且没有任何工资，涉及公交集团检查时，还需承担相关责任，此问题已超出我局职责范围，建议退单至公交集团，由公交集团客八分公司答复 安保人力 | I50: 是 | J50: 诉求 | K50: 安保部（应急管理中心） | L50: 安保专业政策问题 | M50: 安保监查 | N50: 鸿运承物业管理中心 | O50: 河滩分中心 | P50: 安全保卫部（应急管理中心） | Q50: 河滩分中心 | R50: 2026-01-11 23:59:59 | S50: 2026-01-05 | T50: 2026-01-09 08:59:59 | U50: 结束 | V50: 0 | W50: 接到投诉后，我分中心由安保副主任王鹏对场站进行核实，情况不属实。 河滩分中心安保副主任王鹏与马先生解释，因停保中心食堂为外包食堂，马先生为外协人员，工资应由外包单位支付，与物业无关。并且停保中心场站消防操作员人手齐全。马先生表示消防操作员人手不够的情况是自己记错了，外包单位也未对马先生有工资拖欠。因此，马先生反映情况不属实。 | X50: 我分中心于2026年1月5日16时40分由鸿运承物业管理中心河滩分中心安保副主任王鹏与投诉人进行电话回访。河滩分中心核实情况后，对投诉人进行回复，跟投诉人说明事情原因，投诉人表示未发生投诉的相关情况，因此，该情况不属实。处理人：河滩分中心安保副主任王鹏 | Y50: 分中心领导对对外包单位进行叮嘱教育，加强人员管理，做好选人用人筛选，并配合分中心做好各项工作。 | Z50: 停保中心与外包单位签订的合同于2026年1月25日到期，分中心叮嘱外包单位应尽职尽责履行相关责任，配合分中心完成各项工作，避免懈怠。 | AA50: 我分中心主管人员和场站班组长进行督查，落实场站工作。 | AB50: 接到投诉后，我分中心由安保副主任王鹏对该情况进行核实，情况不属实。 因停保中心食堂为外包食堂，马先生为外协人员，工资应由外包单位支付，与物业无关。并且停保中心场站消防操作员人手齐全。马先生表示消防操作员人手不够的情况是自己记错了，外包单位也未对马先生有工资拖欠。 | AC50: 满意 | AD50: 个人 | AE50: 2026-01-04 09:59:21 | AF50: 1725545789 | AG50: 消防安全违法行为 | AH50: 否 | AK50: =AG50&L50&M50 -> 消防安全违法行为安保专业政策问题安保监查 | AP50: 46 | AQ50: 46023 | AR50: =IFERROR(LEFT(A50,FIND("（",A50)-1),A50) -> 热线-260104-013011-1 | AS50: =J50 -> 诉求 | AT50: =IF(MID(AR50,1,2)="热线",12345)+IF(MID(AR50,1,2)="网络",12345) -> 12345 | AU50: =IFERROR(LEFT(D50,FIND(" ",D50)-1),D50) -> 2026-01-04 | AV50: =P50 -> 安全保卫部（应急管理中心） | AW50: =Q50 -> 河滩分中心 | AX50: =H50 -> 市民举报，延庆区延庆停保中心场站，市民称该场站消防操作员人手不够，按理来讲应该有10多人，但是只配备了3个人，把这方面活交给厨师做，然后还不给这方面的工钱，并且消防隐患特别大，要求整改以及支付这方面工资，希望相关工作人员尽快帮助核实或帮助解决，来电反映延庆区延庆停保中心场站消防操作员人手不够问题。注：市民同时反映拖欠工资问题，已建新工单，详见热线-260104-013562工单流转：延庆区分中心退回：区交通局:1月4日，我单位接收停保中心场站消防操作人手不够问题工单，经核实，反映人为公交集团第八客运分公司公交场站第三方外聘人员，公交公司指派物业公司负责站区内消防工作，物业公司因人手不够为由，又要求第三方外聘人员协助处理相关消防工作，且没有任何工资，涉及公交集团检查时，还需承担相关责任，此问题已超出我局职责范围，建议退单至公交集团，由公交集团客八分公司答复 安保人力 | AY50: =AG50 -> 消防安全违法行为 | AZ50: 是 | BA50: 是 | BB50: 否 | BC50: 七有五性,多样性 | BD50: =U50 -> 结束 | BE50: =IFERROR(LEFT(T50,FIND(" ",T50)-1),T50) -> 2026-01-09 | BF50: 劳动人员调配及薪酬（选聘消防操作员） | BG50: 安保部 | BH50: 河滩分中心 | BL50: =IF(BG50="物管行政部","侯旭、郑楠",IF(BG50="安保部","张耕",IF(BG50="工程设备部","华菲",IF(BG50="人力资源部","成琦",IF(BG50="党委工作部","阎鑫雨",IF(BG50="餐饮服务部","赵弘晨",IF(BG50="工会","郑欣",IF(BG50="办公室","董娜",""))))))))&IF(BG50="纪检部","黄倩",IF(BG50="信息管理部","蔡浩然","")) -> 张耕 | BM50: 未主动剔除 | BP50: 政策类 | BV50: =MID(AR50,1,16) -> 热线-260104-013011 | BW50: 七有五性,安全性 | BX50: =IF(COUNTIF(BV:BV,BV50)=1,"否","是") -> 否 | BY50: =MID(AR50,18,1) -> 1 | CG50: =VLOOKUP(AR50,[1]市民意见信息导出!$AI$2:$AK$392,3,FALSE()) -> 结束 | CH50: =VLOOKUP(BV50,[2]Sheet1!$C$2:$AC$99,2,FALSE()) -> #N/A
A51: 热线-260105-038505-2（1个附件） | B51: 2026-01-05 14:24:52 | C51: 2026-01-05 14:36:43 | D51: 2026-01-05 14:37:46 | E51: 张先生 | F51: 男 | G51: 手机,17600538295; | H51: 市民表扬，352路司机，车号3644480，在2026年1月日13点40分，市民称朝阳法院第二执行庭上车，到分钟寺下车，司机帮助老弱病残找座位，并且车内干净卫生，要求车队回复（已作出解释）。来电表扬公交司机的问题。客三物业 | I51: 是 | J51: 表扬 | K51: 行车安全服务部 | L51: 车厢服务意识方面表扬 | M51: 执行规范 | N51: 鸿运承物业管理中心 | O51: 明月湾分中心 | P51: 物管行政部 | Q51: 明月湾分中心 | S51: 2026-01-06 | T51: 2026-01-10 08:59:59 | U51: 结束 | V51: 0 | W51: 您好，关于您表扬352路3644480号车，车内干净卫生派单的办理情况，鸿运承物业管理中心明月湾分中心现对您回复如下： | X51: 我分中心于2026年1月5日下午15点20分对您进行电话回复。办理人：吴岩；部门：鸿运承物业管理中心明月湾分中心；职务：物管副主任。审核人：郑楠；部门：鸿运承物业管理中心物管行政部；职务：物管员。 | Y51: 感谢您对352路公交车卫生的认可，352路公交车我们在旧宫科技路场站进行洗车服务，我们将352路的刷车保洁员进行口头表扬，同时将保洁员这种工作精神在全分中心范围内进行宣传，我们今后也将以良好的工作作风服务于一线及市民，确保运营车辆卫生干净整洁，体现物业良好的服务意识。 | Z51: 我们场站班组长再次与本条线路的保洁人员进行了沟通，要把好的经验和方法保持下去，日常的清洁与维护至关重要，日常工作中仍需要加强出场车辆卫生需符合清洁标准。 | AA51: 我们定期召开车辆保洁专题会议，开展车辆卫生专项检查，日常工作中我们加大巡检力度，强化制度建设，不断提高管理水平。 | AB51: 您好，关于您表扬352路3644480号车，车内干净卫生派单的办理情况，鸿运承物业管理中心明月湾分中心现对您回复如下：感谢您对352路公交车卫生的认可，352路公交车我们在旧宫科技路场站进行洗车服务，我们将352路的刷车保洁员进行口头表扬，同时将保洁员这种工作精神在全分中心范围内进行宣传，我们今后也将以良好的工作作风服务于一线及市民，确保运营车辆卫生干净整洁，体现物业良好的服务意识。我们定期召开车辆保洁专题会议，开展车辆卫生专项检查，日常工作中我们加大巡检力度，强化制度建设，不断提高管理水平。我分中心于2026年1月5日下午15点20分对您进行电话回复。我们场站班组长再次与本条线路的保洁人员进行了沟通，要把好的经验和方法保持下去，日常的清洁与维护至关重要，日常工作中仍需要加强出场车辆卫生需符合清洁标准。欢迎您随时对我们的工作进行监督，我们将继续努力，为您提供一个舒适、整洁的乘车及出行环境，感谢您对我们工作的认可。 | AC51: 满意 | AD51: 个人 | AE51: 2026-01-05 14:04:12 | AF51: 1741937713 | AG51: 服务态度 | AH51: 是 | AK51: =AG51&L51&M51 -> 服务态度车厢服务意识方面表扬执行规范 | AP51: 47 | AQ51: 46023 | AR51: =IFERROR(LEFT(A51,FIND("（",A51)-1),A51) -> 热线-260105-038505-2 | AS51: =J51 -> 表扬 | AT51: =IF(MID(AR51,1,2)="热线",12345)+IF(MID(AR51,1,2)="网络",12345) -> 12345 | AU51: =IFERROR(LEFT(D51,FIND(" ",D51)-1),D51) -> 2026-01-05 | AV51: =P51 -> 物管行政部 | AW51: =Q51 -> 明月湾分中心 | AX51: =H51 -> 市民表扬，352路司机，车号3644480，在2026年1月日13点40分，市民称朝阳法院第二执行庭上车，到分钟寺下车，司机帮助老弱病残找座位，并且车内干净卫生，要求车队回复（已作出解释）。来电表扬公交司机的问题。客三物业 | AY51: =AG51 -> 服务态度 | AZ51: 否 | BA51: 否 | BB51: 否 | BC51: 七有五性,宜居性 | BD51: =U51 -> 结束 | BE51: =IFERROR(LEFT(T51,FIND(" ",T51)-1),T51) -> 2026-01-10 | BF51: 表扬车辆卫生 | BG51: 物管行政部 | BH51: 明月湾分中心 | BL51: =IF(BG51="物管行政部","侯旭、郑楠",IF(BG51="安保部","张耕",IF(BG51="工程设备部","华菲",IF(BG51="人力资源部","成琦",IF(BG51="党委工作部","阎鑫雨",IF(BG51="餐饮服务部","赵弘晨",IF(BG51="工会","郑欣",IF(BG51="办公室","董娜",""))))))))&IF(BG51="纪检部","黄倩",IF(BG51="信息管理部","蔡浩然","")) -> 侯旭、郑楠 | BN51: 表扬 | BP51: 业务类 | BQ51: 多渠道同人同诉：网络-251223-042262-4、热线-260105-038505-2、网络-260109-053098-1、GJ-PHONE-20260111-0012 | BR51: 是 | BS51: 先12345再96166 | BV51: =MID(AR51,1,16) -> 热线-260105-038505 | BX51: =IF(COUNTIF(BV:BV,BV51)=1,"否","是") -> 否 | BY51: =MID(AR51,18,1) -> 2 | CG51: =VLOOKUP(AR51,[1]市民意见信息导出!$AI$2:$AK$392,3,FALSE()) -> 结束 | CH51: =VLOOKUP(BV51,[2]Sheet1!$C$2:$AC$99,2,FALSE()) -> #N/A
A52: 热线-260105-071626（1个附件） | B52: 2026-01-05 21:20:04 | C52: 2026-01-05 21:36:42 | D52: 2026-01-06 10:46:38 | E52: 董女士 | F52: 女 | G52: 手机,15176270680; | H52: 市民表扬，自己要表扬西城区北京公交集团鸿运承物业管理有限公司的刘雪娇，自己有些问题拨打电话咨询了，一个小时给自己回复了，服务态度非常好，对此提出表扬，来电表扬公交集团工作人员的问题。物业物管退回：已沟通，请转人力，谢谢。 | I52: 是 | J52: 表扬 | K52: 人力资源部（人力资源发展中心） | L52: 人力资源方面其他表扬 | M52: 人力资源方面其他表扬 | N52: 鸿运承物业管理中心 | O52: 人力资源部 | P52: 人力资源部 | Q52: 机关 | S52: 2026-01-08 | T52: 2026-01-10 08:59:59 | U52: 结束 | V52: 0 | W52: 经核实，来电人所述工作人员为我单位鸿运承物业管理中心人力资源部职工，接到来电人表扬信息后，我单位十分重视，第一时间与相关职工取得联系，将来电人的表扬信息进行传达。 | X52: 经核实，来电人所述工作人员为我单位鸿运承物业管理中心人力资源部职工，接到来电人表扬信息后，我单位十分重视，第一时间与相关职工取得联系，将来电人的表扬信息进行传达。2026年1月8日上午9点45分左右电话与来电人沟通，对来电人表示感谢，来电人已知晓。 办理人：成琦 ；部门：鸿运承物业管理中心人力资源部，职务：一般管理； 审核人：高强；部门：鸿运承物业管理中心人力资源部；职务：中级管理。 | Y52: 2026年1月8日上午9点45分左右电话与来电人沟通，对来电人表示感谢，来电人已知晓。 | Z52: 无 | AA52: 无 | AB52: 经核实，来电人所述工作人员为我单位鸿运承物业管理中心人力资源部职工，接到来电人表扬信息后，我单位十分重视，第一时间与相关职工取得联系，将来电人的表扬信息进行传达。2026年1月8日上午9点45分左右电话与来电人沟通，对来电人表示感谢，来电人已知晓。 | AC52: 满意 | AD52: 个人 | AE52: 2026-01-05 20:00:22 | AF52: 1049051 | AG52: 工作质量 | AH52: 是 | AK52: =AG52&L52&M52 -> 工作质量人力资源方面其他表扬人力资源方面其他表扬 | AP52: 48 | AQ52: 46023 | AR52: =IFERROR(LEFT(A52,FIND("（",A52)-1),A52) -> 热线-260105-071626 | AS52: =J52 -> 表扬 | AT52: =IF(MID(AR52,1,2)="热线",12345)+IF(MID(AR52,1,2)="网络",12345) -> 12345 | AU52: =IFERROR(LEFT(D52,FIND(" ",D52)-1),D52) -> 2026-01-06 | AV52: =P52 -> 人力资源部 | AW52: =Q52 -> 机关 | AX52: =H52 -> 市民表扬，自己要表扬西城区北京公交集团鸿运承物业管理有限公司的刘雪娇，自己有些问题拨打电话咨询了，一个小时给自己回复了，服务态度非常好，对此提出表扬，来电表扬公交集团工作人员的问题。物业物管退回：已沟通，请转人力，谢谢。 | AY52: =AG52 -> 工作质量 | AZ52: 是 | BA52: 否 | BB52: 否 | BC52: 七有五性,多样性 | BD52: =U52 -> 结束 | BE52: =IFERROR(LEFT(T52,FIND(" ",T52)-1),T52) -> 2026-01-10 | BF52: 表扬工作人员 （办理人员工作） | BG52: 人力资源部 | BH52: 机关 | BL52: =IF(BG52="物管行政部","侯旭、郑楠",IF(BG52="安保部","张耕",IF(BG52="工程设备部","华菲",IF(BG52="人力资源部","成琦",IF(BG52="党委工作部","阎鑫雨",IF(BG52="餐饮服务部","赵弘晨",IF(BG52="工会","郑欣",IF(BG52="办公室","董娜",""))))))))&IF(BG52="纪检部","黄倩",IF(BG52="信息管理部","蔡浩然","")) -> 成琦 | BN52: 表扬 | BP52: 业务类 | BV52: =MID(AR52,1,16) -> 热线-260105-071626 | BX52: =IF(COUNTIF(BV:BV,BV52)=1,"否","是") -> 否 | BY52: =MID(AR52,18,1) | CG52: =VLOOKUP(AR52,[1]市民意见信息导出!$AI$2:$AK$392,3,FALSE()) -> 结束 | CH52: =VLOOKUP(BV52,[2]Sheet1!$C$2:$AC$99,2,FALSE()) -> #N/A
A53: 热线-260106-027290（3个附件） | B53: 2026-01-06 11:50:52 | C53: 2026-01-06 12:16:35 | D53: 2026-01-06 12:52:13 | E53: 王先生 | F53: 男 | G53: 手机,13146533502; | H53: 市民反映，公交集团第二分公司403环形场站允许外卖车辆进入场站，市民表示场站工作人员管理不善，需要书面答复，来电反映公交场站工作人员管理不善问题。 | I53: 是 | J53: 诉求 | K53: 安保部（应急管理中心） | L53: 场站保安问题 | M53: 场站保安 | N53: 鸿运承物业管理中心 | O53: 单店分中心 | P53: 安全保卫部（应急管理中心） | Q53: 单店分中心 | R53: 2026-01-13 23:59:59 | S53: 2026-01-07 | T53: 2026-01-11 08:59:59 | U53: 结束 | V53: 0 | W53: 经与场站班长、车队进行核实，得知打电话的此人为客二分公司17车队驾驶员，根据情况得知，该员工患有抑郁症，在客二分公司已备案，该员工与车队之间一直存在矛盾，遂打此投诉电话。单店分中心安保专业在1月7日上午11点对其进行回复，并说明该员工投诉的外卖车辆进入场站经过监控查询是一个巡逻岗，上面也有明确标示，属于是外卖人员误走行为，场站也会加强巡逻。 | X53: 单店分中心安保专业在1月7日上午11点对其进行回复，并说明该员工投诉的外卖车辆进入场站经过监控查询是一个巡逻岗，上面也有明确标示，属于是外卖人员误走行为，场站也会加强巡逻。 | Y53: 单店分中心安保专业在1月7日上午11点对其进行回复，并说明该员工投诉的外卖车辆进入场站经过监控查询是一个巡逻岗，上面也有明确标示，属于是外卖人员误走行为，场站也会加强巡逻。 | Z53: 单店分中心安保专业在1月7日上午11点对其进行回复，并说明该员工投诉的外卖车辆进入场站经过监控查询是一个巡逻岗，上面也有明确标示，属于是外卖人员误走行为，场站也会加强巡逻。 | AA53: 单店分中心安保专业在1月7日上午11点对其进行回复，并说明该员工投诉的外卖车辆进入场站经过监控查询是一个巡逻岗，上面也有明确标示，属于是外卖人员误走行为，场站也会加强巡逻。 | AB53: 单店分中心安保专业在1月7日上午11点对其进行回复，并说明该员工投诉的外卖车辆进入场站经过监控查询是一个巡逻岗，上面也有明确标示，属于是外卖人员误走行为，场站也会加强巡逻。 | AC53: 满意 | AD53: 个人 | AE53: 2026-01-06 11:45:57 | AF53: 1741937706 | AG53: 违反交通标线 | AH53: 否 | AK53: =AG53&L53&M53 -> 违反交通标线场站保安问题场站保安 | AP53: 49 | AQ53: 46023 | AR53: =IFERROR(LEFT(A53,FIND("（",A53)-1),A53) -> 热线-260106-027290 | AS53: =J53 -> 诉求 | AT53: =IF(MID(AR53,1,2)="热线",12345)+IF(MID(AR53,1,2)="网络",12345) -> 12345 | AU53: =IFERROR(LEFT(D53,FIND(" ",D53)-1),D53) -> 2026-01-06 | AV53: =P53 -> 安全保卫部（应急管理中心） | AW53: =Q53 -> 单店分中心 | AX53: =H53 -> 市民反映，公交集团第二分公司403环形场站允许外卖车辆进入场站，市民表示场站工作人员管理不善，需要书面答复，来电反映公交场站工作人员管理不善问题。 | AY53: =AG53 -> 违反交通标线 | AZ53: 是 | BA53: 否 | BB53: 否 | BC53: 七有五性,安全性、便利性 | BD53: =U53 -> 结束 | BE53: =IFERROR(LEFT(T53,FIND(" ",T53)-1),T53) -> 2026-01-11 | BF53: 场站安保问题 （外卖管理） | BG53: 安保部 | BH53: 单店分中心 | BL53: =IF(BG53="物管行政部","侯旭、郑楠",IF(BG53="安保部","张耕",IF(BG53="工程设备部","华菲",IF(BG53="人力资源部","成琦",IF(BG53="党委工作部","阎鑫雨",IF(BG53="餐饮服务部","赵弘晨",IF(BG53="工会","郑欣",IF(BG53="办公室","董娜",""))))))))&IF(BG53="纪检部","黄倩",IF(BG53="信息管理部","蔡浩然","")) -> 张耕 | BM53: 未主动剔除 | BP53: 业务类 | BQ53: 同人同诉问题: 热线-260106-027290、热线-260113-009666-1、热线-260115-060154-1 | BR53: 是 | BU53: 内部职工王爱民 | BV53: =MID(AR53,1,16) -> 热线-260106-027290 | BX53: =IF(COUNTIF(BV:BV,BV53)=1,"否","是") -> 否 | BY53: =MID(AR53,18,1) | BZ53: 只评价响应率 | CE53: 1月 | CG53: =VLOOKUP(AR53,[1]市民意见信息导出!$AI$2:$AK$392,3,FALSE()) -> 结束 | CH53: =VLOOKUP(BV53,[2]Sheet1!$C$2:$AC$99,2,FALSE()) -> 1月
A54: 热线-260106-028313（1个附件） | B54: 2026-01-06 11:59:53 | C54: 2026-01-06 12:16:48 | D54: 2026-01-06 14:16:33 | E54: 张先生 | F54: 男 | G54: 手机,15801185941; | H54: 市民反映，在海淀区西二旗公交站旁的公交场站，市民称里面的安保人员私自收取社会车辆停车费，穿黑色颜色的保安服装，保安人员姓马，希望有关部门监管处理，来电反映保安人员私自收取停车费问题。 | I54: 是 | J54: 诉求 | K54: 安保部（应急管理中心） | L54: 场站保安问题 | M54: 场站保安 | N54: 鸿运承物业管理中心 | O54: 小营分中心 | P54: 安全保卫部（应急管理中心） | Q54: 小营分中心 | R54: 2026-01-13 23:59:59 | S54: 2026-01-06 | T54: 2026-01-11 08:59:59 | U54: 结束 | V54: 0 | W54: 经核实：分中心接到电话投诉人所反映内容以后，给予了高度的重视，第一时间与场站负责人及保安员取得联系，当日张女士在西二旗桥下临时停车，因停车地点影响公交车进出，与在岗保安员发生矛盾，引起争执。并无收费停车问题。 | X54: 回访情况：2026年1月7日上午9:40分，电话回访市民，已得到投诉人的理解（回访电话：18910177482）办理人：陶春辉。审核员：陶春辉。单位：小营分中心。职务：主任 | Y54: 分中心对在其在职保安公司人员，遇到问题处理措施不当，语言态度不好，已经责成保安公司处理。 | Z54: 出现此事后分中心领导班子给予了高度的重视，对保安公司进行约谈，要求保安公司对所属保安员进行再教育，特别是处理情况的能力和语言态度的文明规范。 | AA54: 分中心会继续加强对保安人员的行为规范，语言文明等进行检查教育。 | AB54: 市民反映，在海淀区西二旗公交站旁的公交场站，市民称里面的安保人员私自收取社会车辆停车费，穿黑色颜色的保安服装，保安人员姓马，希望有关部门监管处理，来电反映保安人员私自收取停车费问题。经核实：投诉不属实。经与场站负责人及保安员取得联系，当日张女士在西二旗桥下临时停车，因停车地点影响公交车进出，与在岗保安员发生矛盾，引起争执。并无收费停车问题。分中心与张女士取得联系，得到投诉人的理解。 | AC54: 满意 | AD54: 个人 | AE54: 2026-01-06 11:56:51 | AF54: 1741937704 | AG54: 停车场乱收费 | AH54: 否 | AK54: =AG54&L54&M54 -> 停车场乱收费场站保安问题场站保安 | AP54: 50 | AQ54: 46023 | AR54: =IFERROR(LEFT(A54,FIND("（",A54)-1),A54) -> 热线-260106-028313 | AS54: =J54 -> 诉求 | AT54: =IF(MID(AR54,1,2)="热线",12345)+IF(MID(AR54,1,2)="网络",12345) -> 12345 | AU54: =IFERROR(LEFT(D54,FIND(" ",D54)-1),D54) -> 2026-01-06 | AV54: =P54 -> 安全保卫部（应急管理中心） | AW54: =Q54 -> 小营分中心 | AX54: =H54 -> 市民反映，在海淀区西二旗公交站旁的公交场站，市民称里面的安保人员私自收取社会车辆停车费，穿黑色颜色的保安服装，保安人员姓马，希望有关部门监管处理，来电反映保安人员私自收取停车费问题。 | AY54: =AG54 -> 停车场乱收费 | AZ54: 否 | BA54: 否 | BB54: 否 | BC54: 七有五性,安全性,便利性 | BD54: =U54 -> 结束 | BE54: =IFERROR(LEFT(T54,FIND(" ",T54)-1),T54) -> 2026-01-11 | BF54: 场站安保问题 （私家车停车收费） | BG54: 安保部 | BH54: 小营分中心 | BL54: =IF(BG54="物管行政部","侯旭、郑楠",IF(BG54="安保部","张耕",IF(BG54="工程设备部","华菲",IF(BG54="人力资源部","成琦",IF(BG54="党委工作部","阎鑫雨",IF(BG54="餐饮服务部","赵弘晨",IF(BG54="工会","郑欣",IF(BG54="办公室","董娜",""))))))))&IF(BG54="纪检部","黄倩",IF(BG54="信息管理部","蔡浩然","")) -> 张耕 | BM54: 未主动剔除 | BP54: 业务类 | BV54: =MID(AR54,1,16) -> 热线-260106-028313 | BX54: =IF(COUNTIF(BV:BV,BV54)=1,"否","是") -> 否 | BY54: =MID(AR54,18,1) | BZ54: 只评价响应率 | CE54: 1月 | CG54: =VLOOKUP(AR54,[1]市民意见信息导出!$AI$2:$AK$392,3,FALSE()) -> 结束 | CH54: =VLOOKUP(BV54,[2]Sheet1!$C$2:$AC$99,2,FALSE()) -> 1月
A55: 热线-260107-005722-2（1个附件） | B55: 2026-01-07 08:55:07 | C55: 2026-01-07 09:23:02 | D55: 2026-01-07 09:23:50 | E55: 匿名先生 | F55: 男 | G55: 手机,17600538295; | H55: 市民表扬，621路公交车司机，帮助老病残找座位，车干净卫生服务到位，要求回复（已解释），编号：1631349，来电反映表扬公交车司机。 | I55: 是 | J55: 表扬 | K55: 行车安全服务部 | L55: 车厢服务意识方面表扬 | M55: 执行规范 | N55: 鸿运承物业管理中心 | O55: 回龙观分中心 | P55: 物管行政部 | Q55: 回龙观分中心 | S55: 2026-01-07 | T55: 2026-01-12 08:59:59 | U55: 结束 | V55: 0 | W55: 您好，关于您表扬621路1631349号车，车干净卫生派单的办理情况，鸿运承物业管理中心回龙观分中心现对您回复如下： | X55: 我分中心已于2026年1月7日下午14点02分对您进行电话回复。办理人：李满；部门：鸿运承物业管理中心回龙观分中心；职务；物管副主任。审核人：郑楠；部门：鸿运承物业管理中心物管行政部；职务：物管员。 | Y55: 感谢您对621路公交车卫生的认可，621路公交车我们在半截塔场站进行洗车服务，我们将621路的刷车保洁员进行口头表扬，同时将保洁员这种工作精神在全分中心范围内进行宣传，我们今后也将以良好的工作作风服务于一线及市民，确保运营车辆卫生干净整洁，体现物业良好的服务意识。 | Z55: 我们场站班组长再次与本条线路的保洁人员进行了沟通，要把好的经验和方法保持下去，日常的清洁与维护至关重要，日常工作中仍需要加强出场车辆卫生需符合清洁标准。 | AA55: 我们定期召开车辆保洁专题会议，开展车辆卫生专项检查，日常工作中我们加大巡检力度，强化制度建设，不断提高管理水平。 | AB55: 您好，关于您表扬621路1631349号车，车干净卫生派单的办理情况，鸿运承物业管理中心回龙观分中心现对您回复如下：感谢您对621路公交车卫生的认可，621路公交车我们在半截塔场站进行洗车服务，我们将621路的刷车保洁员进行口头表扬，同时将保洁员这种工作精神在全分中心范围内进行宣传，我们今后也将以良好的工作作风服务于一线及市民，确保运营车辆卫生干净整洁，体现物业良好的服务意识。我们定期召开车辆保洁专题会议，开展车辆卫生专项检查，日常工作中我们加大巡检力度，强化制度建设，不断提高管理水平。我分中心已于2026年1月7日下午14点02分对您进行电话回复。我们场站班组长再次与本条线路的保洁人员进行了沟通，要把好的经验和方法保持下去，日常的清洁与维护至关重要，日常工作中仍需要加强出场车辆卫生需符合清洁标准。欢迎您随时对我们的工作进行监督，我们将继续努力，为您提供一个舒适、整洁的乘车及出行环境，感谢您对我们工作的认可。 | AC55: 满意 | AD55: 个人 | AE55: 2026-01-07 08:52:43 | AF55: 1725545787 | AG55: 服务态度 | AH55: 是 | AK55: =AG55&L55&M55 -> 服务态度车厢服务意识方面表扬执行规范 | AP55: 51 | AQ55: 46023 | AR55: =IFERROR(LEFT(A55,FIND("（",A55)-1),A55) -> 热线-260107-005722-2 | AS55: =J55 -> 表扬 | AT55: =IF(MID(AR55,1,2)="热线",12345)+IF(MID(AR55,1,2)="网络",12345) -> 12345 | AU55: =IFERROR(LEFT(D55,FIND(" ",D55)-1),D55) -> 2026-01-07 | AV55: =P55 -> 物管行政部 | AW55: =Q55 -> 回龙观分中心 | AX55: =H55 -> 市民表扬，621路公交车司机，帮助老病残找座位，车干净卫生服务到位，要求回复（已解释），编号：1631349，来电反映表扬公交车司机。 | AY55: =AG55 -> 服务态度 | AZ55: 否 | BA55: 否 | BB55: 否 | BC55: 七有五性,宜居性 | BD55: =U55 -> 结束 | BE55: =IFERROR(LEFT(T55,FIND(" ",T55)-1),T55) -> 2026-01-12 | BF55: 表扬车辆卫生 | BG55: 物管行政部 | BH55: 回龙观分中心 | BL55: =IF(BG55="物管行政部","侯旭、郑楠",IF(BG55="安保部","张耕",IF(BG55="工程设备部","华菲",IF(BG55="人力资源部","成琦",IF(BG55="党委工作部","阎鑫雨",IF(BG55="餐饮服务部","赵弘晨",IF(BG55="工会","郑欣",IF(BG55="办公室","董娜",""))))))))&IF(BG55="纪检部","黄倩",IF(BG55="信息管理部","蔡浩然","")) -> 侯旭、郑楠 | BN55: 表扬 | BP55: 业务类 | BV55: =MID(AR55,1,16) -> 热线-260107-005722 | BX55: =IF(COUNTIF(BV:BV,BV55)=1,"否","是") -> 否 | BY55: =MID(AR55,18,1) -> 2 | CG55: =VLOOKUP(AR55,[1]市民意见信息导出!$AI$2:$AK$392,3,FALSE()) -> 结束 | CH55: =VLOOKUP(BV55,[2]Sheet1!$C$2:$AC$99,2,FALSE()) -> #N/A
A56: 热线-260107-002903-3（2个附件） | B56: 2026-01-07 18:48:17 | C56: 2026-01-07 18:53:58 | D56: 2026-01-07 21:58:33 | E56: 保密 | F56: 女 | G56: 保密 | H56: 市民反映，海淀区积水潭地铁出来是公交枢纽总站，现在（2026年1月7日07:55）天已经亮了，车站里面的路灯还在亮着，希望可以按照正常时间调节，来电反映公交站路灯长时间亮问题。注：来电人要求保密个人信息（已解释）工单流转：海淀区分中心退回：来信人您好，您反映的信件，城管委进行了调查，并答复如下：于2026-01-07 08:19:25海淀区城市管理委员会接到市中心热线-260107-002903工单。因诉求人联系电话保密，无法联系诉求人，根据工单内容，诉求人反映积水潭地铁站出口公交场站路灯亮灯时间调整问题。经确认，诉求人反映的点位为德胜门西公交场站，位于西城区德胜门西大街北侧。该点位位于西城区范围，非海淀辖区。经确认此工单已超出海淀区受理范围，此工单为保密件，无法联系诉求人。此工单应由西城区有关部门协调处理，请市中心转派。工单流转：西城区分中心退回：西城区城市管理委街景管理科工作人员接此案件后现场核实关于西城区积水潭地铁出来是公交枢纽总站，现在（2026年1月7日07:55）天已经亮了，车站里面的路灯还在亮着，希望可以按照正常时间调节，来电反映公交站路灯长时间亮问题。经核实此处路灯属于公交集团内部灯光，烦请市中心转北京公交集团核实处理。客一客八鸿运承 | I56: 是 | J56: 诉求 | K56: 基建行政部 | L56: 场站问题 | M56: 场站生活设施问题 | N56: 鸿运承物业管理中心 | O56: 动物园分中心 | P56: 物管行政部 | Q56: 动物园分中心 | R56: 2026-01-14 23:59:59 | S56: 2026-01-08 | T56: 2026-01-12 08:59:59 | U56: 结束 | V56: 0 | W56: 此单为拆单投诉，公交物业负责回复“公交场站内照明灯按照正常时间调节问题”。市民反映的是德胜门西公交场站（照明）站务设施设置问题。德胜门西公交场站是公交首末站。经核实，公交集团物业公司已于2023年对该场站照明设施进行改造，现有场站照明设施是时控和光控双重调节。 | X56: 由于市民联系方式保密，无法进行电话答复。办理人：杜伟 鸿运承物业管理中心动物园分中心物管设备主任。审核人：华菲 物管中心工程设备部 一般管理。 | Y56: 场站照明设施是时控和光控双重调节。首先时控，我们会根据季节设定基本开启和关闭时间，目前场站灯光启动时间17:20，熄灭时间早7:20。其次辅助光控，会根据自然光线亮度自动调节。收到市民反馈，我们再次对场站照明设施进行核查。目前正值冬季昼短夜长，我们会合理进行调试，争取达到既能照顾市民出行照明又能洁能环保目的，感谢市民提出的建议。 | Z56: 场站照明设施是时控和光控双重调节。首先时控，我们会根据季节设定基本开启和关闭时间，目前场站灯光启动时间17:20，熄灭时间早7:20。其次辅助光控，会根据自然光线亮度自动调节。收到市民反馈，我们再次对场站照明设施进行核查。目前正值冬季昼短夜长，我们会合理进行调试，争取达到既能照顾市民出行照明又能洁能环保目的，感谢市民提出的建议。 | AA56: 收到市民反馈，我们会再次对场站照明设施进行核查，避免类似情况造成投诉。 | AB56: 此单为拆单投诉，公交物业负责回复“公交场站内照明灯按照正常时间调节问题”。市民反映的是德胜门西公交场站（照明）站务设施设置问题。德胜门西公交场站是公交首末站。经核实，公交集团物业公司已于2023年对该场站照明设施进行改造，现有场站照明设施是时控和光控双重调节。首先时控，我们会根据季节设定基本开启和关闭时间，目前场站灯光启动时间17:20，熄灭时间早7:20。其次辅助光控，会根据自然光线亮度自动调节。收到市民反馈，我们再次对场站照明设施进行核查。目前正值冬季昼短夜长，我们会合理进行调试，争取达到既能照顾市民出行照明又能洁能环保目的，感谢市民提出的建议。由于市民联系方式保密，无法进行电话答复。 | AC56: 满意 | AD56: 个人 | AE56: 2026-01-07 07:54:31 | AF56: 1741937703 | AG56: 市政路灯 | AH56: 否 | AK56: =AG56&L56&M56 -> 市政路灯场站问题场站生活设施问题 | AP56: 52 | AQ56: 46023 | AR56: =IFERROR(LEFT(A56,FIND("（",A56)-1),A56) -> 热线-260107-002903-3 | AS56: =J56 -> 诉求 | AT56: =IF(MID(AR56,1,2)="热线",12345)+IF(MID(AR56,1,2)="网络",12345) -> 12345 | AU56: =IFERROR(LEFT(D56,FIND(" ",D56)-1),D56) -> 2026-01-07 | AV56: =P56 -> 物管行政部 | AW56: =Q56 -> 动物园分中心 | AX56: =H56 -> 市民反映，海淀区积水潭地铁出来是公交枢纽总站，现在（2026年1月7日07:55）天已经亮了，车站里面的路灯还在亮着，希望可以按照正常时间调节，来电反映公交站路灯长时间亮问题。注：来电人要求保密个人信息（已解释）工单流转：海淀区分中心退回：来信人您好，您反映的信件，城管委进行了调查，并答复如下：于2026-01-07 08:19:25海淀区城市管理委员会接到市中心热线-260107-002903工单。因诉求人联系电话保密，无法联系诉求人，根据工单内容，诉求人反映积水潭地铁站出口公交场站路灯亮灯时间调整问题。经确认，诉求人反映的点位为德胜门西公交场站，位于西城区德胜门西大街北侧。该点位位于西城区范围，非海淀辖区。经确认此工单已超出海淀区受理范围，此工单为保密件，无法联系诉求人。此工单应由西城区有关部门协调处理，请市中心转派。工单流转：西城区分中心退回：西城区城市管理委街景管理科工作人员接此案件后现场核实关于西城区积水潭地铁出来是公交枢纽总站，现在（2026年1月7日07:55）天已经亮了，车站里面的路灯还在亮着，希望可以按照正常时间调节，来电反映公交站路灯长时间亮问题。经核实此处路灯属于公交集团内部灯光，烦请市中心转北京公交集团核实处理。客一客八鸿运承 | AY56: =AG56 -> 市政路灯 | AZ56: 否 | BA56: 否 | BB56: 否 | BC56: 七有五性,安全性,便利性 | BD56: =U56 -> 结束 | BE56: =IFERROR(LEFT(T56,FIND(" ",T56)-1),T56) -> 2026-01-12 | BF56: 站务设施设置 （站内路灯） | BG56: 工程设备部 | BH56: 动物园分中心 | BL56: =IF(BG56="物管行政部","侯旭、郑楠",IF(BG56="安保部","张耕",IF(BG56="工程设备部","华菲",IF(BG56="人力资源部","成琦",IF(BG56="党委工作部","阎鑫雨",IF(BG56="餐饮服务部","赵弘晨",IF(BG56="工会","郑欣",IF(BG56="办公室","董娜",""))))))))&IF(BG56="纪检部","黄倩",IF(BG56="信息管理部","蔡浩然","")) -> 华菲 | BM56: 未主动剔除 | BP56: 政策类 | BV56: =MID(AR56,1,16) -> 热线-260107-002903 | BW56: 七有五性,便利性 | BX56: =IF(COUNTIF(BV:BV,BV56)=1,"否","是") -> 否 | BY56: =MID(AR56,18,1) -> 3 | CG56: =VLOOKUP(AR56,[1]市民意见信息导出!$AI$2:$AK$392,3,FALSE()) -> 结束 | CH56: =VLOOKUP(BV56,[2]Sheet1!$C$2:$AC$99,2,FALSE()) -> #N/A
A57: 网络-260108-018300（1个附件） | B57: 2026-01-08 10:45:09 | C57: 2026-01-08 10:57:19 | D57: 2026-01-08 11:06:05 | E57: 保密 | F57: 女 | G57: 保密 | H57: 工单来源：微信服务号，此工单内容为网民留言时填写的标题及原文。 ============================= 留言标题：反馈北京公交北四环东路小营场站食堂问题留言原文：反馈北京公交北四环东路小营场站食堂价格贵菜品味道难吃人员素质低下卫生差。我是长期在食堂买早餐，晚餐的司机。自从早上没有了早餐大姐后，就只剩一个厨子，一个包子3元，一杯长期盛不满的粥或者汤就1.5元，要知道场站门口的包子也才1.5元，场站对面的早餐套餐(豆腐脑，油饼，鸡蛋)也才6.9元，公交场站的食堂两个包子加上一杯不多的粥或者汤，就7.5元了，这个算价合理吗？我们司机之间多次反映，但是这个厨师也是说这是领导定的，他只管卖。还有晚餐经常是中午没卖完的菜，晚上接着卖！一开始我还不信，后来厨师自己说的，中午剩的，理解卖不完，晚上继续卖，可是价格还是那么贵！这个厨师是穷疯了吗？公交食堂按理来说就应该是公交一线内部食堂，主要为司机提供后勤保障的，不应该以赚钱为目的，这个食堂可是倒好，有一种宰一个是一个的嫌疑，我粗略算了一下，我早上基本上7.5到9元之间，晚上十一二左右！不是怕贵，而是价格对不起这个质量！最后一个就是厨师的素质低下问题，长期不佩戴口罩，一聊天脏话长期挂嘴边，这是说给我们司机听的？还是怎么？我也不知道！最后我希望有管负责人能把这个现有姓谢的厨师调离这个场站，不希望从他嘴里散布一些负能量，不希望他做出的饭菜永远那么难吃，不希望他还吃着公交饭骂我们公交行业。我所说皆可从这个食堂内部的探头查看，包括刷卡机和他本人的微信收款记录查询。望领导重视！谢谢市民填写的详细地址为：区、街道：朝阳区小关街道详细地址：北四环东路104号公交场站 | I57: 是 | J57: 诉求 | K57: 基建行政部 | L57: 后勤保障 | M57: 食堂问题 | N57: 鸿运承物业管理中心 | O57: 小营分中心 | P57: 餐饮服务部 | Q57: 小营分中心 | R57: 2026-01-15 23:59:59 | S57: 2026-01-09 | T57: 2026-01-13 08:59:59 | U57: 结束 | V57: 0 | W57: 分中心于1月9日开展调查。分中心同外包单位进行核实，包子跟据不同的馅料价格不同，有2.5元的也有3元的，鸡蛋是1.5元，粥是1元，粥杯是0.5元。根据场站职工食堂餐饮服务合同中的服务内容的要求，早餐单品不超过普通市场价，食堂早餐定价价格没有违背合同内容。针对炊事员服务态度问题，分中心已约谈外包单位负责人进行批评教育，并要求外包单位更换掉该名炊事员 | X57: 因投诉人未留联系方式，我们未能对市民进行电话回复。办理人：谭琳，鸿运承物业管理中心小营分中心，餐饮员。审核人：赵弘晨，鸿运承物业管理中心，一般管理。 | Y57: 更换掉该名厨师，并对外包单位进行相应考核 | Z57: 分中心将加强对外包食堂的监督和管理，要求食堂员工加强专业素质，注意服务态度，及时听取就餐人员的意见及建议，服务好一线职工。 | AA57: 分中心将加大对外包食堂的检查，防治此类问题发生 | AB57: 分中心于1月9日开展调查。分中心同外包单位进行核实，包子跟据不同的馅料价格不同，有2.5元的也有3元的，鸡蛋是1.5元，粥是1元，粥杯是0.5元。根据场站职工食堂餐饮服务合同中的服务内容的要求，早餐单品不超过普通市场价，食堂早餐定价价格没有违背合同内容。针对炊事员服务态度问题，分中心已约谈外包单位负责人进行批评教育，并要求外包单位更换掉该名炊事员，并对外包单位进行相应考核。分中心将加强对外包食堂的监督和管理，要求食堂员工加强专业素质，注意服务态度，及时听取就餐人员的意见及建议，服务好一线职工。分中心将加大对外包食堂的检查，防治此类问题发生因投诉人未留联系方式，我们未能对市民进行电话回复。办理人：谭琳，鸿运承物业管理中心小营分中心，餐饮员。审核人：赵弘晨，鸿运承物业管理中心，一般管理。 | AC57: 满意 | AD57: 个人 | AE57: 2026-01-08 06:37:18 | AF57: 1741937704 | AG57: 餐饮企业环境卫生差 | AH57: 否 | AK57: =AG57&L57&M57 -> 餐饮企业环境卫生差后勤保障食堂问题 | AP57: 53 | AQ57: 46023 | AR57: =IFERROR(LEFT(A57,FIND("（",A57)-1),A57) -> 网络-260108-018300 | AS57: =J57 -> 诉求 | AT57: =IF(MID(AR57,1,2)="热线",12345)+IF(MID(AR57,1,2)="网络",12345) -> 12345 | AU57: =IFERROR(LEFT(D57,FIND(" ",D57)-1),D57) -> 2026-01-08 | AV57: =P57 -> 餐饮服务部 | AW57: =Q57 -> 小营分中心 | AX57: =H57 -> 工单来源：微信服务号，此工单内容为网民留言时填写的标题及原文。 ============================= 留言标题：反馈北京公交北四环东路小营场站食堂问题留言原文：反馈北京公交北四环东路小营场站食堂价格贵菜品味道难吃人员素质低下卫生差。我是长期在食堂买早餐，晚餐的司机。自从早上没有了早餐大姐后，就只剩一个厨子，一个包子3元，一杯长期盛不满的粥或者汤就1.5元，要知道场站门口的包子也才1.5元，场站对面的早餐套餐(豆腐脑，油饼，鸡蛋)也才6.9元，公交场站的食堂两个包子加上一杯不多的粥或者汤，就7.5元了，这个算价合理吗？我们司机之间多次反映，但是这个厨师也是说这是领导定的，他只管卖。还有晚餐经常是中午没卖完的菜，晚上接着卖！一开始我还不信，后来厨师自己说的，中午剩的，理解卖不完，晚上继续卖，可是价格还是那么贵！这个厨师是穷疯了吗？公交食堂按理来说就应该是公交一线内部食堂，主要为司机提供后勤保障的，不应该以赚钱为目的，这个食堂可是倒好，有一种宰一个是一个的嫌疑，我粗略算了一下，我早上基本上7.5到9元之间，晚上十一二左右！不是怕贵，而是价格对不起这个质量！最后一个就是厨师的素质低下问题，长期不佩戴口罩，一聊天脏话长期挂嘴边，这是说给我们司机听的？还是怎么？我也不知道！最后我希望有管负责人能把这个现有姓谢的厨师调离这个场站，不希望从他嘴里散布一些负能量，不希望他做出的饭菜永远那么难吃，不希望他还吃着公交饭骂我们公交行业。我所说皆可从这个食堂内部的探头查看，包括刷卡机和他本人的微信收款记录查询。望领导重视！谢谢市民填写的详细地址为：区、街道：朝阳区小关街道详细地址：北四环东路104号公交场站 | AY57: =AG57 -> 餐饮企业环境卫生差 | AZ57: 是 | BA57: 否 | BB57: 否 | BC57: 七有五性,多样性 | BD57: =U57 -> 结束 | BE57: =IFERROR(LEFT(T57,FIND(" ",T57)-1),T57) -> 2026-01-13 | BF57: 就餐服务问题（菜品定价、工作人工作态度） | BG57: 餐饮服务部 | BH57: 小营分中心 | BL57: =IF(BG57="物管行政部","侯旭、郑楠",IF(BG57="安保部","张耕",IF(BG57="工程设备部","华菲",IF(BG57="人力资源部","成琦",IF(BG57="党委工作部","阎鑫雨",IF(BG57="餐饮服务部","赵弘晨",IF(BG57="工会","郑欣",IF(BG57="办公室","董娜",""))))))))&IF(BG57="纪检部","黄倩",IF(BG57="信息管理部","蔡浩然","")) -> 赵弘晨 | BM57: 未主动剔除 | BP57: 业务类 | BQ57: 相同内容诉求：网络-260108-018300、网络-260117-035766 | BR57: 是 | BU57: 同一地点诉求 | BV57: =MID(AR57,1,16) -> 网络-260108-018300 | BW57: 七有五性,便利性,安全性 | BX57: =IF(COUNTIF(BV:BV,BV57)=1,"否","是") -> 否 | BY57: =MID(AR57,18,1) | CG57: =VLOOKUP(AR57,[1]市民意见信息导出!$AI$2:$AK$392,3,FALSE()) -> 结束 | CH57: =VLOOKUP(BV57,[2]Sheet1!$C$2:$AC$99,2,FALSE()) -> #N/A
A58: 网络-260108-037140-1 | B58: 2026-01-08 14:07:06 | C58: 2026-01-08 14:10:26 | D58: 2026-01-08 14:24:52 | E58: 保密 | F58: 男 | G58: 保密 | H58: 工单来源：微信服务号，此工单内容为网民留言时填写的标题及原文。 ============================= 留言标题：公交车上又脏又臭还不让开窗户留言原文：在传染病高发的季节，公交车上卫生糟糕，乘务员还坚决不让开窗。到底是有多怕冷？还是车快冻坏了不好意思告诉乘客？市民填写的详细地址为：区、街道：朝阳区望京街道详细地址：536公交车上 | I58: 是 | J58: 诉求 | K58: 行车安全服务部 | L58: 企业政策问题 | M58: 调整服务规范 | N58: 鸿运承物业管理中心 | O58: 动物园分中心 | P58: 物管行政部 | Q58: 动物园分中心 | R58: 2026-01-15 23:59:59 | S58: 2026-01-08 | T58: 2026-01-13 08:59:59 | U58: 结束 | V58: 0 | W58: 您好，关于您反映问题的办理情况，鸿运承物业管理中心动物园分中心现对您回复如下： | X58: 因您的联系方式保密，我们未能对您进行电话回复。办理人：杜伟；部门：鸿运承物业管理中心动物园分中心；职务；物管副主任。审核人：郑楠；部门：鸿运承物业管理中心物管行政部；职务：物管员。 | Y58: 先生您好，536路公交车我们在左家庄新东路北侧场站进行洗车服务工作，您所述车辆运营中公交车上又脏又臭的问题我们非常重视您的反馈，由于我们的工作没有做好，536路给您带来不好的乘车体验，实在是抱歉，先生。该线路车辆回到左家庄新东路北侧场站后，在日常工作时段内，我们的保洁员已对车内卫生进行了全面的清理，确保我们的出场车辆卫生符合企业标准。您反馈的问题我们已整改完毕，同时我们要求保洁员对536路所有运营车辆的卫生再次进行细化清理。我们对于运营车辆车内卫生的清洁工作是一直在做的，也从未停止，已经形成了长效的清洁机制，但有时候卫生清洁工作我们做的还有不尽人意之处，您多多谅解。车内臭味的问题我们保洁员在清理卫生的同时，已将车门、车窗全部打开，对车内进行了通风换气作业。 | Z58: 我们分中心及场站班组长再次与536路的保洁人员进行了沟通，日常工作中我们要把清洁质量做的更加细致，同时加强保洁员清洁技能的培训，熟练掌握清洁方法，密切关注车内空气质量，确保给您带来一个干净、整洁、空气清新的出行环境。 | AA58: 我们定期会召开车辆保洁专题会议，开展车辆卫生专项检查，日常工作中我们加大巡检力度，强化制度建设，不断提高管理水平。 | AB58: 您好，关于您反映问题的办理情况，鸿运承物业管理中心动物园分中心现对您回复如下：先生您好，536路公交车我们在左家庄新东路北侧场站进行洗车服务工作，您所述车辆运营中公交车上又脏又臭的问题我们非常重视您的反馈，由于我们的工作没有做好，536路给您带来不好的乘车体验，实在是抱歉，先生。该线路车辆回到左家庄新东路北侧场站后，在日常工作时段内，我们的保洁员已对车内卫生进行了全面的清理，确保我们的出场车辆卫生符合企业标准。您反馈的问题我们已整改完毕，同时我们要求保洁员对536路所有运营车辆的卫生再次进行细化清理。我们对于运营车辆车内卫生的清洁工作是一直在做的，也从未停止，已经形成了长效的清洁机制，但有时候卫生清洁工作我们做的还有不尽人意之处，您多多谅解。车内臭味的问题我们保洁员在清理卫生的同时，已将车门、车窗全部打开，对车内进行了通风换气作业。我们定期会召开车辆保洁专题会议，开展车辆卫生专项检查，日常工作中我们加大巡检力度，强化制度建设，不断提高管理水平。因您的联系方式保密，我们未能对您进行电话回复。我们分中心及场站班组长再次与536路的保洁人员进行了沟通，日常工作中我们要把清洁质量做的更加细致，同时加强保洁员清洁技能的培训，熟练掌握清洁方法，密切关注车内空气质量，确保给您带来一个干净、整洁、空气清新的出行环境。欢迎您随时对我们的工作进行监督，感谢您提出宝贵意见，给您的出行带来的不便我们和您说声抱歉，谢谢您的支持与谅解。 | AC58: 满意 | AD58: 个人 | AE58: 2026-01-08 13:19:23 | AF58: 1741937703 | AG58: 服务 | AH58: 否 | AK58: =AG58&L58&M58 -> 服务企业政策问题调整服务规范 | AP58: 54 | AQ58: 46023 | AR58: =IFERROR(LEFT(A58,FIND("（",A58)-1),A58) -> 网络-260108-037140-1 | AS58: =J58 -> 诉求 | AT58: =IF(MID(AR58,1,2)="热线",12345)+IF(MID(AR58,1,2)="网络",12345) -> 12345 | AU58: =IFERROR(LEFT(D58,FIND(" ",D58)-1),D58) -> 2026-01-08 | AV58: =P58 -> 物管行政部 | AW58: =Q58 -> 动物园分中心 | AX58: =H58 -> 工单来源：微信服务号，此工单内容为网民留言时填写的标题及原文。 ============================= 留言标题：公交车上又脏又臭还不让开窗户留言原文：在传染病高发的季节，公交车上卫生糟糕，乘务员还坚决不让开窗。到底是有多怕冷？还是车快冻坏了不好意思告诉乘客？市民填写的详细地址为：区、街道：朝阳区望京街道详细地址：536公交车上 | AY58: =AG58 -> 服务 | AZ58: 否 | BA58: 否 | BB58: 否 | BC58: 七有五性,宜居性 | BD58: =U58 -> 结束 | BE58: =IFERROR(LEFT(T58,FIND(" ",T58)-1),T58) -> 2026-01-13 | BF58: 车辆卫生问题 （车内卫生、玻璃） | BG58: 物管行政部 | BH58: 动物园分中心 | BL58: =IF(BG58="物管行政部","侯旭、郑楠",IF(BG58="安保部","张耕",IF(BG58="工程设备部","华菲",IF(BG58="人力资源部","成琦",IF(BG58="党委工作部","阎鑫雨",IF(BG58="餐饮服务部","赵弘晨",IF(BG58="工会","郑欣",IF(BG58="办公室","董娜",""))))))))&IF(BG58="纪检部","黄倩",IF(BG58="信息管理部","蔡浩然","")) -> 侯旭、郑楠 | BM58: 已主动剔除 | BP58: 业务类 | BV58: =MID(AR58,1,16) -> 网络-260108-037140 | BW58: 七有五性,便利性 | BX58: =IF(COUNTIF(BV:BV,BV58)=1,"否","是") -> 否 | BY58: =MID(AR58,18,1) -> 1 | CG58: =VLOOKUP(AR58,[1]市民意见信息导出!$AI$2:$AK$392,3,FALSE()) -> 结束 | CH58: =VLOOKUP(BV58,[2]Sheet1!$C$2:$AC$99,2,FALSE()) -> #N/A
A59: 热线-260109-024500-2（1个附件） | B59: 2026-01-09 11:51:37 | C59: 2026-01-09 12:00:56 | D59: 2026-01-09 12:34:58 | E59: 赵女士 | F59: 女 | G59: 手机,13488762702; | H59: 市民反映，2026年1月9日11:39分在1路公交车公主坟站，车辆后面的台子上有蟑螂，已经录视频了（没有记车牌号），四惠东-公主坟方向，希望尽快核实解决，来电反映1路公交车有蟑螂问题客四鸿运承安服 | I59: 是 | J59: 诉求 | K59: 行车安全服务部 | L59: 企业政策问题 | M59: 调整服务规范 | N59: 鸿运承物业管理中心 | O59: 田顺庄分中心 | P59: 物管行政部 | Q59: 田顺庄分中心 | R59: 2026-01-16 23:59:59 | S59: 2026-01-09 | T59: 2026-01-14 08:59:59 | U59: 结束 | V59: 0 | W59: 您好，关于您反映问题的办理情况，鸿运承物业管理中心田顺庄分中心现对您回复如下： | X59: 我分中心已于2026年1月9日下午16点39分对您进行电话回复。办理人：董鹏；部门：鸿运承物业管理中心田顺庄分中心；职务；物管副主任。审核人：郑楠；部门：鸿运承物业管理中心物管行政部；职务：物管员。 | Y59: 赵女士您好，1路公交车我们在老山场站进行洗车服务工作，您所述车辆运营中车辆后面的台子上有蟑螂的问题我们非常重视您的反馈，由于我们的工作没有做好，1路给您带来不好的乘车体验，实在是抱歉，赵女士。该线路车辆回到老山场站后，在日常工作时段内，我们的保洁员已对车内卫生进行了全面的清理，确保我们的出场车辆卫生符合企业标准。您反馈的问题我们已整改完毕，同时我们要求保洁员对1路所有运营车辆的卫生再次进行细化清理。我们对于运营车辆车内卫生的清洁工作是一直在做的，也从未停止，已经形成了长效的清洁机制，但有时候卫生清洁工作我们做的还有不尽人意之处，您多多谅解。运营车辆的消毒工作，我们目前按照每日对运营车辆消毒一次的标准认真执行。 | Z59: 我们分中心及场站班组长再次与1路的保洁人员进行了沟通，日常工作中我们要把清洁质量做的更加细致，同时加强保洁员清洁技能的培训，熟练掌握清洁方法，确保给您带来一个干净、整洁的出行环境。 | AA59: 我们定期会召开车辆保洁专题会议，开展车辆卫生专项检查，日常工作中我们加大巡检力度，强化制度建设，不断提高管理水平。 | AB59: 您好，关于您反映问题的办理情况，鸿运承物业管理中心田顺庄分中心现对您回复如下：赵女士您好，1路公交车我们在老山场站进行洗车服务工作，您所述车辆运营中车辆后面的台子上有蟑螂的问题我们非常重视您的反馈，由于我们的工作没有做好，1路给您带来不好的乘车体验，实在是抱歉，赵女士。该线路车辆回到老山场站后，在日常工作时段内，我们的保洁员已对车内卫生进行了全面的清理，确保我们的出场车辆卫生符合企业标准。您反馈的问题我们已整改完毕，同时我们要求保洁员对1路所有运营车辆的卫生再次进行细化清理。我们对于运营车辆车内卫生的清洁工作是一直在做的，也从未停止，已经形成了长效的清洁机制，但有时候卫生清洁工作我们做的还有不尽人意之处，您多多谅解。运营车辆的消毒工作，我们目前按照每日对运营车辆消毒一次的标准认真执行。我们定期会召开车辆保洁专题会议，开展车辆卫生专项检查，日常工作中我们加大巡检力度，强化制度建设，不断提高管理水平。我分中心已于2026年1月9日下午16点39分对您进行电话回复。我们分中心及场站班组长再次与1路的保洁人员进行了沟通，日常工作中我们要把清洁质量做的更加细致，同时加强保洁员清洁技能的培训，熟练掌握清洁方法，确保给您带来一个干净、整洁的出行环境。欢迎您随时对我们的工作进行监督，感谢您提出宝贵意见，给您的出行带来的不便我们和您说声抱歉，谢谢您的支持与谅解。 | AC59: 满意 | AD59: 个人 | AE59: 2026-01-09 11:40:23 | AF59: 1725545784 | AG59: 设施设备 | AH59: 否 | AK59: =AG59&L59&M59 -> 设施设备企业政策问题调整服务规范 | AP59: 55 | AQ59: 46023 | AR59: =IFERROR(LEFT(A59,FIND("（",A59)-1),A59) -> 热线-260109-024500-2 | AS59: =J59 -> 诉求 | AT59: =IF(MID(AR59,1,2)="热线",12345)+IF(MID(AR59,1,2)="网络",12345) -> 12345 | AU59: =IFERROR(LEFT(D59,FIND(" ",D59)-1),D59) -> 2026-01-09 | AV59: =P59 -> 物管行政部 | AW59: =Q59 -> 田顺庄分中心 | AX59: =H59 -> 市民反映，2026年1月9日11:39分在1路公交车公主坟站，车辆后面的台子上有蟑螂，已经录视频了（没有记车牌号），四惠东-公主坟方向，希望尽快核实解决，来电反映1路公交车有蟑螂问题客四鸿运承安服 | AY59: =AG59 -> 设施设备 | AZ59: 否 | BA59: 否 | BB59: 否 | BC59: 七有五性,宜居性 | BD59: =U59 -> 结束 | BE59: =IFERROR(LEFT(T59,FIND(" ",T59)-1),T59) -> 2026-01-14 | BF59: 车辆卫生问题 （车内卫生、蟑螂） | BG59: 物管行政部 | BH59: 田顺庄分中心 | BL59: =IF(BG59="物管行政部","侯旭、郑楠",IF(BG59="安保部","张耕",IF(BG59="工程设备部","华菲",IF(BG59="人力资源部","成琦",IF(BG59="党委工作部","阎鑫雨",IF(BG59="餐饮服务部","赵弘晨",IF(BG59="工会","郑欣",IF(BG59="办公室","董娜",""))))))))&IF(BG59="纪检部","黄倩",IF(BG59="信息管理部","蔡浩然","")) -> 侯旭、郑楠 | BM59: 未主动剔除 | BP59: 业务类 | BV59: =MID(AR59,1,16) -> 热线-260109-024500 | BW59: 七有五性,便利性 | BX59: =IF(COUNTIF(BV:BV,BV59)=1,"否","是") -> 否 | BY59: =MID(AR59,18,1) -> 2 | CG59: =VLOOKUP(AR59,[1]市民意见信息导出!$AI$2:$AK$392,3,FALSE()) -> 结束 | CH59: =VLOOKUP(BV59,[2]Sheet1!$C$2:$AC$99,2,FALSE()) -> #N/A
A60: 热线-260109-043939-1（1个附件） | B60: 2026-01-09 15:45:59 | C60: 2026-01-09 15:50:21 | D60: 2026-01-09 15:56:45 | E60: 杨先生 | F60: 男 | G60: 手机,13811081307; | H60: 市民反映，自己被北京公共交通控股集团有限公司鸿运承物业管理中心开除，开除原因为企业说自己为管理人员，自己对此不认可，自己与企业签订的劳动合同为工人岗位，要求企业拿出管理自己人员的证据，地址：北京市西城区广安门内核桃园1号，来电反映要求北京公共交通控股集团有限公司鸿运承物业管理中心拿出自己是管理人员的证据的问题。要求北京公共交通控股集团有限公司鸿运承物业管理中心拿出自己是管理人员的证据的问题人力组织部 | I60: 是 | J60: 诉求 | K60: 人力资源部（人力资源发展中心） | L60: 劳动用工 | M60: 劳动合同 | N60: 鸿运承物业管理中心 | O60: 人力资源部 | P60: 人力资源部 | Q60: 机关 | R60: 2026-01-16 23:59:59 | S60: 2026-01-13 | T60: 2026-01-14 08:59:59 | U60: 结束 | V60: 0 | W60: 经核实，与来电人所述情况不相符。经核查，来电人杨利原为我单位鸿运承物业管理中心工人管理岗位职工，并非管理人员。我单位工人管理及以上岗位为集团公司监察对象，根据北京市监委驻北京公交集团监察专员办公室出具的《关于给予杨利开除处分的决定》，我单位鸿运承物业管理中心与来电人解除劳动合同。 | X60: 经核实，与来电人所述情况不相符。经核查，来电人杨利原为我单位鸿运承物业管理中心工人管理岗位职工，并非管理人员。我单位工人管理及以上岗位为集团公司监察对象，根据北京市监委驻北京公交集团监察专员办公室出具的《关于给予杨利开除处分的决定》，我单位鸿运承物业管理中心与来电人解除劳动合同。2026年1月13日上午8点51分左右电话与来电人回复，经过沟通，来电人对此仍表示不认可。 办理人：周健辉 ；部门：鸿运承物业管理中心人力资源部，职务：一般管理； 审核人：高强；部门：鸿运承物业管理中心人力资源部；职务：中级管理。 | Y60: 2026年1月13日上午8点51分左右电话与来电人回复，经过沟通，来电人对此仍表示不认可。 | Z60: 无 | AA60: 无 | AB60: 经核实，与来电人所述情况不相符。经核查，来电人杨利原为我单位鸿运承物业管理中心工人管理岗位职工，并非管理人员。我单位工人管理及以上岗位为集团公司监察对象，根据北京市监委驻北京公交集团监察专员办公室出具的《关于给予杨利开除处分的决定》，我单位鸿运承物业管理中心与来电人解除劳动合同。2026年1月13日上午8点51分左右电话与来电人回复，经过沟通，来电人对此仍表示不认可。 | AC60: 满意 | AD60: 个人 | AE60: 2026-01-09 15:17:29 | AF60: 1049051 | AG60: 劳动合同及用工管理 | AH60: 否 | AK60: =AG60&L60&M60 -> 劳动合同及用工管理劳动用工劳动合同 | AP60: 56 | AQ60: 46023 | AR60: =IFERROR(LEFT(A60,FIND("（",A60)-1),A60) -> 热线-260109-043939-1 | AS60: =J60 -> 诉求 | AT60: =IF(MID(AR60,1,2)="热线",12345)+IF(MID(AR60,1,2)="网络",12345) -> 12345 | AU60: =IFERROR(LEFT(D60,FIND(" ",D60)-1),D60) -> 2026-01-09 | AV60: =P60 -> 人力资源部 | AW60: =Q60 -> 机关 | AX60: =H60 -> 市民反映，自己被北京公共交通控股集团有限公司鸿运承物业管理中心开除，开除原因为企业说自己为管理人员，自己对此不认可，自己与企业签订的劳动合同为工人岗位，要求企业拿出管理自己人员的证据，地址：北京市西城区广安门内核桃园1号，来电反映要求北京公共交通控股集团有限公司鸿运承物业管理中心拿出自己是管理人员的证据的问题。要求北京公共交通控股集团有限公司鸿运承物业管理中心拿出自己是管理人员的证据的问题人力组织部 | AY60: =AG60 -> 劳动合同及用工管理 | AZ60: 是 | BA60: 是 | BB60: 否 | BC60: 七有五性,公正性 | BD60: =U60 -> 结束 | BE60: =IFERROR(LEFT(T60,FIND(" ",T60)-1),T60) -> 2026-01-14 | BF60: 劳动人员管理及劳动纪律 （纪检问题解除劳动合同） | BG60: 人力资源部 | BH60: 机关 | BL60: =IF(BG60="物管行政部","侯旭、郑楠",IF(BG60="安保部","张耕",IF(BG60="工程设备部","华菲",IF(BG60="人力资源部","成琦",IF(BG60="党委工作部","阎鑫雨",IF(BG60="餐饮服务部","赵弘晨",IF(BG60="工会","郑欣",IF(BG60="办公室","董娜",""))))))))&IF(BG60="纪检部","黄倩",IF(BG60="信息管理部","蔡浩然","")) -> 成琦 | BM60: 未主动剔除 | BP60: 纠纷类 | BQ60: 同人同诉：热线-260109-043939、热线-260113-007090、热线-260113-028565、网络-260124-001044 | BR60: 是 | BV60: =MID(AR60,1,16) -> 热线-260109-043939 | BW60: 七有五性,劳有所得 | BX60: =IF(COUNTIF(BV:BV,BV60)=1,"否","是") -> 是 | BY60: =MID(AR60,18,1) -> 1 | BZ60: 只评价响应率 | CE60: 1月 | CG60: =VLOOKUP(AR60,[1]市民意见信息导出!$AI$2:$AK$392,3,FALSE()) -> 结束 | CH60: =VLOOKUP(BV60,[2]Sheet1!$C$2:$AC$99,2,FALSE()) -> 1月
A61: 热线-260109-043939-2（2个附件） | B61: 2026-01-09 15:45:59 | C61: 2026-01-09 15:50:21 | D61: 2026-01-09 15:56:45 | E61: 杨先生 | F61: 男 | G61: 手机,13811081307; | H61: 市民反映，自己被北京公共交通控股集团有限公司鸿运承物业管理中心开除，开除原因为企业说自己为管理人员，自己对此不认可，自己与企业签订的劳动合同为工人岗位，要求企业拿出管理自己人员的证据，地址：北京市西城区广安门内核桃园1号，来电反映要求北京公共交通控股集团有限公司鸿运承物业管理中心拿出自己是管理人员的证据的问题。要求北京公共交通控股集团有限公司鸿运承物业管理中心拿出自己是管理人员的证据的问题人力组织部 | I61: 是 | J61: 其他 | K61: 党委组织部（统战部） | L61: 组织方面其他问题 | M61: 组织方面补充内容 | N61: 鸿运承物业管理中心 | O61: 党委工作部 | P61: 党委工作部 | Q61: 机关 | R61: 2026-01-16 23:59:59 | S61: 2026-01-13 | T61: 2026-01-14 08:59:59 | U61: 结束 | V61: 0 | W61: 接到市民反映的问题后，我们立即进行了核实，经核实，与实际情况不符。 | X61: 接到市民反映的问题后，党委工作部立即进行核实，经核实，投诉内容与事实不符，不存在投诉人反映的情况，投诉人曾是物业管理中心天宫院分中心劳人员助理，为工人管理岗位。工人管理岗位属于企业基层管理人员和监察对象。感谢职工对我们工作中的不足提出宝贵意见，党委工作部会继续做好干部监督管理。办理人：高伟；部门：鸿运承物业管理中心党委工作部；职务：党委工作部副部长。审核人：吕东霞；职务：党委工作部部长。 | Y61: 无。 | Z61: 无。 | AA61: 无。 | AB61: 接到市民反映的问题后，党委工作部立即进行核实，经核实，投诉内容与事实不符，不存在投诉人反映的情况，投诉人曾是物业管理中心天宫院分中心劳人员助理，为工人管理岗位。工人管理岗位属于企业基层管理人员和监察对象。感谢职工对我们工作中的不足提出宝贵意见，党委工作部会继续做好干部监督管理。 | AC61: 满意 | AD61: 个人 | AE61: 2026-01-09 15:17:29 | AF61: 1047563 | AG61: 劳动合同及用工管理 | AH61: 否 | AK61: =AG61&L61&M61 -> 劳动合同及用工管理组织方面其他问题组织方面补充内容 | AP61: 57 | AQ61: 46023 | AR61: =IFERROR(LEFT(A61,FIND("（",A61)-1),A61) -> 热线-260109-043939-2 | AS61: =J61 -> 其他 | AT61: =IF(MID(AR61,1,2)="热线",12345)+IF(MID(AR61,1,2)="网络",12345) -> 12345 | AU61: =IFERROR(LEFT(D61,FIND(" ",D61)-1),D61) -> 2026-01-09 | AV61: =P61 -> 党委工作部 | AW61: =Q61 -> 机关 | AX61: =H61 -> 市民反映，自己被北京公共交通控股集团有限公司鸿运承物业管理中心开除，开除原因为企业说自己为管理人员，自己对此不认可，自己与企业签订的劳动合同为工人岗位，要求企业拿出管理自己人员的证据，地址：北京市西城区广安门内核桃园1号，来电反映要求北京公共交通控股集团有限公司鸿运承物业管理中心拿出自己是管理人员的证据的问题。要求北京公共交通控股集团有限公司鸿运承物业管理中心拿出自己是管理人员的证据的问题人力组织部 | AY61: =AG61 -> 劳动合同及用工管理 | AZ61: 是 | BA61: 否 | BB61: 否 | BC61: 七有五性,公正性 | BD61: =U61 -> 结束 | BE61: =IFERROR(LEFT(T61,FIND(" ",T61)-1),T61) -> 2026-01-14 | BF61: 劳动人员管理及劳动纪律 （纪检问题解除劳动合同）拆单 | BG61: 党委工作部 | BH61: 机关 | BL61: =IF(BG61="物管行政部","侯旭、郑楠",IF(BG61="安保部","张耕",IF(BG61="工程设备部","华菲",IF(BG61="人力资源部","成琦",IF(BG61="党委工作部","阎鑫雨",IF(BG61="餐饮服务部","赵弘晨",IF(BG61="工会","郑欣",IF(BG61="办公室","董娜",""))))))))&IF(BG61="纪检部","黄倩",IF(BG61="信息管理部","蔡浩然","")) -> 阎鑫雨 | BM61: 未主动剔除 | BP61: 纠纷类 | BQ61: 同人同诉：热线-260109-043939、热线-260113-007090、热线-260113-028565、网络-260124-001044 | BR61: 是 | BV61: =MID(AR61,1,16) -> 热线-260109-043939 | BW61: 七有五性,劳有所得 | BX61: =IF(COUNTIF(BV:BV,BV61)=1,"否","是") -> 是 | BY61: =MID(AR61,18,1) -> 2 | BZ61: 只评价响应率 | CE61: 1月 | CG61: =VLOOKUP(AR61,[1]市民意见信息导出!$AI$2:$AK$392,3,FALSE()) -> 结束 | CH61: =VLOOKUP(BV61,[2]Sheet1!$C$2:$AC$99,2,FALSE()) -> 1月
A62: 网络-260109-053098-2（2个附件） | B62: 2026-01-09 16:41:13 | C62: 2026-01-09 16:50:51 | D62: 2026-01-12 13:53:40 | E62: 高新生 | F62: 男 | G62: 手机,13717801036; | H62: 工单来源：微信服务号，此工单内容为网民留言时填写的标题及原文。 ============================= 留言标题：诓骗.糊弄.不作为.不称职的负责人吴岩（男13391623361）留言原文：他是北京市公交集团明悅湾分公司的负责人，主管599路公交车辆的卫生工作。在2025-12-23上午11：27/599路3628334车内内卫生状况差被乘客投诉，之后他称已打击完成。可是在2026-1-7下午16：30投诉方人员在此车内发现情况依旧！这充分证明他在说谎；且清洁工作并未完全彻底地完全，另书面道歉信至今未见到，误了我方在网络发布的工作开展！望市民热线做进一步敦促其和公司全面改进和整顿工作！！！令市民和政府放心！市民填写的详细地址为：区、街道：大兴区旧宫镇详细地址：南小街五福堂北路一号2号院。分公司内。 | I62: 是 | J62: 其他 | K62: 人力资源部（人力资源发展中心） | L62: 人力资源方面其他问题 | M62: 人力资源方面补充内容 | N62: 鸿运承物业管理中心 | O62: 人力资源部 | P62: 人力资源部 | Q62: 机关 | R62: 2026-01-16 23:59:59 | S62: 2026-01-13 | T62: 2026-01-14 08:59:59 | U62: 结束 | V62: 0 | W62: 针对市民所反映“诓骗.糊弄.不作为.不称职的负责人吴岩（男13391623361）留言原文：他是北京市公交集团明悅湾分公司的负责人，主管599路公交车辆的卫生工作。”的问题诉求经核实，诉求与实际情况有出入。我们就市民提供2025年12月23日、2026年1月7日反馈599路3628334号车车内卫生状况差的诉求线索，与该车卫生清洁所属的明月湾分中心取得联系，并要求相关单位提供整改清理车辆的证明，所在分中心予以视频反馈，就视频内容，我们进行了核实，视频中市民提供的车辆编号、问题时间、车辆卫生问题点位一一进行对应，提供的相关清理卫生的视频佐证有效，明月湾分中心物管主任吴岩未说谎。 | X62: 针对市民所反映“诓骗.糊弄.不作为.不称职的负责人吴岩（男13391623361）留言原文：他是北京市公交集团明悅湾分公司的负责人，主管599路公交车辆的卫生工作。”的问题诉求经核实，诉求与实际情况有出入。我们就市民提供2025年12月23日、2026年1月7日反馈599路3628334号车车内卫生状况差的诉求线索，与该车卫生清洁所属的明月湾分中心取得联系，并要求相关单位提供整改清理车辆的证明，所在分中心予以视频反馈，就视频内容，我们进行了核实，视频中市民提供的车辆编号、问题时间、车辆卫生问题点位一一进行对应，提供的相关清理卫生的视频佐证有效，明月湾分中心物管主任吴岩未说谎。我们与您2026年1月13日下午15：30分进行电话反馈，我们未答复完，您直接挂断了我们的来电。故我们以此短信，向您反馈我们的办理结果，向给您带来的不好乘车体验表示表示歉意。 办理人：高伟；部门：鸿运承物业管理中心党委工作部；职务：党委工作部副部长。 审核人：吕东霞；职务：党委工作部部长。 | Y62: 我们与您2026年1月13日下午15：30分进行电话反馈，我们未答复完，您直接挂断了我们的来电。故我们以此短信，向您反馈我们的办理结果，向给您带来的不好乘车体验表示表示歉意。 | Z62: 无 | AA62: 无 | AB62: 针对市民所反映“诓骗.糊弄.不作为.不称职的负责人吴岩（男13391623361）留言原文：他是北京市公交集团明悅湾分公司的负责人，主管599路公交车辆的卫生工作。”的问题诉求经核实，诉求与实际情况有出入。我们就市民提供2025年12月23日、2026年1月7日反馈599路3628334号车车内卫生状况差的诉求线索，与该车卫生清洁所属的明月湾分中心取得联系，并要求相关单位提供整改清理车辆的证明，所在分中心予以视频反馈，就视频内容，我们进行了核实，视频中市民提供的车辆编号、问题时间、车辆卫生问题点位一一进行对应，提供的相关清理卫生的视频佐证有效，明月湾分中心物管主任吴岩未说谎。我们与您2026年1月13日下午15：30分进行电话反馈，我们未答复完，您直接挂断了我们的来电。故我们以此短信，向您反馈我们的办理结果，向给您带来的不好乘车体验表示表示歉意。 | AC62: 满意 | AD62: 个人 | AE62: 2026-01-09 15:12:34 | AF62: 1049051 | AG62: 服务 | AH62: 否 | AK62: =AG62&L62&M62 -> 服务人力资源方面其他问题人力资源方面补充内容 | AP62: 58 | AQ62: 46023 | AR62: =IFERROR(LEFT(A62,FIND("（",A62)-1),A62) -> 网络-260109-053098-2 | AS62: =J62 -> 其他 | AT62: =IF(MID(AR62,1,2)="热线",12345)+IF(MID(AR62,1,2)="网络",12345) -> 12345 | AU62: =IFERROR(LEFT(D62,FIND(" ",D62)-1),D62) -> 2026-01-12 | AV62: =P62 -> 人力资源部 | AW62: =Q62 -> 机关 | AX62: =H62 -> 工单来源：微信服务号，此工单内容为网民留言时填写的标题及原文。 ============================= 留言标题：诓骗.糊弄.不作为.不称职的负责人吴岩（男13391623361）留言原文：他是北京市公交集团明悅湾分公司的负责人，主管599路公交车辆的卫生工作。在2025-12-23上午11：27/599路3628334车内内卫生状况差被乘客投诉，之后他称已打击完成。可是在2026-1-7下午16：30投诉方人员在此车内发现情况依旧！这充分证明他在说谎；且清洁工作并未完全彻底地完全，另书面道歉信至今未见到，误了我方在网络发布的工作开展！望市民热线做进一步敦促其和公司全面改进和整顿工作！！！令市民和政府放心！市民填写的详细地址为：区、街道：大兴区旧宫镇详细地址：南小街五福堂北路一号2号院。分公司内。 | AY62: =AG62 -> 服务 | AZ62: 否 | BA62: 否 | BB62: 否 | BC62: 七有五性,宜居性 | BD62: =U62 -> 结束 | BE62: =IFERROR(LEFT(T62,FIND(" ",T62)-1),T62) -> 2026-01-14 | BF62: 劳动人员管理及劳动纪律 | BG62: 党委工作部 | BH62: 机关 | BL62: =IF(BG62="物管行政部","侯旭、郑楠",IF(BG62="安保部","张耕",IF(BG62="工程设备部","华菲",IF(BG62="人力资源部","成琦",IF(BG62="党委工作部","阎鑫雨",IF(BG62="餐饮服务部","赵弘晨",IF(BG62="工会","郑欣",IF(BG62="办公室","董娜",""))))))))&IF(BG62="纪检部","黄倩",IF(BG62="信息管理部","蔡浩然","")) -> 阎鑫雨 | BM62: 未主动剔除 | BP62: 业务类 | BQ62: 网络-251223-042262-4 | BR62: 是 | BV62: =MID(AR62,1,16) -> 网络-260109-053098 | BW62: 七有五性,便利性 | BX62: =IF(COUNTIF(BV:BV,BV62)=1,"否","是") -> 是 | BY62: =MID(AR62,18,1) -> 2 | BZ62: 只评价响应率 | CE62: 1月 | CG62: =VLOOKUP(AR62,[1]市民意见信息导出!$AI$2:$AK$392,3,FALSE()) -> 结束 | CH62: =VLOOKUP(BV62,[2]Sheet1!$C$2:$AC$99,2,FALSE()) -> 1月
A63: 网络-260109-053098-1（5个附件） | B63: 2026-01-09 16:41:13 | C63: 2026-01-09 16:50:51 | D63: 2026-01-09 17:02:09 | E63: 高新生 | F63: 男 | G63: 手机,13717801036; | H63: 工单来源：微信服务号，此工单内容为网民留言时填写的标题及原文。 ============================= 留言标题：诓骗.糊弄.不作为.不称职的负责人吴岩（男13391623361）留言原文：他是北京市公交集团明悅湾分公司的负责人，主管599路公交车辆的卫生工作。在2025-12-23上午11：27/599路3628334车内内卫生状况差被乘客投诉，之后他称已打击完成。可是在2026-1-7下午16：30投诉方人员在此车内发现情况依旧！这充分证明他在说谎；且清洁工作并未完全彻底地完全，另书面道歉信至今未见到，误了我方在网络发布的工作开展！望市民热线做进一步敦促其和公司全面改进和整顿工作！！！令市民和政府放心！市民填写的详细地址为：区、街道：大兴区旧宫镇详细地址：南小街五福堂北路一号2号院。分公司内。 | I63: 是 | J63: 诉求 | K63: 行车安全服务部 | L63: 乘车环境问题 | M63: 车辆卫生 | N63: 鸿运承物业管理中心 | O63: 明月湾分中心 | P63: 物管行政部 | Q63: 明月湾分中心 | R63: 2026-01-16 23:59:59 | S63: 2026-01-10 | T63: 2026-01-14 08:59:59 | U63: 结束 | V63: 0 | W63: 您好，关于您反映问题的办理情况，鸿运承物业管理中心明月湾分中心现对您回复如下： | X63: 我分中心已于2026年1月10日中午12点25分对您进行电话回复，通话中您不听我说，您挂断了我的来电，我再次向您致电，您均未接听，为了减少对您的反复打扰，招来不必要的反感，故我冒昧给您发送短信告诉您一下我们对您反映问题的办理结果。办理人：吴岩；部门：鸿运承物业管理中心明月湾分中心；职务；物管副主任。审核人：郑楠；部门：鸿运承物业管理中心物管行政部；职务：物管员。 | Y63: 高先生您好，您25年12月23日反馈599路3628334号车的车辆卫生问题，我们接到您的反馈后，已立即整改了相关的卫生问题。您所述599路车内发现情况依旧，车内卫生状况差的问题，由于我们的工作没有做好，599路给您带来了不好的乘车体验，我和您道个歉，高先生。您提供的问题照片我们已收到，我们非常重视您的来电及反馈的问题，599路公交车我们在泰和园三里场站进行洗车服务工作，车辆运营中发生的卫生问题我们确实没有做到及时有效的去进行清理，您多包涵。该线路车辆运营回到我们的清洁地点后，我们的保洁员已对车辆的内外部卫生进行了全面的清理，已清理完毕。日常工作时段内，我们对于运营车辆车内外部卫生的清洁工作是一直在进行有序的开展，已经形成了长效的清洁机制，但有时候卫生清洁工作我们做的还有不尽人意之处，无论什么原因，都是我们的问题，给您的出行带来的不便，望您担待和理解。您要求我们提供书面道歉信的问题，我们做为国有企业，结合国企服务工作的规范流程，目前实在是无法满足您的这个要求，我们始终将您的意见作为提升服务质量的重要依据，后续会持续跟踪车辆卫生清洁效果。 | Z63: 我们分中心及场站班组长再次与599路的保洁人员进行了沟通，日常工作中我们要把清洁质量做的更加细致，同时加强保洁员清洁技能的培训，熟练掌握清洁方法，确保给您带来一个干净、整洁的出行环境。 | AA63: 我们定期会召开车辆保洁专题会议，开展车辆卫生专项检查，日常工作中我们加大巡检力度，强化制度建设，不断提高管理水平。 | AB63: 您好，关于您反映问题的办理情况，鸿运承物业管理中心明月湾分中心现对您回复如下：高先生您好，您25年12月23日反馈599路3628334号车的车辆卫生问题，我们接到您的反馈后，已立即整改了相关的卫生问题。您所述599路车内发现情况依旧，车内卫生状况差的问题，由于我们的工作没有做好，599路给您带来了不好的乘车体验，我和您道个歉，高先生。您提供的问题照片我们已收到，我们非常重视您的来电及反馈的问题，599路公交车我们在泰和园三里场站进行洗车服务工作，车辆运营中发生的卫生问题我们确实没有做到及时有效的去进行清理，您多包涵。该线路车辆运营回到我们的清洁地点后，我们的保洁员已对车辆的内外部卫生进行了全面的清理，已清理完毕。日常工作时段内，我们对于运营车辆车内外部卫生的清洁工作是一直在进行有序的开展，已经形成了长效的清洁机制，但有时候卫生清洁工作我们做的还有不尽人意之处，无论什么原因，都是我们的问题，给您的出行带来的不便，望您担待和理解。您要求我们提供书面道歉信的问题，我们做为国有企业，结合国企服务工作的规范流程，目前实在是无法满足您的这个要求，我们始终将您的意见作为提升服务质量的重要依据，后续会持续跟踪车辆卫生清洁效果。我们定期会召开车辆保洁专题会议，开展车辆卫生专项检查，日常工作中我们加大巡检力度，强化制度建设，不断提高管理水平。我分中心已于2026年1月10日中午12点25分对您进行电话回复，通话中您不听我说，您挂断了我的来电，我再次向您致电，您均未接听，为了减少对您的反复打扰，招来不必要的反感，故我冒昧给您发送短信告诉您一下我们对您反映问题的办理结果。我们分中心及场站班组长再次与599路的保洁人员进行了沟通，日常工作中我们要把清洁质量做的更加细致，同时加强保洁员清洁技能的培训，熟练掌握清洁方法，确保给您带来一个干净、整洁的出行环境。欢迎您随时对我们的工作进行监督，感谢您提出宝贵意见，给您的出行带来的不便我们和您说声抱歉，谢谢您的支持与谅解。 | AC63: 满意 | AD63: 个人 | AE63: 2026-01-09 15:12:34 | AF63: 1741937713 | AG63: 服务 | AH63: 否 | AK63: =AG63&L63&M63 -> 服务乘车环境问题车辆卫生 | AP63: 59 | AQ63: 46023 | AR63: =IFERROR(LEFT(A63,FIND("（",A63)-1),A63) -> 网络-260109-053098-1 | AS63: =J63 -> 诉求 | AT63: =IF(MID(AR63,1,2)="热线",12345)+IF(MID(AR63,1,2)="网络",12345) -> 12345 | AU63: =IFERROR(LEFT(D63,FIND(" ",D63)-1),D63) -> 2026-01-09 | AV63: =P63 -> 物管行政部 | AW63: =Q63 -> 明月湾分中心 | AX63: =H63 -> 工单来源：微信服务号，此工单内容为网民留言时填写的标题及原文。 ============================= 留言标题：诓骗.糊弄.不作为.不称职的负责人吴岩（男13391623361）留言原文：他是北京市公交集团明悅湾分公司的负责人，主管599路公交车辆的卫生工作。在2025-12-23上午11：27/599路3628334车内内卫生状况差被乘客投诉，之后他称已打击完成。可是在2026-1-7下午16：30投诉方人员在此车内发现情况依旧！这充分证明他在说谎；且清洁工作并未完全彻底地完全，另书面道歉信至今未见到，误了我方在网络发布的工作开展！望市民热线做进一步敦促其和公司全面改进和整顿工作！！！令市民和政府放心！市民填写的详细地址为：区、街道：大兴区旧宫镇详细地址：南小街五福堂北路一号2号院。分公司内。 | AY63: =AG63 -> 服务 | AZ63: 否 | BA63: 否 | BB63: 否 | BC63: 七有五性,宜居性 | BD63: =U63 -> 结束 | BE63: =IFERROR(LEFT(T63,FIND(" ",T63)-1),T63) -> 2026-01-14 | BF63: 车辆卫生问题 （车内卫生、玻璃） | BG63: 物管行政部 | BH63: 明月湾分中心 | BL63: =IF(BG63="物管行政部","侯旭、郑楠",IF(BG63="安保部","张耕",IF(BG63="工程设备部","华菲",IF(BG63="人力资源部","成琦",IF(BG63="党委工作部","阎鑫雨",IF(BG63="餐饮服务部","赵弘晨",IF(BG63="工会","郑欣",IF(BG63="办公室","董娜",""))))))))&IF(BG63="纪检部","黄倩",IF(BG63="信息管理部","蔡浩然","")) -> 侯旭、郑楠 | BM63: 未主动剔除 | BP63: 业务类 | BQ63: 多渠道同人同诉：网络-251223-042262-4、热线-260105-038505-2、网络-260109-053098-1、GJ-PHONE-20260111-0012 | BR63: 是 | BS63: 先12345再96166 | BV63: =MID(AR63,1,16) -> 网络-260109-053098 | BW63: 七有五性,便利性 | BX63: =IF(COUNTIF(BV:BV,BV63)=1,"否","是") -> 是 | BY63: =MID(AR63,18,1) -> 1 | BZ63: 只评价响应率 | CE63: 1月 | CG63: =VLOOKUP(AR63,[1]市民意见信息导出!$AI$2:$AK$392,3,FALSE()) -> 结束 | CH63: =VLOOKUP(BV63,[2]Sheet1!$C$2:$AC$99,2,FALSE()) -> 1月
A64: 热线-260109-028234（5个附件） | B64: 2026-01-09 22:33:56 | C64: 2026-01-09 22:41:14 | D64: 2026-01-10 08:43:09 | E64: 许先生 | F64: 男 | G64: 手机,17801575187; | H64: 市民反映，西城区新文化街西口公交车站，新设的栏杆非常不合理，站台的人行横道非常窄，设置的护栏把盲道给占上了，影响行人通行，行人下车只能从底下走，非常容易发生剐蹭，要求职能部门到现场取证，希望尽快拆除护栏，来电反映希望拆除公交车站的护栏问题。工单流转退回：针对群众反映的问题，经我局西城交通支队秩序管理大队核实，群众反映的问题为新文化街西口公交车站台护拦设置问题，该护拦非我局管辖的交通设施，经核实，该护拦位于公交站台内，由北京公交集团公司设置维护，建议此件转北京公交集团公司办理答复。2026年01月09日15时02分，我局西城交通支队秩序管理大队电话联系群众，针对其诉求的管辖问题进行了沟通，此件转北京公交集团公司办理。希望拆除公交车站的护栏问题 | I64: 是 | J64: 诉求 | K64: 基建行政部 | L64: 站务设施问题 | M64: 站台护栏问题 | N64: 鸿运承物业管理中心 | O64: 工程设备部 | P64: 工程设备部 | Q64: 机关 | R64: 2026-01-16 23:59:59 | S64: 2026-01-11 | T64: 2026-01-14 08:59:59 | U64: 结束 | V64: 0 | W64: 新文化街西口公交站台（护栏）站务设施设置问题。公交站台护栏属于公交站台站务设施。经核实，近期公交集团在“城市网络管理平台”接到西城城管委派单，反馈新文化街西口站台护栏倾斜松动，因为此站台临近长安街，西城区城管委与防控办要求公交集团护栏予以保留，仅做维修加固处理。此站台确实宽度有限，从我们现场核实的照片看，新维修加固后的护栏没有阻挡盲道。 | X64: 我们于2026年1月11日10点12分与市民进行电话答复，向市民说明我们核实的情况、解释说明、计划解决方案及办理情况。办理人：华菲 工程设备部 一般管理。 审核人：贾新宇 工程设备部 经理。 | Y64: 公交集团很重视本次市民诉求，但是依据北京市相关规定，站台护栏属于"城市家具"，无论维修拆除安装，都须到属地管理部门进行规划方案审批。新文化街西口站台护栏西城区城管委、防控办不让拆除，所以公交集团就要向管理部门重新申报调整方案，我们计划是将护栏由2跨改为1跨，同时尽量避让开后方的公交站棚，尽可能扩大通行空间。 | Z64: 我们将按流程向属地城管委进行项目申报。调整护栏施工进度，取决于各类手续的办理情况。政府管理部门内部审批流程，公交集团无权也无法控制，我们只能等待政府管理部门答复。公交集团将根据审批进度，实时跟进，调整护栏完成时间暂时无法向市民承诺。公交集团物业公司会持续关注此事进展，也请市民理解谅解。 | AA64: 公交集团物业公司会持续关注此事进展，也请市民理解谅解。 | AB64: 新文化街西口公交站台（护栏）站务设施设置问题。公交站台护栏属于公交站台站务设施。经核实，近期公交集团在“城市网络管理平台”接到西城城管委派单，反馈新文化街西口站台护栏倾斜松动，因为此站台临近长安街，西城区城管委与防控办要求公交集团护栏予以保留，仅做维修加固处理。此站台确实宽度有限，从我们现场核实的照片看，新维修加固后的护栏没有阻挡盲道。公交集团很重视本次市民诉求，但是依据北京市相关规定，站台护栏属于"城市家具"，无论维修拆除安装，都须到属地管理部门进行规划方案审批。新文化街西口站台护栏西城区城管委、防控办不让拆除，所以公交集团就要向管理部门重新申报调整方案，我们计划是将护栏由2跨改为1跨，同时尽量避让开后方的公交站棚，尽可能扩大通行空间。我们将按流程向属地城管委进行项目申报。调整护栏施工进度，取决于各类手续的办理情况。政府管理部门内部审批流程，公交集团无权也无法控制，我们只能等待政府管理部门答复。公交集团将根据审批进度，实时跟进，调整护栏完成时间暂时无法向市民承诺。公交集团物业公司会持续关注此事进展，也请市民理解谅解。我们于2026年1月11日10点12分与市民进行电话答复，向市民说明我们核实的情况、解释说明、计划解决方案及办理情况。 | AC64: 满意 | AD64: 个人 | AE64: 2026-01-09 12:29:03 | AF64: 1728084326 | AG64: 交通护栏 | AH64: 否 | AK64: =AG64&L64&M64 -> 交通护栏站务设施问题站台护栏问题 | AP64: 60 | AQ64: 46023 | AR64: =IFERROR(LEFT(A64,FIND("（",A64)-1),A64) -> 热线-260109-028234 | AS64: =J64 -> 诉求 | AT64: =IF(MID(AR64,1,2)="热线",12345)+IF(MID(AR64,1,2)="网络",12345) -> 12345 | AU64: =IFERROR(LEFT(D64,FIND(" ",D64)-1),D64) -> 2026-01-10 | AV64: =P64 -> 工程设备部 | AW64: =Q64 -> 机关 | AX64: =H64 -> 市民反映，西城区新文化街西口公交车站，新设的栏杆非常不合理，站台的人行横道非常窄，设置的护栏把盲道给占上了，影响行人通行，行人下车只能从底下走，非常容易发生剐蹭，要求职能部门到现场取证，希望尽快拆除护栏，来电反映希望拆除公交车站的护栏问题。工单流转退回：针对群众反映的问题，经我局西城交通支队秩序管理大队核实，群众反映的问题为新文化街西口公交车站台护拦设置问题，该护拦非我局管辖的交通设施，经核实，该护拦位于公交站台内，由北京公交集团公司设置维护，建议此件转北京公交集团公司办理答复。2026年01月09日15时02分，我局西城交通支队秩序管理大队电话联系群众，针对其诉求的管辖问题进行了沟通，此件转北京公交集团公司办理。希望拆除公交车站的护栏问题 | AY64: =AG64 -> 交通护栏 | AZ64: 否 | BA64: 否 | BB64: 否 | BC64: 七有五性,便利性 | BD64: =U64 -> 结束 | BE64: =IFERROR(LEFT(T64,FIND(" ",T64)-1),T64) -> 2026-01-14 | BF64: 站台护栏 | BG64: 工程设备部 | BH64: 机关 | BL64: =IF(BG64="物管行政部","侯旭、郑楠",IF(BG64="安保部","张耕",IF(BG64="工程设备部","华菲",IF(BG64="人力资源部","成琦",IF(BG64="党委工作部","阎鑫雨",IF(BG64="餐饮服务部","赵弘晨",IF(BG64="工会","郑欣",IF(BG64="办公室","董娜",""))))))))&IF(BG64="纪检部","黄倩",IF(BG64="信息管理部","蔡浩然","")) -> 华菲 | BM64: 未主动剔除 | BP64: 政策类 | BV64: =MID(AR64,1,16) -> 热线-260109-028234 | BW64: 疏整促,城市家具,便利性,七有五性 | BX64: =IF(COUNTIF(BV:BV,BV64)=1,"否","是") -> 否 | BY64: =MID(AR64,18,1) | CG64: =VLOOKUP(AR64,[1]市民意见信息导出!$AI$2:$AK$392,3,FALSE()) -> 结束 | CH64: =VLOOKUP(BV64,[2]Sheet1!$C$2:$AC$99,2,FALSE()) -> #N/A
A65: 网络-260110-041791-2 | B65: 2026-01-10 17:02:07 | C65: 2026-01-10 17:12:36 | D65: 2026-01-10 17:49:58 | E65: 保密 | F65: 女 | G65: 保密 | H65: 工单来源：微信服务号，此工单内容为网民留言时填写的标题及原文。============================= 留言标题：车辆卫生留言原文：今日到西直门坐362车发现车厢里面没有垃圾桶，卫生很差，车厢内都是垃圾。天气冷，空气不流通，车厢卫生脏，影响乘车环境市民填写的详细地址为：区、街道：西城区展览路街道详细地址：西直门 客四鸿运城 | I65: 是 | J65: 诉求 | K65: 行车安全服务部 | L65: 企业政策问题 | M65: 调整服务规范 | N65: 鸿运承物业管理中心 | O65: 动物园分中心 | P65: 物管行政部 | Q65: 动物园分中心 | R65: 2026-01-17 23:59:59 | S65: 2026-01-12 | T65: 2026-01-15 08:59:59 | U65: 结束 | V65: 0 | W65: 您好，关于您反映问题的办理情况，鸿运承物业管理中心动物园分中心现对您回复如下： | X65: 因您的联系方式保密，我们未能对您进行电话回复。办理人：杜伟；部门：鸿运承物业管理中心动物园分中心；职务；物管副主任。审核人：郑楠；部门：鸿运承物业管理中心物管行政部；职务：物管员。 | Y65: 女士您好，362路公交车我们在西直门南场站进行洗车服务工作，您所述车辆运营中车内卫生很差，车厢内都是垃圾，车厢卫生脏的问题我们非常重视您的反馈，由于我们的工作没有做好，362路给您带来不好的乘车体验，实在是抱歉，女士。该线路车辆回到西直门南场站后，在日常工作时段内，我们的保洁员已对车内卫生进行了全面的清理，确保我们的出场车辆卫生符合企业标准。您反馈的问题我们已整改完毕，同时我们要求保洁员对362路所有运营车辆的卫生再次进行细化清理。我们对于运营车辆车内卫生的清洁工作是一直在做的，也从未停止，已经形成了长效的清洁机制，但有时候卫生清洁工作我们做的还有不尽人意之处，您多多谅解。运营中车内空气不流通的问题，我们保洁员在清理卫生的同时，已将车门、车窗全部打开，对车内进行了通风换气作业。 | Z65: 我们分中心及场站班组长再次与362路的保洁人员进行了沟通，日常工作中我们要把清洁质量做的更加细致，同时加强保洁员清洁技能的培训，熟练掌握清洁方法，密切关注车内空气质量，确保给您带来一个干净、整洁、空气清新的出行环境。 | AA65: 我们定期会召开车辆保洁专题会议，开展车辆卫生专项检查，日常工作中我们加大巡检力度，强化制度建设，不断提高管理水平。 | AB65: 您好，关于您反映问题的办理情况，鸿运承物业管理中心动物园分中心现对您回复如下：女士您好，362路公交车我们在西直门南场站进行洗车服务工作，您所述车辆运营中车内卫生很差，车厢内都是垃圾，车厢卫生脏的问题我们非常重视您的反馈，由于我们的工作没有做好，362路给您带来不好的乘车体验，实在是抱歉，女士。该线路车辆回到西直门南场站后，在日常工作时段内，我们的保洁员已对车内卫生进行了全面的清理，确保我们的出场车辆卫生符合企业标准。您反馈的问题我们已整改完毕，同时我们要求保洁员对362路所有运营车辆的卫生再次进行细化清理。我们对于运营车辆车内卫生的清洁工作是一直在做的，也从未停止，已经形成了长效的清洁机制，但有时候卫生清洁工作我们做的还有不尽人意之处，您多多谅解。运营中车内空气不流通的问题，我们保洁员在清理卫生的同时，已将车门、车窗全部打开，对车内进行了通风换气作业。我们定期会召开车辆保洁专题会议，开展车辆卫生专项检查，日常工作中我们加大巡检力度，强化制度建设，不断提高管理水平。因您的联系方式保密，我们未能对您进行电话回复。我们分中心及场站班组长再次与362路的保洁人员进行了沟通，日常工作中我们要把清洁质量做的更加细致，同时加强保洁员清洁技能的培训，熟练掌握清洁方法，密切关注车内空气质量，确保给您带来一个干净、整洁、空气清新的出行环境。欢迎您随时对我们的工作进行监督，感谢您提出宝贵意见，给您的出行带来的不便我们和您说声抱歉，谢谢您的支持与谅解。 | AC65: 满意 | AD65: 个人 | AE65: 2026-01-10 12:44:48 | AF65: 1741937703 | AG65: 服务 | AH65: 否 | AK65: =AG65&L65&M65 -> 服务企业政策问题调整服务规范 | AP65: 61 | AQ65: 46023 | AR65: =IFERROR(LEFT(A65,FIND("（",A65)-1),A65) -> 网络-260110-041791-2 | AS65: =J65 -> 诉求 | AT65: =IF(MID(AR65,1,2)="热线",12345)+IF(MID(AR65,1,2)="网络",12345) -> 12345 | AU65: =IFERROR(LEFT(D65,FIND(" ",D65)-1),D65) -> 2026-01-10 | AV65: =P65 -> 物管行政部 | AW65: =Q65 -> 动物园分中心 | AX65: =H65 -> 工单来源：微信服务号，此工单内容为网民留言时填写的标题及原文。============================= 留言标题：车辆卫生留言原文：今日到西直门坐362车发现车厢里面没有垃圾桶，卫生很差，车厢内都是垃圾。天气冷，空气不流通，车厢卫生脏，影响乘车环境市民填写的详细地址为：区、街道：西城区展览路街道详细地址：西直门 客四鸿运城 | AY65: =AG65 -> 服务 | AZ65: 否 | BA65: 否 | BB65: 否 | BC65: 七有五性,宜居性 | BD65: =U65 -> 结束 | BE65: =IFERROR(LEFT(T65,FIND(" ",T65)-1),T65) -> 2026-01-15 | BF65: 车辆卫生问题 （车内垃圾） | BG65: 物管行政部 | BH65: 动物园分中心 | BL65: =IF(BG65="物管行政部","侯旭、郑楠",IF(BG65="安保部","张耕",IF(BG65="工程设备部","华菲",IF(BG65="人力资源部","成琦",IF(BG65="党委工作部","阎鑫雨",IF(BG65="餐饮服务部","赵弘晨",IF(BG65="工会","郑欣",IF(BG65="办公室","董娜",""))))))))&IF(BG65="纪检部","黄倩",IF(BG65="信息管理部","蔡浩然","")) -> 侯旭、郑楠 | BM65: 未主动剔除 | BP65: 业务类 | BV65: =MID(AR65,1,16) -> 网络-260110-041791 | BW65: 七有五性,便利性 | BX65: =IF(COUNTIF(BV:BV,BV65)=1,"否","是") -> 否 | BY65: =MID(AR65,18,1) -> 2 | CG65: =VLOOKUP(AR65,[1]市民意见信息导出!$AI$2:$AK$392,3,FALSE()) -> 结束 | CH65: =VLOOKUP(BV65,[2]Sheet1!$C$2:$AC$99,2,FALSE()) -> #N/A
A66: 网络-260109-036136-1 | B66: 2026-01-10 12:08:00 | C66: 2026-01-10 12:12:30 | D66: 2026-01-10 13:40:57 | E66: 保密 | F66: 男 | G66: 保密 | H66: 工单来源：微信服务号，此工单内容为网民留言时填写的标题及原文。=============================留言标题：投诉北京公交鸿运承物业管理中心人力部门留言原文：投诉北京公交鸿运承物业管理中心人力部门！1，我们夫妻俩是下属两个不同分中心的基层职工，我们长期被不同的分中心人力要求抽班，要求少工日，多问就是公司安排！这种要求合理吗？2，我们也去过管我们分中心办事地点，发现很多工人管理，一般管理就是玩手机，玩游戏，中午的时候甚至还在办公室里做饭，一直不让我们基层使用大功率，领导就能带头吗？管理合理吗？3，探听过关于刷卡的消息，说只要求我们工人每天必须刷卡，工人管理，一般管理，甚至正副主任都不用刷卡？劳动行为规范就是给我们基层职工制定的？工人管理一般管理不属于物业的职工？还是他们有特权？没有证据我们不会乱说，希望看到物业管理中心解决此事的态度，让我们看到公平公正，不要说工人管理一般管理是管理，是有不同的规范约束！我们看到的，都是职工，都是物业的一员，就应该按照物业管理规定执行，不能有特权！我们要看到公平的处理态度，不然我们将继续收集证据进行上报到底！违规克扣员工工日，造成工资下降！违法！管理人员不能按时上下班搞特权，违规！有些管理人员行为不检点，跟女同事暧昧，马上过节暗示职工送礼，违纪！市民填写的详细地址为：区、街道：西城区广内街道详细地址：北京公共交通控股(集团)有限公司鸿运承物业管理中心--------------------------------------------------工单流转【西城区】：诉求人反映投诉北京公交鸿运承物业管理中心人力部门违规克扣员工工日问题。经查，鸿运承物业管理中心上级单位为北京公共交通控股（集团）有限公司。市民来件中反映抽班、少工日属于对工作安排不认可。公司管理人员玩手机，玩游戏、使用大功率电器、上下班不刷卡等特权，还存在行为不检点，跟女同事暧昧，过节暗示职工送礼等行为，属于对公司管理不认可。以上问题均属于单位内部管理问题，不涉及劳动违法，不属于劳动监察及劳动争议仲裁受理范围。关于单位内部管理制度问题应转北京公交集团协调鸿运承物业中心进一步处理。北京公共交通控股（集团）有限公司为市属46家国企，烦请市中心转北京公共交通控股（集团）有限公司进一步帮助市民处理。人力组织部纪检 | I66: 是 | J66: 诉求 | K66: 人力资源部（人力资源发展中心） | L66: 劳动用工 | M66: 人员配备 | N66: 鸿运承物业管理中心 | O66: 人力资源部 | P66: 人力资源部（人力资源发展中心） | Q66: 机关 | R66: 2026-01-17 23:59:59 | S66: 2026-01-13 | T66: 2026-01-15 08:59:59 | U66: 结束 | V66: 0 | W66: 经核实，与来电人所述情况存在出入：1.按照企业降低效、减无效整体经营发展，物业管理中心作为保障性单位，需要对场站相关工作进一步优化调整，我单位按照场站业务实际需求，合理安排场站职工出勤，根据场站业务需要动态调整职工出勤安排，并非是要克扣职工工日。 2.物业管理中心要求各单位严格按照企业规章制度执行，如发现违反企业规章制度的行为，依照《鸿运承物业管理中心员工岗位规范考核实施细则》以及《管理人员绩效考核薪酬管理实施细则》相关政策文件严格处理。 3.管理人员为标准工时和不定时工作制，工人岗位主要为综合计算工时制，依照《鸿运承物业管理中心员工考勤管理规定》相关规定开展考勤管理工作。 | X66: 经核实，与来电人所述情况存在出入：1.按照企业降低效、减无效整体经营发展，物业管理中心作为保障性单位，需要对场站相关工作进一步优化调整，我单位按照场站业务实际需求，合理安排场站职工出勤，根据场站业务需要动态调整职工出勤安排，并非是要克扣职工工日。 2.物业管理中心要求各单位严格按照企业规章制度执行，如发现违反企业规章制度的行为，依照《鸿运承物业管理中心员工岗位规范考核实施细则》以及《管理人员绩效考核薪酬管理实施细则》相关政策文件严格处理。 3.管理人员为标准工时和不定时工作制，工人岗位主要为综合计算工时制，依照《鸿运承物业管理中心员工考勤管理规定》相关规定开展考勤管理工作。 因来电人未留姓名及联系方式，故我单位无法电话回复来电人，因来电人未留具体单位，故我单位无法进行更为有针对性的核实。为了能够促进问题解决，特在此留下人力资源部政策咨询电话83122233，希望能够与来电人直接沟通促进问题解决。 办理人：周健辉 ；部门：鸿运承物业管理中心人力资源部，职务：一般管理； 审核人：高强；部门：鸿运承物业管理中心人力资源部；职务：中级管理。 | Y66: 因来电人未留姓名及联系方式，故我单位无法电话回复来电人，因来电人未留具体单位，故我单位无法进行更为有针对性的核实。为了能够促进问题解决，特在此留下人力资源部政策咨询电话83122233，希望能够与来电人直接沟通促进问题解决。 | Z66: 无 | AA66: 无 | AB66: 经核实，与来电人所述情况存在出入：1.按照企业降低效、减无效整体经营发展，物业管理中心作为保障性单位，需要对场站相关工作进一步优化调整，我单位按照场站业务实际需求，合理安排场站职工出勤，根据场站业务需要动态调整职工出勤安排，并非是要克扣职工工日。 2.物业管理中心要求各单位严格按照企业规章制度执行，如发现违反企业规章制度的行为，依照《鸿运承物业管理中心员工岗位规范考核实施细则》以及《管理人员绩效考核薪酬管理实施细则》相关政策文件严格处理。 3.管理人员为标准工时和不定时工作制，工人岗位主要为综合计算工时制，依照《鸿运承物业管理中心员工考勤管理规定》相关规定开展考勤管理工作。 因来电人未留姓名及联系方式，故我单位无法电话回复来电人，因来电人未留具体单位，故我单位无法进行更为有针对性的核实。为了能够促进问题解决，特在此留下人力资源部政策咨询电话83122233，希望能够与来电人直接沟通促进问题解决。 | AC66: 满意 | AD66: 个人 | AE66: 2026-01-09 09:23:36 | AF66: 1049051 | AG66: 劳动合同及用工管理 | AH66: 否 | AK66: =AG66&L66&M66 -> 劳动合同及用工管理劳动用工人员配备 | AP66: 62 | AQ66: 46023 | AR66: =IFERROR(LEFT(A66,FIND("（",A66)-1),A66) -> 网络-260109-036136-1 | AS66: =J66 -> 诉求 | AT66: =IF(MID(AR66,1,2)="热线",12345)+IF(MID(AR66,1,2)="网络",12345) -> 12345 | AU66: =IFERROR(LEFT(D66,FIND(" ",D66)-1),D66) -> 2026-01-10 | AV66: =P66 -> 人力资源部（人力资源发展中心） | AW66: =Q66 -> 机关 | AX66: =H66 -> 工单来源：微信服务号，此工单内容为网民留言时填写的标题及原文。=============================留言标题：投诉北京公交鸿运承物业管理中心人力部门留言原文：投诉北京公交鸿运承物业管理中心人力部门！1，我们夫妻俩是下属两个不同分中心的基层职工，我们长期被不同的分中心人力要求抽班，要求少工日，多问就是公司安排！这种要求合理吗？2，我们也去过管我们分中心办事地点，发现很多工人管理，一般管理就是玩手机，玩游戏，中午的时候甚至还在办公室里做饭，一直不让我们基层使用大功率，领导就能带头吗？管理合理吗？3，探听过关于刷卡的消息，说只要求我们工人每天必须刷卡，工人管理，一般管理，甚至正副主任都不用刷卡？劳动行为规范就是给我们基层职工制定的？工人管理一般管理不属于物业的职工？还是他们有特权？没有证据我们不会乱说，希望看到物业管理中心解决此事的态度，让我们看到公平公正，不要说工人管理一般管理是管理，是有不同的规范约束！我们看到的，都是职工，都是物业的一员，就应该按照物业管理规定执行，不能有特权！我们要看到公平的处理态度，不然我们将继续收集证据进行上报到底！违规克扣员工工日，造成工资下降！违法！管理人员不能按时上下班搞特权，违规！有些管理人员行为不检点，跟女同事暧昧，马上过节暗示职工送礼，违纪！市民填写的详细地址为：区、街道：西城区广内街道详细地址：北京公共交通控股(集团)有限公司鸿运承物业管理中心--------------------------------------------------工单流转【西城区】：诉求人反映投诉北京公交鸿运承物业管理中心人力部门违规克扣员工工日问题。经查，鸿运承物业管理中心上级单位为北京公共交通控股（集团）有限公司。市民来件中反映抽班、少工日属于对工作安排不认可。公司管理人员玩手机，玩游戏、使用大功率电器、上下班不刷卡等特权，还存在行为不检点，跟女同事暧昧，过节暗示职工送礼等行为，属于对公司管理不认可。以上问题均属于单位内部管理问题，不涉及劳动违法，不属于劳动监察及劳动争议仲裁受理范围。关于单位内部管理制度问题应转北京公交集团协调鸿运承物业中心进一步处理。北京公共交通控股（集团）有限公司为市属46家国企，烦请市中心转北京公共交通控股（集团）有限公司进一步帮助市民处理。人力组织部纪检 | AY66: =AG66 -> 劳动合同及用工管理 | AZ66: 是 | BA66: 是 | BB66: 是 | BC66: 七有五性,公正性 | BD66: =U66 -> 结束 | BE66: =IFERROR(LEFT(T66,FIND(" ",T66)-1),T66) -> 2026-01-15 | BF66: 劳动人员管理及劳动纪律 | BG66: 人力资源部 | BH66: 机关 | BL66: =IF(BG66="物管行政部","侯旭、郑楠",IF(BG66="安保部","张耕",IF(BG66="工程设备部","华菲",IF(BG66="人力资源部","成琦",IF(BG66="党委工作部","阎鑫雨",IF(BG66="餐饮服务部","赵弘晨",IF(BG66="工会","郑欣",IF(BG66="办公室","董娜",""))))))))&IF(BG66="纪检部","黄倩",IF(BG66="信息管理部","蔡浩然","")) -> 成琦 | BM66: 未主动剔除 | BP66: 政策类 | BV66: =MID(AR66,1,16) -> 网络-260109-036136 | BW66: 七有五性,劳有所得 | BX66: =IF(COUNTIF(BV:BV,BV66)=1,"否","是") -> 是 | BY66: =MID(AR66,18,1) -> 1 | CG66: =VLOOKUP(AR66,[1]市民意见信息导出!$AI$2:$AK$392,3,FALSE()) -> 结束 | CH66: =VLOOKUP(BV66,[2]Sheet1!$C$2:$AC$99,2,FALSE()) -> #N/A
A67: 网络-260109-036136-2 | B67: 2026-01-10 12:08:00 | C67: 2026-01-10 12:12:30 | D67: 2026-01-10 13:40:57 | E67: 保密 | F67: 男 | G67: 保密 | H67: 工单来源：微信服务号，此工单内容为网民留言时填写的标题及原文。=============================留言标题：投诉北京公交鸿运承物业管理中心人力部门留言原文：投诉北京公交鸿运承物业管理中心人力部门！1，我们夫妻俩是下属两个不同分中心的基层职工，我们长期被不同的分中心人力要求抽班，要求少工日，多问就是公司安排！这种要求合理吗？2，我们也去过管我们分中心办事地点，发现很多工人管理，一般管理就是玩手机，玩游戏，中午的时候甚至还在办公室里做饭，一直不让我们基层使用大功率，领导就能带头吗？管理合理吗？3，探听过关于刷卡的消息，说只要求我们工人每天必须刷卡，工人管理，一般管理，甚至正副主任都不用刷卡？劳动行为规范就是给我们基层职工制定的？工人管理一般管理不属于物业的职工？还是他们有特权？没有证据我们不会乱说，希望看到物业管理中心解决此事的态度，让我们看到公平公正，不要说工人管理一般管理是管理，是有不同的规范约束！我们看到的，都是职工，都是物业的一员，就应该按照物业管理规定执行，不能有特权！我们要看到公平的处理态度，不然我们将继续收集证据进行上报到底！违规克扣员工工日，造成工资下降！违法！管理人员不能按时上下班搞特权，违规！有些管理人员行为不检点，跟女同事暧昧，马上过节暗示职工送礼，违纪！市民填写的详细地址为：区、街道：西城区广内街道详细地址：北京公共交通控股(集团)有限公司鸿运承物业管理中心--------------------------------------------------工单流转【西城区】：诉求人反映投诉北京公交鸿运承物业管理中心人力部门违规克扣员工工日问题。经查，鸿运承物业管理中心上级单位为北京公共交通控股（集团）有限公司。市民来件中反映抽班、少工日属于对工作安排不认可。公司管理人员玩手机，玩游戏、使用大功率电器、上下班不刷卡等特权，还存在行为不检点，跟女同事暧昧，过节暗示职工送礼等行为，属于对公司管理不认可。以上问题均属于单位内部管理问题，不涉及劳动违法，不属于劳动监察及劳动争议仲裁受理范围。关于单位内部管理制度问题应转北京公交集团协调鸿运承物业中心进一步处理。北京公共交通控股（集团）有限公司为市属46家国企，烦请市中心转北京公共交通控股（集团）有限公司进一步帮助市民处理。人力组织部纪检 | I67: 是 | J67: 诉求 | K67: 党委组织部（统战部） | L67: 领导干部问题 | M67: 领导行为不当 | N67: 鸿运承物业管理中心 | O67: 党委工作部 | P67: 党委组织部（统战部） | Q67: 机关 | R67: 2026-01-17 23:59:59 | S67: 2026-01-12 | T67: 2026-01-15 08:59:59 | U67: 结束 | V67: 0 | W67: 接到市民反映的问题后，我们立即进行了核实，经核实，与实际情况不符。 | X67: 接到市民反映的问题后，党委工作部立即进行核实，经核实，投诉内容与事实不符，不存在投诉人反映的情况，如果投诉人持有相关证据，可联系党委工作部，感谢职工对我们工作中的不足提出宝贵意见，党委工作部会继续做好干部监督管理。办理人：高伟；部门：鸿运承物业管理中心党委工作部；职务：党委工作部副部长。审核人：吕东霞；职务：党委工作部部长。 | Y67: 无。 | Z67: 无。 | AA67: 无。 | AB67: 接到市民反映的问题后，党委工作部立即进行核实，经核实，投诉内容与事实不符，不存在投诉人反映的情况，如果投诉人持有相关证据，可联系党委工作部，感谢职工对我们工作中的不足提出宝贵意见，党委工作部会继续做好干部监督管理。 | AC67: 满意 | AD67: 个人 | AE67: 2026-01-09 09:23:36 | AF67: 1047563 | AG67: 劳动合同及用工管理 | AH67: 否 | AK67: =AG67&L67&M67 -> 劳动合同及用工管理领导干部问题领导行为不当 | AP67: 63 | AQ67: 46023 | AR67: =IFERROR(LEFT(A67,FIND("（",A67)-1),A67) -> 网络-260109-036136-2 | AS67: =J67 -> 诉求 | AT67: =IF(MID(AR67,1,2)="热线",12345)+IF(MID(AR67,1,2)="网络",12345) -> 12345 | AU67: =IFERROR(LEFT(D67,FIND(" ",D67)-1),D67) -> 2026-01-10 | AV67: =P67 -> 党委组织部（统战部） | AW67: =Q67 -> 机关 | AX67: =H67 -> 工单来源：微信服务号，此工单内容为网民留言时填写的标题及原文。=============================留言标题：投诉北京公交鸿运承物业管理中心人力部门留言原文：投诉北京公交鸿运承物业管理中心人力部门！1，我们夫妻俩是下属两个不同分中心的基层职工，我们长期被不同的分中心人力要求抽班，要求少工日，多问就是公司安排！这种要求合理吗？2，我们也去过管我们分中心办事地点，发现很多工人管理，一般管理就是玩手机，玩游戏，中午的时候甚至还在办公室里做饭，一直不让我们基层使用大功率，领导就能带头吗？管理合理吗？3，探听过关于刷卡的消息，说只要求我们工人每天必须刷卡，工人管理，一般管理，甚至正副主任都不用刷卡？劳动行为规范就是给我们基层职工制定的？工人管理一般管理不属于物业的职工？还是他们有特权？没有证据我们不会乱说，希望看到物业管理中心解决此事的态度，让我们看到公平公正，不要说工人管理一般管理是管理，是有不同的规范约束！我们看到的，都是职工，都是物业的一员，就应该按照物业管理规定执行，不能有特权！我们要看到公平的处理态度，不然我们将继续收集证据进行上报到底！违规克扣员工工日，造成工资下降！违法！管理人员不能按时上下班搞特权，违规！有些管理人员行为不检点，跟女同事暧昧，马上过节暗示职工送礼，违纪！市民填写的详细地址为：区、街道：西城区广内街道详细地址：北京公共交通控股(集团)有限公司鸿运承物业管理中心--------------------------------------------------工单流转【西城区】：诉求人反映投诉北京公交鸿运承物业管理中心人力部门违规克扣员工工日问题。经查，鸿运承物业管理中心上级单位为北京公共交通控股（集团）有限公司。市民来件中反映抽班、少工日属于对工作安排不认可。公司管理人员玩手机，玩游戏、使用大功率电器、上下班不刷卡等特权，还存在行为不检点，跟女同事暧昧，过节暗示职工送礼等行为，属于对公司管理不认可。以上问题均属于单位内部管理问题，不涉及劳动违法，不属于劳动监察及劳动争议仲裁受理范围。关于单位内部管理制度问题应转北京公交集团协调鸿运承物业中心进一步处理。北京公共交通控股（集团）有限公司为市属46家国企，烦请市中心转北京公共交通控股（集团）有限公司进一步帮助市民处理。人力组织部纪检 | AY67: =AG67 -> 劳动合同及用工管理 | AZ67: 是 | BA67: 是 | BB67: 是 | BC67: 七有五性,公正性 | BD67: =U67 -> 结束 | BE67: =IFERROR(LEFT(T67,FIND(" ",T67)-1),T67) -> 2026-01-15 | BF67: 劳动人员管理及劳动纪律 | BG67: 党委工作部 | BH67: 机关 | BL67: =IF(BG67="物管行政部","侯旭、郑楠",IF(BG67="安保部","张耕",IF(BG67="工程设备部","华菲",IF(BG67="人力资源部","成琦",IF(BG67="党委工作部","阎鑫雨",IF(BG67="餐饮服务部","赵弘晨",IF(BG67="工会","郑欣",IF(BG67="办公室","董娜",""))))))))&IF(BG67="纪检部","黄倩",IF(BG67="信息管理部","蔡浩然","")) -> 阎鑫雨 | BM67: 未主动剔除 | BP67: 政策类 | BV67: =MID(AR67,1,16) -> 网络-260109-036136 | BW67: 七有五性,劳有所得 | BX67: =IF(COUNTIF(BV:BV,BV67)=1,"否","是") -> 是 | BY67: =MID(AR67,18,1) -> 2 | CG67: =VLOOKUP(AR67,[1]市民意见信息导出!$AI$2:$AK$392,3,FALSE()) -> 结束 | CH67: =VLOOKUP(BV67,[2]Sheet1!$C$2:$AC$99,2,FALSE()) -> #N/A
A68: 热线-260111-023626-2（2个附件） | B68: 2026-01-11 13:52:07 | C68: 2026-01-11 14:00:27 | D68: 2026-01-12 10:13:58 | E68: 梁先生 | F68: 男 | G68: 手机,13311358442; | H68: 市民反映，北京客5分公司的物业刷车人员上班酒气冲天，就是今天上午这辆车，该人员走路都走不稳，名字应该是刘芳女士。希望处理一下。来电反映客5公交车工作人员上班喝酒问题。 | I68: 是 | J68: 其他 | K68: 人力资源部（人力资源发展中心） | L68: 人力资源方面其他问题 | M68: 人力资源方面补充内容 | N68: 鸿运承物业管理中心 | O68: 土桥分中心 | P68: 人力资源部 | Q68: 土桥分中心 | R68: 2026-01-18 23:59:59 | S68: 2026-01-13 | T68: 2026-01-16 08:59:59 | U68: 结束 | V68: 0 | W68: 经与车辆保洁刘芳及当天的其他人员核实，刘芳当天是开车上班，且肠胃不舒服，并未喝酒。来电人反映的事情不属实。 | X68: 分中心在2026年1月12日下午13点48分和2026年1月12日下午16点18分和2026年1月13日上午9点58分给来电人进行电话回复均未接听，只能给来电人以短信形式回复。经与车辆保洁刘芳及当天的其他人员核实，刘芳当天是开车上班，且肠胃不舒服，并未喝酒。来电人反映的事情不属实。办理人：姜月；鸿运承物业管理中心土桥分中心劳人员；职务：一般管理；审核人：高强；鸿运承物业管理中心人力资源部；职务：中级管理。 | Y68: 分中心在2026年1月12日下午13点48分和2026年1月12日下午16点18分和2026年1月13日上午9点58分给来电人进行电话回复均未接听，只能给来电人以短信形式回复。经与车辆保洁刘芳及当天的其他人员核实，刘芳当天是开车上班，且肠胃不舒服，并未喝酒。来电人反映的事情不属实。 | Z68: 无 | AA68: 无 | AB68: 分中心在2026年1月12日下午13点48分和2026年1月12日下午16点18分和2026年1月13日上午9点58分给来电人进行电话回复均未接听，只能给来电人以短信形式回复。经与车辆保洁刘芳及当天的其他人员核实，刘芳当天是开车上班，且肠胃不舒服，并未喝酒。来电人反映的事情不属实。 | AC68: 满意 | AD68: 个人 | AE68: 2026-01-11 13:39:42 | AF68: 1741937711 | AG68: 服务 | AH68: 否 | AK68: =AG68&L68&M68 -> 服务人力资源方面其他问题人力资源方面补充内容 | AP68: 64 | AQ68: 46023 | AR68: =IFERROR(LEFT(A68,FIND("（",A68)-1),A68) -> 热线-260111-023626-2 | AS68: =J68 -> 其他 | AT68: =IF(MID(AR68,1,2)="热线",12345)+IF(MID(AR68,1,2)="网络",12345) -> 12345 | AU68: =IFERROR(LEFT(D68,FIND(" ",D68)-1),D68) -> 2026-01-12 | AV68: =P68 -> 人力资源部 | AW68: =Q68 -> 土桥分中心 | AX68: =H68 -> 市民反映，北京客5分公司的物业刷车人员上班酒气冲天，就是今天上午这辆车，该人员走路都走不稳，名字应该是刘芳女士。希望处理一下。来电反映客5公交车工作人员上班喝酒问题。 | AY68: =AG68 -> 服务 | AZ68: 否 | BA68: 否 | BB68: 否 | BC68: 七有五性,公正性 | BD68: =U68 -> 结束 | BE68: =IFERROR(LEFT(T68,FIND(" ",T68)-1),T68) -> 2026-01-16 | BF68: 劳动人员管理及劳动纪律 （反映刷车人员工作问题）拆单 | BG68: 人力资源部 | BH68: 土桥分中心 | BL68: =IF(BG68="物管行政部","侯旭、郑楠",IF(BG68="安保部","张耕",IF(BG68="工程设备部","华菲",IF(BG68="人力资源部","成琦",IF(BG68="党委工作部","阎鑫雨",IF(BG68="餐饮服务部","赵弘晨",IF(BG68="工会","郑欣",IF(BG68="办公室","董娜",""))))))))&IF(BG68="纪检部","黄倩",IF(BG68="信息管理部","蔡浩然","")) -> 成琦 | BM68: 未主动剔除 | BP68: 业务类 | BV68: =MID(AR68,1,16) -> 热线-260111-023626 | BX68: =IF(COUNTIF(BV:BV,BV68)=1,"否","是") -> 是 | BY68: =MID(AR68,18,1) -> 2 | CG68: =VLOOKUP(AR68,[1]市民意见信息导出!$AI$2:$AK$392,3,FALSE()) -> 结束 | CH68: =VLOOKUP(BV68,[2]Sheet1!$C$2:$AC$99,2,FALSE()) -> #N/A
